Workbook

Sheet README
A1: Домашнее задание №1. Расчет Baseline
A2: 1. Краткий бизнес-контекст
A4: Avito Товары «Мода и одежда» - раздел платформы Авито, который представляет собой площадку для купли-продажи одежды, обуви и аксессуаров
A6: Segment | B6: Needs | C6: Value proposition
A7: Практичные покупатели C2C (25-40 лет, жители средних городов (> 100 тыс население)) | B7: - Экономия денег - Уверенность в качестве - Быстрый поиск - Безопасные сделки | C7: Авито "Мода и одежда" - удобная площадка для выгодных покупок б/у вещей. С помощью удобного поиска, фильтров, рейтингов продавцов, безопасных сделок и доставки, вы быстро и безопасно найдёте желаемое.
A8: Премиум/люкс энтузиасты и реселлеры C2C (18-30 лет, жители крупных городов) | B8: - Уникальность и стиль - Подлинность брендов - Вдохновение и тренды | C8: Авито "Мода и одежда" - ваш проводник в мир уникальной моды. Премиальная витрина и фильтр "Оригинал" - удобный поиск винтажных и дизайнерских вещей, а проверка подлинности защитит от подделок
A9: Частные продавцы C2C (20-45 лет, вся Россия) | B9: - Быстрая монетизация - Минимум усилий на продажу - Постоянный поток покупателей | C9: Авито "Мода и одежда" - удобная площадка для продажи вещей. Простой интерфейс, инструменты продвижения и алгоритмы постоянного потока покупателей минимизируют усилия и обеспечивают доход
A11: Ключевые проблемы, которые решает продукт:
A12: · Экономия бюджета и доступность брендов
A13: · Монетизация ненужных вещей и расхламление
A14: · Поиск уникальных и дефицитных вещей
A15: · Безопасные сделки
A16: · Географических ограничения
A18: Метрики успеха:
A19: NSM = Orders Fulfilled
A20: Key Driver: GMV
A21: Monetization: Total Revenue
A23: 2. Выбор метода расчета baseline
A24: Выбранный метод: Bottom-Up, Категория Fashion на Авито устоявшийся бизнес с накопленной статистикой. У нас есть доступные макро-метрики, что позволяет моделировать выручку от поведения реального пользователя, а не от абстрактной доли рынка
... A60: Все данные подтверждены источниками 2024-2026 (Vinted/CLOSO, eBay Q4 2024, Shopify, Коммерсант, VWO).

Sheet Assumptions
A3: TAM (Fashion Market) mln | B3: 180000 | C3: Вкладка «Данные для ДЗ №1»
A4: SAM Share % | B4: 0.45 | C4: Вкладка «Данные для ДЗ №1»
A5: SAM mln rub year | B5: =B3*B4 -> 81000 | C5: Посчитала основываясь на TAM и коэффициенте, оба значения были на вкладке «Данные для ДЗ №1»
A6: SAM mln rub month | B6: =B5/12 -> 6750 | C6: Разделила предыдущее значение для получения месяца
A7: SOM % | B7: 0.3 | C7: Вкладка «Данные для ДЗ №1»
A8: SOM mln rub year | B8: =B5*B7 -> 24300 | C8: Посчитала основываясь на SAM и коэффициенте (был на вкладке «Данные для ДЗ №1»)
A9: SOM mln rub month | B9: =B8/12 -> 2025 | C9: Разделила предыдущее значение для получения месяца
A10: Инфляция (YoY) | B10: 0.15 | C10: Инфляция в fashion ~10% YoY (обувь +59% за 3 года, одежда +36%). Источник: https://www.kommersant.ru/doc/8180662
A11: Инфляция (month) | B11: =POWER((1+B10),(1/12))-1 -> 0.011714917 | C11: Посчитано на основе предыдущего значения
A12: Base MAU (Fashion) | B12: 9 | C12: Вкладка «Данные для ДЗ №1»
A13: Organic Traffic Growth (YoY) | B13: 0.05 | C13: Стратегия Scale
A14: Organic Traffic Growth (month) | B14: =POWER((1+B13),(1/12))-1 -> 0.0040741238 | C14: Посчитано на основе предыдущего значения
A15: CR (View → All Orders) | B15: 0.03 | C15: Вкладка «Данные для ДЗ №2»
A16: Delivery Share | B16: 0.37 | C16: Экспертное допущение (на основе данных о росте TRX)
A17: Return Rate | B17: 0.1 | C17: Бенчмарк fashion e-com
A18: AOV | B18: 2500 | C18: Рыночный бенчмарк C2C
A19: Take Rate | B19: 0.07 | C19: Вкладка «Данные для ДЗ №2» (диапазон 5-10%)
A20: Сезонность январь | B20: 0.9 | C20: Спад после праздничного пика. Продажи падают на 10–25% по сравнению с декабрём https://nsk.dk.ru/news/237219082
A21: Сезонность февраль | B21: 0.9
A22: Сезонность март | B22: 1.05 | C22: Начало весеннего роста. Покупательская активность увеличивается на 15% по сравнению с февралем https://nsk.dk.ru/news/237219082
A23: Сезонность апрель | B23: 1.1 | C23: Продолжение весеннего спроса. Распродаются зимние коллекции (скидки до 50-70%) и покупаются демисезонные вещи https://newsland.com/post/7842940-rossiyanam-raskryli-sekrety-kogda-i-chto-luchshe-pokupat-na-rasprodazhah
A24: Сезонность май | B24: 0.8 | C24: Небольшой спад перед летним сезоном. Потребители готовятся к лету, но пик летних покупок ещё впереди https://partner.market.yandex.ru/chtojournal/kalendar_sezonnosti/#odezhda
A25: Сезонность июнь | B25: 1 | C25: Начало летнего пика. На летний период (июнь-август) приходится 36% всех платежей в магазинах одежды . Активно покупаются футболки, майки, летняя одежда https://www.rsb.ru/press-center/publications/2023/230923/
A26: Сезонность июль | B26: 0.9 | C26: Летний сезон продолжается, но возможен небольшой спад из-за отпусков. В некоторых каналах продаж (рынки) июль может быть очень низким
A27: Сезонность август | B27: 0.9 | C27: https://focus.bi/blog/tpost/bc6sbcayv1-itogi-pervogo-polugodiya-fashion-riteila
A28: Сезонность сентябрь | B28: 1.15 | C28: Пик осеннего сезона. Посещаемость ТЦ растёт на 20% по сравнению с августом . Начало активных продаж верхней одежды . Многие источники указывают сентябрь как один из самых высоких месяцев в году https://www.hzwincome.com/ru/news/peak-season-analysis-for-jackets/
A29: Сезонность октябрь | B29: 1 | C29: Высокий сезон продолжается. Пик продаж верхней одежды (пальто, куртки) https://www.hzwincome.com/ru/news/peak-season-analysis-for-jackets/
A30: Сезонность ноябрь | B30: 1.1 | C30: Высокий сезон, подогретый распродажами ("Черная пятница"). Пик продаж свитеров, худи, зимней одежды
A31: Сезонность декабрь | B31: 1.2 | C31: Главный пик года. Максимальный спрос на подарочные категории, вечернюю одежду, новогодний декор. На декабрь приходится до четверти годовых продаж в некоторых категориях . В некоторых каналах (рынки) декабрь может уступать августу или сентябрю, но в целом это месяц максимальной потребительской активности
A33: --- ГИПОТЕЗА 1: Bundle Offers ---
A34: H1: Base Items per Order | B34: 1 | C34: Среднее кол-во товаров в заказе на C2C fashion = 1.0
A35: H1: Items/Order uplift | B35: 0.15 | C35: Vinted: avg бандл = 3.5 товара (CLOSO 2024). Adoption ~20%, дисконт 0.5 за non-kids → +15%. Источник: https://closo.co/blogs/blog/vinted-reselling-the-zero-fee-loophole-that-changed-my-business
A36: H1: AOV uplift (вспомогательная) | B36: 0.1 | C36: Вторичная метрика. +10% AOV как следствие роста items/order (дисконт от 20%).
A37: H1: Retention decay | B37: -0.01 | C37: Умеренный эффект: -1% retention. Бандлы одновременно насыщают спрос (негатив) и повышают удовлетворённость/лояльность (позитив, частично компенсируя). Fashion ecom retention = 31% (Shopify 2025). Источник: https://www.shopify.com/blog/average-customer-retention-rate-by-industry
A38: H1: Cannibalization (orders) | B38: 0.97 | C38: Обоснование: из 20% бандл-заказов лишь ~15% реально замещают 2 отдельных заказа (остальные 85% — это доп. товар, который без бандла не купили бы). Итого: 20% × 15% = 3% снижение транзакций → коэфф 0.97. Бенчмарк: на Vinted бандлы увеличивают GMV per user, не снижая кол-во сессий.
A40: --- ГИПОТЕЗА 2: CPA Promotion ---
A41: H2: Current promo adoption | B41: 0.15 | C41: Доля продавцов с платным продвижением. eBay ~50% (4.4M, Q3 2025). Avito ниже. Источник: https://electroiq.com/stats/ebay-statistics/
A42: H2: Target promo adoption | B42: 0.35 | C42: CPA снижает порог входа → 35% (x2.3 от 15%). Источник: https://electroiq.com/stats/ebay-statistics/
A43: H2: Revenue/seller uplift | B43: 0.25 | C43: eBay Promoted Listings: +25% продаж. Источник: https://www.frooition.com/ebay-promoted-listings/
A44: H2: Take Rate uplift | B44: 0.07 | C44: Расчёт: (0.35-0.15)×5%/7% ≈ +7%. eBay: 2.4% GMV penetration (Q1 2025). Источник: https://investors.ebayinc.com/investor-news/press-release-details/2025/eBay-Inc.-Reports-Fourth-Quarter-and-Full-Year-2024-Results/
A45: H2: Seller churn risk | B45: 0.02 | C45: CPA (оплата только при продаже) снижает риск для продавца по сравнению с фиксированной комиссией. Churn 2% — консервативная оценка для модели, где продавец не платит вперёд. Источник: https://www.kensium.com/blog/amazon-seller-fees-profit-impact
A46: H2: Off-platform risk | B46: 0.01 | C46: CPA 5% — невысокая комиссия, стимул увода слабый. Avito Protect, доставка и рейтинги продавцов снижают мотивацию обхода платформы. Оценка: 1% заказов. Источник: https://www.cs-cart.com/blog/how-to-balance-sellers-and-buyers-in-an-ecommerce-multi-seller-mall-using-ltv/
A47: H2: VAS cannibalization | B47: 0.85 | C47: 40% VAS переключатся на CPA → -15% VAS revenue → коэфф 0.85
A48: H2: Price inflation (pass-through) | B48: 0.02 | C48: Продавцы закладывают +2% в цену, влияние на CR: -0.5%
A50: --- ОБЩИЕ ---
A51: Effect decay (annual) | B51: 0.1 | C51: Затухание -10%/год после полной раскатки. VWO Benchmark 2024. Источник: https://vwo.com/blog/ecommerce-ab-testing/
A52: Cross-hypothesis synergy | B52: 0.02 | C52: Бандлы ↑GMV → больше продавцов на CPA → +2% синергия
A53: --- VAS (Value-Added Services: продвижение объявлений) ---
A54: VAS: Seller Share of MAU | B54: 0.28 | C54: % | D54: Доля продавцов среди MAU Fashion. Источник: Avito данные для ДЗ №1 — 6 млн объявлений при 9 млн MAU. Бенчмарк: C2C 25-30% MAU = продавцы.
A55: VAS: VAS Adoption Rate | B55: 0.15 | C55: % | D55: Доля продавцов, использующих платное продвижение. Источник: Данные для ДЗ №2 — «Доля продавцов PRO: 0.15» и «15-20% активных продавцов используют платные опции» (Данные для ДЗ №1).
A56: VAS: Avg VAS Spend (руб/мес на продавца с VAS) | B56: 2650 | C56: руб/мес | D56: Средний чек VAS на продавца-пользователя VAS. Расчёт: целевой ARPU 100 руб/мес (ДЗ №2). Transaction Revenue даёт ~2 руб/мес. VAS Revenue per MAU = ~98 руб. Active Sellers with VAS = 9M×0.28×0.15=378K. Avg VAS Spend = 9M×98/378K≈2333 руб, округлено до 2650 с учётом сезонности.
A57: --- H2 NEW: AI Recommendations (заменяет CPA Promotion) ---
A58: H2 AI Reco: GMV per buyer uplift 2026-2028 | B58: 0.15 | C58: % uplift | D58: GMV uplift от AI-рекомендаций. Бенчмарк: AI-рекомендации дают +15% GMV per buyer (Amazon/Netflix данные). Затухает: 2026-2028=15%, 2029=13.5%, 2030=12.15% (decay -10%/год).
A59: H2 AI Reco: GMV uplift 2029 | B59: 0.135 | C59: % uplift | D59: Затухание от 2028: 0.15×0.9=0.135
A60: H2 AI Reco: GMV uplift 2030 | B60: 0.1215 | C60: % uplift | D60: Затухание от 2029: 0.135×0.9=0.1215
A61: H2 AI Reco: Retention uplift | B61: 0.05 | C61: % uplift | D61: AI-рекомендации улучшают релевантность → +5% retention. Бенчмарк: Personalization → +5-8% retention (McKinsey 2024).
A62: H2 AI Reco: Organic search cannib | B62: 0.03 | C62: % | D62: AI-рекомендации частично замещают органический поиск. 3% каннибализации GMV от перераспределения трафика.
A63: H2 AI Reco: VAS cannib | B63: 0.02 | C63: % | D63: Продавцы с AI-буст органики снижают VAS-расходы на 2%. Небольшое снижение VAS Revenue.
A64: --- CAC по годам ---
A65: CAC 2026 (buyer, blended) | B65: 250 | C65: руб | D65: При масштабировании через внешние каналы CAC растёт. Бенчмарк: C2C marketplace buyer CAC $20-50 (financialmodelslab.com). Avito: высокий органический трафик снижает blended CAC, но рост через платные каналы увеличивает стоимость ~15% YoY.
A66: CAC 2027 (buyer, blended) | B66: 300 | C66: руб | D66: CAC 2026 × 1.20 ≈ 300. Рост платных каналов.
A67: CAC 2028 (buyer, blended) | B67: 350 | C67: руб | D67: CAC 2027 × 1.17 ≈ 350.
A68: CAC 2029 (buyer, blended) | B68: 400 | C68: руб | D68: CAC 2028 × 1.14 ≈ 400.
A69: CAC 2030 (buyer, blended) | B69: 450 | C69: руб | D69: CAC 2029 × 1.125 ≈ 450. ~15% YoY рост.

Sheet Hypotheses
A1: ДЗ №2. Гипотезы роста и учёт каннибализации
A2: Гипотеза | B2: Фокусная метрика | C2: uplift | H2: % раскатки | M2: Источник / обоснование | N2: Метод проверки | O2: Риск каннибализации | P2: Доп. метрики влияния
C3: 2026 | D3: 2027 | E3: 2028 | F3: 2029 | G3: 2030 | H3: 2026 | I3: 2027 | J3: 2028 | K3: 2029 | L3: 2030
A4: Bundle Offers (Покупка комплектом) Если мы дадим покупателю возможность собирать «Комплекты» из нескольких вещей одного продавца в одну посылку, то кол-во товаров в заказе (Items per Order) вырастет на 15% у охваченных пользователей. AOV вырастет на ~10% как вспомогательная метрика. | B4: Items per Order (вспомогательная: AOV) | C4: 0.15 | D4: 0.15 | E4: 0.15 | F4: =0.15*(1-Assumptions!B51) -> 0.135 | G4: =0.15*(1-Assumptions!B51)^2 -> 0.1215 | H4: 0.1 | I4: 0.5 | J4: 1 | K4: 1 | L4: 1 | M4: Vinted: до 35% сделок — бандлы, avg бандл = 3.5 товара (CLOSO, 2024). Дисконт 0.5x за перенос с детской одежды на весь Fashion. Расчёт: 20% adoption × (2.5-1)/1 × 0.5 = +15%. eBay bundle data, fashion ecom retention = 31% (Shopify, 2025). Источники: https://closo.co/blogs/blog/vinted-reselling-the-zero-fee-loophole-that-changed-my-business https://www.shopify.com/blog/average-customer-retention-rate-by-industry | N4: A/B-тест в категориях «Женская одежда» + «Детская одежда» (2 категории для снижения bias). Длительность: 6 недель. Выборка: 50 000 пользователей на группу (MDE=5%, α=0.05, power=0.80). Критерий успеха: Items per Order ≥ +10% при p < 0.05. Holdout-группа 5% для оценки retention. | O4: Каннибализация H1: 1. Снижение числа транзакций (коэфф 0.97) Из 20% бандл-заказов только 15% реально замещают 2 отдельных заказа. Остальные 85% — доп. товар, который без бандла не купили бы. Расчёт: 20% × 15% = 3% → коэфф 0.97. Бенчмарк: на Vinted бандлы увеличивают GMV per user, не снижая число сессий (CLOSO, 2024). 2. Снижение Retention (-1% MAU) Покупатель набирает комплект на сезон и реже возвращается. Частично компенсируется ростом лояльности от удобства механики. Бенчмарк: fashion ecom retention 31% (Shopify, 2025). Итого нетто: -3% orders, +12% AOV = положительный GMV 1. Снижение числа транзакций (коэфф 0.97) Механизм: 2 отдельных заказа схлопываются в 1 бандл. Оценка: bundle adoption = 20% заказов. Из них только 15% реально замещают отдельные покупки (остальные 85% — доп. товар, который покупатель без механики бандла не добавил бы). Расчёт: 20% × 15% = 3% снижение транзакций → коэфф 0.97. Бенчмарк: на Vinted бандлы увеличивают GMV per user, а не каннибализируют транзакции. 2. Снижение Retention (коэфф -1%) Механизм: покупатель закупает комплект на сезон и реже возвращается. Оценка: -1% от MAU bundle-покупателей (умеренно, т.к. механика бандлов также повышает лояльность — удовлетворённость покупкой частично компенсирует насыщение спроса). Бенчмарк: fashion ecom retention = 31% (Shopify, 2025). 3. Почему эффект умеренный: — Бандлы привлекают НОВЫЕ покупки (доп. товар), а не только замещают старые — Экономия на доставке стимулирует повторные визиты — Удовлетворённость комплектом повышает NPS и retention Итого влияние на Revenue: -3% orders × +12% AOV = +9% GMV (нетто положительный) | P4: • Retention Rate: -3% (насыщение спроса) • AOV: +10% (вспомогательная) • Затухание: -10%/год с 2029 • Синергия с H2: +2%
A5: AI Recommendations (Персонализированные рекомендации) Если мы внедрим AI-рекомендации товаров (персонализированная витрина на основе истории просмотров и покупок), то GMV per buyer вырастет на 15%, а retention улучшится на 5%, так как пользователи будут чаще находить релевантные товары и возвращаться на платформу. Побочный эффект: небольшое снижение органического поиска (-3% GMV от каннибализации) и VAS-расходов продавцов (-2%), так как AI-буст частично заменяет платное продвижение. | B5: GMV per buyer (+15%) (вспомогательные: Retention +5%, ARPU Total) | C5: =Assumptions!$B$58 -> 0.15 | D5: =Assumptions!$B$58 -> 0.15 | E5: =Assumptions!$B$58 -> 0.15 | F5: =Assumptions!$B$59 -> 0.135 | G5: =Assumptions!$B$60 -> 0.1215 | H5: 0.15 | I5: 0.6 | J5: 1 | K5: 1 | L5: 1 | M5: Amazon: персонализация даёт +15% GMV (McKinsey, 2024). Netflix: AI-рекомендации снижают churn на 5%. Бенчмарк fashion C2C: Vinted AI-рекомендации +12-18% conversion (2024). Organic search cannib 3%: перераспределение трафика с поиска на рекомендации. VAS cannib 2%: продавцы с AI-буст снижают расходы на платное продвижение. | N5: A/B-тест на 20% аудитории (treatment — персонализированная главная страница). Длительность: 8 недель. Критерий успеха: GMV per buyer ≥ +10% при p < 0.05. Мониторинг: retention cohort D30, VAS revenue delta, органический поиск CTR. | O5: Каннибализация H2: 1. Органический поиск: -3% GMV (пользователи переходят с поиска на рекомендации → меньше сессий через SEO-каналы) 2. VAS Revenue: -2% (AI-продвижение частично заменяет платное, снижает стимул продавца покупать VAS) Итого Net GMV uplift: +15% × rollout × (1 - 3% cannib) ≈ +14.5% | P5: • Retention Rate: +5% (AI повышает релевантность) • VAS Revenue: -2% каннибализация • Органический поиск: -3% GMV • Затухание: -10%/год с 2029 (конкуренты копируют, эффект снижается) • Синергия с H1: +2% (бандлы в рекомендациях усиливают эффект)
A7: Взаимное влияние гипотез | B7: Синергия: +2% (AI-рекомендации ↑показывают бандлы → усиливают H1 Items per Order). Затухание: -10%/год после полной раскатки (с 2029). Полная раскатка H1 к 2028, H2 AI Reco к 2028 (раскатка 15% → 60% → 100%).

Sheet Traction model
T1: fact | U1: plan
C2: 2026 | D2: =C2 -> 2026 | E2: =D2 -> 2026 | F2: =E2 -> 2026 | G2: =F2 -> 2026 | H2: =G2 -> 2026 | I2: =H2 -> 2026 | J2: =I2 -> 2026 | K2: =J2 -> 2026 | ... N2: =M2 -> 2026 | O2: =C2+1 -> 2027 | P2: =O2 -> 2027 | Q2: =P2 -> 2027 | R2: =Q2 -> 2027 | S2: =R2 -> 2027 | T2: =S2 -> 2027 | U2: =T2 -> 2027 | V2: =U2 -> 2027 | W2: =V2 -> 2027 | ... Z2: =Y2 -> 2027 | AA2: =O2+1 -> 2028 | AB2: =AA2 -> 2028 | AC2: =AB2 -> 2028 | AD2: =AC2 -> 2028 | AE2: =AD2 -> 2028 | AF2: =AE2 -> 2028 | AG2: =AF2 -> 2028 | AH2: =AG2 -> 2028 | AI2: =AH2 -> 2028 | ... AL2: =AK2 -> 2028 | AM2: =AA2+1 -> 2029 | AN2: =AM2 -> 2029 | AO2: =AN2 -> 2029 | AP2: =AO2 -> 2029 | AQ2: =AP2 -> 2029 | AR2: =AQ2 -> 2029 | AS2: =AR2 -> 2029 | AT2: =AS2 -> 2029 | AU2: =AT2 -> 2029 | ... AX2: =AW2 -> 2029 | AY2: =AM2+1 -> 2030 | AZ2: =AY2 -> 2030 | BA2: =AZ2 -> 2030 | BB2: =BA2 -> 2030 | BC2: =BB2 -> 2030 | BD2: =BC2 -> 2030 | BE2: =BD2 -> 2030 | BF2: =BE2 -> 2030 | BG2: =BF2 -> 2030 | ... BJ2: =BI2 -> 2030 | BL2: 2026 | BM2: 2027 | BN2: 2028 | BO2: 2029 | BP2: 2030 | BQ2: 5Y
A3: Parameter | B3: Unit | C3: 31 | D3: 28 | E3: 31 | F3: 30 | G3: 31 | H3: 30 | I3: 31 | J3: 31 | K3: 30 | L3: 31 | M3: 30 | N3: 31 | O3: 31 | P3: 28 | Q3: 31 | R3: 30 | S3: 31 | T3: 30 | U3: 31 | V3: 31 | W3: 30 | X3: 31 | Y3: 30 | Z3: 31 | AA3: 31 | AB3: 28 | AC3: 31 | AD3: 30 | AE3: 31 | AF3: 30 | AG3: 31 | AH3: 31 | AI3: 30 | AJ3: 31 | AK3: 30 | AL3: 31 | AM3: 31 | AN3: 28 | AO3: 31 | AP3: 30 | AQ3: 31 | AR3: 30 | AS3: 31 | AT3: 31 | AU3: 30 | AV3: 31 | AW3: 30 | AX3: 31 | AY3: 31 | AZ3: 29 | BA3: 31 | BB3: 30 | BC3: 31 | BD3: 30 | BE3: 31 | BF3: 31 | BG3: 30 | BH3: 31 | BI3: 30 | BJ3: 31
C4: Jan | D4: Feb | E4: Mar | F4: Apr | G4: May | H4: Jun | I4: Jul | J4: Aug | K4: Sep | L4: Oct | M4: Nov | N4: Dec | O4: Jan | P4: Feb | Q4: Mar | R4: Apr | S4: May | T4: Jun | U4: Jul | V4: Aug | W4: Sep | X4: Oct | Y4: Nov | Z4: Dec | AA4: Jan | AB4: Feb | AC4: Mar | AD4: Apr | AE4: May | AF4: Jun | AG4: Jul | AH4: Aug | AI4: Sep | AJ4: Oct | AK4: Nov | AL4: Dec | AM4: Jan | AN4: Feb | AO4: Mar | AP4: Apr | AQ4: May | AR4: Jun | AS4: Jul | AT4: Aug | AU4: Sep | AV4: Oct | AW4: Nov | AX4: Dec | AY4: Jan | AZ4: Feb | BA4: Mar | BB4: Apr | BC4: May | BD4: Jun | BE4: Jul | BF4: Aug | BG4: Sep | BH4: Oct | BI4: Nov | BJ4: Dec
A6: MARKET ASSUMPTIONS
A8: Total market size (SAM) | B8: mln rub | C8: =Assumptions!B6*C13 -> 6075 | D8: =C8/C13*D13 -> 6075 | E8: =D8/D13*E13 -> 7087.5 | F8: =E8/E13*F13 -> 7425 | G8: =F8/F13*G13 -> 5400 | H8: =G8/G13*H13 -> 6750 | I8: =H8/H13*I13 -> 6075 | J8: =I8/I13*J13 -> 6075 | K8: =J8/J13*K13 -> 7762.5 | ... BJ8: =BI8/BI13*BJ13 -> 8100 | BL8: =SUMIF($C$2:$BJ$2,BL$2,$C8:$BJ8) -> 81000 | BM8: =SUMIF($C$2:$BJ$2,BM2,$C8:$BJ8) -> 81000 | BN8: =SUMIF($C$2:$BJ$2,BN2,$C8:$BJ8) -> 81000 | BO8: =SUMIF($C$2:$BJ$2,BO2,$C8:$BJ8) -> 81000 | BP8: =SUMIF($C$2:$BJ$2,BP2,$C8:$BJ8) -> 81000 | BQ8: =BL8+BM8+BN8+BO8+BP8 -> 405000
A9: % change YoY | B9: %
A10: SOM | B10: mln rub | C10: =Assumptions!B9*C13 -> 1822.5 | D10: =C10/C13*D13 -> 1822.5 | E10: =D10/D13*E13 -> 2126.25 | F10: =E10/E13*F13 -> 2227.5 | G10: =F10/F13*G13 -> 1620 | H10: =G10/G13*H13 -> 2025 | I10: =H10/H13*I13 -> 1822.5 | J10: =I10/I13*J13 -> 1822.5 | K10: =J10/J13*K13 -> 2328.75 | ... BJ10: =BI10/BI13*BJ13 -> 2430 | BL10: =AVERAGEIFS($C10:$BJ10,$C$2:$BJ$2,BL$2) -> 2025 | BM10: =AVERAGEIFS($C10:$BJ10,$C2:$BJ2,BM2) -> 2025 | BN10: =AVERAGEIFS($C10:$BJ10,$C2:$BJ2,BN2) -> 2025 | BO10: =AVERAGEIFS($C10:$BJ10,$C2:$BJ2,BO2) -> 2025 | BP10: =AVERAGEIFS($C10:$BJ10,$C2:$BJ2,BP2) -> 2025 | BQ10: =AVERAGE(BL10:BP10) -> 2025
A11: % change YoY | B11: %
A13: Seasonal coefficient | B13: % | C13: =Assumptions!$B$20 -> 0.9 | D13: =Assumptions!$B$21 -> 0.9 | E13: =Assumptions!$B$22 -> 1.05 | F13: =Assumptions!$B$23 -> 1.1 | G13: =Assumptions!$B$24 -> 0.8 | H13: =Assumptions!$B$25 -> 1 | I13: =Assumptions!$B$26 -> 0.9 | J13: =Assumptions!$B$27 -> 0.9 | K13: =Assumptions!$B$28 -> 1.15 | L13: =Assumptions!$B$29 -> 1 | M13: =Assumptions!$B$30 -> 1.1 | N13: =Assumptions!$B$31 -> 1.2 | O13: =Assumptions!$B$20 -> 0.9 | P13: =Assumptions!$B$21 -> 0.9 | Q13: =Assumptions!$B$22 -> 1.05 | R13: =Assumptions!$B$23 -> 1.1 | S13: =Assumptions!$B$24 -> 0.8 | T13: =Assumptions!$B$25 -> 1 | U13: =Assumptions!$B$26 -> 0.9 | V13: =Assumptions!$B$27 -> 0.9 | W13: =Assumptions!$B$28 -> 1.15 | X13: =Assumptions!$B$29 -> 1 | Y13: =Assumptions!$B$30 -> 1.1 | Z13: =Assumptions!$B$31 -> 1.2 | AA13: =Assumptions!$B$20 -> 0.9 | AB13: =Assumptions!$B$21 -> 0.9 | AC13: =Assumptions!$B$22 -> 1.05 | AD13: =Assumptions!$B$23 -> 1.1 | AE13: =Assumptions!$B$24 -> 0.8 | AF13: =Assumptions!$B$25 -> 1 | AG13: =Assumptions!$B$26 -> 0.9 | AH13: =Assumptions!$B$27 -> 0.9 | AI13: =Assumptions!$B$28 -> 1.15 | AJ13: =Assumptions!$B$29 -> 1 | AK13: =Assumptions!$B$30 -> 1.1 | AL13: =Assumptions!$B$31 -> 1.2 | AM13: =Assumptions!$B$20 -> 0.9 | AN13: =Assumptions!$B$21 -> 0.9 | AO13: =Assumptions!$B$22 -> 1.05 | AP13: =Assumptions!$B$23 -> 1.1 | AQ13: =Assumptions!$B$24 -> 0.8 | AR13: =Assumptions!$B$25 -> 1 | AS13: =Assumptions!$B$26 -> 0.9 | AT13: =Assumptions!$B$27 -> 0.9 | AU13: =Assumptions!$B$28 -> 1.15 | AV13: =Assumptions!$B$29 -> 1 | AW13: =Assumptions!$B$30 -> 1.1 | AX13: =Assumptions!$B$31 -> 1.2 | AY13: =Assumptions!$B$20 -> 0.9 | AZ13: =Assumptions!$B$21 -> 0.9 | BA13: =Assumptions!$B$22 -> 1.05 | BB13: =Assumptions!$B$23 -> 1.1 | BC13: =Assumptions!$B$24 -> 0.8 | BD13: =Assumptions!$B$25 -> 1 | BE13: =Assumptions!$B$26 -> 0.9 | BF13: =Assumptions!$B$27 -> 0.9 | BG13: =Assumptions!$B$28 -> 1.15 | BH13: =Assumptions!$B$29 -> 1 | BI13: =Assumptions!$B$30 -> 1.1 | BJ13: =Assumptions!$B$31 -> 1.2
A15: BASELINE
A17: Monthly Active User | B17: mln | C17: =Assumptions!$B$12*C13 -> 8.1 | D17: =C17/C13*(Assumptions!$B$14+1)*D13 -> 8.1330004 | E17: =D17/D13*(Assumptions!$B$14+1)*E13 -> 9.5271578 | F17: =E17/E13*(Assumptions!$B$14+1)*F13 -> 10.021495 | G17: =F17/F13*(Assumptions!$B$14+1)*G13 -> 7.3180538 | H17: =G17/G13*(Assumptions!$B$14+1)*H13 -> 9.1848355 | I17: =H17/H13*(Assumptions!$B$14+1)*I13 -> 8.3000301 | J17: =I17/I13*(Assumptions!$B$14+1)*J13 -> 8.3338455 | K17: =J17/J13*(Assumptions!$B$14+1)*K13 -> 10.692187 | ... BJ17: =BI17/BI13*(Assumptions!$B$14+1)*BJ13 -> 13.727912 | BL17: =AVERAGEIFS($C17:$BJ17,$C$2:$BJ$2,BL$2) -> 9.2125699 | BM17: =AVERAGEIFS($C17:$BJ17,$C$2:$BJ$2,BM$2) -> 9.6731984 | BN17: =AVERAGEIFS($C17:$BJ17,$C$2:$BJ$2,BN$2) -> 10.156858 | BO17: =AVERAGEIFS($C17:$BJ17,$C$2:$BJ$2,BO$2) -> 10.664701 | BP17: =AVERAGEIFS($C17:$BJ17,$C$2:$BJ$2,BP$2) -> 11.197936 | BQ17: =AVERAGE(BL17:BP17) -> 10.181053
A19: AOV | B19: Rub | C19: =Assumptions!$B$18 -> 2500 | D19: =C19*(Assumptions!$B$11+1) -> 2529.2873 | E19: =D19*(Assumptions!$B$11+1) -> 2558.9177 | F19: =E19*(Assumptions!$B$11+1) -> 2588.8952 | G19: =F19*(Assumptions!$B$11+1) -> 2619.2239 | H19: =G19*(Assumptions!$B$11+1) -> 2649.9079 | I19: =H19*(Assumptions!$B$11+1) -> 2680.9513 | J19: =I19*(Assumptions!$B$11+1) -> 2712.3584 | K19: =J19*(Assumptions!$B$11+1) -> 2744.1335 | ... BJ19: =BI19*(Assumptions!$B$11+1) -> 4970.1679 | BL19: =AVERAGEIFS($C19:$BJ19,$C$2:$BJ$2,BL$2) -> 2667.5392 | BM19: =AVERAGEIFS($C19:$BJ19,$C$2:$BJ$2,BM$2) -> 3067.6701 | BN19: =AVERAGEIFS($C19:$BJ19,$C$2:$BJ$2,BN$2) -> 3527.8206 | BO19: =AVERAGEIFS($C19:$BJ19,$C$2:$BJ$2,BO$2) -> 4056.9937 | BP19: =AVERAGEIFS($C19:$BJ19,$C$2:$BJ$2,BP$2) -> 4665.5427 | BQ19: =AVERAGE(BL19,BM19,BN19,BO19,BP19) -> 3597.1132
A21: CR MAU -> Order placed | B21: % | C21: =Assumptions!$B$15 -> 0.03 | D21: =C21 -> 0.03 | E21: =D21 -> 0.03 | F21: =E21 -> 0.03 | G21: =F21 -> 0.03 | H21: =G21 -> 0.03 | I21: =H21 -> 0.03 | J21: =I21 -> 0.03 | K21: =J21 -> 0.03 | ... BJ21: =BI21 -> 0.03 | BL21: =AVERAGEIFS($C21:$BJ21,$C$2:$BJ$2,BL$2) -> 0.03 | BM21: =AVERAGEIFS($C21:$BJ21,$C$2:$BJ$2,BM$2) -> 0.03 | BN21: =AVERAGEIFS($C21:$BJ21,$C$2:$BJ$2,BN$2) -> 0.03 | BO21: =AVERAGEIFS($C21:$BJ21,$C$2:$BJ$2,BO$2) -> 0.03 | BP21: =AVERAGEIFS($C21:$BJ21,$C$2:$BJ$2,BP$2) -> 0.03 | BQ21: =AVERAGE(BL21:BP21) -> 0.03
A23: Total Orders | B23: count | C23: =C17*1000000*C21 -> 243000 | D23: =D17*1000000*D21 -> 243990.01 | E23: =E17*1000000*E21 -> 285814.73 | F23: =F17*1000000*F21 -> 300644.85 | G23: =G17*1000000*G21 -> 219541.61 | H23: =H17*1000000*H21 -> 275545.07 | I23: =I17*1000000*I21 -> 249000.9 | J23: =J17*1000000*J21 -> 250015.36 | ... BJ23: =BJ17*1000000*BJ21 -> 411837.35 | BL23: =SUMIF($C$2:$BJ$2,BL$2,$C23:$BJ23) -> 3316525.2 | BM23: =SUMIF($C$2:$BJ$2,BM$2,$C23:$BJ23) -> 3482351.4 | BN23: =SUMIF($C$2:$BJ$2,BN$2,$C23:$BJ23) -> 3656469 | BO23: =SUMIF($C$2:$BJ$2,BO$2,$C23:$BJ23) -> 3839292.5 | BP23: =SUMIF($C$2:$BJ$2,BP$2,$C23:$BJ23) -> 4031257.1 | BQ23: =BL23+BM23+BN23+BO23+BP23 -> 18325895
A25: Orders paid | B25: count | C25: =C23*Assumptions!$B$16 -> 89910 | D25: =D23*Assumptions!$B$16 -> 90276.304 | E25: =E23*Assumptions!$B$16 -> 105751.45 | F25: =F23*Assumptions!$B$16 -> 111238.6 | G25: =G23*Assumptions!$B$16 -> 81230.397 | H25: =H23*Assumptions!$B$16 -> 101951.67 | I25: =I23*Assumptions!$B$16 -> 92130.334 | J25: =J23*Assumptions!$B$16 -> 92505.685 | ... BJ25: =BJ23*Assumptions!$B$16 -> 152379.82 | BL25: =SUMIF($C$2:$BJ$2,BL$2,$C25:$BJ25) -> 1227114.3 | BM25: =SUMIF($C$2:$BJ$2,BM$2,$C25:$BJ25) -> 1288470 | BN25: =SUMIF($C$2:$BJ$2,BN$2,$C25:$BJ25) -> 1352893.5 | BO25: =SUMIF($C$2:$BJ$2,BO$2,$C25:$BJ25) -> 1420538.2 | BP25: =SUMIF($C$2:$BJ$2,BP$2,$C25:$BJ25) -> 1491565.1 | BQ25: =BL25+BM25+BN25+BO25+BP25 -> 6780581.2
A27: Share of Canceled | B27: % | C27: =Assumptions!$B$17 -> 0.1 | D27: =$C$27 -> 0.1 | E27: =$C$27 -> 0.1 | F27: =$C$27 -> 0.1 | G27: =$C$27 -> 0.1 | H27: =$C$27 -> 0.1 | I27: =$C$27 -> 0.1 | J27: =$C$27 -> 0.1 | K27: =$C$27 -> 0.1 | ... BJ27: =$C$27 -> 0.1 | BL27: =AVERAGEIFS($C27:$BJ27,$C$2:$BJ$2,BL$2) -> 0.1 | BM27: =AVERAGEIFS($C27:$BJ27,$C$2:$BJ$2,BM$2) -> 0.1 | BN27: =AVERAGEIFS($C27:$BJ27,$C$2:$BJ$2,BN$2) -> 0.1 | BO27: =AVERAGEIFS($C27:$BJ27,$C$2:$BJ$2,BO$2) -> 0.1 | BP27: =AVERAGEIFS($C27:$BJ27,$C$2:$BJ$2,BP$2) -> 0.1 | BQ27: =AVERAGE(BL27:BP27) -> 0.1
A29: Orders Fulfilled | B29: count | C29: =C25*(1-C27) -> 80919 | D29: =D25*(1-D27) -> 81248.674 | E29: =E25*(1-E27) -> 95176.306 | F29: =F25*(1-F27) -> 100114.74 | G29: =G25*(1-G27) -> 73107.357 | H29: =H25*(1-H27) -> 91756.507 | I29: =I25*(1-I27) -> 82917.301 | J29: =J25*(1-J27) -> 83255.116 | ... BJ29: =BJ25*(1-BJ27) -> 137141.84 | BL29: =SUMIF($C$2:$BJ$2,BL$2,$C29:$BJ29) -> 1104402.9 | BM29: =SUMIF($C$2:$BJ$2,BM$2,$C29:$BJ29) -> 1159623 | BN29: =SUMIF($C$2:$BJ$2,BN$2,$C29:$BJ29) -> 1217604.2 | BO29: =SUMIF($C$2:$BJ$2,BO$2,$C29:$BJ29) -> 1278484.4 | BP29: =SUMIF($C$2:$BJ$2,BP$2,$C29:$BJ29) -> 1342408.6 | BQ29: =BL29+BM29+BN29+BO29+BP29 -> 6102523.1
A31: GMV | B31: mln Rub | C31: =C29*C19/1000000 -> 202.2975 | D31: =D29*D19/1000000 -> 205.50124 | E31: =E29*E19/1000000 -> 243.54833 | F31: =F29*F19/1000000 -> 259.18656 | G31: =G29*G19/1000000 -> 191.48454 | H31: =H29*H19/1000000 -> 243.14629 | I31: =I29*I19/1000000 -> 222.29725 | J31: =J29*J19/1000000 -> 225.81772 | ... BJ31: =BJ29*BJ19/1000000 -> 681.61795 | BL31: =SUMIF($C$2:$BJ$2,BL$2,$C31:$BJ31) -> 2955.2549 | BM31: =SUMIF($C$2:$BJ$2,BM$2,$C31:$BJ31) -> 3568.4704 | BN31: =SUMIF($C$2:$BJ$2,BN$2,$C31:$BJ31) -> 4308.9279 | BO31: =SUMIF($C$2:$BJ$2,BO$2,$C31:$BJ31) -> 5203.0305 | BP31: =SUMIF($C$2:$BJ$2,BP$2,$C31:$BJ31) -> 6282.6593 | BQ31: =BL31+BM31+BN31+BO31+BP31 -> 22318.343
A33: Take Rate | B33: % | C33: =Assumptions!$B$19 -> 0.07 | D33: =$C$33 -> 0.07 | E33: =$C$33 -> 0.07 | F33: =$C$33 -> 0.07 | G33: =$C$33 -> 0.07 | H33: =$C$33 -> 0.07 | I33: =$C$33 -> 0.07 | J33: =$C$33 -> 0.07 | K33: =$C$33 -> 0.07 | ... BJ33: =$C$33 -> 0.07 | BL33: =AVERAGEIFS($C33:$BJ33,$C$2:$BJ$2,BL$2) -> 0.07 | BM33: =AVERAGEIFS($C33:$BJ33,$C$2:$BJ$2,BM$2) -> 0.07 | BN33: =AVERAGEIFS($C33:$BJ33,$C$2:$BJ$2,BN$2) -> 0.07 | BO33: =AVERAGEIFS($C33:$BJ33,$C$2:$BJ$2,BO$2) -> 0.07 | BP33: =AVERAGEIFS($C33:$BJ33,$C$2:$BJ$2,BP$2) -> 0.07 | BQ33: =AVERAGE(BL33:BP33) -> 0.07
D34: =C34 -> 0
A35: Total Revenue | B35: mln Rub | C35: =C31*C33 -> 14.160825 | D35: =D31*D33 -> 14.385087 | E35: =E31*E33 -> 17.048383 | F35: =F31*F33 -> 18.143059 | G35: =G31*G33 -> 13.403918 | H35: =H31*H33 -> 17.02024 | I35: =I31*I33 -> 15.560807 | J35: =J31*J33 -> 15.80724 | ... BJ35: =BJ31*BJ33 -> 47.713257 | BL35: =SUMIF($C$2:$BJ$2,BL$2,$C35:$BJ35) -> 206.86785 | BM35: =SUMIF($C$2:$BJ$2,BM$2,$C35:$BJ35) -> 249.79292 | BN35: =SUMIF($C$2:$BJ$2,BN$2,$C35:$BJ35) -> 301.62496 | BO35: =SUMIF($C$2:$BJ$2,BO$2,$C35:$BJ35) -> 364.21213 | BP35: =SUMIF($C$2:$BJ$2,BP$2,$C35:$BJ35) -> 439.78615 | BQ35: =BL35+BM35+BN35+BO35+BP35 -> 1562.284
A36: VAS Revenue Baseline | B36: mln Rub | C36: =C17*Assumptions!$B$54*Assumptions!$B$55*Assumptions!$B$56 -> 901.53 | D36: =D17*Assumptions!$B$54*Assumptions!$B$55*Assumptions!$B$56 -> 905.20294 | E36: =E17*Assumptions!$B$54*Assumptions!$B$55*Assumptions!$B$56 -> 1060.3727 | F36: =F17*Assumptions!$B$54*Assumptions!$B$55*Assumptions!$B$56 -> 1115.3924 | G36: =G17*Assumptions!$B$54*Assumptions!$B$55*Assumptions!$B$56 -> 814.49938 | H36: =H17*Assumptions!$B$54*Assumptions!$B$55*Assumptions!$B$56 -> 1022.2722 | I36: =I17*Assumptions!$B$54*Assumptions!$B$55*Assumptions!$B$56 -> 923.79335 | J36: =J17*Assumptions!$B$54*Assumptions!$B$55*Assumptions!$B$56 -> 927.557 | ... BJ36: =BJ17*Assumptions!$B$54*Assumptions!$B$55*Assumptions!$B$56 -> 1527.9166 | BL36: =SUMIF($C$2:$BJ$2,BL$2,$C36:$BJ36) -> 12304.308 | BM36: =SUMIF($C$2:$BJ$2,BM$2,$C36:$BJ36) -> 12919.524 | BN36: =SUMIF($C$2:$BJ$2,BN$2,$C36:$BJ36) -> 13565.5 | BO36: =SUMIF($C$2:$BJ$2,BO$2,$C36:$BJ36) -> 14243.775 | BP36: =SUMIF($C$2:$BJ$2,BP$2,$C36:$BJ36) -> 14955.964 | BQ36: =BL36+BM36+BN36+BO36+BP36 -> 67989.071
A37: Total Revenue Baseline (Tx+VAS) | B37: mln Rub | C37: =C35+C36 -> 915.69083 | D37: =D35+D36 -> 919.58803 | E37: =E35+E36 -> 1077.421 | F37: =F35+F36 -> 1133.5355 | G37: =G35+G36 -> 827.9033 | H37: =H35+H36 -> 1039.2924 | I37: =I35+I36 -> 939.35416 | J37: =J35+J36 -> 943.36424 | ... BJ37: =BJ35+BJ36 -> 1575.6298 | BL37: =SUMIF($C$2:$BJ$2,BL$2,$C37:$BJ37) -> 12511.176 | BM37: =SUMIF($C$2:$BJ$2,BM$2,$C37:$BJ37) -> 13169.317 | BN37: =SUMIF($C$2:$BJ$2,BN$2,$C37:$BJ37) -> 13867.125 | BO37: =SUMIF($C$2:$BJ$2,BO$2,$C37:$BJ37) -> 14607.987 | BP37: =SUMIF($C$2:$BJ$2,BP$2,$C37:$BJ37) -> 15395.75 | BQ37: =BL37+BM37+BN37+BO37+BP37 -> 69551.355
A38: HYPOTHESES
A40: H1 Bundle (Items/Order uplift) | B40: % uplift | C40: =Assumptions!$B$35 -> 0.15 | D40: =Assumptions!$B$35 -> 0.15 | E40: =Assumptions!$B$35 -> 0.15 | F40: =Assumptions!$B$35 -> 0.15 | G40: =Assumptions!$B$35 -> 0.15 | H40: =Assumptions!$B$35 -> 0.15 | I40: =Assumptions!$B$35 -> 0.15 | J40: =Assumptions!$B$35 -> 0.15 | ... AL40: =Assumptions!$B$35 -> 0.15 | AM40: =Assumptions!$B$35*(1-Assumptions!$B$51)^1 -> 0.135 | AN40: =Assumptions!$B$35*(1-Assumptions!$B$51)^1 -> 0.135 | AO40: =Assumptions!$B$35*(1-Assumptions!$B$51)^1 -> 0.135 | AP40: =Assumptions!$B$35*(1-Assumptions!$B$51)^1 -> 0.135 | AQ40: =Assumptions!$B$35*(1-Assumptions!$B$51)^1 -> 0.135 | AR40: =Assumptions!$B$35*(1-Assumptions!$B$51)^1 -> 0.135 | AS40: =Assumptions!$B$35*(1-Assumptions!$B$51)^1 -> 0.135 | AT40: =Assumptions!$B$35*(1-Assumptions!$B$51)^1 -> 0.135 | ... AX40: =Assumptions!$B$35*(1-Assumptions!$B$51)^1 -> 0.135 | AY40: =Assumptions!$B$35*(1-Assumptions!$B$51)^2 -> 0.1215 | AZ40: =Assumptions!$B$35*(1-Assumptions!$B$51)^2 -> 0.1215 | BA40: =Assumptions!$B$35*(1-Assumptions!$B$51)^2 -> 0.1215 | BB40: =Assumptions!$B$35*(1-Assumptions!$B$51)^2 -> 0.1215 | BC40: =Assumptions!$B$35*(1-Assumptions!$B$51)^2 -> 0.1215 | BD40: =Assumptions!$B$35*(1-Assumptions!$B$51)^2 -> 0.1215 | BE40: =Assumptions!$B$35*(1-Assumptions!$B$51)^2 -> 0.1215 | BF40: =Assumptions!$B$35*(1-Assumptions!$B$51)^2 -> 0.1215 | ... BJ40: =Assumptions!$B$35*(1-Assumptions!$B$51)^2 -> 0.1215 | BL40: =AVERAGEIFS($C40:$BJ40,$C$2:$BJ$2,BL$2) -> 0.15 | BM40: =AVERAGEIFS($C40:$BJ40,$C$2:$BJ$2,BM$2) -> 0.15 | BN40: =AVERAGEIFS($C40:$BJ40,$C$2:$BJ$2,BN$2) -> 0.15 | BO40: =AVERAGEIFS($C40:$BJ40,$C$2:$BJ$2,BO$2) -> 0.135 | BP40: =AVERAGEIFS($C40:$BJ40,$C$2:$BJ$2,BP$2) -> 0.1215 | BQ40: =AVERAGE(BL40:BP40) -> 0.1413
A41: H1 Bundle (AOV uplift, secondary) | B41: % uplift | C41: =Assumptions!$B$36 -> 0.1 | D41: =Assumptions!$B$36 -> 0.1 | E41: =Assumptions!$B$36 -> 0.1 | F41: =Assumptions!$B$36 -> 0.1 | G41: =Assumptions!$B$36 -> 0.1 | H41: =Assumptions!$B$36 -> 0.1 | I41: =Assumptions!$B$36 -> 0.1 | J41: =Assumptions!$B$36 -> 0.1 | ... AL41: =Assumptions!$B$36 -> 0.1 | AM41: =Assumptions!$B$36*(1-Assumptions!$B$51)^1 -> 0.09 | AN41: =Assumptions!$B$36*(1-Assumptions!$B$51)^1 -> 0.09 | AO41: =Assumptions!$B$36*(1-Assumptions!$B$51)^1 -> 0.09 | AP41: =Assumptions!$B$36*(1-Assumptions!$B$51)^1 -> 0.09 | AQ41: =Assumptions!$B$36*(1-Assumptions!$B$51)^1 -> 0.09 | AR41: =Assumptions!$B$36*(1-Assumptions!$B$51)^1 -> 0.09 | AS41: =Assumptions!$B$36*(1-Assumptions!$B$51)^1 -> 0.09 | AT41: =Assumptions!$B$36*(1-Assumptions!$B$51)^1 -> 0.09 | ... AX41: =Assumptions!$B$36*(1-Assumptions!$B$51)^1 -> 0.09 | AY41: =Assumptions!$B$36*(1-Assumptions!$B$51)^2 -> 0.081 | AZ41: =Assumptions!$B$36*(1-Assumptions!$B$51)^2 -> 0.081 | BA41: =Assumptions!$B$36*(1-Assumptions!$B$51)^2 -> 0.081 | BB41: =Assumptions!$B$36*(1-Assumptions!$B$51)^2 -> 0.081 | BC41: =Assumptions!$B$36*(1-Assumptions!$B$51)^2 -> 0.081 | BD41: =Assumptions!$B$36*(1-Assumptions!$B$51)^2 -> 0.081 | BE41: =Assumptions!$B$36*(1-Assumptions!$B$51)^2 -> 0.081 | BF41: =Assumptions!$B$36*(1-Assumptions!$B$51)^2 -> 0.081 | ... BJ41: =Assumptions!$B$36*(1-Assumptions!$B$51)^2 -> 0.081 | BL41: =AVERAGEIFS($C41:$BJ41,$C$2:$BJ$2,BL$2) -> 0.1 | BM41: =AVERAGEIFS($C41:$BJ41,$C$2:$BJ$2,BM$2) -> 0.1 | BN41: =AVERAGEIFS($C41:$BJ41,$C$2:$BJ$2,BN$2) -> 0.1 | BO41: =AVERAGEIFS($C41:$BJ41,$C$2:$BJ$2,BO$2) -> 0.09 | BP41: =AVERAGEIFS($C41:$BJ41,$C$2:$BJ$2,BP$2) -> 0.081 | BQ41: =AVERAGE(BL41:BP41) -> 0.0942
A42: H1 Retention decay | B42: % | C42: =Assumptions!$B$37 -> -0.01 | D42: =Assumptions!$B$37 -> -0.01 | E42: =Assumptions!$B$37 -> -0.01 | F42: =Assumptions!$B$37 -> -0.01 | G42: =Assumptions!$B$37 -> -0.01 | H42: =Assumptions!$B$37 -> -0.01 | I42: =Assumptions!$B$37 -> -0.01 | J42: =Assumptions!$B$37 -> -0.01 | ... BJ42: =Assumptions!$B$37 -> -0.01 | BL42: =AVERAGEIFS($C42:$BJ42,$C$2:$BJ$2,BL$2) -> -0.01 | BM42: =AVERAGEIFS($C42:$BJ42,$C$2:$BJ$2,BM$2) -> -0.01 | BN42: =AVERAGEIFS($C42:$BJ42,$C$2:$BJ$2,BN$2) -> -0.01 | BO42: =AVERAGEIFS($C42:$BJ42,$C$2:$BJ$2,BO$2) -> -0.01 | BP42: =AVERAGEIFS($C42:$BJ42,$C$2:$BJ$2,BP$2) -> -0.01 | BQ42: =AVERAGE(BL42:BP42) -> -0.01
A43: H2 CPA (Take Rate uplift) | B43: % uplift | C43: =Assumptions!$B$44 -> 0.07 | D43: =Assumptions!$B$44 -> 0.07 | E43: =Assumptions!$B$44 -> 0.07 | F43: =Assumptions!$B$44 -> 0.07 | G43: =Assumptions!$B$44 -> 0.07 | H43: =Assumptions!$B$44 -> 0.07 | I43: =Assumptions!$B$44 -> 0.07 | J43: =Assumptions!$B$44 -> 0.07 | ... AL43: =Assumptions!$B$44 -> 0.07 | AM43: =Assumptions!$B$44*(1-Assumptions!$B$51)^1 -> 0.063 | AN43: =Assumptions!$B$44*(1-Assumptions!$B$51)^1 -> 0.063 | AO43: =Assumptions!$B$44*(1-Assumptions!$B$51)^1 -> 0.063 | AP43: =Assumptions!$B$44*(1-Assumptions!$B$51)^1 -> 0.063 | AQ43: =Assumptions!$B$44*(1-Assumptions!$B$51)^1 -> 0.063 | AR43: =Assumptions!$B$44*(1-Assumptions!$B$51)^1 -> 0.063 | AS43: =Assumptions!$B$44*(1-Assumptions!$B$51)^1 -> 0.063 | AT43: =Assumptions!$B$44*(1-Assumptions!$B$51)^1 -> 0.063 | ... AX43: =Assumptions!$B$44*(1-Assumptions!$B$51)^1 -> 0.063 | AY43: =Assumptions!$B$44*(1-Assumptions!$B$51)^2 -> 0.0567 | AZ43: =Assumptions!$B$44*(1-Assumptions!$B$51)^2 -> 0.0567 | BA43: =Assumptions!$B$44*(1-Assumptions!$B$51)^2 -> 0.0567 | BB43: =Assumptions!$B$44*(1-Assumptions!$B$51)^2 -> 0.0567 | BC43: =Assumptions!$B$44*(1-Assumptions!$B$51)^2 -> 0.0567 | BD43: =Assumptions!$B$44*(1-Assumptions!$B$51)^2 -> 0.0567 | BE43: =Assumptions!$B$44*(1-Assumptions!$B$51)^2 -> 0.0567 | BF43: =Assumptions!$B$44*(1-Assumptions!$B$51)^2 -> 0.0567 | ... BJ43: =Assumptions!$B$44*(1-Assumptions!$B$51)^2 -> 0.0567 | BL43: =AVERAGEIFS($C43:$BJ43,$C$2:$BJ$2,BL$2) -> 0.07 | BM43: =AVERAGEIFS($C43:$BJ43,$C$2:$BJ$2,BM$2) -> 0.07 | BN43: =AVERAGEIFS($C43:$BJ43,$C$2:$BJ$2,BN$2) -> 0.07 | BO43: =AVERAGEIFS($C43:$BJ43,$C$2:$BJ$2,BO$2) -> 0.063 | BP43: =AVERAGEIFS($C43:$BJ43,$C$2:$BJ$2,BP$2) -> 0.0567 | BQ43: =AVERAGE(BL43:BP43) -> 0.06594
A44: H2 Seller churn risk | B44: % | C44: =Assumptions!$B$45 -> 0.02 | D44: =Assumptions!$B$45 -> 0.02 | E44: =Assumptions!$B$45 -> 0.02 | F44: =Assumptions!$B$45 -> 0.02 | G44: =Assumptions!$B$45 -> 0.02 | H44: =Assumptions!$B$45 -> 0.02 | I44: =Assumptions!$B$45 -> 0.02 | J44: =Assumptions!$B$45 -> 0.02 | ... BJ44: =Assumptions!$B$45 -> 0.02 | BL44: =AVERAGEIFS($C44:$BJ44,$C$2:$BJ$2,BL$2) -> 0.02 | BM44: =AVERAGEIFS($C44:$BJ44,$C$2:$BJ$2,BM$2) -> 0.02 | BN44: =AVERAGEIFS($C44:$BJ44,$C$2:$BJ$2,BN$2) -> 0.02 | BO44: =AVERAGEIFS($C44:$BJ44,$C$2:$BJ$2,BO$2) -> 0.02 | BP44: =AVERAGEIFS($C44:$BJ44,$C$2:$BJ$2,BP$2) -> 0.02 | BQ44: =AVERAGE(BL44:BP44) -> 0.02
A45: H2 Off-platform risk | B45: % | C45: =Assumptions!$B$46 -> 0.01 | D45: =Assumptions!$B$46 -> 0.01 | E45: =Assumptions!$B$46 -> 0.01 | F45: =Assumptions!$B$46 -> 0.01 | G45: =Assumptions!$B$46 -> 0.01 | H45: =Assumptions!$B$46 -> 0.01 | I45: =Assumptions!$B$46 -> 0.01 | J45: =Assumptions!$B$46 -> 0.01 | ... BJ45: =Assumptions!$B$46 -> 0.01 | BL45: =AVERAGEIFS($C45:$BJ45,$C$2:$BJ$2,BL$2) -> 0.01 | BM45: =AVERAGEIFS($C45:$BJ45,$C$2:$BJ$2,BM$2) -> 0.01 | BN45: =AVERAGEIFS($C45:$BJ45,$C$2:$BJ$2,BN$2) -> 0.01 | BO45: =AVERAGEIFS($C45:$BJ45,$C$2:$BJ$2,BO$2) -> 0.01 | BP45: =AVERAGEIFS($C45:$BJ45,$C$2:$BJ$2,BP$2) -> 0.01 | BQ45: =AVERAGE(BL45:BP45) -> 0.01
A46: H2 Seller price inflation | B46: % | C46: =Assumptions!$B$48 -> 0.02 | D46: =Assumptions!$B$48 -> 0.02 | E46: =Assumptions!$B$48 -> 0.02 | F46: =Assumptions!$B$48 -> 0.02 | G46: =Assumptions!$B$48 -> 0.02 | H46: =Assumptions!$B$48 -> 0.02 | I46: =Assumptions!$B$48 -> 0.02 | J46: =Assumptions!$B$48 -> 0.02 | ... BJ46: =Assumptions!$B$48 -> 0.02 | BL46: =AVERAGEIFS($C46:$BJ46,$C$2:$BJ$2,BL$2) -> 0.02 | BM46: =AVERAGEIFS($C46:$BJ46,$C$2:$BJ$2,BM$2) -> 0.02 | BN46: =AVERAGEIFS($C46:$BJ46,$C$2:$BJ$2,BN$2) -> 0.02 | BO46: =AVERAGEIFS($C46:$BJ46,$C$2:$BJ$2,BO$2) -> 0.02 | BP46: =AVERAGEIFS($C46:$BJ46,$C$2:$BJ$2,BP$2) -> 0.02 | BQ46: =AVERAGE(BL46:BP46) -> 0.02
A48: H1 % раскатки | B48: % | C48: 0.1 | D48: 0.1 | E48: 0.1 | F48: 0.1 | G48: 0.1 | H48: 0.1 | I48: 0.1 | J48: 0.1 | K48: 0.1 | L48: 0.1 | M48: 0.1 | N48: 0.1 | O48: 0.5 | P48: 0.5 | Q48: 0.5 | R48: 0.5 | S48: 0.5 | T48: 0.5 | U48: 0.5 | V48: 0.5 | W48: 0.5 | X48: 0.5 | Y48: 0.5 | Z48: 0.5 | AA48: 1 | AB48: 1 | AC48: 1 | AD48: 1 | AE48: 1 | AF48: 1 | AG48: 1 | AH48: 1 | AI48: 1 | AJ48: 1 | AK48: 1 | AL48: 1 | AM48: 1 | AN48: 1 | AO48: 1 | AP48: 1 | AQ48: 1 | AR48: 1 | AS48: 1 | AT48: 1 | AU48: 1 | AV48: 1 | AW48: 1 | AX48: 1 | AY48: 1 | AZ48: 1 | BA48: 1 | BB48: 1 | BC48: 1 | BD48: 1 | BE48: 1 | BF48: 1 | BG48: 1 | BH48: 1 | BI48: 1 | BJ48: 1 | BL48: =AVERAGEIFS($C48:$BJ48,$C$2:$BJ$2,BL$2) -> 0.1 | BM48: =AVERAGEIFS($C48:$BJ48,$C$2:$BJ$2,BM$2) -> 0.5 | BN48: =AVERAGEIFS($C48:$BJ48,$C$2:$BJ$2,BN$2) -> 1 | BO48: =AVERAGEIFS($C48:$BJ48,$C$2:$BJ$2,BO$2) -> 1 | BP48: =AVERAGEIFS($C48:$BJ48,$C$2:$BJ$2,BP$2) -> 1 | BQ48: =AVERAGE(BL48:BP48) -> 0.72
A49: H2 % раскатки | B49: % | C49: 0.2 | D49: 0.2 | E49: 0.2 | F49: 0.2 | G49: 0.2 | H49: 0.2 | I49: 0.2 | J49: 0.2 | K49: 0.2 | L49: 0.2 | M49: 0.2 | N49: 0.2 | O49: 0.7 | P49: 0.7 | Q49: 0.7 | R49: 0.7 | S49: 0.7 | T49: 0.7 | U49: 0.7 | V49: 0.7 | W49: 0.7 | X49: 0.7 | Y49: 0.7 | Z49: 0.7 | AA49: 1 | AB49: 1 | AC49: 1 | AD49: 1 | AE49: 1 | AF49: 1 | AG49: 1 | AH49: 1 | AI49: 1 | AJ49: 1 | AK49: 1 | AL49: 1 | AM49: 1 | AN49: 1 | AO49: 1 | AP49: 1 | AQ49: 1 | AR49: 1 | AS49: 1 | AT49: 1 | AU49: 1 | AV49: 1 | AW49: 1 | AX49: 1 | AY49: 1 | AZ49: 1 | BA49: 1 | BB49: 1 | BC49: 1 | BD49: 1 | BE49: 1 | BF49: 1 | BG49: 1 | BH49: 1 | BI49: 1 | BJ49: 1 | BL49: =AVERAGEIFS($C49:$BJ49,$C$2:$BJ$2,BL$2) -> 0.2 | BM49: =AVERAGEIFS($C49:$BJ49,$C$2:$BJ$2,BM$2) -> 0.7 | BN49: =AVERAGEIFS($C49:$BJ49,$C$2:$BJ$2,BN$2) -> 1 | BO49: =AVERAGEIFS($C49:$BJ49,$C$2:$BJ$2,BO$2) -> 1 | BP49: =AVERAGEIFS($C49:$BJ49,$C$2:$BJ$2,BP$2) -> 1 | BQ49: =AVERAGE(BL49:BP49) -> 0.78
A50: Cross-hypothesis synergy | B50: % | C50: =Assumptions!$B$52 -> 0.02 | D50: =Assumptions!$B$52 -> 0.02 | E50: =Assumptions!$B$52 -> 0.02 | F50: =Assumptions!$B$52 -> 0.02 | G50: =Assumptions!$B$52 -> 0.02 | H50: =Assumptions!$B$52 -> 0.02 | I50: =Assumptions!$B$52 -> 0.02 | J50: =Assumptions!$B$52 -> 0.02 | ... BJ50: =Assumptions!$B$52 -> 0.02 | BL50: =AVERAGEIFS($C50:$BJ50,$C$2:$BJ$2,BL$2) -> 0.02 | BM50: =AVERAGEIFS($C50:$BJ50,$C$2:$BJ$2,BM$2) -> 0.02 | BN50: =AVERAGEIFS($C50:$BJ50,$C$2:$BJ$2,BN$2) -> 0.02 | BO50: =AVERAGEIFS($C50:$BJ50,$C$2:$BJ$2,BO$2) -> 0.02 | BP50: =AVERAGEIFS($C50:$BJ50,$C$2:$BJ$2,BP$2) -> 0.02 | BQ50: =AVERAGE(BL50:BP50) -> 0.02
A52: CASE TOTAL
A53: H2 AI Reco % раскатки | B53: % | C53: 0.15 | D53: 0.15 | E53: 0.15 | F53: 0.15 | G53: 0.15 | H53: 0.15 | I53: 0.15 | J53: 0.15 | K53: 0.15 | L53: 0.15 | M53: 0.15 | N53: 0.15 | O53: 0.6 | P53: 0.6 | Q53: 0.6 | R53: 0.6 | S53: 0.6 | T53: 0.6 | U53: 0.6 | V53: 0.6 | W53: 0.6 | X53: 0.6 | Y53: 0.6 | Z53: 0.6 | AA53: 1 | AB53: 1 | AC53: 1 | AD53: 1 | AE53: 1 | AF53: 1 | AG53: 1 | AH53: 1 | AI53: 1 | AJ53: 1 | AK53: 1 | AL53: 1 | AM53: 1 | AN53: 1 | AO53: 1 | AP53: 1 | AQ53: 1 | AR53: 1 | AS53: 1 | AT53: 1 | AU53: 1 | AV53: 1 | AW53: 1 | AX53: 1 | AY53: 1 | AZ53: 1 | BA53: 1 | BB53: 1 | BC53: 1 | BD53: 1 | BE53: 1 | BF53: 1 | BG53: 1 | BH53: 1 | BI53: 1 | BJ53: 1 | BL53: =AVERAGEIFS($C53:$BJ53,$C$2:$BJ$2,BL$2) -> 0.15 | BM53: =AVERAGEIFS($C53:$BJ53,$C$2:$BJ$2,BM$2) -> 0.6 | BN53: =AVERAGEIFS($C53:$BJ53,$C$2:$BJ$2,BN$2) -> 1 | BO53: =AVERAGEIFS($C53:$BJ53,$C$2:$BJ$2,BO$2) -> 1 | BP53: =AVERAGEIFS($C53:$BJ53,$C$2:$BJ$2,BP$2) -> 1 | BQ53: =AVERAGE(BL53:BP53) -> 0.75
A54: Monthly Active Users | B54: mln | C54: =C17*(1+C42*C48)*(1+Assumptions!$B$61*C53) -> 8.1525893 | D54: =D17*(1+D42*D48)*(1+Assumptions!$B$61*D53) -> 8.1858039 | E54: =E17*(1+E42*E48)*(1+Assumptions!$B$61*E53) -> 9.5890129 | F54: =F17*(1+F42*F48)*(1+Assumptions!$B$61*F53) -> 10.08656 | G54: =G17*(1+G42*G48)*(1+Assumptions!$B$61*G53) -> 7.3655662 | H54: =H17*(1+H42*H48)*(1+Assumptions!$B$61*H53) -> 9.2444681 | I54: =I17*(1+I42*I48)*(1+Assumptions!$B$61*I53) -> 8.3539181 | J54: =J17*(1+J42*J48)*(1+Assumptions!$B$61*J53) -> 8.387953 | ... BJ54: =BJ17*(1+BJ42*BJ48)*(1+Assumptions!$B$61*BJ53) -> 14.270164 | BL54: =AVERAGEIFS($C54:$BJ54,$C$2:$BJ$2,BL$2) -> 9.2723826 | BM54: =AVERAGEIFS($C54:$BJ54,$C$2:$BJ$2,BM$2) -> 9.9135774 | BN54: =AVERAGEIFS($C54:$BJ54,$C$2:$BJ$2,BN$2) -> 10.558054 | BO54: =AVERAGEIFS($C54:$BJ54,$C$2:$BJ$2,BO$2) -> 11.085957 | BP54: =AVERAGEIFS($C54:$BJ54,$C$2:$BJ$2,BP$2) -> 11.640255 | BQ54: =AVERAGE(BL54:BP54) -> 10.494045
A55: Items per Order | B55: count | C55: =Assumptions!$B$34*(1+C40*C48) -> 1.015 | D55: =Assumptions!$B$34*(1+D40*D48) -> 1.015 | E55: =Assumptions!$B$34*(1+E40*E48) -> 1.015 | F55: =Assumptions!$B$34*(1+F40*F48) -> 1.015 | G55: =Assumptions!$B$34*(1+G40*G48) -> 1.015 | H55: =Assumptions!$B$34*(1+H40*H48) -> 1.015 | I55: =Assumptions!$B$34*(1+I40*I48) -> 1.015 | J55: =Assumptions!$B$34*(1+J40*J48) -> 1.015 | ... BJ55: =Assumptions!$B$34*(1+BJ40*BJ48) -> 1.1215 | BL55: =AVERAGEIFS($C55:$BJ55,$C$2:$BJ$2,BL$2) -> 1.015 | BM55: =AVERAGEIFS($C55:$BJ55,$C$2:$BJ$2,BM$2) -> 1.075 | BN55: =AVERAGEIFS($C55:$BJ55,$C$2:$BJ$2,BN$2) -> 1.15 | BO55: =AVERAGEIFS($C55:$BJ55,$C$2:$BJ$2,BO$2) -> 1.135 | BP55: =AVERAGEIFS($C55:$BJ55,$C$2:$BJ$2,BP$2) -> 1.1215 | BQ55: =AVERAGE(BL55:BP55) -> 1.0993
A56: AOV | B56: Rub | C56: =C19*(1+C41*C48) -> 2525 | D56: =D19*(1+D41*D48) -> 2554.5802 | E56: =E19*(1+E41*E48) -> 2584.5069 | F56: =F19*(1+F41*F48) -> 2614.7841 | G56: =G19*(1+G41*G48) -> 2645.4161 | H56: =H19*(1+H41*H48) -> 2676.407 | I56: =I19*(1+I41*I48) -> 2707.7608 | J56: =J19*(1+J41*J48) -> 2739.482 | ... BJ56: =BJ19*(1+BJ41*BJ48) -> 5372.7515 | BL56: =AVERAGEIFS($C56:$BJ56,$C$2:$BJ$2,BL$2) -> 2694.2146 | BM56: =AVERAGEIFS($C56:$BJ56,$C$2:$BJ$2,BM$2) -> 3221.0536 | BN56: =AVERAGEIFS($C56:$BJ56,$C$2:$BJ$2,BN$2) -> 3880.6026 | BO56: =AVERAGEIFS($C56:$BJ56,$C$2:$BJ$2,BO$2) -> 4422.1231 | BP56: =AVERAGEIFS($C56:$BJ56,$C$2:$BJ$2,BP$2) -> 5043.4517 | BQ56: =AVERAGE(BL56:BP56) -> 3852.2891
A57: CR MAU -> Order placed | B57: % | C57: =C21 -> 0.03 | D57: =D21 -> 0.03 | E57: =E21 -> 0.03 | F57: =F21 -> 0.03 | G57: =G21 -> 0.03 | H57: =H21 -> 0.03 | I57: =I21 -> 0.03 | J57: =J21 -> 0.03 | ... BJ57: =BJ21 -> 0.03 | BL57: =AVERAGEIFS($C57:$BJ57,$C$2:$BJ$2,BL$2) -> 0.03 | BM57: =AVERAGEIFS($C57:$BJ57,$C$2:$BJ$2,BM$2) -> 0.03 | BN57: =AVERAGEIFS($C57:$BJ57,$C$2:$BJ$2,BN$2) -> 0.03 | BO57: =AVERAGEIFS($C57:$BJ57,$C$2:$BJ$2,BO$2) -> 0.03 | BP57: =AVERAGEIFS($C57:$BJ57,$C$2:$BJ$2,BP$2) -> 0.03 | BQ57: =AVERAGE(BL57:BP57) -> 0.03
A58: Total Orders | B58: count | C58: =C54*1000000*C57*(1-(1-Assumptions!$B$38)*C48) -> 243843.94 | D58: =D54*1000000*D57*(1-(1-Assumptions!$B$38)*D48) -> 244837.39 | E58: =E54*1000000*E57*(1-(1-Assumptions!$B$38)*E48) -> 286807.37 | F58: =F54*1000000*F57*(1-(1-Assumptions!$B$38)*F48) -> 301689 | G58: =G54*1000000*G57*(1-(1-Assumptions!$B$38)*G48) -> 220304.09 | H58: =H54*1000000*H57*(1-(1-Assumptions!$B$38)*H48) -> 276502.04 | I58: =I54*1000000*I57*(1-(1-Assumptions!$B$38)*I48) -> 249865.69 | J58: =J54*1000000*J57*(1-(1-Assumptions!$B$38)*J48) -> 250883.67 | ... BJ58: =BJ54*1000000*BJ57*(1-(1-Assumptions!$B$38)*BJ48) -> 415261.78 | BL58: =SUMIF($C$2:$BJ$2,BL$2,$C58:$BJ58) -> 3328043.5 | BM58: =SUMIF($C$2:$BJ$2,BM$2,$C58:$BJ58) -> 3515354.6 | BN58: =SUMIF($C$2:$BJ$2,BN$2,$C58:$BJ58) -> 3686872.6 | BO58: =SUMIF($C$2:$BJ$2,BO$2,$C58:$BJ58) -> 3871216.2 | BP58: =SUMIF($C$2:$BJ$2,BP$2,$C58:$BJ58) -> 4064777 | BQ58: =BL58+BM58+BN58+BO58+BP58 -> 18466264
A59: Orders Paid | B59: count | C59: =C58*Assumptions!$B$16 -> 90222.259 | D59: =D58*Assumptions!$B$16 -> 90589.836 | E59: =E58*Assumptions!$B$16 -> 106118.73 | F59: =F58*Assumptions!$B$16 -> 111624.93 | G59: =G58*Assumptions!$B$16 -> 81512.512 | H59: =H58*Assumptions!$B$16 -> 102305.75 | I59: =I58*Assumptions!$B$16 -> 92450.305 | J59: =J58*Assumptions!$B$16 -> 92826.959 | ... BJ59: =BJ58*Assumptions!$B$16 -> 153646.86 | BL59: =SUMIF($C$2:$BJ$2,BL$2,$C59:$BJ59) -> 1231376.1 | BM59: =SUMIF($C$2:$BJ$2,BM$2,$C59:$BJ59) -> 1300681.2 | BN59: =SUMIF($C$2:$BJ$2,BN$2,$C59:$BJ59) -> 1364142.8 | BO59: =SUMIF($C$2:$BJ$2,BO$2,$C59:$BJ59) -> 1432350 | BP59: =SUMIF($C$2:$BJ$2,BP$2,$C59:$BJ59) -> 1503967.5 | BQ59: =BL59+BM59+BN59+BO59+BP59 -> 6832517.6
A60: Share of Canceled | B60: % | C60: =Assumptions!$B$17 -> 0.1 | D60: =Assumptions!$B$17 -> 0.1 | E60: =Assumptions!$B$17 -> 0.1 | F60: =Assumptions!$B$17 -> 0.1 | G60: =Assumptions!$B$17 -> 0.1 | H60: =Assumptions!$B$17 -> 0.1 | I60: =Assumptions!$B$17 -> 0.1 | J60: =Assumptions!$B$17 -> 0.1 | ... BJ60: =Assumptions!$B$17 -> 0.1 | BL60: =AVERAGEIFS($C60:$BJ60,$C$2:$BJ$2,BL$2) -> 0.1 | BM60: =AVERAGEIFS($C60:$BJ60,$C$2:$BJ$2,BM$2) -> 0.1 | BN60: =AVERAGEIFS($C60:$BJ60,$C$2:$BJ$2,BN$2) -> 0.1 | BO60: =AVERAGEIFS($C60:$BJ60,$C$2:$BJ$2,BO$2) -> 0.1 | BP60: =AVERAGEIFS($C60:$BJ60,$C$2:$BJ$2,BP$2) -> 0.1 | BQ60: =AVERAGE(BL60:BP60) -> 0.1
A61: Orders Fulfilled | B61: count | C61: =C59*(1-C60) -> 81200.034 | D61: =D59*(1-D60) -> 81530.852 | E61: =E59*(1-E60) -> 95506.856 | F61: =F59*(1-F60) -> 100462.44 | G61: =G59*(1-G60) -> 73361.261 | H61: =H59*(1-H60) -> 92075.179 | I61: =I59*(1-I60) -> 83205.275 | J61: =J59*(1-J60) -> 83544.263 | ... BJ61: =BJ59*(1-BJ60) -> 138282.17 | BL61: =SUMIF($C$2:$BJ$2,BL$2,$C61:$BJ61) -> 1108238.5 | BM61: =SUMIF($C$2:$BJ$2,BM$2,$C61:$BJ61) -> 1170613.1 | BN61: =SUMIF($C$2:$BJ$2,BN$2,$C61:$BJ61) -> 1227728.6 | BO61: =SUMIF($C$2:$BJ$2,BO$2,$C61:$BJ61) -> 1289115 | BP61: =SUMIF($C$2:$BJ$2,BP$2,$C61:$BJ61) -> 1353570.7 | BQ61: =BL61+BM61+BN61+BO61+BP61 -> 6149265.9
A62: GMV | B62: mln Rub | C62: =C61*C56/1000000*(1+IF(C$2=2030,Assumptions!$B$60,IF(C$2=2029,Assumptions!$B$59,Assumptions!$B$58))*C53)*(1-Assumptions!$B$62*C53) -> 208.69987 | D62: =D61*D56/1000000*(1+IF(D$2=2030,Assumptions!$B$60,IF(D$2=2029,Assumptions!$B$59,Assumptions!$B$58))*D53)*(1-Assumptions!$B$62*D53) -> 212.005 | E62: =E61*E56/1000000*(1+IF(E$2=2030,Assumptions!$B$60,IF(E$2=2029,Assumptions!$B$59,Assumptions!$B$58))*E53)*(1-Assumptions!$B$62*E53) -> 251.25622 | F62: =F61*F56/1000000*(1+IF(F$2=2030,Assumptions!$B$60,IF(F$2=2029,Assumptions!$B$59,Assumptions!$B$58))*F53)*(1-Assumptions!$B$62*F53) -> 267.38937 | G62: =G61*G56/1000000*(1+IF(G$2=2030,Assumptions!$B$60,IF(G$2=2029,Assumptions!$B$59,Assumptions!$B$58))*G53)*(1-Assumptions!$B$62*G53) -> 197.54469 | H62: =H61*H56/1000000*(1+IF(H$2=2030,Assumptions!$B$60,IF(H$2=2029,Assumptions!$B$59,Assumptions!$B$58))*H53)*(1-Assumptions!$B$62*H53) -> 250.84145 | I62: =I61*I56/1000000*(1+IF(I$2=2030,Assumptions!$B$60,IF(I$2=2029,Assumptions!$B$59,Assumptions!$B$58))*I53)*(1-Assumptions!$B$62*I53) -> 229.33257 | J62: =J61*J56/1000000*(1+IF(J$2=2030,Assumptions!$B$60,IF(J$2=2029,Assumptions!$B$59,Assumptions!$B$58))*J53)*(1-Assumptions!$B$62*J53) -> 232.96446 | ... BJ62: =BJ61*BJ56/1000000*(1+IF(BJ$2=2030,Assumptions!$B$60,IF(BJ$2=2029,Assumptions!$B$59,Assumptions!$B$58))*BJ53)*(1-Assumptions!$B$62*BJ53) -> 808.22812 | BL62: =SUMIF($C$2:$BJ$2,BL$2,$C62:$BJ62) -> 3048.7837 | BM62: =SUMIF($C$2:$BJ$2,BM$2,$C62:$BJ62) -> 4048.6097 | BN62: =SUMIF($C$2:$BJ$2,BN$2,$C62:$BJ62) -> 5331.2337 | BO62: =SUMIF($C$2:$BJ$2,BO$2,$C62:$BJ62) -> 6295.7387 | BP62: =SUMIF($C$2:$BJ$2,BP$2,$C62:$BJ62) -> 7449.6599 | BQ62: =BL62+BM62+BN62+BO62+BP62 -> 26174.026
A63: Take Rate | B63: % | C63: =C33 -> 0.07 | D63: =D33 -> 0.07 | E63: =E33 -> 0.07 | F63: =F33 -> 0.07 | G63: =G33 -> 0.07 | H63: =H33 -> 0.07 | I63: =I33 -> 0.07 | J63: =J33 -> 0.07 | ... BJ63: =BJ33 -> 0.07 | BL63: =AVERAGEIFS($C63:$BJ63,$C$2:$BJ$2,BL$2) -> 0.07 | BM63: =AVERAGEIFS($C63:$BJ63,$C$2:$BJ$2,BM$2) -> 0.07 | BN63: =AVERAGEIFS($C63:$BJ63,$C$2:$BJ$2,BN$2) -> 0.07 | BO63: =AVERAGEIFS($C63:$BJ63,$C$2:$BJ$2,BO$2) -> 0.07 | BP63: =AVERAGEIFS($C63:$BJ63,$C$2:$BJ$2,BP$2) -> 0.07 | BQ63: =AVERAGE(BL63:BP63) -> 0.07
A64: Synergy multiplier | B64: x | C64: =1+C50*MIN(C48,C53) -> 1.002 | D64: =1+D50*MIN(D48,D53) -> 1.002 | E64: =1+E50*MIN(E48,E53) -> 1.002 | F64: =1+F50*MIN(F48,F53) -> 1.002 | G64: =1+G50*MIN(G48,G53) -> 1.002 | H64: =1+H50*MIN(H48,H53) -> 1.002 | I64: =1+I50*MIN(I48,I53) -> 1.002 | J64: =1+J50*MIN(J48,J53) -> 1.002 | ... BJ64: =1+BJ50*MIN(BJ48,BJ53) -> 1.02 | BL64: =AVERAGEIFS($C64:$BJ64,$C$2:$BJ$2,BL$2) -> 1.002 | BM64: =AVERAGEIFS($C64:$BJ64,$C$2:$BJ$2,BM$2) -> 1.01 | BN64: =AVERAGEIFS($C64:$BJ64,$C$2:$BJ$2,BN$2) -> 1.02 | BO64: =AVERAGEIFS($C64:$BJ64,$C$2:$BJ$2,BO$2) -> 1.02 | BP64: =AVERAGEIFS($C64:$BJ64,$C$2:$BJ$2,BP$2) -> 1.02 | BQ64: =AVERAGE(BL64:BP64) -> 1.0144
A65: Transaction Revenue Case | B65: mln Rub | C65: =C62*C63*C64 -> 14.638209 | D65: =D62*D63*D64 -> 14.870031 | E65: =E62*E63*E64 -> 17.623111 | F65: =F62*F63*F64 -> 18.75469 | G65: =G62*G63*G64 -> 13.855785 | H65: =H62*H63*H64 -> 17.594019 | I65: =I62*I63*I64 -> 16.085387 | J65: =J62*J63*J64 -> 16.340127 | ... BJ65: =BJ62*BJ63*BJ64 -> 57.707488 | BL65: =SUMIF($C$2:$BJ$2,BL$2,$C65:$BJ65) -> 213.84169 | BM65: =SUMIF($C$2:$BJ$2,BM$2,$C65:$BJ65) -> 286.23671 | BN65: =SUMIF($C$2:$BJ$2,BN$2,$C65:$BJ65) -> 380.65009 | BO65: =SUMIF($C$2:$BJ$2,BO$2,$C65:$BJ65) -> 449.51574 | BP65: =SUMIF($C$2:$BJ$2,BP$2,$C65:$BJ65) -> 531.90572 | BQ65: =BL65+BM65+BN65+BO65+BP65 -> 1862.1499
A66: VAS Revenue Case | B66: mln Rub | C66: =C36*(1-Assumptions!$B$63*C53) -> 898.82541 | D66: =D36*(1-Assumptions!$B$63*D53) -> 902.48734 | E66: =E36*(1-Assumptions!$B$63*E53) -> 1057.1915 | F66: =F36*(1-Assumptions!$B$63*F53) -> 1112.0462 | G66: =G36*(1-Assumptions!$B$63*G53) -> 812.05589 | H66: =H36*(1-Assumptions!$B$63*H53) -> 1019.2054 | I66: =I36*(1-Assumptions!$B$63*I53) -> 921.02197 | J66: =J36*(1-Assumptions!$B$63*J53) -> 924.77433 | ... BJ66: =BJ36*(1-Assumptions!$B$63*BJ53) -> 1497.3582 | BL66: =SUMIF($C$2:$BJ$2,BL$2,$C66:$BJ66) -> 12267.395 | BM66: =SUMIF($C$2:$BJ$2,BM$2,$C66:$BJ66) -> 12764.49 | BN66: =SUMIF($C$2:$BJ$2,BN$2,$C66:$BJ66) -> 13294.19 | BO66: =SUMIF($C$2:$BJ$2,BO$2,$C66:$BJ66) -> 13958.9 | BP66: =SUMIF($C$2:$BJ$2,BP$2,$C66:$BJ66) -> 14656.845 | BQ66: =BL66+BM66+BN66+BO66+BP66 -> 66941.819
A67: Total Revenue Case (Tx+VAS) | B67: mln Rub | C67: =C65+C66 -> 913.46362 | D67: =D65+D66 -> 917.35737 | E67: =E65+E66 -> 1074.8147 | F67: =F65+F66 -> 1130.8009 | G67: =G65+G66 -> 825.91167 | H67: =H65+H66 -> 1036.7994 | I67: =I65+I66 -> 937.10736 | J67: =J65+J66 -> 941.11446 | ... BJ67: =BJ65+BJ66 -> 1555.0657 | BL67: =SUMIF($C$2:$BJ$2,BL$2,$C67:$BJ67) -> 12481.237 | BM67: =SUMIF($C$2:$BJ$2,BM$2,$C67:$BJ67) -> 13050.726 | BN67: =SUMIF($C$2:$BJ$2,BN$2,$C67:$BJ67) -> 13674.84 | BO67: =SUMIF($C$2:$BJ$2,BO$2,$C67:$BJ67) -> 14408.415 | BP67: =SUMIF($C$2:$BJ$2,BP$2,$C67:$BJ67) -> 15188.75 | BQ67: =BL67+BM67+BN67+BO67+BP67 -> 68803.969
A68: DELTA (vs Baseline)
A69: Delta GMV | B69: mln Rub | C69: =C62-C31 -> 6.4023668 | D69: =D62-D31 -> 6.5037596 | E69: =E62-E31 -> 7.7078845 | F69: =F62-F31 -> 8.2028074 | G69: =G62-G31 -> 6.0601552 | H69: =H62-H31 -> 7.6951606 | I69: =I62-I31 -> 7.0353243 | J69: =J62-J31 -> 7.1467411 | ... BJ69: =BJ62-BJ31 -> 126.61016 | BL69: =SUMIF($C$2:$BJ$2,BL$2,$C69:$BJ69) -> 93.52872 | BM69: =SUMIF($C$2:$BJ$2,BM$2,$C69:$BJ69) -> 480.13937 | BN69: =SUMIF($C$2:$BJ$2,BN$2,$C69:$BJ69) -> 1022.3057 | BO69: =SUMIF($C$2:$BJ$2,BO$2,$C69:$BJ69) -> 1092.7082 | BP69: =SUMIF($C$2:$BJ$2,BP$2,$C69:$BJ69) -> 1167.0006 | BQ69: =BL69+BM69+BN69+BO69+BP69 -> 3855.6826
A70: Delta Revenue | B70: mln Rub | C70: =C67-C37 -> -2.2272063 | D70: =D67-D37 -> -2.230665 | E70: =E67-E37 -> -2.6063902 | F70: =F67-F37 -> -2.7345462 | G70: =G67-G37 -> -1.991631 | H70: =H67-H37 -> -2.4930375 | I70: =I67-I37 -> -2.2468008 | J70: =J67-J37 -> -2.2497841 | ... BJ70: =BJ67-BJ37 -> -20.564101 | BL70: =SUMIF($C$2:$BJ$2,BL$2,$C70:$BJ70) -> -29.939085 | BM70: =SUMIF($C$2:$BJ$2,BM$2,$C70:$BJ70) -> -118.5905 | BN70: =SUMIF($C$2:$BJ$2,BN$2,$C70:$BJ70) -> -192.28487 | BO70: =SUMIF($C$2:$BJ$2,BO$2,$C70:$BJ70) -> -199.57189 | BP70: =SUMIF($C$2:$BJ$2,BP$2,$C70:$BJ70) -> -206.99971 | BQ70: =BL70+BM70+BN70+BO70+BP70 -> -747.38607
A71: Delta Revenue % | B71: % | C71: =IF(C37=0,0,C70/C37) -> -0.0024322689 | D71: =IF(D37=0,0,D70/D37) -> -0.002425722 | E71: =IF(E37=0,0,E70/E37) -> -0.0024191009 | F71: =IF(F37=0,0,F70/F37) -> -0.0024124046 | G71: =IF(G37=0,0,G70/G37) -> -0.0024056324 | H71: =IF(H37=0,0,H70/H37) -> -0.0023987835 | I71: =IF(I37=0,0,I70/I37) -> -0.002391857 | J71: =IF(J37=0,0,J70/J37) -> -0.002384852 | ... BJ71: =IF(BJ37=0,0,BJ70/BJ37) -> -0.013051353 | BL71: =AVERAGEIFS($C71:$BJ71,$C$2:$BJ$2,BL$2) -> -0.0023948651 | BM71: =AVERAGEIFS($C71:$BJ71,$C$2:$BJ$2,BM$2) -> -0.0090143148 | BN71: =AVERAGEIFS($C71:$BJ71,$C$2:$BJ$2,BN$2) -> -0.013885164 | BO71: =AVERAGEIFS($C71:$BJ71,$C$2:$BJ$2,BO$2) -> -0.013681358 | BP71: =AVERAGEIFS($C71:$BJ71,$C$2:$BJ$2,BP$2) -> -0.013465404 | BQ71: =AVERAGE(BL71:BP71) -> -0.010488221

Sheet Монетизация и юнит
A1: ПАРАМЕТРЫ ЮНИТ-ЭКОНОМИКИ
A3: Параметр | B3: Значение | C3: Единица | D3: Источник / обоснование
A4: Monthly Retention Rate | B4: 0.925 | C4: % | D4: Fashion ecom retention 31% annually (Shopify 2025) → monthly = 0.40^(1/12) ≈ 92.5%. Avito выше чистого fashion из-за платформенной лояльности. Источник: https://www.shopify.com/blog/average-customer-retention-rate-by-industry
A5: Monthly Churn Rate | B5: =1-B4 -> 0.075 | C5: % | D5: 1 -Retention
A6: Average Lifetime (months) | B6: =1/B5 -> 13.333333 | C6: мес | D6: 1 /Monthly Churn
A7: CAC (buyer, blended) — по годам, см. ниже | B7: =Assumptions!$B$65 -> 250 | C7: руб | D7: CAC растёт ~15% YoY при масштабировании через платные каналы. Бенчмарк: C2C marketplace buyer CAC $20-50 (financialmodelslab.com). Значения: 2026=250р, 2027=300р, 2028=350р, 2029=400р, 2030=450р. Источник: Assumptions B65-B69.
A8: Purchases per buyer per year | B8: 4 | C8: шт | D8: Бенчмарк fashion C2C: 3-5 покупок/год. Avito Fashion — средний сценарий.
A9: Share of paying users (CR × Delivery) | B9: =Assumptions!B15*Assumptions!B16 -> 0.0111 | C9: % | D9: CR *Delivery Share (из Assumptions)
A10: Discount rate (monthly) | B10: 0.01 | C10: % | D10: Для расчёта DCF LTV. ~12% годовых → 1% в месяц.
A13: РАСЧЁТ ARPU, CAC, LTV
A15: Метрика | B15: Единица | C15: 2026 | D15: 2027 | E15: 2028 | F15: 2029 | G15: 2030
A16: MAU (avg monthly, Case Total) | B16: mln | C16: ='Traction model'!BL54 -> 9.2723826 | D16: ='Traction model'!BM54 -> 9.9135774 | E16: ='Traction model'!BN54 -> 10.558054 | F16: ='Traction model'!BO54 -> 11.085957 | G16: ='Traction model'!BP54 -> 11.640255
A17: Annual Revenue (Case Total) | B17: mln руб | C17: ='Traction model'!BL67 -> 12481.237 | D17: ='Traction model'!BM67 -> 13050.726 | E17: ='Traction model'!BN67 -> 13674.84 | F17: ='Traction model'!BO67 -> 14408.415 | G17: ='Traction model'!BP67 -> 15188.75
A18: ARPU (monthly) | B18: руб | C18: =C17*1000000/12/C16/1000000 -> 112.17215 | D18: =D17*1000000/12/D16/1000000 -> 109.70414 | E18: =E17*1000000/12/E16/1000000 -> 107.93371 | F18: =F17*1000000/12/F16/1000000 -> 108.30831 | G18: =G17*1000000/12/G16/1000000 -> 108.73724
A19: ARPU (annual) | B19: руб | C19: =C18*12 -> 1346.0658 | D19: =D18*12 -> 1316.4497 | E19: =E18*12 -> 1295.2046 | F19: =F18*12 -> 1299.6997 | G19: =G18*12 -> 1304.8469
A20: CAC | B20: руб | C20: =Assumptions!$B$65 -> 250 | D20: =Assumptions!$B$66 -> 300 | E20: =Assumptions!$B$67 -> 350 | F20: =Assumptions!$B$68 -> 400 | G20: =Assumptions!$B$69 -> 450
A21: LTV (simple) | B21: руб | C21: =C18*$B$6 -> 1495.6287 | D21: =D18*$B$6 -> 1462.7219 | E21: =E18*$B$6 -> 1439.1162 | F21: =F18*$B$6 -> 1444.1108 | G21: =G18*$B$6 -> 1449.8299
A22: LTV (DCF, discounted) | B22: руб | C22: =C18*$B$4/(1+$B$10-$B$4) -> 1220.6969 | D22: =D18*$B$4/(1+$B$10-$B$4) -> 1193.8392 | E22: =E18*$B$4/(1+$B$10-$B$4) -> 1174.5728 | F22: =F18*$B$4/(1+$B$10-$B$4) -> 1178.6493 | G22: =G18*$B$4/(1+$B$10-$B$4) -> 1183.317
A23: LTV / CAC | B23: x | C23: =C21/C20 -> 5.9825147 | D23: =D21/D20 -> 4.8757397 | E23: =E21/E20 -> 4.1117605 | F23: =F21/F20 -> 3.610277 | G23: =G21/G20 -> 3.2218442
A24: Payback Period | B24: мес | C24: =C20/C18 -> 2.2287172 | D24: =D20/D18 -> 2.7346278 | E24: =E20/E18 -> 3.242731 | F24: =F20/F18 -> 3.6931607 | G24: =G20/G18 -> 4.1384166
A25: ARPPU (monthly, per paying user) | B25: руб | C25: =C18/$B$9 -> 10105.599 | D25: =D18/$B$9 -> 9883.2562 | E25: =E18/$B$9 -> 9723.758 | F25: =F18/$B$9 -> 9757.5055 | G25: =G18/$B$9 -> 9796.1478
A28: СРАВНЕНИЕ: Baseline vs Case Total
A30: Метрика | B30: Ед. | C30: 2026 Base | D30: 2026 Case | E30: 2028 Base | F30: 2028 Case | G30: 2030 Base | H30: 2030 Case
A31: Monthly ARPU | B31: руб | C31: ='Traction model'!BL37*1000000/12/'Traction model'!BL17/1000000 -> 113.17125 | D31: =C18 -> 112.17215 | E31: ='Traction model'!BN37*1000000/12/'Traction model'!BN17/1000000 -> 113.77472 | F31: =E18 -> 107.93371 | G31: ='Traction model'!BP37*1000000/12/'Traction model'!BP17/1000000 -> 114.57282 | H31: =G18 -> 108.73724
A32: LTV | B32: руб | C32: =C31*$B$6 -> 1508.95 | D32: =D31*$B$6 -> 1495.6287 | E32: =E31*$B$6 -> 1516.9963 | F32: =F31*$B$6 -> 1439.1162 | G32: =G31*$B$6 -> 1527.6376 | H32: =H31*$B$6 -> 1449.8299
A33: LTV/CAC | B33: x | C33: =C32/C20 -> 6.0357998 | D33: =D32/C20 -> 5.9825147 | E33: =E32/E20 -> 4.3342752 | F33: =F32/E20 -> 4.1117605 | G33: =G32/G20 -> 3.3947503 | H33: =H32/G20 -> 3.2218442
A36: SENSITIVITY: LTV при разном Retention
A38: Monthly Retention | B38: Lifetime (мес) | C38: LTV 2026 (руб) | D38: LTV 2028 (руб) | E38: LTV 2030 (руб)
A39: 0.85 | B39: =1/(1-A39) -> 6.6666667 | C39: =C18*B39 -> 747.81434 | D39: =E18*B39 -> 719.55809 | E39: =G18*B39 -> 724.91493
A40: 0.875 | B40: =1/(1-A40) -> 8 | C40: =C18*B40 -> 897.37721 | D40: =E18*B40 -> 863.46971 | E40: =G18*B40 -> 869.89792
A41: 0.9 | B41: =1/(1-A41) -> 10 | C41: =C18*B41 -> 1121.7215 | D41: =E18*B41 -> 1079.3371 | E41: =G18*B41 -> 1087.3724
A42: 0.925 | B42: =1/(1-A42) -> 13.333333 | C42: =C18*B42 -> 1495.6287 | D42: =E18*B42 -> 1439.1162 | E42: =G18*B42 -> 1449.8299
A43: 0.95 | B43: =1/(1-A43) -> 20 | C43: =C18*B43 -> 2243.443 | D43: =E18*B43 -> 2158.6743 | E43: =G18*B43 -> 2174.7448
A44: 0.96 | B44: =1/(1-A44) -> 25 | C44: =C18*B44 -> 2804.3038 | D44: =E18*B44 -> 2698.3428 | E44: =G18*B44 -> 2718.431
A45: 0.97 | B45: =1/(1-A45) -> 33.333333 | C45: =C18*B45 -> 3739.0717 | D45: =E18*B45 -> 3597.7905 | E45: =G18*B45 -> 3624.5747
A46: 0.98 | B46: =1/(1-A46) -> 50 | C46: =C18*B46 -> 5608.6076 | D46: =E18*B46 -> 5396.6857 | E46: =G18*B46 -> 5436.862
A85: ПРОВЕРКА ДОПУЩЕНИЙ
A87: Допущение | B87: Значение | C87: Когда проверить | D87: Как проверить
A88: Monthly Retention 92.5% | B88: =B4 -> 0.925 | C88: Через 3 мес после запуска | D88: Когортный анализ: % MAU, вернувшихся через 30 дней. Сегментация по fashion-only пользователям.
A89: CAC растёт по годам (2026-2030) | B89: =B7 -> 250 | C89: Сразу | D89: CAC 2026=250, 2027=300, 2028=350, 2029=400, 2030=450. Источник: Assumptions B65-B69.
A90: CR × Delivery = 0.45% | B90: =B9 -> 0.0111 | C90: Сразу (внутренние данные) | D90: Фактический CR и Delivery Share из аналитики Avito. Обновлять ежемесячно.
A91: Purchases/buyer/year = 4 | B91: =B8 -> 4 | C91: Через 6 мес | D91: Среднее число заказов на уникального покупателя за 6 мес × 2. Когортный анализ.
A92: Take Rate 7% | B92: =Assumptions!B19 -> 0.07 | C92: Сразу | D92: Фактическая выручка / GMV. Внутренние данные Avito.

Sheet Checkers
A1: ЧЕКЕРЫ ВАЛИДАЦИИ МОДЕЛИ
A3: Проверка | B3: Формула / значение | C3: Статус | D3: Комментарий
A4: ЛОГИЧЕСКИЕ ПРОВЕРКИ
A5: Revenue Case > Revenue Baseline (2028) | B5: =IF('Traction model'!BN67>'Traction model'!BN37,"✓ OK","✗ ОШИБКА") -> ✗ ОШИБКА | D5: Гипотезы должны давать прирост total revenue (Transaction + VAS) vs baseline
A6: GMV Case > 0 (all months) | B6: =IF(MIN('Traction model'!C62:'Traction model'!BJ62)>0,"✓ OK","✗ ОШИБКА") -> ✓ OK | D6: GMV не может быть отрицательным
A7: Take Rate Case в диапазоне 5-12% | B7: =IF(AND(MIN('Traction model'!C63:'Traction model'!BJ63)>=0.05,MAX('Traction model'!C63:'Traction model'!BJ63)<=0.12),"✓ OK","✗ ОШИБКА") -> ✓ OK | D7: Take Rate должен быть реалистичным
A8: MAU Case ≤ MAU Baseline × 1.1 | B8: =IF(MAX('Traction model'!C54:BJ54)<=MAX('Traction model'!C17:BJ17)*1.1,"✓ OK","✗ ВНИМАНИЕ") -> ✓ OK | D8: H2 AI Retention uplift (+5%) при полной раскатке даёт +4% MAU сверх Baseline. Порог 10% — контроль нереалистичного роста.
A9: Orders Fulfilled > 0 (all months) | B9: =IF(MIN('Traction model'!C61:'Traction model'!BJ61)>0,"✓ OK","✗ ОШИБКА") -> ✓ OK | D9: Заказы не могут быть отрицательными
A10: LTV/CAC > 1 (2028) | B10: =IF('Монетизация и юнит'!E23>1,"✓ OK","✗ ОШИБКА") -> ✓ OK | D10: Юнит-экономика должна быть положительной
A11: H1 каннибализация применена (Orders Case < MAU Case × CR) | B11: =IF('Traction model'!C58<'Traction model'!C54*1000000*'Traction model'!C21,"✓ OK (H1 cannib снижает заказы от MAU×CR)","✗ Каннибализация не работает") -> ✓ OK (H1 cannib снижает заказы от MAU×CR) | D11: H1 Bundle каннибализация (коэфф 0.97) снижает Orders vs "чистого" MAU×CR. Orders Case < MAU_Case × CR × 1M. В новой модели Orders Case > Baseline нормально — H2 AI растит MAU.
A12: H2 AI Retention uplift положителен (MAU Case ≥ MAU Baseline) | B12: =IF('Traction model'!C54>='Traction model'!C17,"✓ OK (H2 AI retention поднимает MAU сверх baseline)","✗ H2 AI retention не работает") -> ✓ OK (H2 AI retention поднимает MAU сверх baseline) | D12: H2 AI Reco улучшает retention (+5%), что перевешивает H1 retention decay (-1%). Итого MAU Case > MAU Baseline. Это ожидаемое поведение новой H2.
A14: ТЕХНИЧЕСКИЕ ПРОВЕРКИ
A15: Нет зашитых чисел в Baseline | B15: ="✓ Все формулы ссылаются на Assumptions" -> ✓ Все формулы ссылаются на Assumptions | D15: CR, Delivery, Return Rate, Take Rate, AOV, MAU — все из Assumptions
A16: Нет зашитых чисел в Case Total | B16: ="✓ Все формулы ссылаются на Assumptions и Hypotheses inputs" -> ✓ Все формулы ссылаются на Assumptions и Hypotheses inputs | D16: Uplift, rollout, churn, cannibalization — все параметризованы
A17: Консистентность временных рамок | B17: ="✓ Все расчёты помесячные (C-BJ), годовые итоги (BL-BP)" -> ✓ Все расчёты помесячные (C-BJ), годовые итоги (BL-BP) | D17: Inflation и growth пересчитаны из YoY в monthly через POWER
A18: Каскадирование метрик | B18: ="✓ MAU → CR → Orders → Delivery → Fulfilled → GMV → Revenue" -> ✓ MAU → CR → Orders → Delivery → Fulfilled → GMV → Revenue | D18: Каждая метрика зависит от предыдущей, нет пропусков
A19: Seasonal coefficients sum ≈ 12 | B19: =IF(ABS(SUM(Assumptions!B20:B31)-12)<0.5,"✓ OK (sum="&ROUND(SUM(Assumptions!B20:B31),2)&")","✗ ОШИБКА") -> ✓ OK (sum=12) | D19: Сумма сезонных коэффициентов должна быть ≈ 12 (среднее ≈ 1)
A20: AOV растёт с инфляцией | B20: =IF('Traction model'!N19>'Traction model'!C19,"✓ OK (Dec > Jan)","✗ ОШИБКА") -> ✓ OK (Dec > Jan) | D20: AOV должен монотонно расти за счёт инфляции
A22: ПРОВЕРКИ РЕАЛИСТИЧНОСТИ
A23: Market Share (GMV/SAM) < 5% | B23: =IF(MAX('Traction model'!C31:'Traction model'!BJ31)/MAX('Traction model'!C8:'Traction model'!BJ8)<0.05,"✓ OK","✗ Доля рынка нереалистична") -> ✗ Доля рынка нереалистична | D23: Доля рынка не должна быть слишком высокой для C2C fashion
A24: MAU рост CAGR ~5% | B24: =IF(AND('Traction model'!BP17/'Traction model'!BL17>1.03,'Traction model'!BP17/'Traction model'!BL17<1.08),"✓ OK","✗ Рост MAU нереалистичен") -> ✗ Рост MAU нереалистичен | D24: Ожидаемый CAGR MAU 5% (Strategy Scale)
A25: CR 3% — бенчмарк C2C fashion | B25: =IF(Assumptions!B15=0.03,"✓ OK (3%)","✗ CR отличается от бенчмарка") -> ✓ OK (3%) | D25: Бенчмарк C2C fashion: 2-4% CR (Vinted ~2.5-3%)
A26: Take Rate 7% в диапазоне 5-10% | B26: =IF(AND(Assumptions!B19>=0.05,Assumptions!B19<=0.1),"✓ OK","✗ Вне диапазона") -> ✓ OK | D26: Задано в условиях ДЗ: Take Rate 5-10%
A27: Return Rate 10% — бенчмарк fashion | B27: =IF(AND(Assumptions!B17>=0.05,Assumptions!B17<=0.3),"✓ OK","✗ Вне бенчмарка") -> ✓ OK | D27: Fashion ecom: 10-30% returns. 10% — консервативно для C2C (без примерки)
A28: Fashion resale market 253 млрд руб 2025 | B28: ="Бенчмарк: Коммерсант, 2025" -> Бенчмарк: Коммерсант, 2025 | D28: Рынок fashion-ресейла 253 млрд руб (2025). Источник: https://www.kommersant.ru/doc/8420884
A29: НОВЫЕ ПРОВЕРКИ (VAS + AI Reco + CAC)
A30: VAS Revenue > 0 (all months) | B30: =IF(MIN('Traction model'!C36:BJ36)>0,"✓ OK","✗ ОШИБКА") -> ✓ OK | D30: VAS не может быть отрицательным
A31: VAS Revenue < Transaction Revenue × 50 | B31: =IF(MAX('Traction model'!C36:BJ36)<MAX('Traction model'!C35:BJ35)*50,"✓ OK","✗ Sanity check VAS") -> ✓ OK | D31: Санчек: VAS не должен быть абсурдно большим
A32: ARPU ~100 руб/мес (2026) | B32: =IF(ABS('Монетизация и юнит'!C18-100)<50,"✓ OK (~"&ROUND('Монетизация и юнит'!C18,0)&" руб/мес)","✗ ARPU далёко от 100 руб") -> ✓ OK (~112 руб/мес) | D32: Должен соответствовать данным ДЗ №2 (ARPU ~100 руб/мес)
A33: CAC растёт по годам (2026→2030) | B33: =IF(Assumptions!B69>Assumptions!B65,"✓ OK (CAC2030="&Assumptions!B69&" > CAC2026="&Assumptions!B65&")","✗ CAC не растёт") -> ✓ OK (CAC2030=450 > CAC2026=250) | D33: CAC 2030 > CAC 2026 при масштабировании
A34: H2 AI GMV uplift ≤ 20% | B34: =IF(Assumptions!B58<=0.2,"✓ OK ("&TEXT(Assumptions!B58,"0%")&")","✗ GMV uplift нереалистичен") -> ✓ OK (15%) | D34: AI-рекомендации не должны давать нереалистичный uplift
A35: Total Revenue (2026) ≈ MAU × ARPU target | B35: =IF(ABS('Traction model'!BL67-'Traction model'!BL17*1000000*100*12/1000000)/'Traction model'!BL67<0.5,"✓ OK","✗ Revenue/ARPU несоответствие") -> ✓ OK | D35: Сверка с ARPU из данных ДЗ №2: Total Revenue ≈ MAU × 100 руб/мес × 12
A36: VAS Revenue Case > 0 (all months) | B36: =IF(MIN('Traction model'!C66:BJ66)>0,"✓ OK","✗ VAS Case отрицательный") -> ✓ OK | D36: VAS Revenue Case не может быть отрицательным

Sheet PnL
A1: ДЗ №4 · Планирование затрат, PnL и CashFlow | Avito «Мода и одежда»
A2: Гипотезы: Bundle Offers (H1) + AI Recommendations (H2) | Монетизация: Transactional 7% + CPA 5%
A4: БЛОК ДОПУЩЕНИЙ — все входные параметры
B5: Параметр | C5: Значение | D5: Единица | E5: Источник / Обоснование
B6: РЫНОК И ПРОДУКТ
B7: Base MAU Fashion | C7: 9 | D7: млн | E7: Данные Avito, ДЗ №1
B8: MAU Growth YoY | C8: 0.05 | D8: % | E8: Стратегия Scale (5%/год)
B9: CR MAU → Order | C9: 0.03 | D9: % | E9: Данные ДЗ №2, бенчмарк C2C
B10: Delivery Share | C10: 0.37 | D10: % | E10: Экспертная оценка (рост TRX)
B11: Return Rate | C11: 0.1 | D11: % | E11: Бенчмарк fashion e-com
B12: AOV 2026 | C12: 2500 | D12: руб | E12: Рыночный бенчмарк C2C fashion
B13: AOV Inflation YoY | C13: 0.15 | D13: % | E13: Инфляция fashion ~15%/год (Коммерсант 2025)
B14: Take Rate (base) | C14: 0.07 | D14: % | E14: ДЗ №2, конкурентный диапазон 5-10%
B15: VAS: Seller Share of MAU | C15: 0.28 | D15: % | E15: ДЗ №1, ~6 млн объявлений при 9 млн MAU
B16: VAS: Adoption Rate | C16: 0.15 | D16: % | E16: ДЗ №2, 15% активных продавцов используют VAS
B17: VAS: Avg Spend (руб/мес/продавец) | C17: 2650 | D17: руб/мес | E17: Расчёт из ARPU-target ДЗ №2
B18: ГИПОТЕЗЫ РОСТА
B19: H1 Bundle: AOV uplift | C19: 0.1 | D19: % | E19: Vinted: avg bundle = 3.5 товара → +10% AOV. CLOSO 2024
B20: AI Reco: GMV per buyer uplift (2026–2028) | C20: 0.15 | D20: % | E20: Amazon/Netflix AI рекомендации +15% GMV per buyer. McKinsey 2024
B21: AI Reco: GMV uplift 2029 (decay -10%) | C21: 0.135 | D21: % | E21: Затухание: 2028×0.9 = 13.5%
B22: AI Reco: GMV uplift 2030 (decay -10%) | C22: 0.1215 | D22: % | E22: Затухание: 2029×0.9 = 12.15%
B23: Cross-hypothesis synergy | C23: 0.02 | D23: % | E23: Бандлы усиливают AI-рекомендации (больше комплектов в ленте) → +2%
B24: Effect decay annual (с 2029) | C24: 0.1 | D24: % | E24: VWO Benchmark 2024: -10%/год после полной раскатки
B25: Cannibalization (orders, H1) | C25: 0.03 | D25: % | E25: Из 20% бандл-заказов лишь 15% замещают два отдельных → 3% снижение TRX
B26: VAS cannibalization (AI Reco) | C26: 0.02 | D26: % | E26: AI-буст органики снижает VAS-расходы продавцов на 2%
B27: КОМАНДА — ставки из таблицы ДЗ №4
B28: Tech Lead (Тимлид, Senior) — годовая ЗП | C28: 6000 | D28: тыс.руб/год | E28: Таблица ДЗ №4, Senior
B29: Backend (Senior) — годовая ЗП | C29: 5400 | D29: тыс.руб/год | E29: Таблица ДЗ №4, Senior. 2 FTE в фазе разработки
B30: Frontend (Senior) — годовая ЗП | C30: 4800 | D30: тыс.руб/год | E30: Таблица ДЗ №4, Senior
B31: iOS (Senior) — годовая ЗП | C31: 5000 | D31: тыс.руб/год | E31: Таблица ДЗ №4, Senior
B32: Android (Senior) — годовая ЗП | C32: 4800 | D32: тыс.руб/год | E32: Таблица ДЗ №4, Senior
B33: QA-инженер (Manual+Auto) — годовая ЗП | C33: 3400 | D33: тыс.руб/год | E33: Таблица ДЗ №4, Manual + Automation
B34: Продуктовый дизайнер (Middle/Senior) — годовая ЗП | C34: 3600 | D34: тыс.руб/год | E34: Таблица ДЗ №4, Middle/Senior
B35: Продуктовый аналитик (Middle/Senior) — годовая ЗП | C35: 3800 | D35: тыс.руб/год | E35: Таблица ДЗ №4, Middle/Senior
B36: Социальные взносы (IT-льгота) | C36: 0.15 | D36: % | E36: Avito — аккредитованная IT-компания. IT-льгота: страх. взносы ~7.6% выше порога + прочие ~7% = ~15% к gross. Ставка сущ. ниже стандарт. 30%
B37: Индексация ЗП (YoY) | C37: 0.1 | D37: % | E37: Рост рынка труда IT-специалистов ~10%/год (SuperJob 2025)
B38: TtM — TIME TO MARKET (ФАЗЫ РЕАЛИЗАЦИИ)
B39: Фаза 1: Discovery & Design | C39: 1 | D39: мес | E39: Тимлид + Аналитик + Дизайнер: scope, user research, wireframes, CPA-договоры
B40: Фаза 2: Development | C40: 4 | D40: мес | E40: Вся команда 9 FTE: backend API (Bundle+CPA), frontend UI, mobile apps, QA-подготовка, MLOps инфра
B41: Фаза 3: QA & Stabilization | C41: 1.5 | D41: мес | E41: Тимлид + Backend×2 + QA + Аналитик: тестирование, баг-фикс, нагрузочные тесты, pre-launch review
B42: Фаза 4: A/B Launch & Monitoring | C42: 1.5 | D42: мес | E42: Тимлид + Backend×1 + QA + Аналитик: раскатка H1 10%/мес + H2 20%/мес, мониторинг метрик NSM
B43: Итого TtM (мес) | C43: =C39+C40+C41+C42 -> 8 | D43: мес | E43: Старт: янв 2026. Запуск: сент 2026. Буфер +15% → TtM консерв. ≤ 10 мес.
B44: Буфер рисков | C44: 0.15 | D44: % | E44: Риск задержки интеграции с Avito Доставка API + согласование бизнес-оферты CPA. Стандарт Avito: 10-15% буфер на внешние зависимости
B45: OPEX — ДОПОЛНИТЕЛЬНЫЕ ПАРАМЕТРЫ (CAPEX = 0 — всё cloud-based)
B46: CoS: % от суммы доставленных заказов (Delivery GMV) | C46: 0.025 | D46: % | E46: Эквайринг ~1.5% GMV + комиссия партнёров Avito Доставка ~1% = 2.5%. Avito IT-льгота снижает банковские комиссии.
B47: IT-инфраструктура: полный год (тыс.руб) | C47: 5000 | D47: тыс.руб/год | E47: GPU-инстансы для AI Reco (IaaS, OPEX, без покупки серверов): 2 GPU-инст. × ~1.5 mln/год + MLOps pipeline + модельное хранилище ~2 mln/год. CAPEX = 0.
B48: IT-инфраструктура: 2026 (тыс.руб, частичный год) | C48: 1500 | D48: тыс.руб | E48: AI Reco запускается в сент-окт 2026 (~4 мес × 375 тыс./мес). Bundle/CPA — минимальная облачная нагрузка.
B49: Маркетинг: запуск 2026 (тыс.руб) | C49: 3000 | D49: тыс.руб | E49: Кампания среди продавцов: CPA onboarding, email/push, обучающий контент, A/B тест промо-материалов. Внутри Avito-экосистемы.
B50: Маркетинг: поддержка, год (тыс.руб) | C50: 2000 | D50: тыс.руб/год | E50: Регулярные активации: Bundle Adoption growth-кампании (цель 20%→100% MAU), продавческие бриф-сессии, ретаргетинг
B51: G&A: 2026 (тыс.руб) | C51: 1500 | D51: тыс.руб | E51: Юр. сопровождение CPA-оферты (договор с продавцами), compliance, аллокация накладных на вертикаль Fashion.
B52: G&A: поддержка, год (тыс.руб) | C52: 2000 | D52: тыс.руб/год | E52: Текущий compliance + регуляторная поддержка C2C + аллокация G&A на вертикаль.
A54: ПЛАНИРОВАНИЕ КОМАНДЫ И TtM — численность, роли, стоимость по фазам
B55: Роль | C55: ЗП gross (тыс.руб/год) | D55: Employer cost/yr (тыс.руб) | E55: FTE Фаза 1 (1 мес) | F55: FTE Фаза 2 (4 мес) | G55: FTE Фаза 3 (1.5 мес) | H55: FTE Фаза 4 (1.5 мес) | I55: FTE Поддержка (ongoing)
B56: Tech Lead (Тимлид, Senior) | C56: =C28 -> 6000 | D56: =C56*(1+C36) -> 6900 | E56: 1 | F56: 1 | G56: 1 | H56: 1 | I56: 0
B57: Backend (Senior) × 2 | C57: =C29*2 -> 10800 | D57: =C57*(1+C36) -> 12420 | E57: 0 | F57: 2 | G57: 2 | H57: 1 | I57: 1
B58: Frontend (Senior) | C58: =C30 -> 4800 | D58: =C58*(1+C36) -> 5520 | E58: 0 | F58: 1 | G58: 0 | H58: 0 | I58: 0
B59: iOS-разработчик (Senior) | C59: =C31 -> 5000 | D59: =C59*(1+C36) -> 5750 | E59: 0 | F59: 1 | G59: 0 | H59: 0 | I59: 0
B60: Android-разработчик (Senior) | C60: =C32 -> 4800 | D60: =C60*(1+C36) -> 5520 | E60: 0 | F60: 1 | G60: 0 | H60: 0 | I60: 0
B61: QA-инженер (Manual + Automation) | C61: =C33 -> 3400 | D61: =C61*(1+C36) -> 3910 | E61: 0 | F61: 1 | G61: 1 | H61: 1 | I61: 0.5
B62: Продуктовый дизайнер | C62: =C34 -> 3600 | D62: =C62*(1+C36) -> 4140 | E62: 1 | F62: 1 | G62: 0 | H62: 0 | I62: 0.5
B63: Продуктовый аналитик | C63: =C35 -> 3800 | D63: =C63*(1+C36) -> 4370 | E63: 1 | F63: 1 | G63: 1 | H63: 1 | I63: 1
B64: ИТОГО | C64: =SUM(C56:C63) -> 42200 | D64: =SUM(D56:D63) -> 48530 | E64: =SUM(E56:E63) -> 3 | F64: =SUM(F56:F63) -> 9 | G64: =SUM(G56:G63) -> 5 | H64: =SUM(H56:H63) -> 4 | I64: =SUM(I56:I63) -> 3
B66: РАЗБИВКА ЗАТРАТ НА КОМАНДУ ПО ФАЗАМ (2026)
B67: Фаза | C67: Длит. (мес) | D67: Состав команды | E67: Стоимость (тыс.руб) | F67: % от бюджета разработки
B68: Фаза 1: Discovery & Design | C68: =C39 -> 1 | D68: 3 FTE: Тимлид + Дизайнер + Аналитик | E68: =(C28*1+C34*1+C35*1)/12*(1+C36)*C39 -> 1284.1667 | F68: =IF(E73=0,0,E68/E73) -> 0.045133041
B69: Фаза 2: Development | C69: =C40 -> 4 | D69: 9 FTE (10 слотов): вся команда | E69: =(C28*1+C29*2+C30*1+C31*1+C32*1+C33*1+C34*1+C35*1)/12*(1+C36)*C40 -> 16176.667 | F69: =IF(E73=0,0,E69/E73) -> 0.5685416
B70: Фаза 3: QA & Stabilization | C70: =C41 -> 1.5 | D70: 5 FTE: Тимлид + Backend×2 + QA + Аналитик | E70: =(C28*1+C29*2+C33*1+C35*1)/12*(1+C36)*C41 -> 3450 | F70: =IF(E73=0,0,E70/E73) -> 0.12125295
B71: Фаза 4: A/B Launch & Monitoring | C71: =C42 -> 1.5 | D71: 4 FTE: Тимлид + Backend×1 + QA + Аналитик | E71: =(C28*1+C29*1+C33*1+C35*1)/12*(1+C36)*C42 -> 2673.75 | F71: =IF(E73=0,0,E71/E73) -> 0.093971034
B72: Поддержка (остаток 2026, 4 мес) | C72: =MAX(0,12-C39-C40-C41-C42) -> 4 | D72: 3 FTE: Backend + QA×0.5 + Аналитик + Дизайнер×0.5 | E72: =(C29*1+C33*0.5+C35*1+C34*0.5)/12*(1+C36)*MAX(0,12-C39-C40-C41-C42) -> 4868.3333 | F72: =IF(E73=0,0,E72/E73) -> 0.17110138
B73: ИТОГО бюджет команды 2026 (тыс.руб) | E73: =SUM(E68:E72) -> 28452.917
B75: TtM ВАРИАНТЫ: (1) БАЗОВЫЙ 8 мес — H1 и H2 разрабатываются параллельно, оптимальное соотношение скорость/стоимость. (2) КОНСЕРВАТИВНЫЙ 10 мес — буфер +15% на интеграции Avito Доставка и согласование CPA. (3) УСКОРЕННЫЙ 6 мес — аутсорс iOS/Android (+15% стоимость мобильной разработки). Выбран Вариант 1 как оптимальный.
A77: ПРОГНОЗНЫЙ P&L ДО EBITDA — 5 лет (Case Total with Hypotheses)
B78: CAPEX = 0. Серверная инфраструктура — cloud IaaS (аренда, OPEX). Нет закупки оборудования, нет капитальных вложений. Все расходы операционные (OPEX) и отражены ниже.
B79: Показатель | C79: Ед. | D79: 2026 | E79: 2027 | F79: 2028 | G79: 2029 | H79: 2030
B80: ВЫРУЧКА — из Traction model ДЗ №3 (ссылки на лист «Traction model»)
B81: Revenue AS IS (Baseline) | C81: mln руб | D81: ='Traction model'!BL37 -> 12511.176 | E81: ='Traction model'!BM37 -> 13169.317 | F81: ='Traction model'!BN37 -> 13867.125 | G81: ='Traction model'!BO37 -> 14607.987 | H81: ='Traction model'!BP37 -> 15395.75
B82: Revenue TO BE (Case Total с гипотезами) | C82: mln руб | D82: ='Traction model'!BL67 -> 12481.237 | E82: ='Traction model'!BM67 -> 13050.726 | F82: ='Traction model'!BN67 -> 13674.84 | G82: ='Traction model'!BO67 -> 14408.415 | H82: ='Traction model'!BP67 -> 15188.75
B83: Δ Increment Revenue (Case - Base) | C83: mln руб | D83: =D82-D81 -> -29.939085 | E83: =E82-E81 -> -118.5905 | F83: =F82-F81 -> -192.28487 | G83: =G82-G81 -> -199.57189 | H83: =H82-H81 -> -206.99971
B84: Δ Increment Revenue % | C84: % | D84: =IF(D81=0,0,D83/D81) -> -0.0023929872 | E84: =IF(E81=0,0,E83/E81) -> -0.0090050612 | F84: =IF(F81=0,0,F83/F81) -> -0.013866239 | G84: =IF(G81=0,0,G83/G81) -> -0.013661834 | H84: =IF(H81=0,0,H83/H81) -> -0.01344525
B86: COST OF SALES (CoS) — переменные затраты, связанные с транзакциями
B87: CoS — эквайринг + комиссии Avito Доставка | C87: mln руб | D87: =-'Traction model'!BL62*C10*C46 -> -28.201249 | E87: =-'Traction model'!BM62*C10*C46 -> -37.44964 | F87: =-'Traction model'!BN62*C10*C46 -> -49.313912 | G87: =-'Traction model'!BO62*C10*C46 -> -58.235583 | H87: =-'Traction model'!BP62*C10*C46 -> -68.909354
B88: (Delivery GMV = Case GMV × Delivery Share; CoS rate = 2.5%)
B90: STAFF COSTS — затраты на персонал
B91: Staff Costs TOTAL (Фаза разработки + поддержка) | C91: mln руб | D91: =-((C28*1+C34*1+C35*1)/12*(1+C36)*C39+(C28*1+C29*2+C30*1+C31*1+C32*1+C33*1+C34*1+C35*1)/12*(1+C36)*C40+(C28*1+C29*2+C33*1+C35*1)/12*(1+C36)*C41+(C28*1+C29*1+C33*1+C35*1)/12*(1+C36)*C42+(C29*1+C33*0.5+C35*1+C34*0.5)/12*(1+C36)*MAX(0,12-C39-C40-C41-C42)) -> -28452.917 | E91: =-((C29*1+C33*0.5+C35*1+C34*0.5)/12*(1+C36)*12*1+(C28*1+C29*1+C35*1)/12*(1+C36)*4)*(1+C37) -> -22474.833 | F91: =-(C29*1+C33*0.5+C35*1+C34*0.5)/12*(1+C36)*12*(1+C37)^2 -> -17672.05 | G91: =-(C29*1+C33*0.5+C35*1+C34*0.5)/12*(1+C36)*12*(1+C37)^3 -> -19439.255 | H91: =-(C29*1+C33*0.5+C35*1+C34*0.5)/12*(1+C36)*12*(1+C37)^4 -> -21383.181
B92: в т.ч. Команда разработки (Dev+QA+Design, Фазы 1-4) | C92: mln руб | D92: =-((C28*1+C34*1+C35*1)/12*(1+C36)*C39+(C28*1+C29*2+C30*1+C31*1+C32*1+C33*1+C34*1+C35*1)/12*(1+C36)*C40+(C28*1+C29*2+C33*1+C35*1)/12*(1+C36)*C41+(C28*1+C29*1+C33*1+C35*1)/12*(1+C36)*C42) -> -23584.583 | E92: =-(C28*1+C29*1+C35*1)/12*(1+C36)*4*(1+C37) -> -6409.3333 | F92: =0 -> 0 | G92: =0 -> 0 | H92: =0 -> 0
B93: в т.ч. Поддержка & Оптимизация (ongoing) | C93: mln руб | D93: =-(C29*1+C33*0.5+C35*1+C34*0.5)/12*(1+C36)*MAX(0,12-C39-C40-C41-C42) -> -4868.3333 | E93: =-(C29*1+C33*0.5+C35*1+C34*0.5)/12*(1+C36)*12*(1+C37) -> -16065.5 | F93: =-(C29*1+C33*0.5+C35*1+C34*0.5)/12*(1+C36)*12*(1+C37)^2 -> -17672.05 | G93: =-(C29*1+C33*0.5+C35*1+C34*0.5)/12*(1+C36)*12*(1+C37)^3 -> -19439.255 | H93: =-(C29*1+C33*0.5+C35*1+C34*0.5)/12*(1+C36)*12*(1+C37)^4 -> -21383.181
B95: IT COSTS — облачная инфраструктура (OPEX, без CAPEX)
B96: IT Infrastructure (GPU-инстансы, MLOps, cloud-based) | C96: mln руб | D96: =-C48/1000 -> -1.5 | E96: =-C47/1000 -> -5 | F96: =-C47*1.1/1000 -> -5.5 | G96: =-C47*1.2/1000 -> -6 | H96: =-C47*1.3/1000 -> -6.5
B98: MARKETING COSTS
B99: Marketing (запуск, онбординг продавцов, A/B тесты) | C99: mln руб | D99: =-C49/1000 -> -3 | E99: =-C50/1000 -> -2 | F99: =-C50/1000 -> -2 | G99: =-C50/1000 -> -2 | H99: =-C50/1000 -> -2
B101: G&A COSTS (General & Administrative)
B102: G&A (legal, compliance, аллокация накладных) | C102: mln руб | D102: =-C51/1000 -> -1.5 | E102: =-C52/1000 -> -2 | F102: =-C52/1000 -> -2 | G102: =-C52/1000 -> -2 | H102: =-C52/1000 -> -2
B104: TOTAL OPEX (CoS + Staff + IT + Marketing + G&A) | C104: mln руб | D104: =SUM(D87,D91,D96,D99,D102) -> -28487.118 | E104: =SUM(E87,E91,E96,E99,E102) -> -22521.283 | F104: =SUM(F87,F91,F96,F99,F102) -> -17730.864 | G104: =SUM(G87,G91,G96,G99,G102) -> -19507.491 | H104: =SUM(H87,H91,H96,H99,H102) -> -21462.59
B106: EBITDA (Revenue Case + Total OPEX) | C106: mln руб | D106: =D82+D104 -> -16005.881 | E106: =E82+E104 -> -9470.5567 | F106: =F82+F104 -> -4056.0238 | G106: =G82+G104 -> -5099.0753 | H106: =H82+H104 -> -6273.8396
B107: EBITDA Margin % | C107: % | D107: =IF(D82=0,0,D106/D82) -> -1.2823954 | E107: =IF(E82=0,0,E106/E82) -> -0.72567277 | F107: =IF(F82=0,0,F106/F82) -> -0.29660484 | G107: =IF(G82=0,0,G106/G82) -> -0.35389564 | H107: =IF(H82=0,0,H106/H82) -> -0.41305832
B109: YoY Revenue Growth (Case) | C109: % | D109: — | E109: =IF(D82=0,0,E82/D82-1) -> 0.045627615 | F109: =IF(E82=0,0,F82/E82-1) -> 0.047822155 | G109: =IF(F82=0,0,G82/F82-1) -> 0.053644149 | H109: =IF(G82=0,0,H82/G82-1) -> 0.054158277
B110: 5Y Cumulative Increment Revenue (Case vs Base) | C110: mln руб | D110: =SUM(D83:H83) -> -747.38607 | E110: ← 5-летний прирост выручки от гипотез
A113: CASH FLOW — ПРЯМОЙ МЕТОД (Operating Cash Flow, Direct Method)
B114: Прямой метод: суммируем фактические денежные притоки и оттоки. Поскольку нет CAPEX и D&A ≈ 0, Operating CF ≈ EBITDA. Дебиторская задолженность минимальна (оплата онлайн, задержка ≤7 дней). NWC изменение незначительно (Avito — prepaid модель).
B115: Статья | C115: Ед. | D115: 2026 | E115: 2027 | F115: 2028 | G115: 2029 | H115: 2030
...
