Workbook

Sheet Assumptions_DZ4
A1: ДЗ№4 — Assumptions (OPEX, команда, TtM)
A3: Parameter | B3: Value | C3: Unit | D3: Comment/why | E3: Source / validation plan | F3: Confidence
A4: TtM_months | B4: 6 | C4: months | D4: Discovery 1 + Build 3 + Beta/A-B 1 + Launch ramp 1. | E4: Из брифа ДЗ4: требуется TtM по этапам; уточнить по roadmap. | F4: Medium
A5: Loaded_cost_multiplier | B5: 1.3 | C5: x | D5: Налоги/бонусы/соцпакет к окладам. | E5: HR/Finance: payroll taxes + бонусы/соцпакет; типично 1.25–1.45 для РФ (уточнить по компании). | F5: Medium
A6: Infra_tools_%_payroll | B6: 0.1 | C6: % | D6: Облако, мониторинг, аналитика, dev tools. | E6: Бенчмарк SaaS/marketplace: 5–15% от payroll; уточнить по фактическим счетам облака/Amplitude/Jira. | F6: Low
A7: Support_%_revenue | B7: 0.03 | C7: % | D7: Поддержка/операции. | E7: Бенчмарк support+ops 2–5% от revenue; уточнить по обращаемости и SLA в категории. | F7: Low
A8: Marketing_%_revenue | B8: 0.08 | C8: % | D8: Привлечение/активация исполнителей. | E8: Альтернатива: CAC*new paying providers (из ДЗ3); временно % от revenue как baseline. Уточнить по плану маркетинга. | F8: Low
A9: G&A_%_revenue | B9: 0.02 | C9: % | D9: Юристы, финансы, админ. | E9: Бенчмарк 1–3% от revenue для небольшого продукта; уточнить у finance. | F9: Low
A10: Run_team_YoY_growth | B10: 0.1 | C10: % | D10: Рост команды поддержки/продаж. | E10: План найма/OKR: рост run-команды по мере роста paying providers и обращений в поддержку. | F10: Low
A11: Gross_margin_services | B11: 0.85 | C11: % | D11: Маржа digital-сервисов. | E11: Digital services gross margin обычно 80–90% (серверы/поддержка). Уточнить у finance/PEO. | F11: Low

Sheet Team & TtM
A1: Команда, TtM и стоимость (OPEX)
L2: Loaded_mult | M2: =Assumptions_DZ4!B5 -> 1.3
A3: Role | B3: Annual cost (₽/yr) | C3: Loaded (₽/yr) | D3: Phase | E3: FTE build | F3: Months | G3: Build cost (₽) | H3: FTE run | I3: Run annual (₽) | J3: Why needed | K3: Source
A4: PM | B4: 3600000 | C4: =B4*$M$2 -> 4680000 | D4: Build+Run | E4: 1 | F4: 6 | G4: =C4/12*E4*F4 -> 2340000 | H4: 1 | I4: =C4*H4 -> 4680000 | J4: Координация 3 гипотез, метрики, релизы. | K4: Бенчмарк зарплат: HH.ru / Habr Career (IT) + внутренние вилки курса; проверить на финальной оценке: калькуляция cost/FTE от HR/Finance.
A5: Tech Lead | B5: 5000000 | C5: =B5*$M$2 -> 6500000 | D5: Build+Run | E5: 0.5 | F5: 6 | G5: =C5/12*E5*F5 -> 1625000 | H5: 0.3 | I5: =C5*H5 -> 1950000 | J5: Архитектура, интеграции, качество. | K5: Бенчмарк зарплат: HH.ru / Habr Career (IT) + внутренние вилки курса; проверить на финальной оценке: калькуляция cost/FTE от HR/Finance.
A6: Backend Dev | B6: 4000000 | C6: =B6*$M$2 -> 5200000 | D6: Build+Run | E6: 2 | F6: 6 | G6: =C6/12*E6*F6 -> 5200000 | H6: 1 | I6: =C6*H6 -> 5200000 | J6: API, шаблон КП, монетизация пакетов. | K6: Бенчмарк зарплат: HH.ru / Habr Career (IT) + внутренние вилки курса; проверить на финальной оценке: калькуляция cost/FTE от HR/Finance.
A7: Frontend Dev | B7: 3600000 | C7: =B7*$M$2 -> 4680000 | D7: Build+Run | E7: 1 | F7: 6 | G7: =C7/12*E7*F7 -> 2340000 | H7: 0.5 | I7: =C7*H7 -> 2340000 | J7: Карточка/формы/флоу КП, UX. | K7: Бенчмарк зарплат: HH.ru / Habr Career (IT) + внутренние вилки курса; проверить на финальной оценке: калькуляция cost/FTE от HR/Finance.
A8: Mobile Dev | B8: 4000000 | C8: =B8*$M$2 -> 5200000 | D8: Build+Run | E8: 1 | F8: 6 | G8: =C8/12*E8*F8 -> 2600000 | H8: 0.5 | I8: =C8*H8 -> 2600000 | J8: Мобильный флоу заказчика/исполнителя. | K8: Бенчмарк зарплат: HH.ru / Habr Career (IT) + внутренние вилки курса; проверить на финальной оценке: калькуляция cost/FTE от HR/Finance.
A9: ML/Ranking Eng | B9: 5000000 | C9: =B9*$M$2 -> 6500000 | D9: Build+Run | E9: 0.5 | F9: 4 | G9: =C9/12*E9*F9 -> 1083333.3 | H9: 0.2 | I9: =C9*H9 -> 1300000 | J9: Ранжирование/релевантность. | K9: Бенчмарк зарплат: HH.ru / Habr Career (IT) + внутренние вилки курса; проверить на финальной оценке: калькуляция cost/FTE от HR/Finance.
A10: QA | B10: 2400000 | C10: =B10*$M$2 -> 3120000 | D10: Build+Run | E10: 1 | F10: 6 | G10: =C10/12*E10*F10 -> 1560000 | H10: 0.5 | I10: =C10*H10 -> 1560000 | J10: Тестирование, регрессия, A/B. | K10: Бенчмарк зарплат: HH.ru / Habr Career (IT) + внутренние вилки курса; проверить на финальной оценке: калькуляция cost/FTE от HR/Finance.
A11: Analyst | B11: 3000000 | C11: =B11*$M$2 -> 3900000 | D11: Build+Run | E11: 0.5 | F11: 6 | G11: =C11/12*E11*F11 -> 975000 | H11: 0.5 | I11: =C11*H11 -> 1950000 | J11: Метрики, A/B, каннибализация. | K11: Бенчмарк зарплат: HH.ru / Habr Career (IT) + внутренние вилки курса; проверить на финальной оценке: калькуляция cost/FTE от HR/Finance.
A12: Product Designer | B12: 2400000 | C12: =B12*$M$2 -> 3120000 | D12: Build+Run | E12: 0.5 | F12: 4 | G12: =C12/12*E12*F12 -> 520000 | H12: 0.2 | I12: =C12*H12 -> 624000 | J12: Прототипы, UX, доверие. | K12: Бенчмарк зарплат: HH.ru / Habr Career (IT) + внутренние вилки курса; проверить на финальной оценке: калькуляция cost/FTE от HR/Finance.
A13: B2B CS/Account | B13: 2400000 | C13: =B13*$M$2 -> 3120000 | D13: Run | E13: 0.2 | F13: 2 | G13: =C13/12*E13*F13 -> 104000 | H13: 1 | I13: =C13*H13 -> 3120000 | J13: Запуск пакетов, удержание платящих. | K13: Бенчмарк зарплат: HH.ru / Habr Career (IT) + внутренние вилки курса; проверить на финальной оценке: калькуляция cost/FTE от HR/Finance.
A15: TOTAL | G15: =SUM(G4:G13) -> 18347333 | I15: =SUM(I4:I13) -> 25324000
A18: TtM breakdown
A19: Stage | B19: Months | C19: Outputs | D19: Risks | E19: Mitigation
A20: Discovery | B20: 1 | C20: Прототип КП, требования, метрики/guardrails. | D20: Неясные требования. | E20: UX-исследование, прототип, click-test.
A21: Build MVP | B21: 3 | C21: Шаблон КП v1, ранжирование v1, пакет v0. | D21: Техдолг/задержки. | E21: Фича-флаги, параллельная разработка.
A22: Beta / A-B | B22: 1 | C22: A/B 10–20% трафика, настройка метрик. | D22: Недостаточная мощность. | E22: Увеличить длительность/трафик.
A23: Launch ramp | B23: 1 | C23: Rollout 10/20/40/70/100. | D23: Инциденты. | E23: Canary rollout, on-call.

Sheet PnL
A1: PnL (до EBITDA), 2026–2030
A3: Line item | B3: 2026 | C3: 2027 | D3: 2028 | E3: 2029 | F3: 2030 | G3: Comment
A4: Revenue | B4: ='Baseline - Avito Стройка'!O25 -> 7.1231333e+08 | C4: ='Baseline - Avito Стройка'!P25 -> 8.0776332e+08 | D4: ='Baseline - Avito Стройка'!Q25 -> 9.160036e+08 | E4: ='Baseline - Avito Стройка'!R25 -> 1.0387481e+09 | F4: ='Baseline - Avito Стройка'!S25 -> 1.1779403e+09 | G4: Из baseline (ДЗ1–ДЗ3).
A5: Payroll | B5: ='Team & TtM'!G15+'Team & TtM'!I15*0.5 -> 31009333 | C5: ='Team & TtM'!I15 -> 25324000 | D5: ='Team & TtM'!I15*(1+Assumptions_DZ4!B10) -> 27856400 | E5: ='Team & TtM'!I15*(1+Assumptions_DZ4!B10)^2 -> 30642040 | F5: ='Team & TtM'!I15*(1+Assumptions_DZ4!B10)^3 -> 33706244 | G5: Команда build+run, loaded cost.
A6: Infra & tools | B6: =B5*Assumptions_DZ4!B6 -> 3100933.3 | C6: =C5*Assumptions_DZ4!B6 -> 2532400 | D6: =D5*Assumptions_DZ4!B6 -> 2785640 | E6: =E5*Assumptions_DZ4!B6 -> 3064204 | F6: =F5*Assumptions_DZ4!B6 -> 3370624.4 | G6: % от payroll.
A7: Support/Operations | B7: =B4*Assumptions_DZ4!B7 -> 21369400 | C7: =C4*Assumptions_DZ4!B7 -> 24232900 | D7: =D4*Assumptions_DZ4!B7 -> 27480108 | E7: =E4*Assumptions_DZ4!B7 -> 31162443 | F7: =F4*Assumptions_DZ4!B7 -> 35338210 | G7: % от revenue.
A8: Marketing | B8: =B4*Assumptions_DZ4!B8 -> 56985067 | C8: =C4*Assumptions_DZ4!B8 -> 64621066 | D8: =D4*Assumptions_DZ4!B8 -> 73280288 | E8: =E4*Assumptions_DZ4!B8 -> 83099847 | F8: =F4*Assumptions_DZ4!B8 -> 94235227 | G8: % от revenue (или CAC*new paying).
A9: G&A | B9: =B4*Assumptions_DZ4!B9 -> 14246267 | C9: =C4*Assumptions_DZ4!B9 -> 16155266 | D9: =D4*Assumptions_DZ4!B9 -> 18320072 | E9: =E4*Assumptions_DZ4!B9 -> 20774962 | F9: =F4*Assumptions_DZ4!B9 -> 23558807 | G9: % от revenue.
A10: Total OPEX | B10: =SUM(B5:B9) -> 1.26711e+08 | C10: =SUM(C5:C9) -> 1.3286563e+08 | D10: =SUM(D5:D9) -> 1.4972251e+08 | E10: =SUM(E5:E9) -> 1.687435e+08 | F10: =SUM(F5:F9) -> 1.9020911e+08 | G10: OPEX only, no CAPEX.
A11: EBITDA | B11: =B4-B10 -> 5.8560233e+08 | C11: =C4-C10 -> 6.7489769e+08 | D11: =D4-D10 -> 7.662811e+08 | E11: =E4-E10 -> 8.7000459e+08 | F11: =F4-F10 -> 9.8773122e+08 | G11: Revenue - OPEX.

Sheet CashFlow
A1: Operating CashFlow (direct), 2026–2030
A3: Line item | B3: 2026 | C3: 2027 | D3: 2028 | E3: 2029 | F3: 2030 | G3: Comment
A4: Cash In: Revenue receipts | B4: =PnL!B4 -> 7.1231333e+08 | C4: =PnL!C4 -> 8.0776332e+08 | D4: =PnL!D4 -> 9.160036e+08 | E4: =PnL!E4 -> 1.0387481e+09 | F4: =PnL!F4 -> 1.1779403e+09 | G4: Лаг 0 (упрощение).
A5: Cash Out: Payroll | B5: =PnL!B5 -> 31009333 | C5: =PnL!C5 -> 25324000 | D5: =PnL!D5 -> 27856400 | E5: =PnL!E5 -> 30642040 | F5: =PnL!F5 -> 33706244
A6: Cash Out: Infra & tools | B6: =PnL!B6 -> 3100933.3 | C6: =PnL!C6 -> 2532400 | D6: =PnL!D6 -> 2785640 | E6: =PnL!E6 -> 3064204 | F6: =PnL!F6 -> 3370624.4
A7: Cash Out: Support/Operations | B7: =PnL!B7 -> 21369400 | C7: =PnL!C7 -> 24232900 | D7: =PnL!D7 -> 27480108 | E7: =PnL!E7 -> 31162443 | F7: =PnL!F7 -> 35338210
A8: Cash Out: Marketing | B8: =PnL!B8 -> 56985067 | C8: =PnL!C8 -> 64621066 | D8: =PnL!D8 -> 73280288 | E8: =PnL!E8 -> 83099847 | F8: =PnL!F8 -> 94235227
A9: Cash Out: G&A | B9: =PnL!B9 -> 14246267 | C9: =PnL!C9 -> 16155266 | D9: =PnL!D9 -> 18320072 | E9: =PnL!E9 -> 20774962 | F9: =PnL!F9 -> 23558807
A10: Net operating cashflow | B10: =B4-SUM(B5:B9) -> 5.8560233e+08 | C10: =C4-SUM(C5:C9) -> 6.7489769e+08 | D10: =D4-SUM(D5:D9) -> 7.662811e+08 | E10: =E4-SUM(E5:E9) -> 8.7000459e+08 | F10: =F4-SUM(F5:F9) -> 9.8773122e+08 | G10: ≈ EBITDA без лагов.
A11: Cumulative cashflow | B11: =B10 -> 5.8560233e+08 | C11: =B11+C10 -> 1.2605e+09 | D11: =B12+D10 -> 7.662811e+08 | E11: =B13+E10 -> 8.7000459e+08 | F11: =B14+F10 -> 9.8773122e+08 | G11: Накопленный поток.

Sheet Checkers_DZ4
A1: Checkers — ДЗ4 (валидируем OPEX / PnL / CashFlow)
A3: Checker | B3: Value | C3: Expected / comment
A4: EBITDA formula check | B4: =PnL!B11/(PnL!B4-PnL!B10) -> 1 | C4: Should be 1.00
A5: Cashflow vs EBITDA check | B5: =CashFlow!B10/PnL!B11 -> 1 | C5: Should be ~1.00 (no lags)
A6: No CAPEX (manual) | B6: OK | C6: Проверено: CAPEX-строк нет; модель OPEX-only, разработка учтена в Payroll.
A7: Payroll includes build | B7: =PnL!B5/('Team & TtM'!G15) -> 1.6901275 | C7: Should be ≥ 1.0 (build cost covered)
A8: LTV/CAC (from DZ3) | B8: ='Монетизация и юнит'!C17 -> 13888.889 | C8: Target ≥ 3.00
A9: Payback months (from DZ3) | B9: ='Монетизация и юнит'!C18 -> 11805.556 | C9: Target ≤ 6–9 months

Sheet Монетизация и юнит
A1: Монетизация и юнит-экономика — Avito Стройка
A3: Параметры (Assumptions) | F3: Сенситивити: LTV vs retention
A4: Параметр | B4: Значение | C4: Ед. | D4: Комментарий/как проверить | F4: Retention | G4: Churn | H4: LTV (GM), ₽ | I4: LTV/CAC
A5: ARPU (исполнитель), ₽/год | B5: ='Assumptions - Baseline (Стройка'!B12 -> 2500 | C5: ₽/год | D5: Из baseline (ДЗ1). Проверка: выручка/активные исполнители по когорте.
A6: Share paying providers | B6: ='Assumptions - Baseline (Стройка'!B11 -> 0.1 | C6: % | D6: Доля платящих исполнителей. Проверка: paying/active providers по месяцам.
A7: ARPPU (платящий), ₽/мес | B7: ='Assumptions - Baseline (Стройка'!B16 -> 2083.3333 | C7: ₽/мес | D7: Derived: (ARPU_year/share_paying)/12.
A8: Gross margin (services) | B8: 0.85 | C8: % | D8: Допущение: высокая маржа digital-сервисов.
A9: Monthly retention paying | B9: 0.85 | C9: % | D9: Допущение для LTV. Проверка: когорты платящих (churn). | F9: 0.7 | G9: =1-F9 -> 0.3 | H9: =$B$7*$B$8/G9 -> 5902.7778 | I9: =H9/$B$10 -> 1.4756944
A10: CAC per paying provider, ₽ | B10: 4000 | C10: ₽ | D10: Бенчмарк для SMB/B2B. Проверка: spend/new paying. | F10: 0.75 | G10: =1-F10 -> 0.25 | H10: =$B$7*$B$8/G10 -> 7083.3333 | I10: =H10/$B$10 -> 1.7708333
F11: 0.8 | G11: =1-F11 -> 0.2 | H11: =$B$7*$B$8/G11 -> 8854.1667 | I11: =H11/$B$10 -> 2.2135417
F12: 0.85 | G12: =1-F12 -> 0.15 | H12: =$B$7*$B$8/G12 -> 11805.556 | I12: =H12/$B$10 -> 2.9513889
A13: Расчёт юнит-экономики (unit = paying provider) | F13: 0.9 | G13: =1-F13 -> 0.1 | H13: =$B$7*$B$8/G13 -> 17708.333 | I13: =H13/$B$10 -> 4.4270833
A14: Метрика | B14: Формула | C14: Значение | D14: Интерпретация | F14: 0.92 | G14: =1-F14 -> 0.08 | H14: =$B$7*$B$8/G14 -> 22135.417 | I14: =H14/$B$10 -> 5.5338542
A15: Churn (monthly) | B15: =1-$B$9 -> 0.15 | C15: =1-$B$9 -> 0.15 | D15: Monthly churn. | F15: 0.95 | G15: =1-F15 -> 0.05 | H15: =$B$7*$B$8/G15 -> 35416.667 | I15: =H15/$B$10 -> 8.8541667
A16: Expected lifetime, months | B16: =1/(1-$B$9) -> 6.6666667 | C16: =1/(1-$B$9) -> 6.6666667 | D16: 1/churn.
A17: LTV (gross), ₽ | B17: =$B$7*1/(1-$B$9) -> 13888.889 | C17: =$B$7*1/(1-$B$9) -> 13888.889 | D17: Revenue over lifetime.
A18: LTV (GM), ₽ | B18: =$B$7*$B$8/(1-$B$9) -> 11805.556 | C18: =$B$7*$B$8/(1-$B$9) -> 11805.556 | D18: LTV with gross margin.
A19: CAC, ₽ | B19: =$B$10 -> 4000 | C19: =$B$10 -> 4000 | D19: Acquisition cost per new paying.
A20: LTV/CAC | B20: =C18/C19 -> 2.9513889 | C20: =C18/C19 -> 2.9513889 | D20: Target ≥ 3.
A21: Payback, months | B21: =C19/($B$7*$B$8) -> 2.2588235 | C21: =C19/($B$7*$B$8) -> 2.2588235 | D21: CAC payback in months.

Sheet Checkers
A1: Чекеры валидации модели
A3: Checker | B3: Value | C3: Expected / comment
A4: Seasonality avg | B4: ='Baseline - Avito Стройка'!O28 -> 0.0004 | C4: Should be 1.00
A5: Seasonality sum | B5: ='Baseline - Avito Стройка'!O29 -> 0.0048 | C5: Should be 12.00
A6: Contacts 2026 / Contacts_Y1 | B6: ='Baseline - Avito Стройка'!O30 -> 1.0257312 | C6: Should be 100%
A7: Deals 2026 / Deals_Y1 | B7: ='Baseline - Avito Стройка'!O31 -> 1.0257312 | C7: Close to 100% (or within chosen range)
A8: ARPPU formula check | B8: ='Assumptions - Baseline (Стройка'!B16/(('Assumptions - Baseline (Стройка'!B12/'Assumptions - Baseline (Стройка'!B11)/12) -> 1 | C8: Should be 1.00
A9: LTV/CAC (GM) | B9: ='Монетизация и юнит'!C20 -> 2.9513889 | C9: Target ≥ 3.00

Sheet Гипотезы
A1: Avito Стройка — ДЗ №2. Гипотезы роста (2–3) + учёт каннибализации. Формат соответствует шаблону: uplift 2026–2030, % раскатки, источники/референсы, метод проверки, каннибализация, сценарии.
A2: Гипотеза | B2: Метрика | C2: Status | D2: Confidence | E2: Confidence Rate | F2: uplift | K2: % раскатки | P2: Источник / обоснование (ссылки) | Q2: Метод проверки (срок/выборка/guardrails) | R2: Риск каннибализации (и учёт в модели) | S2: Комментарий | T2: Сценарий 1 | U2: Сценарий 2
F3: 2026 | G3: 2027 | H3: 2028 | I3: 2029 | J3: 2030 | K3: 2026 | L3: 2027 | M3: 2028 | N3: 2029 | O3: 2030
A4: Если мы внедрим структурированный шаблон КП/сметы + чек‑лист обязательных полей (стоимость, сроки, материалы, гарантия) и единый формат сравнения предложений, то CR контакт→сделка (Conversion to Deal) вырастет на +5–10 п.п. (консервативно моделируем как +3–8% относит. uplift к CR) у заказчиков, потому что предложения станут сопоставимыми и снизится сложность выбора. | B4: CR | C4: not started | D4: high | E4: 80% | F4: 3% | G4: 5% | H4: 6% | I4: 7% | J4: 8% | K4: 10% | L4: 40% | M4: 70% | N4: 100% | O4: 100% | P4: Внутренние референсы из прошлых ДЗ: ожидаемый бизнес‑эффект от шаблонов КП — рост Conversion to Deal на +5–10 п.п. и рост запросов на +10–15% при стабильных SLA (ДЗ№4, план исследований). Прокси‑метрики и риски (TTFR, отмены, CTR на КП) описаны в дереве метрик (ДЗ№1 Анализ данных). | Q4: Пошаговая проверка: (1) интервью + прототип (Figma) + клик‑тест (1–2 недели), (2) Fake Door (CTR на «КП по шаблону») 1–2 недели, (3) A/B-тест 10% трафика 3–4 недели или до n≥3–5k сделок/конверсий. Primary: CR contact→deal. Guardrails: TTFR, cancellation, CTR на КП, NPS/CES. | R4: Риск: усложнение жизни исполнителям → рост TTFR/снижение отклика и отток части исполнителей (падение active listings), а также снижение потребности в платном продвижении у части (органика растёт). Учёт: в сценарии 2 вводим коэффициент −1% к Active listings при 100% rollout и/или −0.5 п.п. к Share paying (∝rollout). | S4: Ключевая гипотеза из прошлых ДЗ: снижает «разнородность КП» и ускоряет выбор. | T4: включено | U4: включено
A5: Если мы внедрим фильтры по специализациям/типу работ и улучшим ранжирование (учёт рейтинга, скорости ответа, портфолио), то CR просмотр→контакт вырастет на +2–5% и увеличится доля релевантных просмотров, потому что заказчик быстрее находит подходящего подрядчика. | B5: CR | C5: not started | D5: medium | E5: 70% | F5: 2% | G5: 3% | H5: 4% | I5: 5% | J5: 5% | K5: 0% | L5: 20% | M5: 60% | N5: 100% | O5: 100% | P5: Аналоги персонализированного ранжирования: eBay (user-based ranking) https://innovation.ebayinc.com/stories/evolving-recommendations-a-personalized-user-based-ranking-model/ ; SIGIR eCom’21 (personalized ranking live traffic): https://sigir-ecom.github.io/ecom21Papers/paper9.pdf . | Q5: A/B: 10–20% трафика, 3–4 недели (или до n≥10k sessions). Primary: Views/listing, CR view→contact. Guardrails: концентрация показов (Gini), жалобы, retention исполнителей, active listings. | R5: Риск: перераспределение показов в пользу «топов» → отток long-tail → падение инвентаря. Учёт: −1% к Active listings при 100% (лаг 1–2 мес/квартал) в сценарии 2. | S5: Гипотеза про релевантность выдачи; критичны контр‑метрики по распределению трафика. | T5: включено | U5: включено
A6: Если мы запустим B2B пакет для исполнителей «фиксированные показы/лиды + аналитика», то вырастут доля платящих (+2 п.п.) и ARPPU (+5–10%), потому что повысится предсказуемость окупаемости и ценность платных инструментов. | B6: ARPPU | C6: not started | D6: medium | E6: 50% | F6: 0% | G6: 5% | H6: 8% | I6: 10% | J6: 10% | K6: 0% | L6: 10% | M6: 40% | N6: 70% | O6: 100% | P6: RevenueCat (hybrid monetization/cannibalization): https://www.revenuecat.com/blog/growth/hybrid-monetization-techniques/ ; Simon‑Kucher (ARPU growth кейс как верхняя граница): https://www.simon-kucher.com/en/insights/driving-growth-re-balancing-monetization-software-and-payments . | Q6: Пилот (MVP) 2–3 региона/подкатегории, 4–6 недель. Primary: CR leads→paying, ARPPU. Guardrails: churn платящих, support tickets, NPS исполнителей. Далее A/B раскатка 10/20/40/70/100. | R6: Каннибализация: переток бюджета с existing promo → net ARPPU ниже. Учёт: коэффициент 40% (net uplift = uplift*(1−0.4)) + мониторинг mix выручки. | S6: Гипотеза про монетизацию supply; считать net uplift после каннибализации. | T6: не включено | U6: включено

Sheet Graph_2026_Contacts
A1: График: baseline vs baseline + uplift (Contacts), 2026
A2: Baseline Contacts подтягиваются ссылками из листа Baseline (Jan–Dec). При желании uplift/rollout можно связать с листом «Гипотезы».
A4: Metric / Inputs | B4: Jan | C4: Feb | D4: Mar | E4: Apr | F4: May | G4: Jun | H4: Jul | I4: Aug | J4: Sep | K4: Oct | L4: Nov | M4: Dec | N4: Sum
A5: Contacts baseline | B5: 127500 | C5: 142500 | D5: 157500 | E5: 165000 | F5: 165000 | G5: 165000 | H5: 150000 | I5: 142500 | J5: 150000 | K5: 157500 | L5: 157500 | M5: 120000 | N5: =SUM(B5:M5) -> 1800000
A6: Rollout H1 (2026) | B6: 0 | C6: 0.1 | D6: 0.2 | E6: 0.4 | F6: 0.7 | G6: 1 | H6: 1 | I6: 1 | J6: 1 | K6: 1 | L6: 1 | M6: 1 | N6: =AVERAGE(B6:M6) -> 0.7
A7: Rollout H2 (2026) | B7: 0 | C7: 0 | D7: 0 | E7: 0.1 | F7: 0.2 | G7: 0.4 | H7: 0.7 | I7: 1 | J7: 1 | K7: 1 | L7: 1 | M7: 1 | N7: =AVERAGE(B7:M7) -> 0.53333333
A8: Uplift H1 (2026, %) | B8: 0.03 | C8: =$B8 -> 0.03 | D8: =$B8 -> 0.03 | E8: =$B8 -> 0.03 | F8: =$B8 -> 0.03 | G8: =$B8 -> 0.03 | H8: =$B8 -> 0.03 | I8: =$B8 -> 0.03 | J8: =$B8 -> 0.03 | ... N8: =$B8 -> 0.03
A9: Uplift H2 (2026, %) | B9: 0.02 | C9: =$B9 -> 0.02 | D9: =$B9 -> 0.02 | E9: =$B9 -> 0.02 | F9: =$B9 -> 0.02 | G9: =$B9 -> 0.02 | H9: =$B9 -> 0.02 | I9: =$B9 -> 0.02 | J9: =$B9 -> 0.02 | ... N9: =$B9 -> 0.02
A10: Total uplift % | B10: =B8*B6+B9*B7 -> 0 | C10: =C8*C6+C9*C7 -> 0.003 | D10: =D8*D6+D9*D7 -> 0.006 | E10: =E8*E6+E9*E7 -> 0.014 | F10: =F8*F6+F9*F7 -> 0.025 | G10: =G8*G6+G9*G7 -> 0.038 | H10: =H8*H6+H9*H7 -> 0.044 | I10: =I8*I6+I9*I7 -> 0.05 | ... M10: =M8*M6+M9*M7 -> 0.05 | N10: =AVERAGE(B10:M10) -> 0.031666667
A11: Contacts baseline + uplift | B11: =B5*(1+B10) -> 127500 | C11: =C5*(1+C10) -> 142927.5 | D11: =D5*(1+D10) -> 158445 | E11: =E5*(1+E10) -> 167310 | F11: =F5*(1+F10) -> 169125 | G11: =G5*(1+G10) -> 171270 | H11: =H5*(1+H10) -> 156600 | I11: =I5*(1+I10) -> 149625 | ... M11: =M5*(1+M10) -> 126000 | N11: =SUM(B11:M11) -> 1857052.5

Sheet Baseline - Avito Стройка
A1: Baseline model - Avito Стройка
A3: Metric | B3: Unit | C3: 2026 Jan | D3: 2026 Feb | E3: 2026 Mar | F3: 2026 Apr | G3: 2026 May | H3: 2026 Jun | I3: 2026 Jul | J3: 2026 Aug | K3: 2026 Sep | L3: 2026 Oct | M3: 2026 Nov | N3: 2026 Dec | O3: 2026 | P3: 2027 | Q3: 2028 | R3: 2029 | S3: 2030 | T3: 5Y (2026-2030)
A5: Assumptions (links)
A6: Seasonality coefficient | B6: x | C6: ='Assumptions - Baseline (Стройка'!B20 -> 0.85 | D6: ='Assumptions - Baseline (Стройка'!C20 -> 0.95 | E6: ='Assumptions - Baseline (Стройка'!D20 -> 1.05 | F6: ='Assumptions - Baseline (Стройка'!E20 -> 1.1 | G6: ='Assumptions - Baseline (Стройка'!F20 -> 1.1 | H6: ='Assumptions - Baseline (Стройка'!G20 -> 1.1 | I6: ='Assumptions - Baseline (Стройка'!H20 -> 1 | J6: ='Assumptions - Baseline (Стройка'!I20 -> 0.95 | ... N6: ='Assumptions - Baseline (Стройка'!M20 -> 0.8 | O6: =AVERAGE(C6:N6) -> 1 | P6: =O6 -> 1 | Q6: =O6 -> 1 | R6: =O6 -> 1 | S6: =O6 -> 1 | T6: =O6 -> 1
A7: CR view → contact | B7: % | C7: =O7 -> 0.0004 | D7: =O7 -> 0.0004 | E7: =O7 -> 0.0004 | F7: =O7 -> 0.0004 | G7: =O7 -> 0.0004 | H7: =O7 -> 0.0004 | I7: =O7 -> 0.0004 | J7: =O7 -> 0.0004 | K7: =O7 -> 0.0004 | L7: =O7 -> 0.0004 | M7: =O7 -> 0.0004 | N7: =O7 -> 0.0004 | O7: ='Assumptions - Baseline (Стройка'!B7 -> 0.0004 | P7: =O7 -> 0.0004 | Q7: =O7 -> 0.0004 | R7: =O7 -> 0.0004 | S7: =O7 -> 0.0004 | T7: =O7 -> 0.0004
A8: CR contact → deal | B8: % | C8: =O8 -> 0.16666667 | D8: =O8 -> 0.16666667 | E8: =O8 -> 0.16666667 | F8: =O8 -> 0.16666667 | G8: =O8 -> 0.16666667 | H8: =O8 -> 0.16666667 | I8: =O8 -> 0.16666667 | J8: =O8 -> 0.16666667 | K8: =O8 -> 0.16666667 | L8: =O8 -> 0.16666667 | M8: =O8 -> 0.16666667 | N8: =O8 -> 0.16666667 | O8: ='Assumptions - Baseline (Стройка'!B6 -> 0.16666667 | P8: =O8 -> 0.16666667 | Q8: =O8 -> 0.16666667 | R8: =O8 -> 0.16666667 | S8: =O8 -> 0.16666667 | T8: =O8 -> 0.16666667
A9: Active listings (Jan) | B9: listings | C9: =O9 -> 427388 | D9: =O9 -> 427388 | E9: =O9 -> 427388 | F9: =O9 -> 427388 | G9: =O9 -> 427388 | H9: =O9 -> 427388 | I9: =O9 -> 427388 | J9: =O9 -> 427388 | K9: =O9 -> 427388 | L9: =O9 -> 427388 | M9: =O9 -> 427388 | N9: =O9 -> 427388 | O9: ='Assumptions - Baseline (Стройка'!B8 -> 427388 | P9: =O9 -> 427388 | Q9: =O9 -> 427388 | R9: =O9 -> 427388 | S9: =O9 -> 427388 | T9: =O9 -> 427388
A10: Listings per provider per month | B10: list/provider | C10: =O10 -> 1.5 | D10: =O10 -> 1.5 | E10: =O10 -> 1.5 | F10: =O10 -> 1.5 | G10: =O10 -> 1.5 | H10: =O10 -> 1.5 | I10: =O10 -> 1.5 | J10: =O10 -> 1.5 | K10: =O10 -> 1.5 | L10: =O10 -> 1.5 | M10: =O10 -> 1.5 | N10: =O10 -> 1.5 | O10: ='Assumptions - Baseline (Стройка'!B9 -> 1.5 | P10: =O10 -> 1.5 | Q10: =O10 -> 1.5 | R10: =O10 -> 1.5 | S10: =O10 -> 1.5 | T10: =O10 -> 1.5
A11: Views per listing per month | B11: views/listing | C11: =O11 -> 900 | D11: =O11 -> 900 | E11: =O11 -> 900 | F11: =O11 -> 900 | G11: =O11 -> 900 | H11: =O11 -> 900 | I11: =O11 -> 900 | J11: =O11 -> 900 | K11: =O11 -> 900 | L11: =O11 -> 900 | M11: =O11 -> 900 | N11: =O11 -> 900 | O11: ='Assumptions - Baseline (Стройка'!B10 -> 900 | P11: =O11 -> 900 | Q11: =O11 -> 900 | R11: =O11 -> 900 | S11: =O11 -> 900 | T11: =O11 -> 900
A12: Share paying providers | B12: % | C12: =O12 -> 0.1 | D12: =O12 -> 0.1 | E12: =O12 -> 0.1 | F12: =O12 -> 0.1 | G12: =O12 -> 0.1 | H12: =O12 -> 0.1 | I12: =O12 -> 0.1 | J12: =O12 -> 0.1 | K12: =O12 -> 0.1 | L12: =O12 -> 0.1 | M12: =O12 -> 0.1 | N12: =O12 -> 0.1 | O12: ='Assumptions - Baseline (Стройка'!B11 -> 0.1 | P12: =O12 -> 0.1 | Q12: =O12 -> 0.1 | R12: =O12 -> 0.1 | S12: =O12 -> 0.1 | T12: =O12 -> 0.1
A13: ARPPU (month) | B13: RUB/month | C13: =O13 -> 2083.3333 | D13: =O13 -> 2083.3333 | E13: =O13 -> 2083.3333 | F13: =O13 -> 2083.3333 | G13: =O13 -> 2083.3333 | H13: =O13 -> 2083.3333 | I13: =O13 -> 2083.3333 | J13: =O13 -> 2083.3333 | K13: =O13 -> 2083.3333 | L13: =O13 -> 2083.3333 | M13: =O13 -> 2083.3333 | N13: =O13 -> 2083.3333 | O13: ='Assumptions - Baseline (Стройка'!B16 -> 2083.3333 | P13: =O13*(1+'Assumptions - Baseline (Стройка'!B15) -> 2187.5 | Q13: =P13*(1+'Assumptions - Baseline (Стройка'!B15) -> 2296.875 | R13: =Q13*(1+'Assumptions - Baseline (Стройка'!B15) -> 2411.7188 | S13: =R13*(1+'Assumptions - Baseline (Стройка'!B15) -> 2532.3047 | T13: =O13 -> 2083.3333
A15: Product funnel
A16: Active listings | B16: listings | C16: =O9 -> 427388 | D16: =C16 -> 427388 | E16: =C16 -> 427388 | F16: =C16 -> 427388 | G16: =C16 -> 427388 | H16: =C16 -> 427388 | I16: =C16 -> 427388 | J16: =C16 -> 427388 | K16: =C16 -> 427388 | L16: =C16 -> 427388 | M16: =C16 -> 427388 | N16: =C16 -> 427388 | O16: =AVERAGE(C16:N16) -> 427388 | P16: =O16*(1+'Assumptions - Baseline (Стройка'!B14) -> 461579.04 | Q16: =P16*(1+'Assumptions - Baseline (Стройка'!B14) -> 498505.36 | R16: =Q16*(1+'Assumptions - Baseline (Стройка'!B14) -> 538385.79 | S16: =R16*(1+'Assumptions - Baseline (Стройка'!B14) -> 581456.66 | T16: =SUM(O16:S16) -> 2507314.9
A17: Views | B17: views | C17: =C16*C11*C6 -> 3.2695182e+08 | D17: =D16*D11*D6 -> 3.6541674e+08 | E17: =E16*E11*E6 -> 403881660 | F17: =F16*F11*F6 -> 4.2311412e+08 | G17: =G16*G11*G6 -> 4.2311412e+08 | H17: =H16*H11*H6 -> 4.2311412e+08 | I17: =I16*I11*I6 -> 3.846492e+08 | J17: =J16*J11*J6 -> 3.6541674e+08 | ... N17: =N16*N11*N6 -> 3.0771936e+08 | O17: =SUM(C17:N17) -> 4615790400 | P17: =P16*P11*12 -> 4.9850536e+09 | Q17: =Q16*Q11*12 -> 5.3838579e+09 | R17: =R16*R11*12 -> 5.8145666e+09 | S17: =S16*S11*12 -> 6.2797319e+09 | T17: =SUM(O17:S17) -> 2.7079e+10
A18: Contacts (raw) | B18: contacts | C18: =C17*C7 -> 130780.73 | D18: =D17*D7 -> 146166.7 | E18: =E17*E7 -> 161552.66 | F18: =F17*F7 -> 169245.65 | G18: =G17*G7 -> 169245.65 | H18: =H17*H7 -> 169245.65 | I18: =I17*I7 -> 153859.68 | J18: =J17*J7 -> 146166.7 | ... N18: =N17*N7 -> 123087.74 | O18: =SUM(C18:N18) -> 1846316.2 | P18: =O18*(1+'Assumptions - Baseline (Стройка'!B13) -> 2030947.8 | Q18: =P18*(1+'Assumptions - Baseline (Стройка'!B13) -> 2234042.6 | R18: =Q18*(1+'Assumptions - Baseline (Стройка'!B13) -> 2457446.8 | S18: =R18*(1+'Assumptions - Baseline (Стройка'!B13) -> 2703191.5 | T18: =SUM(O18:S18) -> 11271945
A19: Contacts (leads) | B19: contacts | C19: =C18*'Assumptions - Baseline (Стройка'!$B$17 -> 127500 | D19: =D18*'Assumptions - Baseline (Стройка'!$B$17 -> 142500 | E19: =E18*'Assumptions - Baseline (Стройка'!$B$17 -> 157500 | F19: =F18*'Assumptions - Baseline (Стройка'!$B$17 -> 165000 | G19: =G18*'Assumptions - Baseline (Стройка'!$B$17 -> 165000 | H19: =H18*'Assumptions - Baseline (Стройка'!$B$17 -> 165000 | I19: =I18*'Assumptions - Baseline (Стройка'!$B$17 -> 150000 | J19: =J18*'Assumptions - Baseline (Стройка'!$B$17 -> 142500 | ... N19: =N18*'Assumptions - Baseline (Стройка'!$B$17 -> 120000 | O19: =SUM(C19:N19) -> 1800000 | P19: =P18*'Assumptions - Baseline (Стройка'!$B$17 -> 1980000 | Q19: =Q18*'Assumptions - Baseline (Стройка'!$B$17 -> 2178000 | R19: =R18*'Assumptions - Baseline (Стройка'!$B$17 -> 2395800 | S19: =S18*'Assumptions - Baseline (Стройка'!$B$17 -> 2635380 | T19: =T18*'Assumptions - Baseline (Стройка'!$B$17 -> 10989180
A20: Deals (offline outcome) | B20: deals | C20: =C18*C8 -> 21796.788 | D20: =D18*D8 -> 24361.116 | E20: =E18*E8 -> 26925.444 | F20: =F18*F8 -> 28207.608 | G20: =G18*G8 -> 28207.608 | H20: =H18*H8 -> 28207.608 | I20: =I18*I8 -> 25643.28 | J20: =J18*J8 -> 24361.116 | ... N20: =N18*N8 -> 20514.624 | O20: =SUM(C20:N20) -> 307719.36 | P20: =O20*(1+'Assumptions - Baseline (Стройка'!B13) -> 338491.3 | Q20: =P20*(1+'Assumptions - Baseline (Стройка'!B13) -> 372340.43 | R20: =Q20*(1+'Assumptions - Baseline (Стройка'!B13) -> 409574.47 | S20: =R20*(1+'Assumptions - Baseline (Стройка'!B13) -> 450531.91 | T20: =SUM(O20:S20) -> 1878657.5
A22: Monetization (B2B services)
A23: Active providers (estimated) | B23: providers | C23: =C16/C10 -> 284925.33 | D23: =D16/D10 -> 284925.33 | E23: =E16/E10 -> 284925.33 | F23: =F16/F10 -> 284925.33 | G23: =G16/G10 -> 284925.33 | H23: =H16/H10 -> 284925.33 | I23: =I16/I10 -> 284925.33 | J23: =J16/J10 -> 284925.33 | ... N23: =N16/N10 -> 284925.33 | O23: =AVERAGE(C23:N23) -> 284925.33 | P23: =P16/P10 -> 307719.36 | Q23: =Q16/Q10 -> 332336.91 | R23: =R16/R10 -> 358923.86 | S23: =S16/S10 -> 387637.77 | T23: =SUM(O23:S23) -> 1671543.2
A24: Paying providers | B24: providers | C24: =C23*C12 -> 28492.533 | D24: =D23*D12 -> 28492.533 | E24: =E23*E12 -> 28492.533 | F24: =F23*F12 -> 28492.533 | G24: =G23*G12 -> 28492.533 | H24: =H23*H12 -> 28492.533 | I24: =I23*I12 -> 28492.533 | J24: =J23*J12 -> 28492.533 | ... N24: =N23*N12 -> 28492.533 | O24: =AVERAGE(C24:N24) -> 28492.533 | P24: =P23*P12 -> 30771.936 | Q24: =Q23*Q12 -> 33233.691 | R24: =R23*R12 -> 35892.386 | S24: =S23*S12 -> 38763.777 | T24: =SUM(O24:S24) -> 167154.32
A25: Revenue | B25: RUB | C25: =C24*C13 -> 59359444 | D25: =D24*D13 -> 59359444 | E25: =E24*E13 -> 59359444 | F25: =F24*F13 -> 59359444 | G25: =G24*G13 -> 59359444 | H25: =H24*H13 -> 59359444 | I25: =I24*I13 -> 59359444 | J25: =J24*J13 -> 59359444 | ... N25: =N24*N13 -> 59359444 | O25: =SUM(C25:N25) -> 7.1231333e+08 | P25: =P24*P13*12 -> 8.0776332e+08 | Q25: =Q24*Q13*12 -> 9.160036e+08 | R25: =R24*R13*12 -> 1.0387481e+09 | S25: =S24*S13*12 -> 1.1779403e+09 | T25: =SUM(O25:S25) -> 4.6527687e+09
A27: Sanity checks
A28: Seasonality avg (should be 1.00) | B28: x | O28: =AVERAGE(C7:N7) -> 0.0004
A29: Seasonality sum (should be 12.00) | B29: x | O29: =SUM(C7:N7) -> 0.0048
A30: Contacts vs Contacts_Y1 (assumption) | B30: ratio | O30: =O18/'[1]Assumptions - Baseline (Стройка'!B4 -> 1.0257312
A31: Deals vs Deals_Y1 (assumption) | B31: ratio | O31: =O20/'[1]Assumptions - Baseline (Стройка'!B5 -> 1.0257312

Sheet Assumptions - Baseline (Стройка
A1: Baseline assumptions - Avito Стройка
A2: Parameter | B2: Value | C2: Unit | D2: Comment | E2: Source / note | F2: Confidence
A3: Year 1 (baseline year) | B3: 2026 | D3: Первый год прогноза (помесячно) | E3: Данные ДЗ №1 (горизонт прогноза: 2026 помесячно, далее годами) | F3: High
A4: Contacts_Y1 | B4: 1800000 | C4: contacts/year | D4: Из данных ДЗ: 1.8 млн/год трактуем как лиды/контакты | E4: Данные ДЗ №1 (вкладка “Данные…”, Стройка: 1.8 млн/год; трактуем как contacts/leads) | F4: Med
A5: Deals_Y1 | B5: 300000 | C5: deals/year | D5: Из данных ДЗ: 300 тыс сделок/год (офлайн outcome) | E5: Данные ДЗ №1 (Стройка: 300 тыс сделок/год; офлайн outcome) | F5: Med
A6: CR_contact_to_deal | B6: =B5/B4 -> 0.16666667 | C6: % | D6: Формула: Deals_Y1 / Contacts_Y1 | E6: Derived: =Deals_Y1 / Contacts_Y1 (расчёт из данных ДЗ) | F6: High
A7: CR_view_to_contact | B7: 0.0004 | C7: share | D7: ДЗ: 0.03–0.05% (берём 0.04%) | E7: Данные ДЗ №1: 0.03–0.05% (берём 0.04% как midpoint диапазона) | F7: Med
A8: Active_listings_Jan | B8: 427388 | C8: listings | D8: Стартовое допущение; калибруется под Contacts_Y1 | E8: Калибровано под Contacts_Y1 из ДЗ через воронку Active listings → Views → Contacts при заданных CR и сезонности; требует валидации по фактическому инвентарю категории (внутр. аналитика). | F8: Low
A9: Listings_per_provider_per_month | B9: 1.5 | C9: list/provider | D9: ДЗ: 1.2–1.8 (берём 1.5) | E9: Данные ДЗ №1: 1.2–1.8 (берём 1.5 как среднее значение диапазона) | F9: Med
A10: Views_per_listing_per_month | B10: 900 | C10: views/listing | D10: Калибровка под Contacts_Y1 при CR view→contact | E10: Калибровочный параметр: подобран так, чтобы годовой Contacts в модели совпал с Contacts_Y1 (1.8 млн) при CR view→contact=0.04%; требует валидации по просмотрам категории. | F10: Low
A11: Share_paying_providers | B11: 0.1 | C11: share | D11: Доля платящих исполнителей (baseline) | E11: Экспертная оценка baseline: доля платящих исполнителей в classifieds/услугах обычно однозначные проценты; взято 10% как консервативное значение, требует валидации по внутр. данным/аналогам. | F11: Low
A12: ARPU_provider_year | B12: 2500 | C12: RUB/year | D12: ДЗ: 1 200–3 500 ₽/год (берём 2 500) | E12: Данные ДЗ №1: ARPU продавца 1 200–3 500 ₽/год (берём 2 500 ₽ как midpoint) | F12: Med
A13: YoY_growth_contacts | B13: 0.1 | C13: share | D13: Базовый рост лидов YoY | E13: Экспертная оценка baseline без гипотез роста: умеренный рост спроса/проникновения онлайн; при наличии заменить на CAGR рынка/категории (источник/отчёт). | F13: Low
A14: YoY_growth_listings | B14: 0.08 | C14: share | D14: Базовый рост объявлений YoY | E14: Экспертная оценка: рост предложения следует за спросом; baseline ниже роста контактов (0.08 vs 0.10), требует валидации по динамике активных объявлений. | F14: Low
A15: YoY_growth_ARPU | B15: 0.05 | C15: share | D15: Индексация ARPU YoY | E15: Индексация тарифов/инфляция + микс платных услуг; при наличии добавить ссылку (например, официальная инфляция Росстат или практика индексации тарифов). | F15: Low
A16: ARPPU_month | B16: =(B12/B11)/12 -> 2083.3333 | C16: RUB/month | D16: ARPPU = (ARPU_provider_year / Share_paying) / 12 | E16: Derived: =(ARPU_provider_year / Share_paying_providers) / 12 | F16: High
A17: Calibration_factor_contacts | B17: =B4/'Baseline - Avito Стройка'!O18 -> 0.97491429 | E17: Derived: =Contacts_Y1 / Contacts_raw_2026. Используется для точной калибровки baseline под данные ДЗ (0% отклонения по 2026).
A18: Seasonality (avg=1.0)
A19: Month | B19: Jan | C19: Feb | D19: Mar | E19: Apr | F19: May | G19: Jun | H19: Jul | I19: Aug | J19: Sep | K19: Oct | L19: Nov | M19: Dec
A20: Coefficient | B20: 0.85 | C20: 0.95 | D20: 1.05 | E20: 1.1 | F20: 1.1 | G20: 1.1 | H20: 1 | I20: 0.95 | J20: 1 | K20: 1.05 | L20: 1.05 | M20: 0.8

Sheet Top-down
A1: Top-down sanity check — Avito Стройка
A2: Параметр | B2: Значение | C2: Ед. | D2: Источник/комментарий
A3: TAM (рынок стройки/ремонта), ₽/год | B3: 1200000000000 | C3: ₽ | D3: Данные для ДЗ №1
A4: Online share (SAM/TAM) | B4: 0.2 | C4: % | D4: Данные для ДЗ №1
A5: Avito share within online (SOM/SAM) | B5: 0.25 | C5: % | D5: Данные для ДЗ №1
A6: AOV (средний чек работ), ₽ | B6: 120000 | C6: ₽ | D6: Бенчмарк/экспертная оценка; заменить ссылкой при наличии
A7: Contacts per deal (Contacts_Y1 / Deals_Y1) | B7: ='[1]Assumptions - Baseline (Стройка'!B4/'[1]Assumptions - Baseline (Стройка'!B5 -> 6 | C7: contacts/deal | D7: Derived из данных ДЗ
A9: Расчёт
A10: SAM, ₽/год | B10: =B3*B4 -> 240000000000
A11: SOM-cap (market volume), ₽/год | B11: =B10*B5 -> 60000000000
A12: SOM deals (approx), deals/год | B12: =B11/B6 -> 500000
A13: SOM contacts (approx), contacts/год | B13: =B12*B7 -> 3000000
A14: Bottom-up Contacts 2026 (from model) | B14: ='[1]Baseline - Avito Стройка'!O18 -> 0 | D14: Ссылка на baseline (колонка 2026)
A15: Share bottom-up / SOM contacts | B15: =B14/B13 -> 0 | D15: Должно быть значительно < 100%

Sheet Текст
A1: Я строю baseline-прогноз для направления Avito Стройка. Это категория в Avito, которая помогает заказчикам находить подрядчиков и исполнителей строительных и ремонтных работ. Ключевая специфика продукта — оплата и сделка происходят вне платформы: Avito не является транзакционным посредником и не зарабатывает take rate с суммы работ. Поэтому для Стройки корректная продуктовая логика — не GMV и не доля транзакций “внутри”, а качество матчинга и лид-генерация. Пользовательская ценность измеряется тем, что заказчик находит подходящего исполнителя и связывается с ним, а бизнес-ценность для Avito — монетизацией исполнителей через платные инструменты (продвижение, пакеты, платные опции размещения). Целевая аудитория двусторонняя. Со стороны спроса это прежде всего частные заказчики (B2C), которым нужен ремонт/строительство и отдельные работы; частично — малый бизнес/управляющие компании (в зависимости от сегмента). Со стороны предложения — мастера, бригады и небольшие строительные компании, которые размещают объявления, конкурируют за внимание заказчиков и покупают платные инструменты продвижения. Продукт решает для заказчика проблему быстрого поиска подрядчика и снижения неопределённости по качеству/срокам/надёжности; для исполнителя — проблему стабильного потока обращений и видимости в выдаче. Целевая метрика (North Star / NSM) для baseline выбрана как количество контактов (Contacts / Leads) — число обращений заказчиков к исполнителям (звонок, чат, открытие контакта). Это оптимальная NSM для нетранзакционного: контакт отражает реальное намерение и является самым ранним измеримым “успехом” матчинга, который коррелирует с вероятностью офлайн-сделки. Для того чтобы NSM была управляемой, я связываю её с прокси-метриками, которые продукт реально может улучшать: Active listings (инвентарь объявлений) → Views (просмотры) → CR view→contact (конверсия просмотр→контакт). Именно эта цепочка позволяет прозрачно объяснить, что лежит “под капотом” контактов: наличие актуальных объявлений, распределение трафика и эффективность карточки/контактного действия. Дополнительно, хотя Avito не фиксирует оплату внутри платформы, я оставляю outcome-метрику Deals (офлайн) как “дальний” результат и sanity check ценности. Коммерческие метрики (для бизнеса Avito) строятся отдельно: Active providers → Paying providers → ARPPU → Revenue. Таким образом метрики в модели логически связаны: продуктовые драйверы создают поток контактов, который повышает ценность для исполнителей и поддерживает монетизацию со стороны предложения. Для расчёта baseline я использую комбинацию bottom-up и top-down, причём bottom-up — основной метод. Это осознанный выбор, потому что у Стройки нет транзакций внутри Avito, и подход “рынок → GMV → take rate → revenue” здесь методологически неверен. Bottom-up позволяет моделировать именно те микропараметры, которыми реально управляет Avito: объём и активность контента, просмотры, конверсии в контакт, долю платящих исполнителей и ARPU/ARPPU. Top-down я использую как ограничитель и проверку реалистичности: через TAM/SAM/SOM оцениваю верхнюю границу масштаба, чтобы baseline не “пробивал” ёмкость рынка и не уходил в нереалистичный рост. Такое сочетание отражает специфику продукта: bottom-up даёт детальную, проверяемую по формулам динамику, а top-down задаёт “потолок” и снижает риск самообмана. Расчёт baseline организован так, чтобы проверяющему было легко проверить логику. Все входные параметры и допущения вынесены на отдельный лист Assumptions (включая источники и уровень уверенности), а на листе Baseline — только формулы, ссылающиеся на assumptions. В прогнозе 2026 год посчитан помесячно, а 2027–2030 — годовым шагом, что соответствует требованиям задания. Также добавлена сезонность (коэффициенты по 12 месяцам со средним значением 1), чтобы не “искажать” годовой объём искусственным завышением и одновременно отражать реальную сезонность спроса на ремонт/стройку. Основная bottom-up логика построена как воронка. Сначала задаётся стартовый инвентарь Active listings (активные объявления) и параметр Views per listing (просмотров на объявление в месяц). Далее по каждому месяцу 2026 рассчитываются просмотры: Views_m = Active_listings_m × Views_per_listing × Seasonality_m. Затем рассчитываются контакты: Contacts_m = Views_m × CR(view→contact). Конверсия просмотр→контакт берётся из стартовых данных задания (0,03–0,05%), в baseline используется среднее значение и вынесено на assumptions. Outcome-метрика офлайн-сделок считается как Deals_m = Contacts_m × CR(contact→deal) и служит проверкой того, что воронка даёт реалистичный “выход”. В предоставленных данных по Стройке указано 1,8 млн “запросов/год” и 300 тыс “сделок”, а также комментарий к bottom-up “конверсия в сделку ~10–15%, высокий LTV, длинный цикл”. Поскольку в текущем продукте нет механики “запрос КП” как отдельного объекта, я фиксирую интерпретацию, согласованную с реальным измеримым событием Avito: трактую 1,8 млн/год как объём контактов (leads), то есть фактически NSM в год. Тогда CR(contact→deal) выводится из данных как 300k / 1.8m = 16,7%. Это чуть выше указанного диапазона 10–15%, поэтому я делаю это прозрачно и честно: в assumptions параметр помечен как derived и снабжён комментарием, что расхождение возможно из-за разных определений “сделки” (например, включение повторных/частичных работ) и что при валидации метрики в продуктовой аналитике диапазон может быть уточнён. Такой подход позволяет избежать “подгонки”: baseline согласован с данными по объёмам и одновременно фиксирует зону неопределённости. Монетизация в baseline считается отдельно от сделок, потому что транзакций и оплаты в Avito нет. Я моделирую выручку со стороны предложения: сначала оцениваю число активных исполнителей через инвентарь: Active providers = Active listings / Listings per provider. Параметр “объявлений на пользователя в месяц” берётся из стартовых данных задания (1,2–1,8) и вынесен в assumptions. Затем оцениваю число платящих: Paying providers = Active providers × Share paying providers. Доля платящих исполнителей — допущение baseline, помеченное как требующее валидации (так как зависит от ценовой политики и зрелости категории). Далее рассчитываю ARPPU. В данных задан годовой ARPU продавца 1 200–3 500 ₽/год. Чтобы не допустить типичную ошибку смешения ARPU и ARPPU, я считаю ARPPU_month = (ARPU_year / Share paying) / 12. Это делает модель внутренне консистентной: если доля платящих ниже, ARPPU на платящего выше, но средний ARPU на всех остаётся в исходном диапазоне. Итоговая выручка считается как Revenue_m = Paying providers_m × ARPPU_month, а годовая — суммой 12 месяцев и ростом через YoY-индикаторы. Прогноз на 5 лет построен как реалистичный baseline без гипотез роста: по ключевым драйверам задаются умеренные YoY изменения (рост контактов/трафика, рост инвентаря, индексация ARPU), а не “скачки” от новых фич. Такой baseline удобно использовать как отправную точку для трекшн-модели: любые будущие инициативы будут измеряться как инкремент к конкретным драйверам (например, рост CR(view→contact) после улучшения карточки, или рост Share paying после изменения пакетов). Top-down часть используется как sanity check и в модели оформлена как отдельная логика “потолка рынка”. По стартовым данным: TAM Стройки = 1,2 трлн ₽, доля онлайн-запросов 20%, доля Avito 25%. Это даёт ориентир SAM = 240 млрд ₽ и SOM-cap ≈ 60 млрд ₽ в терминах объёма рынка, доступного в периметре Avito. Я подчёркиваю, что это не выручка Avito, а верхняя граница рынка, и использую её для проверки адекватности масштаба: baseline-показатели активности и выручки от сервисов не должны подразумевать долю, несовместимую с этим потолком. Таким образом выбранная комбинация методов применена корректно: bottom-up даёт детальную динамику метрик продукта и монетизации, а top-down ограничивает и подтверждает реалистичность. Реалистичность baseline я проверяю несколькими способами. Во-первых, конверсии не выходят за разумные диапазоны: CR(view→contact) остаётся в пределах 0,03–0,05% из данных; CR(contact→deal) либо согласован с парами 1,8 млн и 300 тыс, либо может быть зафиксирован в коридоре 10–15% с явной пометкой о различиях определений. Во-вторых, я избегаю “красных флагов” в монетизации: не использую take rate и долю транзакций в платформе, потому что это не соответствует продукту; ARPPU согласован с ARPU через долю платящих; доля платящих и YoY-росты заданы умеренно и вынесены в assumptions. В-третьих, сезонность учтена отдельным рядом коэффициентов, что делает помесячный прогноз правдоподобным и позволяет при необходимости обсуждать влияние сезонов на спрос. В-четвёртых, я осознанно фиксирую зоны неопределённости и риски: качество и актуальность инвентаря (active listings), изменения в ранжировании/поиске (влияние на views), изменения UX контакта (влияние на CR view→contact), изменение цен/пакетов (влияние на ARPU и долю платящих), а также внешние факторы (стоимость материалов, макроэкономика, сезонность спроса и конкуренция). Все параметры без прямого источника помечены как “экспертная оценка, требует валидации”, а ключевые параметры из задания (конверсии, ARPU, TAM/SAM/SOM) — как “данные ДЗ” с дальнейшим планом добавить ссылки на публичные источники (например, отчёты Avito для MAU и исследования рынка строительства). В части оформления и технической корректности модель соответствует требованиям: отдельный лист assumptions содержит все “хардовые” параметры, лист baseline содержит формулы и прозрачные связи между метриками; прогноз рассчитан на 5 лет с помесячной детализацией первого года; добавлена сезонность и sanity checks, позволяющие быстро увидеть, не “уплыла” ли модель от исходных объёмов; предусмотрено построение графика динамики ключевой метрики (контакты или выручка) за 12 месяцев. Такой baseline получается достаточно прозрачным и реалистичным, чтобы служить отправной точкой для дальнейшей трекшн-модели и оценки инкремента от продуктовых гипотез. Источники: “Данные для ДЗ №1” для всех чисел из таблицы (ARPU, CR view→contact, TAM/SAM/SOM, listings/user)
