Workbook

Sheet FinSummary
A1: Avito Confidential
A3: 1 | B3: GENERAL INFORMATION
B4: Project name | D4: Avito Животные - 3 гипотезы (рекомендации, индикатор цены, видео)
B5: Project leader | D5: Коростелев Александр | K5: CF cumulative (5 лет, INCR) | L5: =CashFlow!BK30 -> 100.73241
K6: Current request (peak funding need) | L6: =CashFlow!C33 -> -8.3612993
K7: Negative CF (minimum) | L7: =CashFlow!C33 -> -8.3612993
K8: NPV (WACC 26,3%, 5 лет) | L8: =CashFlow!C36 -> 47.843436
B12: Parameter | C12: Units | D12: base | E12: 2026 | F12: 2027 | G12: 2028 | H12: 2029 | I12: 2030
A13: 2 | B13: ASSUMPTIONS
B14: Project start date | D14: 2026-01-01
B15: WACC | D15: =PnL!B10 -> 0.263
B16: TGR | D16: =PnL!B11 -> 0.05
B17: Income Tax | E17: 0.05 | F17: 0.05 | G17: 0.05 | H17: 0.05 | I17: 0.05
B18: НДС | E18: 0.2 | F18: 0.22 | G18: 0.22 | H18: 0.22 | I18: 0.22
B21: Revenue effect (cannibalization) | D21: no | E21: Каннибализация не учтена - гипотезы добавляют новые сценарии (рекомендации профи, индикатор цены, видео в карточках), не отнимая трафик у существующих видов монетизации. Анализ риска - см. ДЗ2.
B22: Cannibalization object | D22: n/a
B23: Incremental revenue methodology | D23: 1 - uplift as % (× rollout × confidence rate) | E23: Каждая гипотеза имеет: uplift к метрике, % раскатки по годам (W1: 30/70/100/100/100; W2: 10/50/100/100/100; W3: 30/100/100/100/100), confidence rate (W1: 0.75, W2: 0.6, W3: 0.4). Итог = ARPPU × Uplift × Rollout × Confidence.
B24: Revenue calc method | D24: 1 - uplift as %
A27: 3 | B27: FINANCIALS AS IS
B28: Revenue | C28: mR | E28: =PnL!BL20 -> 409.36014 | F28: =PnL!BM20 -> 412.94306 | G28: =PnL!BN20 -> 429.46078 | H28: =PnL!BO20 -> 446.63921 | I28: =PnL!BP20 -> 464.50478
B29: CoS | C29: mR | E29: =PnL!BL21 -> -8.1872029 | F29: =PnL!BM21 -> -8.2588611 | G29: =PnL!BN21 -> -8.5892156 | H29: =PnL!BO21 -> -8.9327842 | I29: =PnL!BP21 -> -9.2900956
B30: Staff costs | C30: mR | E30: =PnL!BL22 -> -84 | F30: =PnL!BM22 -> -89.88 | G30: =PnL!BN22 -> -96.1716 | H30: =PnL!BO22 -> -102.90361 | I30: =PnL!BP22 -> -110.10686
B31: Marketing | C31: mR | E31: =PnL!BL23 -> -20.468007 | F31: =PnL!BM23 -> -20.647153 | G31: =PnL!BN23 -> -21.473039 | H31: =PnL!BO23 -> -22.33196 | I31: =PnL!BP23 -> -23.225239
B32: Consulting | C32: mR | E32: =PnL!BL24 -> 0 | F32: =PnL!BM24 -> 0 | G32: =PnL!BN24 -> 0 | H32: =PnL!BO24 -> 0 | I32: =PnL!BP24 -> 0
B33: IT Costs | C33: mR | E33: =PnL!BL25 -> -3 | F33: =PnL!BM25 -> -3 | G33: =PnL!BN25 -> -3 | H33: =PnL!BO25 -> -3 | I33: =PnL!BP25 -> -3
B34: G&A Costs | C34: mR | E34: =PnL!BL26 -> -4.2 | F34: =PnL!BM26 -> -4.494 | G34: =PnL!BN26 -> -4.80858 | H34: =PnL!BO26 -> -5.1451806 | I34: =PnL!BP26 -> -5.5053432
B35: Other Costs | C35: mR | E35: =PnL!BL27 -> 0 | F35: =PnL!BM27 -> 0 | G35: =PnL!BN27 -> 0 | H35: =PnL!BO27 -> 0 | I35: =PnL!BP27 -> 0
B36: EBITDA | C36: mR | E36: =PnL!BL28 -> 289.50493 | F36: =PnL!BM28 -> 286.66304 | G36: =PnL!BN28 -> 295.41834 | H36: =PnL!BO28 -> 304.32567 | I36: =PnL!BP28 -> 313.37724
B37: Income Tax | C37: mR | E37: =PnL!BL30 -> -14.475247 | F37: =PnL!BM30 -> -14.333152 | G37: =PnL!BN30 -> -14.770917 | H37: =PnL!BO30 -> -15.216284 | I37: =PnL!BP30 -> -15.668862
B38: EBITDA margin | C38: % | E38: =IFERROR(PnL!BL28/PnL!BL20,0) -> 0.70721329 | F38: =IFERROR(PnL!BM28/PnL!BM20,0) -> 0.69419509 | G38: =IFERROR(PnL!BN28/PnL!BN20,0) -> 0.68788201 | H38: =IFERROR(PnL!BO28/PnL!BO20,0) -> 0.68136802 | I38: =IFERROR(PnL!BP28/PnL!BP20,0) -> 0.67464803
B39: Change in NWC | C39: mR | E39: =PnL!BL35 -> -74.521272 | F39: =PnL!BM35 -> -2.9798509 | G39: =PnL!BN35 -> -3.0975749 | H39: =PnL!BO35 -> -3.219905 | I39: =PnL!BP35 -> -3.3470182
B40: FCF (free cash flow) | C40: mR | E40: =PnL!BL36 -> 200.50841 | F40: =PnL!BM36 -> 269.35004 | G40: =PnL!BN36 -> 277.54985 | H40: =PnL!BO36 -> 285.88948 | I40: =PnL!BP36 -> 294.36136
A44: 4 | B44: FINANCIALS INCREMENT
B45: Revenue | C45: mR | E45: =PnL!BL39 -> 12.39892 | F45: =PnL!BM39 -> 29.299167 | G45: =PnL!BN39 -> 30.769894 | H45: =PnL!BO39 -> 32.000806 | I45: =PnL!BP39 -> 33.280838
B46: CoS | C46: mR | E46: =PnL!BL40 -> -0.4959568 | F46: =PnL!BM40 -> -1.1719667 | G46: =PnL!BN40 -> -1.2307957 | H46: =PnL!BO40 -> -1.2800322 | I46: =PnL!BP40 -> -1.3312335
B47: Staff costs | C47: mR | E47: =PnL!BL41 -> -12.510652 | F47: =PnL!BM41 -> -3.371065 | G47: =PnL!BN41 -> -3.6070395 | H47: =PnL!BO41 -> -3.8595323 | I47: =PnL!BP41 -> -4.1296995
B48: Marketing | C48: mR | E48: =PnL!BL42 -> -1.6666667 | F48: =PnL!BM42 -> -3.5833333 | G48: =PnL!BN42 -> -3 | H48: =PnL!BO42 -> -3 | I48: =PnL!BP42 -> -3
B49: Consulting | C49: mR | E49: =PnL!BL43 -> 0 | F49: =PnL!BM43 -> 0 | G49: =PnL!BN43 -> 0 | H49: =PnL!BO43 -> 0 | I49: =PnL!BP43 -> 0
B50: IT Costs | C50: mR | E50: =PnL!BL44 -> -2.5 | F50: =PnL!BM44 -> -2.1 | G50: =PnL!BN44 -> -1.5 | H50: =PnL!BO44 -> -1.5 | I50: =PnL!BP44 -> -1.5
B51: G&A Costs | C51: mR | E51: =PnL!BL45 -> -0.6255326 | F51: =PnL!BM45 -> -0.16855325 | G51: =PnL!BN45 -> -0.18035198 | H51: =PnL!BO45 -> -0.19297661 | I51: =PnL!BP45 -> -0.20648498
B52: Other Costs | C52: mR | E52: =PnL!BL46 -> 0 | F52: =PnL!BM46 -> 0 | G52: =PnL!BN46 -> 0 | H52: =PnL!BO46 -> 0 | I52: =PnL!BP46 -> 0
B53: EBITDA | C53: mR | E53: =PnL!BL47 -> -5.399888 | F53: =PnL!BM47 -> 18.904248 | G53: =PnL!BN47 -> 21.251706 | H53: =PnL!BO47 -> 22.168265 | I53: =PnL!BP47 -> 23.11342
B54: Income Tax | C54: mR | E54: =PnL!BL49 -> -0.18637838 | F54: =PnL!BM49 -> -0.94521242 | G54: =PnL!BN49 -> -1.0625853 | H54: =PnL!BO49 -> -1.1084132 | I54: =PnL!BP49 -> -1.155671
B55: EBITDA margin | C55: % | E55: =IFERROR(PnL!BL47/PnL!BL39,0) -> -0.43551277 | F55: =IFERROR(PnL!BM47/PnL!BM39,0) -> 0.64521454 | G55: =IFERROR(PnL!BN47/PnL!BN39,0) -> 0.69066558 | H55: =IFERROR(PnL!BO47/PnL!BO39,0) -> 0.69274083 | I55: =IFERROR(PnL!BP47/PnL!BP39,0) -> 0.69449634
B56: Change in NWC | C56: mR | E56: =PnL!BL54 -> -3.980545 | F56: =PnL!BM54 -> -1.0653394 | G56: =PnL!BN54 -> -0.23132689 | H56: =PnL!BO54 -> -0.24018681 | I56: =PnL!BP54 -> -0.24973104
B57: FCF (free cash flow) | C57: mR | E57: =PnL!BL55 -> -9.5668114 | F57: =PnL!BM55 -> 16.893697 | G57: =PnL!BN55 -> 19.957794 | H57: =PnL!BO55 -> 20.819665 | I57: =PnL!BP55 -> 21.708018
A61: 5 | B61: FINANCIALS TO BE
B62: Revenue | C62: mR | E62: =PnL!BL58 -> 421.75906 | F62: =PnL!BM58 -> 442.24222 | G62: =PnL!BN58 -> 460.23067 | H62: =PnL!BO58 -> 478.64002 | I62: =PnL!BP58 -> 497.78562
B63: CoS | C63: mR | E63: =PnL!BL59 -> -8.6831597 | F63: =PnL!BM59 -> -9.4308278 | G63: =PnL!BN59 -> -9.8200113 | H63: =PnL!BO59 -> -10.212816 | I63: =PnL!BP59 -> -10.621329
B64: Staff costs | C64: mR | E64: =PnL!BL60 -> -96.510652 | F64: =PnL!BM60 -> -93.251065 | G64: =PnL!BN60 -> -99.77864 | H64: =PnL!BO60 -> -106.76314 | I64: =PnL!BP60 -> -114.23656
B65: Marketing | C65: mR | E65: =PnL!BL61 -> -22.134674 | F65: =PnL!BM61 -> -24.230486 | G65: =PnL!BN61 -> -24.473039 | H65: =PnL!BO61 -> -25.33196 | I65: =PnL!BP61 -> -26.225239
B66: Consulting | C66: mR | E66: =PnL!BL62 -> 0 | F66: =PnL!BM62 -> 0 | G66: =PnL!BN62 -> 0 | H66: =PnL!BO62 -> 0 | I66: =PnL!BP62 -> 0
B67: IT Costs | C67: mR | E67: =PnL!BL63 -> -5.5 | F67: =PnL!BM63 -> -5.1 | G67: =PnL!BN63 -> -4.5 | H67: =PnL!BO63 -> -4.5 | I67: =PnL!BP63 -> -4.5
B68: G&A Costs | C68: mR | E68: =PnL!BL64 -> -4.8255326 | F68: =PnL!BM64 -> -4.6625532 | G68: =PnL!BN64 -> -4.988932 | H68: =PnL!BO64 -> -5.3381572 | I68: =PnL!BP64 -> -5.7118282
B69: Other Costs | C69: mR | E69: =PnL!BL65 -> 0 | F69: =PnL!BM65 -> 0 | G69: =PnL!BN65 -> 0 | H69: =PnL!BO65 -> 0 | I69: =PnL!BP65 -> 0
B70: EBITDA | C70: mR | E70: =PnL!BL66 -> 284.10505 | F70: =PnL!BM66 -> 305.56729 | G70: =PnL!BN66 -> 316.67005 | H70: =PnL!BO66 -> 326.49394 | I70: =PnL!BP66 -> 336.49066
B71: Income Tax | C71: mR | E71: =PnL!BL68 -> -14.661625 | F71: =PnL!BM68 -> -15.278365 | G71: =PnL!BN68 -> -15.833503 | H71: =PnL!BO68 -> -16.324697 | I71: =PnL!BP68 -> -16.824533
B72: EBITDA margin | C72: % | E72: =IFERROR(PnL!BL66/PnL!BL58,0) -> 0.6736193 | F72: =IFERROR(PnL!BM66/PnL!BM58,0) -> 0.69095006 | G72: =IFERROR(PnL!BN66/PnL!BN58,0) -> 0.68806811 | H72: =IFERROR(PnL!BO66/PnL!BO58,0) -> 0.68212838 | I72: =IFERROR(PnL!BP66/PnL!BP58,0) -> 0.67597505
B73: Change in NWC | C73: mR | E73: =PnL!BL73 -> -78.501817 | F73: =PnL!BM73 -> -4.0451903 | G73: =PnL!BN73 -> -3.3289018 | H73: =PnL!BO73 -> -3.4600918 | I73: =PnL!BP73 -> -3.5967492
B74: FCF (free cash flow) | C74: mR | E74: =PnL!BL74 -> 190.9416 | F74: =PnL!BM74 -> 286.24374 | G74: =PnL!BN74 -> 297.50765 | H74: =PnL!BO74 -> 306.70915 | I74: =PnL!BP74 -> 316.06937
A78: 6 | B78: BREAK-DOWNS (детализация INCREMENT)
B79: Staff costs команда разработки (наша команда) | C79: mR | E79: =PnL!BL41 -> -12.510652 | F79: =PnL!BM41 -> -3.371065 | G79: =PnL!BN41 -> -3.6070395 | H79: =PnL!BO41 -> -3.8595323 | I79: =PnL!BP41 -> -4.1296995
B80: Staff costs (расшифровка по ролям) | C80: mR | D80: См. лист «Команда и TtM» - Cost matrix rows 44-51, 8 ролей
B81: Marketing breakdown | C81: mR | D81: Год 1 после Launch Wave 1 (мес 8-19): 15 млн ₽ - промо новых фич. Годы 2-5: по 5 млн ₽/год - поддержка узнаваемости.
B82: IT breakdown | C82: mR | D82: Лицензии (GPU/CDN/storage): 2,5 млн ₽/год + IT-оборудование на нового HC: 100 тыс ₽ × 16 чел (за 3 волны) единоразово.
A86: 7 | B86: NWC (Net Working Capital)
B87: NWC (год end) | C87: mR | E87: =PnL!BL72 -> 78.501817 | F87: =PnL!BM72 -> 82.547007 | G87: =PnL!BN72 -> 85.875909 | H87: =PnL!BO72 -> 89.336001 | I87: =PnL!BP72 -> 92.93275
B88: AR (incl. НДС) | C88: mR | D88: no delay (онлайн-платежи Avito) | E88: =PnL!BL70 -> 86.58307 | F88: =PnL!BM70 -> 90.744194 | G88: =PnL!BN70 -> 94.37431 | H88: =PnL!BO70 -> 98.149282 | I88: =PnL!BP70 -> 102.07525
B89: AP (incl. НДС) | C89: mR | D89: assuming 60 days | E89: =PnL!BL71 -> -8.0812531 | F89: =PnL!BM71 -> -8.1971865 | G89: =PnL!BN71 -> -8.4984006 | H89: =PnL!BO71 -> -8.8132813 | I89: =PnL!BP71 -> -9.1425034
A93: 8 | B93: ПОМЕСЯЧНАЯ ДЕТАЛИЗАЦИЯ
B94: Помесячные данные см. на листах:
B95: • «PnL» - Revenue/EBITDA/FCF помесячно за 2026-2030 (60 месяцев), 3 блока AS IS / Increment / TO BE
B96: • «CashFlow» - Operating CashFlow и Cumulative CashFlow помесячно (Increment, прямой метод)
B97: • «Cost assumptions» - каждая статья OPEX помесячно с разделением AS IS / Increment
B98: • «Команда и TtM» - FTE и Staff cost помесячно по 8 ролям

Sheet PnL
A1: Avito Animals - PnL: Развитие классифайдной монетизации
A2: 1. GENERAL INFORMATION
A3: Project name | B3: Avito Animals - Алгоритм рекомендаций + Индикатор цены + Видео в карточках
A4: Project leader | B4: Коростелев Александр
A5: Period | B5: 2026-2030 (5 лет)
A6: Currency | B6: млн ₽
A8: 2. ASSUMPTIONS
A9: Project start date | B9: 2026-01-01
A10: WACC | B10: 0.263
A11: TGR | B11: 0.05
A12: Income Tax | D12: 0.05 | E12: 0.05 | F12: 0.05 | G12: 0.05 | H12: 0.05 | I12: 0.05 | J12: 0.05 | K12: 0.05 | L12: 0.05 | M12: 0.05 | N12: 0.05 | O12: 0.05 | P12: 0.05 | Q12: 0.05 | R12: 0.05 | S12: 0.05 | T12: 0.05 | U12: 0.05 | V12: 0.05 | W12: 0.05 | X12: 0.05 | Y12: 0.05 | Z12: 0.05 | AA12: 0.05 | AB12: 0.05 | AC12: 0.05 | AD12: 0.05 | AE12: 0.05 | AF12: 0.05 | AG12: 0.05 | AH12: 0.05 | AI12: 0.05 | AJ12: 0.05 | AK12: 0.05 | AL12: 0.05 | AM12: 0.05 | AN12: 0.05 | AO12: 0.05 | AP12: 0.05 | AQ12: 0.05 | AR12: 0.05 | AS12: 0.05 | AT12: 0.05 | AU12: 0.05 | AV12: 0.05 | AW12: 0.05 | AX12: 0.05 | AY12: 0.05 | AZ12: 0.05 | BA12: 0.05 | BB12: 0.05 | BC12: 0.05 | BD12: 0.05 | BE12: 0.05 | BF12: 0.05 | BG12: 0.05 | BH12: 0.05 | BI12: 0.05 | BJ12: 0.05 | BK12: 0.05
A13: НДС | D13: 0.2 | E13: 0.2 | F13: 0.2 | G13: 0.2 | H13: 0.2 | I13: 0.2 | J13: 0.2 | K13: 0.2 | L13: 0.2 | M13: 0.2 | N13: 0.2 | O13: 0.2 | P13: 0.22 | Q13: 0.22 | R13: 0.22 | S13: 0.22 | T13: 0.22 | U13: 0.22 | V13: 0.22 | W13: 0.22 | X13: 0.22 | Y13: 0.22 | Z13: 0.22 | AA13: 0.22 | AB13: 0.22 | AC13: 0.22 | AD13: 0.22 | AE13: 0.22 | AF13: 0.22 | AG13: 0.22 | AH13: 0.22 | AI13: 0.22 | AJ13: 0.22 | AK13: 0.22 | AL13: 0.22 | AM13: 0.22 | AN13: 0.22 | AO13: 0.22 | AP13: 0.22 | AQ13: 0.22 | AR13: 0.22 | AS13: 0.22 | AT13: 0.22 | AU13: 0.22 | AV13: 0.22 | AW13: 0.22 | AX13: 0.22 | AY13: 0.22 | AZ13: 0.22 | BA13: 0.22 | BB13: 0.22 | BC13: 0.22 | BD13: 0.22 | BE13: 0.22 | BF13: 0.22 | BG13: 0.22 | BH13: 0.22 | BI13: 0.22 | BJ13: 0.22 | BK13: 0.22
A14: Cannibalization | B14: Не учтена (см. ДЗ2), так как инициативы направлены на повышение конверсий и не влияют на переток пользователей из других категорий
A16: Параметр | B16: Ед. изм. | D16: 2026 | E16: 2026 | F16: 2026 | G16: 2026 | H16: 2026 | I16: 2026 | J16: 2026 | K16: 2026 | L16: 2026 | M16: 2026 | N16: 2026 | O16: 2026 | P16: 2027 | Q16: 2027 | R16: 2027 | S16: 2027 | T16: 2027 | U16: 2027 | V16: 2027 | W16: 2027 | X16: 2027 | Y16: 2027 | Z16: 2027 | AA16: 2027 | AB16: 2028 | AC16: 2028 | AD16: 2028 | AE16: 2028 | AF16: 2028 | AG16: 2028 | AH16: 2028 | AI16: 2028 | AJ16: 2028 | AK16: 2028 | AL16: 2028 | AM16: 2028 | AN16: 2029 | AO16: 2029 | AP16: 2029 | AQ16: 2029 | AR16: 2029 | AS16: 2029 | AT16: 2029 | AU16: 2029 | AV16: 2029 | AW16: 2029 | AX16: 2029 | AY16: 2029 | AZ16: 2030 | BA16: 2030 | BB16: 2030 | BC16: 2030 | BD16: 2030 | BE16: 2030 | BF16: 2030 | BG16: 2030 | BH16: 2030 | BI16: 2030 | BJ16: 2030 | BK16: 2030 | BL16: 2026 Total | BM16: 2027 Total | BN16: 2028 Total | BO16: 2029 Total | BP16: 2030 Total
D17: Jan | E17: Feb | F17: Mar | G17: Apr | H17: May | I17: Jun | J17: Jul | K17: Aug | L17: Sep | M17: Oct | N17: Nov | O17: Dec | P17: Jan | Q17: Feb | R17: Mar | S17: Apr | T17: May | U17: Jun | V17: Jul | W17: Aug | X17: Sep | Y17: Oct | Z17: Nov | AA17: Dec | AB17: Jan | AC17: Feb | AD17: Mar | AE17: Apr | AF17: May | AG17: Jun | AH17: Jul | AI17: Aug | AJ17: Sep | AK17: Oct | AL17: Nov | AM17: Dec | AN17: Jan | AO17: Feb | AP17: Mar | AQ17: Apr | AR17: May | AS17: Jun | AT17: Jul | AU17: Aug | AV17: Sep | AW17: Oct | AX17: Nov | AY17: Dec | AZ17: Jan | BA17: Feb | BB17: Mar | BC17: Apr | BD17: May | BE17: Jun | BF17: Jul | BG17: Aug | BH17: Sep | BI17: Oct | BJ17: Nov | BK17: Dec
A19: 3. FINANCIALS AS IS
A20: Revenue | B20: млн ₽ | D20: ='Cost assumptions'!D28/1000000 -> 20.454545 | E20: ='Cost assumptions'!E28/1000000 -> 41.043017 | F20: ='Cost assumptions'!F28/1000000 -> 32.941905 | G20: ='Cost assumptions'!G28/1000000 -> 33.049748 | H20: ='Cost assumptions'!H28/1000000 -> 33.157944 | I20: ='Cost assumptions'!I28/1000000 -> 33.266495 | J20: ='Cost assumptions'!J28/1000000 -> 33.3754 | K20: ='Cost assumptions'!K28/1000000 -> 33.484663 | ... BK20: ='Cost assumptions'!BK28/1000000 -> 47.625365 | BL20: =SUM(D20:O20) -> 409.36014 | BM20: =SUM(P20:AA20) -> 412.94306 | BN20: =SUM(AB20:AM20) -> 429.46078 | BO20: =SUM(AN20:AY20) -> 446.63921 | BP20: =SUM(AZ20:BK20) -> 464.50478
A21: CoS | B21: млн ₽ | D21: =-'Cost assumptions'!D29/1000000 -> -0.40909091 | E21: =-'Cost assumptions'!E29/1000000 -> -0.82086033 | F21: =-'Cost assumptions'!F29/1000000 -> -0.65883809 | G21: =-'Cost assumptions'!G29/1000000 -> -0.66099496 | H21: =-'Cost assumptions'!H29/1000000 -> -0.66315888 | I21: =-'Cost assumptions'!I29/1000000 -> -0.66532989 | J21: =-'Cost assumptions'!J29/1000000 -> -0.66750801 | K21: =-'Cost assumptions'!K29/1000000 -> -0.66969326 | ... BK21: =-'Cost assumptions'!BK29/1000000 -> -0.95250729 | BL21: =SUM(D21:O21) -> -8.1872029 | BM21: =SUM(P21:AA21) -> -8.2588611 | BN21: =SUM(AB21:AM21) -> -8.5892156 | BO21: =SUM(AN21:AY21) -> -8.9327842 | BP21: =SUM(AZ21:BK21) -> -9.2900956
A22: Staff costs | B22: млн ₽ | D22: =-'Cost assumptions'!D30/1000000 -> -7 | E22: =-'Cost assumptions'!E30/1000000 -> -7 | F22: =-'Cost assumptions'!F30/1000000 -> -7 | G22: =-'Cost assumptions'!G30/1000000 -> -7 | H22: =-'Cost assumptions'!H30/1000000 -> -7 | I22: =-'Cost assumptions'!I30/1000000 -> -7 | J22: =-'Cost assumptions'!J30/1000000 -> -7 | K22: =-'Cost assumptions'!K30/1000000 -> -7 | ... BK22: =-'Cost assumptions'!BK30/1000000 -> -9.1755721 | BL22: =SUM(D22:O22) -> -84 | BM22: =SUM(P22:AA22) -> -89.88 | BN22: =SUM(AB22:AM22) -> -96.1716 | BO22: =SUM(AN22:AY22) -> -102.90361 | BP22: =SUM(AZ22:BK22) -> -110.10686
A23: Marketing | B23: млн ₽ | D23: =-'Cost assumptions'!D31/1000000 -> -1.0227273 | E23: =-'Cost assumptions'!E31/1000000 -> -2.0521508 | F23: =-'Cost assumptions'!F31/1000000 -> -1.6470952 | G23: =-'Cost assumptions'!G31/1000000 -> -1.6524874 | H23: =-'Cost assumptions'!H31/1000000 -> -1.6578972 | I23: =-'Cost assumptions'!I31/1000000 -> -1.6633247 | J23: =-'Cost assumptions'!J31/1000000 -> -1.66877 | K23: =-'Cost assumptions'!K31/1000000 -> -1.6742331 | ... BK23: =-'Cost assumptions'!BK31/1000000 -> -2.3812682 | BL23: =SUM(D23:O23) -> -20.468007 | BM23: =SUM(P23:AA23) -> -20.647153 | BN23: =SUM(AB23:AM23) -> -21.473039 | BO23: =SUM(AN23:AY23) -> -22.33196 | BP23: =SUM(AZ23:BK23) -> -23.225239
A24: Consulting | B24: млн ₽ | D24: 0 | E24: 0 | F24: 0 | G24: 0 | H24: 0 | I24: 0 | J24: 0 | K24: 0 | L24: 0 | M24: 0 | N24: 0 | O24: 0 | P24: 0 | Q24: 0 | R24: 0 | S24: 0 | T24: 0 | U24: 0 | V24: 0 | W24: 0 | X24: 0 | Y24: 0 | Z24: 0 | AA24: 0 | AB24: 0 | AC24: 0 | AD24: 0 | AE24: 0 | AF24: 0 | AG24: 0 | AH24: 0 | AI24: 0 | AJ24: 0 | AK24: 0 | AL24: 0 | AM24: 0 | AN24: 0 | AO24: 0 | AP24: 0 | AQ24: 0 | AR24: 0 | AS24: 0 | AT24: 0 | AU24: 0 | AV24: 0 | AW24: 0 | AX24: 0 | AY24: 0 | AZ24: 0 | BA24: 0 | BB24: 0 | BC24: 0 | BD24: 0 | BE24: 0 | BF24: 0 | BG24: 0 | BH24: 0 | BI24: 0 | BJ24: 0 | BK24: 0 | BL24: =SUM(D24:O24) -> 0 | BM24: =SUM(P24:AA24) -> 0 | BN24: =SUM(AB24:AM24) -> 0 | BO24: =SUM(AN24:AY24) -> 0 | BP24: =SUM(AZ24:BK24) -> 0
A25: IT Costs | B25: млн ₽ | D25: =-'Cost assumptions'!D32/1000000 -> -0.25 | E25: =-'Cost assumptions'!E32/1000000 -> -0.25 | F25: =-'Cost assumptions'!F32/1000000 -> -0.25 | G25: =-'Cost assumptions'!G32/1000000 -> -0.25 | H25: =-'Cost assumptions'!H32/1000000 -> -0.25 | I25: =-'Cost assumptions'!I32/1000000 -> -0.25 | J25: =-'Cost assumptions'!J32/1000000 -> -0.25 | K25: =-'Cost assumptions'!K32/1000000 -> -0.25 | ... BK25: =-'Cost assumptions'!BK32/1000000 -> -0.25 | BL25: =SUM(D25:O25) -> -3 | BM25: =SUM(P25:AA25) -> -3 | BN25: =SUM(AB25:AM25) -> -3 | BO25: =SUM(AN25:AY25) -> -3 | BP25: =SUM(AZ25:BK25) -> -3
A26: G&A Costs | B26: млн ₽ | D26: =-'Cost assumptions'!D33/1000000 -> -0.35 | E26: =-'Cost assumptions'!E33/1000000 -> -0.35 | F26: =-'Cost assumptions'!F33/1000000 -> -0.35 | G26: =-'Cost assumptions'!G33/1000000 -> -0.35 | H26: =-'Cost assumptions'!H33/1000000 -> -0.35 | I26: =-'Cost assumptions'!I33/1000000 -> -0.35 | J26: =-'Cost assumptions'!J33/1000000 -> -0.35 | K26: =-'Cost assumptions'!K33/1000000 -> -0.35 | ... BK26: =-'Cost assumptions'!BK33/1000000 -> -0.4587786 | BL26: =SUM(D26:O26) -> -4.2 | BM26: =SUM(P26:AA26) -> -4.494 | BN26: =SUM(AB26:AM26) -> -4.80858 | BO26: =SUM(AN26:AY26) -> -5.1451806 | BP26: =SUM(AZ26:BK26) -> -5.5053432
A27: Other Costs | B27: млн ₽ | D27: 0 | E27: 0 | F27: 0 | G27: 0 | H27: 0 | I27: 0 | J27: 0 | K27: 0 | L27: 0 | M27: 0 | N27: 0 | O27: 0 | P27: 0 | Q27: 0 | R27: 0 | S27: 0 | T27: 0 | U27: 0 | V27: 0 | W27: 0 | X27: 0 | Y27: 0 | Z27: 0 | AA27: 0 | AB27: 0 | AC27: 0 | AD27: 0 | AE27: 0 | AF27: 0 | AG27: 0 | AH27: 0 | AI27: 0 | AJ27: 0 | AK27: 0 | AL27: 0 | AM27: 0 | AN27: 0 | AO27: 0 | AP27: 0 | AQ27: 0 | AR27: 0 | AS27: 0 | AT27: 0 | AU27: 0 | AV27: 0 | AW27: 0 | AX27: 0 | AY27: 0 | AZ27: 0 | BA27: 0 | BB27: 0 | BC27: 0 | BD27: 0 | BE27: 0 | BF27: 0 | BG27: 0 | BH27: 0 | BI27: 0 | BJ27: 0 | BK27: 0 | BL27: =SUM(D27:O27) -> 0 | BM27: =SUM(P27:AA27) -> 0 | BN27: =SUM(AB27:AM27) -> 0 | BO27: =SUM(AN27:AY27) -> 0 | BP27: =SUM(AZ27:BK27) -> 0
A28: EBITDA | B28: млн ₽ | D28: =D20+SUM(D21:D27) -> 11.422727 | E28: =E20+SUM(E21:E27) -> 30.570005 | F28: =F20+SUM(F21:F27) -> 23.035971 | G28: =G20+SUM(G21:G27) -> 23.136266 | H28: =H20+SUM(H21:H27) -> 23.236888 | I28: =I20+SUM(I21:I27) -> 23.33784 | J28: =J20+SUM(J21:J27) -> 23.439122 | K28: =K20+SUM(K21:K27) -> 23.540736 | ... BK28: =BK20+SUM(BK21:BK27) -> 34.407238 | BL28: =SUM(D28:O28) -> 289.50493 | BM28: =SUM(P28:AA28) -> 286.66304 | BN28: =SUM(AB28:AM28) -> 295.41834 | BO28: =SUM(AN28:AY28) -> 304.32567 | BP28: =SUM(AZ28:BK28) -> 313.37724
A29: EBITDA margin | B29: % | D29: =IFERROR(D28/D20,0) -> 0.55844444 | E29: =IFERROR(E28/E20,0) -> 0.74482843 | F29: =IFERROR(F28/F20,0) -> 0.69929081 | G29: =IFERROR(G28/G20,0) -> 0.70004363 | H29: =IFERROR(H28/H20,0) -> 0.70079399 | I29: =IFERROR(I28/I20,0) -> 0.7015419 | J29: =IFERROR(J28/J20,0) -> 0.70228738 | K29: =IFERROR(K28/K20,0) -> 0.70303042 | ... BP29: =IFERROR(BP28/BP20,0) -> 0.67464803
A30: Income Tax | B30: млн ₽ | D30: =-MAX(D28,0)*D12 -> -0.57113636 | E30: =-MAX(E28,0)*E12 -> -1.5285003 | F30: =-MAX(F28,0)*F12 -> -1.1517986 | G30: =-MAX(G28,0)*G12 -> -1.1568133 | H30: =-MAX(H28,0)*H12 -> -1.1618444 | I30: =-MAX(I28,0)*I12 -> -1.166892 | J30: =-MAX(J28,0)*J12 -> -1.1719561 | K30: =-MAX(K28,0)*K12 -> -1.1770368 | ... BK30: =-MAX(BK28,0)*BK12 -> -1.7203619 | BL30: =SUM(D30:O30) -> -14.475247 | BM30: =SUM(P30:AA30) -> -14.333152 | BN30: =SUM(AB30:AM30) -> -14.770917 | BO30: =SUM(AN30:AY30) -> -15.216284 | BP30: =SUM(AZ30:BK30) -> -15.668862
A31: NOPAT (EBITDA - Tax) | B31: млн ₽ | D31: =D28+D30 -> 10.851591 | E31: =E28+E30 -> 29.041505 | F31: =F28+F30 -> 21.884173 | G31: =G28+G30 -> 21.979452 | H31: =H28+H30 -> 22.075044 | I31: =I28+I30 -> 22.170948 | J31: =J28+J30 -> 22.267166 | K31: =K28+K30 -> 22.3637 | ... BK31: =BK28+BK30 -> 32.686876 | BL31: =SUM(D31:O31) -> 275.02969 | BM31: =SUM(P31:AA31) -> 272.32989 | BN31: =SUM(AB31:AM31) -> 280.64743 | BO31: =SUM(AN31:AY31) -> 289.10939 | BP31: =SUM(AZ31:BK31) -> 297.70837
A32: AR (упрощение: 60 дней оборачиваемости от Revenue) | B32: млн ₽ | D32: =D20*2 -> 40.909091 | E32: =E20*2 -> 82.086033 | F32: =F20*2 -> 65.883809 | G32: =G20*2 -> 66.099496 | H32: =H20*2 -> 66.315888 | I32: =I20*2 -> 66.532989 | J32: =J20*2 -> 66.750801 | K32: =K20*2 -> 66.969326 | ... BK32: =BK20*2 -> 95.250729 | BL32: =O32 -> 81.420722 | BM32: =AA32 -> 84.677551 | BN32: =AM32 -> 88.064653 | BO32: =AY32 -> 91.58724 | BP32: =BK32 -> 95.250729
A33: AP (60 дней оборачиваемости от затрат) | B33: млн ₽ | D33: =(D21+D23+D25+D26)*2 -> -4.0636364 | E33: =(E21+E23+E25+E26)*2 -> -6.9460223 | F33: =(F21+F23+F25+F26)*2 -> -5.8118666 | G33: =(G21+G23+G25+G26)*2 -> -5.8269647 | H33: =(H21+H23+H25+H26)*2 -> -5.8421122 | I33: =(I21+I23+I25+I26)*2 -> -5.8573092 | J33: =(J21+J23+J25+J26)*2 -> -5.8725561 | K33: =(K21+K23+K25+K26)*2 -> -5.8878528 | ... BK33: =(BK21+BK23+BK25+BK26)*2 -> -8.0851082 | BL33: =O33 -> -6.8994506 | BM33: =AA33 -> -7.1764286 | BN33: =AM33 -> -7.4659557 | BO33: =AY33 -> -7.7686369 | BP33: =BK33 -> -8.0851082
A34: NWC = AR + AP | B34: млн ₽ | D34: =D32+D33 -> 36.845455 | E34: =E32+E33 -> 75.140011 | F34: =F32+F33 -> 60.071943 | G34: =G32+G33 -> 60.272531 | H34: =H32+H33 -> 60.473776 | I34: =I32+I33 -> 60.67568 | J34: =J32+J33 -> 60.878245 | K34: =K32+K33 -> 61.081473 | ... BK34: =BK32+BK33 -> 87.165621 | BL34: =O34 -> 74.521272 | BM34: =AA34 -> 77.501123 | BN34: =AM34 -> 80.598698 | BO34: =AY34 -> 83.818603 | BP34: =BK34 -> 87.165621
A35: Change in NWC | B35: млн ₽ | D35: =-D34 -> -36.845455 | E35: =-(E34-D34) -> -38.294556 | F35: =-(F34-E34) -> 15.068068 | G35: =-(G34-F34) -> -0.2005884 | H35: =-(H34-G34) -> -0.20124507 | I35: =-(I34-H34) -> -0.20190389 | J35: =-(J34-I34) -> -0.20256488 | K35: =-(K34-J34) -> -0.20322802 | L35: =-(L34-K34) -> -0.20389334 | ... BK35: =-(BK34-BJ34) -> -0.28905199 | BL35: =-BL34 -> -74.521272 | BM35: =-(BM34-BL34) -> -2.9798509 | BN35: =-(BN34-BM34) -> -3.0975749 | BO35: =-(BO34-BN34) -> -3.219905 | BP35: =-(BP34-BO34) -> -3.3470182
A36: FCF (Free Cash Flow) | B36: млн ₽ | D36: =D31+D35 -> -25.993864 | E36: =E31+E35 -> -9.2530512 | F36: =F31+F35 -> 36.952241 | G36: =G31+G35 -> 21.778864 | H36: =H31+H35 -> 21.873799 | I36: =I31+I35 -> 21.969044 | J36: =J31+J35 -> 22.064601 | K36: =K31+K35 -> 22.160472 | ... BP36: =BP31+BP35 -> 294.36136
A38: 4. FINANCIALS INCREMENT (эффект инициативы)
A39: Revenue | B39: млн ₽ | D39: ='Cost assumptions'!D39/1000000 -> 0 | E39: ='Cost assumptions'!E39/1000000 -> 0 | F39: ='Cost assumptions'!F39/1000000 -> 0.15844522 | G39: ='Cost assumptions'!G39/1000000 -> 0.27819143 | H39: ='Cost assumptions'!H39/1000000 -> 0.49853749 | I39: ='Cost assumptions'!I39/1000000 -> 0.74955597 | J39: ='Cost assumptions'!J39/1000000 -> 1.0177593 | K39: ='Cost assumptions'!K39/1000000 -> 1.3382381 | ... BK39: ='Cost assumptions'!BK39/1000000 -> 3.4122621 | BL39: =SUM(D39:O39) -> 12.39892 | BM39: =SUM(P39:AA39) -> 29.299167 | BN39: =SUM(AB39:AM39) -> 30.769894 | BO39: =SUM(AN39:AY39) -> 32.000806 | BP39: =SUM(AZ39:BK39) -> 33.280838
A40: CoS | B40: млн ₽ | D40: =-'Cost assumptions'!D40/1000000 -> 0 | E40: =-'Cost assumptions'!E40/1000000 -> 0 | F40: =-'Cost assumptions'!F40/1000000 -> -0.0063378089 | G40: =-'Cost assumptions'!G40/1000000 -> -0.011127657 | H40: =-'Cost assumptions'!H40/1000000 -> -0.019941499 | I40: =-'Cost assumptions'!I40/1000000 -> -0.029982239 | J40: =-'Cost assumptions'!J40/1000000 -> -0.040710371 | K40: =-'Cost assumptions'!K40/1000000 -> -0.053529525 | ... BK40: =-'Cost assumptions'!BK40/1000000 -> -0.13649048 | BL40: =SUM(D40:O40) -> -0.4959568 | BM40: =SUM(P40:AA40) -> -1.1719667 | BN40: =SUM(AB40:AM40) -> -1.2307957 | BO40: =SUM(AN40:AY40) -> -1.2800322 | BP40: =SUM(AZ40:BK40) -> -1.3312335
A41: Staff costs | B41: млн ₽ | D41: =-'Cost assumptions'!D41/1000000 -> -1.212652 | E41: =-'Cost assumptions'!E41/1000000 -> -1.212652 | F41: =-'Cost assumptions'!F41/1000000 -> -1.239552 | G41: =-'Cost assumptions'!G41/1000000 -> -1.239552 | H41: =-'Cost assumptions'!H41/1000000 -> -1.609696 | I41: =-'Cost assumptions'!I41/1000000 -> -1.532224 | J41: =-'Cost assumptions'!J41/1000000 -> -1.532224 | K41: =-'Cost assumptions'!K41/1000000 -> -0.58642 | ... BK41: =-'Cost assumptions'!BK41/1000000 -> -0.34414163 | BL41: =SUM(D41:O41) -> -12.510652 | BM41: =SUM(P41:AA41) -> -3.371065 | BN41: =SUM(AB41:AM41) -> -3.6070395 | BO41: =SUM(AN41:AY41) -> -3.8595323 | BP41: =SUM(AZ41:BK41) -> -4.1296995
A42: Marketing | B42: млн ₽ | D42: =-'Cost assumptions'!D42/1000000 -> 0 | E42: =-'Cost assumptions'!E42/1000000 -> 0 | F42: =-'Cost assumptions'!F42/1000000 -> 0 | G42: =-'Cost assumptions'!G42/1000000 -> 0 | H42: =-'Cost assumptions'!H42/1000000 -> 0 | I42: =-'Cost assumptions'!I42/1000000 -> 0 | J42: =-'Cost assumptions'!J42/1000000 -> 0 | K42: =-'Cost assumptions'!K42/1000000 -> -0.33333333 | ... BK42: =-'Cost assumptions'!BK42/1000000 -> -0.25 | BL42: =SUM(D42:O42) -> -1.6666667 | BM42: =SUM(P42:AA42) -> -3.5833333 | BN42: =SUM(AB42:AM42) -> -3 | BO42: =SUM(AN42:AY42) -> -3 | BP42: =SUM(AZ42:BK42) -> -3
A43: Consulting | B43: млн ₽ | D43: 0 | E43: 0 | F43: 0 | G43: 0 | H43: 0 | I43: 0 | J43: 0 | K43: 0 | L43: 0 | M43: 0 | N43: 0 | O43: 0 | P43: 0 | Q43: 0 | R43: 0 | S43: 0 | T43: 0 | U43: 0 | V43: 0 | W43: 0 | X43: 0 | Y43: 0 | Z43: 0 | AA43: 0 | AB43: 0 | AC43: 0 | AD43: 0 | AE43: 0 | AF43: 0 | AG43: 0 | AH43: 0 | AI43: 0 | AJ43: 0 | AK43: 0 | AL43: 0 | AM43: 0 | AN43: 0 | AO43: 0 | AP43: 0 | AQ43: 0 | AR43: 0 | AS43: 0 | AT43: 0 | AU43: 0 | AV43: 0 | AW43: 0 | AX43: 0 | AY43: 0 | AZ43: 0 | BA43: 0 | BB43: 0 | BC43: 0 | BD43: 0 | BE43: 0 | BF43: 0 | BG43: 0 | BH43: 0 | BI43: 0 | BJ43: 0 | BK43: 0 | BL43: =SUM(D43:O43) -> 0 | BM43: =SUM(P43:AA43) -> 0 | BN43: =SUM(AB43:AM43) -> 0 | BO43: =SUM(AN43:AY43) -> 0 | BP43: =SUM(AZ43:BK43) -> 0
A44: IT Costs | B44: млн ₽ | D44: =-'Cost assumptions'!D43/1000000 -> -0.125 | E44: =-'Cost assumptions'!E43/1000000 -> -0.125 | F44: =-'Cost assumptions'!F43/1000000 -> -0.825 | G44: =-'Cost assumptions'!G43/1000000 -> -0.125 | H44: =-'Cost assumptions'!H43/1000000 -> -0.125 | I44: =-'Cost assumptions'!I43/1000000 -> -0.125 | J44: =-'Cost assumptions'!J43/1000000 -> -0.125 | K44: =-'Cost assumptions'!K43/1000000 -> -0.425 | ... BK44: =-'Cost assumptions'!BK43/1000000 -> -0.125 | BL44: =SUM(D44:O44) -> -2.5 | BM44: =SUM(P44:AA44) -> -2.1 | BN44: =SUM(AB44:AM44) -> -1.5 | BO44: =SUM(AN44:AY44) -> -1.5 | BP44: =SUM(AZ44:BK44) -> -1.5
A45: G&A Costs | B45: млн ₽ | D45: =-'Cost assumptions'!D44/1000000 -> -0.0606326 | E45: =-'Cost assumptions'!E44/1000000 -> -0.0606326 | F45: =-'Cost assumptions'!F44/1000000 -> -0.0619776 | G45: =-'Cost assumptions'!G44/1000000 -> -0.0619776 | H45: =-'Cost assumptions'!H44/1000000 -> -0.0804848 | I45: =-'Cost assumptions'!I44/1000000 -> -0.0766112 | J45: =-'Cost assumptions'!J44/1000000 -> -0.0766112 | K45: =-'Cost assumptions'!K44/1000000 -> -0.029321 | ... BK45: =-'Cost assumptions'!BK44/1000000 -> -0.017207081 | BL45: =SUM(D45:O45) -> -0.6255326 | BM45: =SUM(P45:AA45) -> -0.16855325 | BN45: =SUM(AB45:AM45) -> -0.18035198 | BO45: =SUM(AN45:AY45) -> -0.19297661 | BP45: =SUM(AZ45:BK45) -> -0.20648498
A46: Other Costs | B46: млн ₽ | D46: 0 | E46: 0 | F46: 0 | G46: 0 | H46: 0 | I46: 0 | J46: 0 | K46: 0 | L46: 0 | M46: 0 | N46: 0 | O46: 0 | P46: 0 | Q46: 0 | R46: 0 | S46: 0 | T46: 0 | U46: 0 | V46: 0 | W46: 0 | X46: 0 | Y46: 0 | Z46: 0 | AA46: 0 | AB46: 0 | AC46: 0 | AD46: 0 | AE46: 0 | AF46: 0 | AG46: 0 | AH46: 0 | AI46: 0 | AJ46: 0 | AK46: 0 | AL46: 0 | AM46: 0 | AN46: 0 | AO46: 0 | AP46: 0 | AQ46: 0 | AR46: 0 | AS46: 0 | AT46: 0 | AU46: 0 | AV46: 0 | AW46: 0 | AX46: 0 | AY46: 0 | AZ46: 0 | BA46: 0 | BB46: 0 | BC46: 0 | BD46: 0 | BE46: 0 | BF46: 0 | BG46: 0 | BH46: 0 | BI46: 0 | BJ46: 0 | BK46: 0 | BL46: =SUM(D46:O46) -> 0 | BM46: =SUM(P46:AA46) -> 0 | BN46: =SUM(AB46:AM46) -> 0 | BO46: =SUM(AN46:AY46) -> 0 | BP46: =SUM(AZ46:BK46) -> 0
A47: EBITDA | B47: млн ₽ | D47: =D39+SUM(D40:D46) -> -1.3982846 | E47: =E39+SUM(E40:E46) -> -1.3982846 | F47: =F39+SUM(F40:F46) -> -1.9744222 | G47: =G39+SUM(G40:G46) -> -1.1594658 | H47: =H39+SUM(H40:H46) -> -1.3365848 | I47: =I39+SUM(I40:I46) -> -1.0142615 | J47: =J39+SUM(J40:J46) -> -0.7567863 | K47: =K39+SUM(K40:K46) -> -0.089365723 | ... BK47: =BK39+SUM(BK40:BK46) -> 2.5394229 | BL47: =SUM(D47:O47) -> -5.399888 | BM47: =SUM(P47:AA47) -> 18.904248 | BN47: =SUM(AB47:AM47) -> 21.251706 | BO47: =SUM(AN47:AY47) -> 22.168265 | BP47: =SUM(AZ47:BK47) -> 23.11342
A48: EBITDA margin | B48: % | D48: =IFERROR(D47/D39,0) -> 0 | E48: =IFERROR(E47/E39,0) -> 0 | F48: =IFERROR(F47/F39,0) -> -12.461229 | G48: =IFERROR(G47/G39,0) -> -4.1678704 | H48: =IFERROR(H47/H39,0) -> -2.6810117 | I48: =IFERROR(I47/I39,0) -> -1.3531497 | J48: =IFERROR(J47/J39,0) -> -0.74358084 | K48: =IFERROR(K47/K39,0) -> -0.066778641 | ... BP48: =IFERROR(BP47/BP39,0) -> 0.69449634
A49: Income Tax | B49: млн ₽ | D49: =-MAX(D47,0)*D12 -> 0 | E49: =-MAX(E47,0)*E12 -> 0 | F49: =-MAX(F47,0)*F12 -> 0 | G49: =-MAX(G47,0)*G12 -> 0 | H49: =-MAX(H47,0)*H12 -> 0 | I49: =-MAX(I47,0)*I12 -> 0 | J49: =-MAX(J47,0)*J12 -> 0 | K49: =-MAX(K47,0)*K12 -> 0 | ... BK49: =-MAX(BK47,0)*BK12 -> -0.12697115 | BL49: =SUM(D49:O49) -> -0.18637838 | BM49: =SUM(P49:AA49) -> -0.94521242 | BN49: =SUM(AB49:AM49) -> -1.0625853 | BO49: =SUM(AN49:AY49) -> -1.1084132 | BP49: =SUM(AZ49:BK49) -> -1.155671
A50: NOPAT (EBITDA - Tax) | B50: млн ₽ | D50: =D47+D49 -> -1.3982846 | E50: =E47+E49 -> -1.3982846 | F50: =F47+F49 -> -1.9744222 | G50: =G47+G49 -> -1.1594658 | H50: =H47+H49 -> -1.3365848 | I50: =I47+I49 -> -1.0142615 | J50: =J47+J49 -> -0.7567863 | K50: =K47+K49 -> -0.089365723 | ... BK50: =BK47+BK49 -> 2.4124518 | BL50: =SUM(D50:O50) -> -5.5862664 | BM50: =SUM(P50:AA50) -> 17.959036 | BN50: =SUM(AB50:AM50) -> 20.189121 | BO50: =SUM(AN50:AY50) -> 21.059852 | BP50: =SUM(AZ50:BK50) -> 21.957749
A51: AR (упрощение: 60 дней оборачиваемости от Revenue) | B51: млн ₽ | D51: =D39*2 -> 0 | E51: =E39*2 -> 0 | F51: =F39*2 -> 0.31689044 | G51: =G39*2 -> 0.55638286 | H51: =H39*2 -> 0.99707497 | I51: =I39*2 -> 1.4991119 | J51: =J39*2 -> 2.0355185 | K51: =K39*2 -> 2.6764763 | ... BK51: =BK39*2 -> 6.8245242 | BL51: =O51 -> 5.1623476 | BM51: =AA51 -> 6.0666423 | BN51: =AM51 -> 6.3096562 | BO51: =AY51 -> 6.5620425 | BP51: =BK51 -> 6.8245242
A52: AP (60 дней оборачиваемости от затрат) | B52: млн ₽ | D52: =(D40+D42+D44+D45)*2 -> -0.3712652 | E52: =(E40+E42+E44+E45)*2 -> -0.3712652 | F52: =(F40+F42+F44+F45)*2 -> -1.7866308 | G52: =(G40+G42+G44+G45)*2 -> -0.39621051 | H52: =(H40+H42+H44+H45)*2 -> -0.4508526 | I52: =(I40+I42+I44+I45)*2 -> -0.46318688 | J52: =(J40+J42+J44+J45)*2 -> -0.48464314 | K52: =(K40+K42+K44+K45)*2 -> -1.6823677 | ... BK52: =(BK40+BK42+BK44+BK45)*2 -> -1.0573951 | BL52: =O52 -> -1.1818026 | BM52: =AA52 -> -1.0207579 | BN52: =AM52 -> -1.0324449 | BO52: =AY52 -> -1.0446445 | BP52: =BK52 -> -1.0573951
A53: NWC = AR + AP | B53: млн ₽ | D53: =D51+D52 -> -0.3712652 | E53: =E51+E52 -> -0.3712652 | F53: =F51+F52 -> -1.4697404 | G53: =G51+G52 -> 0.16017235 | H53: =H51+H52 -> 0.54622237 | I53: =I51+I52 -> 1.0359251 | J53: =J51+J52 -> 1.5508754 | K53: =K51+K52 -> 0.99410855 | ... BK53: =BK51+BK52 -> 5.7671291 | BL53: =O53 -> 3.980545 | BM53: =AA53 -> 5.0458844 | BN53: =AM53 -> 5.2772113 | BO53: =AY53 -> 5.5173981 | BP53: =BK53 -> 5.7671291
A54: Change in NWC | B54: млн ₽ | D54: =-D53 -> 0.3712652 | E54: =-(E53-D53) -> 0 | F54: =-(F53-E53) -> 1.0984752 | G54: =-(G53-F53) -> -1.6299127 | H54: =-(H53-G53) -> -0.38605003 | I54: =-(I53-H53) -> -0.48970269 | J54: =-(J53-I53) -> -0.51495034 | K54: =-(K53-J53) -> 0.55676685 | L54: =-(L53-K53) -> -1.0735835 | ... BK54: =-(BK53-BJ53) -> -0.021378062 | BL54: =-BL53 -> -3.980545 | BM54: =-(BM53-BL53) -> -1.0653394 | BN54: =-(BN53-BM53) -> -0.23132689 | BO54: =-(BO53-BN53) -> -0.24018681 | BP54: =-(BP53-BO53) -> -0.24973104
A55: FCF (Free Cash Flow) | B55: млн ₽ | D55: =D50+D54 -> -1.0270194 | E55: =E50+E54 -> -1.3982846 | F55: =F50+F54 -> -0.87594701 | G55: =G50+G54 -> -2.7893785 | H55: =H50+H54 -> -1.7226348 | I55: =I50+I54 -> -1.5039642 | J55: =J50+J54 -> -1.2717366 | K55: =K50+K54 -> 0.46740113 | ... BP55: =BP50+BP54 -> 21.708018
A57: 5. FINANCIALS TO BE (AS IS + INCREMENT)
A58: Revenue | B58: млн ₽ | D58: =D20+D39 -> 20.454545 | E58: =E20+E39 -> 41.043017 | F58: =F20+F39 -> 33.10035 | G58: =G20+G39 -> 33.327939 | H58: =H20+H39 -> 33.656482 | I58: =I20+I39 -> 34.016051 | J58: =J20+J39 -> 34.39316 | K58: =K20+K39 -> 34.822901 | ... BP58: =BP20+BP39 -> 497.78562
A59: CoS | B59: млн ₽ | D59: =D21+D40 -> -0.40909091 | E59: =E21+E40 -> -0.82086033 | F59: =F21+F40 -> -0.6651759 | G59: =G21+G40 -> -0.67212261 | H59: =H21+H40 -> -0.68310038 | I59: =I21+I40 -> -0.69531213 | J59: =J21+J40 -> -0.70821838 | K59: =K21+K40 -> -0.72322278 | ... BP59: =BP21+BP40 -> -10.621329
A60: Staff costs | B60: млн ₽ | D60: =D22+D41 -> -8.212652 | E60: =E22+E41 -> -8.212652 | F60: =F22+F41 -> -8.239552 | G60: =G22+G41 -> -8.239552 | H60: =H22+H41 -> -8.609696 | I60: =I22+I41 -> -8.532224 | J60: =J22+J41 -> -8.532224 | K60: =K22+K41 -> -7.58642 | ... BP60: =BP22+BP41 -> -114.23656
A61: Marketing | B61: млн ₽ | D61: =D23+D42 -> -1.0227273 | E61: =E23+E42 -> -2.0521508 | F61: =F23+F42 -> -1.6470952 | G61: =G23+G42 -> -1.6524874 | H61: =H23+H42 -> -1.6578972 | I61: =I23+I42 -> -1.6633247 | J61: =J23+J42 -> -1.66877 | K61: =K23+K42 -> -2.0075665 | ... BP61: =BP23+BP42 -> -26.225239
A62: Consulting | B62: млн ₽ | D62: =D24+D43 -> 0 | E62: =E24+E43 -> 0 | F62: =F24+F43 -> 0 | G62: =G24+G43 -> 0 | H62: =H24+H43 -> 0 | I62: =I24+I43 -> 0 | J62: =J24+J43 -> 0 | K62: =K24+K43 -> 0 | ... BP62: =BP24+BP43 -> 0
A63: IT Costs | B63: млн ₽ | D63: =D25+D44 -> -0.375 | E63: =E25+E44 -> -0.375 | F63: =F25+F44 -> -1.075 | G63: =G25+G44 -> -0.375 | H63: =H25+H44 -> -0.375 | I63: =I25+I44 -> -0.375 | J63: =J25+J44 -> -0.375 | K63: =K25+K44 -> -0.675 | ... BP63: =BP25+BP44 -> -4.5
A64: G&A Costs | B64: млн ₽ | D64: =D26+D45 -> -0.4106326 | E64: =E26+E45 -> -0.4106326 | F64: =F26+F45 -> -0.4119776 | G64: =G26+G45 -> -0.4119776 | H64: =H26+H45 -> -0.4304848 | I64: =I26+I45 -> -0.4266112 | J64: =J26+J45 -> -0.4266112 | K64: =K26+K45 -> -0.379321 | ... BP64: =BP26+BP45 -> -5.7118282
A65: Other Costs | B65: млн ₽ | D65: =D27+D46 -> 0 | E65: =E27+E46 -> 0 | F65: =F27+F46 -> 0 | G65: =G27+G46 -> 0 | H65: =H27+H46 -> 0 | I65: =I27+I46 -> 0 | J65: =J27+J46 -> 0 | K65: =K27+K46 -> 0 | ... BP65: =BP27+BP46 -> 0
A66: EBITDA | B66: млн ₽ | D66: =D28+D47 -> 10.024443 | E66: =E28+E47 -> 29.171721 | F66: =F28+F47 -> 21.061549 | G66: =G28+G47 -> 21.9768 | H66: =H28+H47 -> 21.900303 | I66: =I28+I47 -> 22.323579 | J66: =J28+J47 -> 22.682336 | K66: =K28+K47 -> 23.451371 | ... BP66: =BP28+BP47 -> 336.49066
A67: EBITDA margin | B67: % | D67: =IFERROR(D66/D58,0) -> 0.49008386 | E67: =IFERROR(E66/E58,0) -> 0.71075967 | F67: =IFERROR(F66/F58,0) -> 0.63629385 | G67: =IFERROR(G66/G58,0) -> 0.6594107 | H67: =IFERROR(H66/H58,0) -> 0.65070091 | I67: =IFERROR(I66/I58,0) -> 0.65626603 | J67: =IFERROR(J66/J58,0) -> 0.65950137 | K67: =IFERROR(K66/K58,0) -> 0.67344679 | ... BP67: =IFERROR(BP66/BP58,0) -> 0.67597505
A68: Income Tax | B68: млн ₽ | D68: =D30+D49 -> -0.57113636 | E68: =E30+E49 -> -1.5285003 | F68: =F30+F49 -> -1.1517986 | G68: =G30+G49 -> -1.1568133 | H68: =H30+H49 -> -1.1618444 | I68: =I30+I49 -> -1.166892 | J68: =J30+J49 -> -1.1719561 | K68: =K30+K49 -> -1.1770368 | ... BP68: =BP30+BP49 -> -16.824533
A69: NOPAT (EBITDA - Tax) | B69: млн ₽ | D69: =D31+D50 -> 9.4533063 | E69: =E31+E50 -> 27.643221 | F69: =F31+F50 -> 19.909751 | G69: =G31+G50 -> 20.819986 | H69: =H31+H50 -> 20.738459 | I69: =I31+I50 -> 21.156687 | J69: =J31+J50 -> 21.51038 | K69: =K31+K50 -> 22.274334 | ... BP69: =BP31+BP50 -> 319.66612
A70: AR (упрощение: 60 дней оборачиваемости от Revenue) | B70: млн ₽ | D70: =D32+D51 -> 40.909091 | E70: =E32+E51 -> 82.086033 | F70: =F32+F51 -> 66.2007 | G70: =G32+G51 -> 66.655879 | H70: =H32+H51 -> 67.312963 | I70: =I32+I51 -> 68.032101 | J70: =J32+J51 -> 68.786319 | K70: =K32+K51 -> 69.645802 | ... BP70: =BP32+BP51 -> 102.07525
A71: AP (60 дней оборачиваемости от затрат) | B71: млн ₽ | D71: =D33+D52 -> -4.4349016 | E71: =E33+E52 -> -7.3172875 | F71: =F33+F52 -> -7.5984975 | G71: =G33+G52 -> -6.2231752 | H71: =H33+H52 -> -6.2929648 | I71: =I33+I52 -> -6.3204961 | J71: =J33+J52 -> -6.3571992 | K71: =K33+K52 -> -7.5702205 | ... BP71: =BP33+BP52 -> -9.1425034
A72: NWC = AR + AP | B72: млн ₽ | D72: =D34+D53 -> 36.474189 | E72: =E34+E53 -> 74.768746 | F72: =F34+F53 -> 58.602202 | G72: =G34+G53 -> 60.432703 | H72: =H34+H53 -> 61.019998 | I72: =I34+I53 -> 61.711605 | J72: =J34+J53 -> 62.42912 | K72: =K34+K53 -> 62.075581 | ... BP72: =BP34+BP53 -> 92.93275
A73: Change in NWC | B73: млн ₽ | D73: =D35+D54 -> -36.474189 | E73: =E35+E54 -> -38.294556 | F73: =F35+F54 -> 16.166543 | G73: =G35+G54 -> -1.8305011 | H73: =H35+H54 -> -0.5872951 | I73: =I35+I54 -> -0.69160658 | J73: =J35+J54 -> -0.71751522 | K73: =K35+K54 -> 0.35353883 | ... BP73: =BP35+BP54 -> -3.5967492
A74: FCF (Free Cash Flow) | B74: млн ₽ | D74: =D36+D55 -> -27.020883 | E74: =E36+E55 -> -10.651336 | F74: =F36+F55 -> 36.076294 | G74: =G36+G55 -> 18.989485 | H74: =H36+H55 -> 20.151164 | I74: =I36+I55 -> 20.46508 | J74: =J36+J55 -> 20.792865 | K74: =K36+K55 -> 22.627873 | ... BP74: =BP36+BP55 -> 316.06937

Sheet Команда и TtM
A1: Команда и Time-to-Market (TtM)
A2: Инициатива: 3 гипотезы из ДЗ2, реализуемые волнами по приоритету (от high confidence к low)
A4: 1. Тарифная сетка
A5: Роль | B5: Уровень | C5: Salary gross, ₽/мес | D5: Налоги (×k) | E5: Cost ₽/мес (с налогами) | F5: Cost млн ₽/мес | G5: Источник
A6: Product Manager | B6: Senior | C6: 250000 | D6: 1.076 | E6: =C6*D6 -> 269000 | F6: =E6/1000000 -> 0.269
A7: UX Designer | B7: Middle+ | C7: 180000 | D7: 1.076 | E7: =C7*D7 -> 193680 | F7: =E7/1000000 -> 0.19368
A8: Data Analyst | B8: Middle+ | C8: 180000 | D8: 1.076 | E8: =C8*D8 -> 193680 | F8: =E8/1000000 -> 0.19368
A9: ML Engineer | B9: Middle+ | C9: 280000 | D9: 1.076 | E9: =C9*D9 -> 301280 | F9: =E9/1000000 -> 0.30128
A10: Backend Engineer | B10: Middle+ | C10: 250000 | D10: 1.076 | E10: =C10*D10 -> 269000 | F10: =E10/1000000 -> 0.269
A11: Frontend Engineer | B11: Middle | C11: 200000 | D11: 1.076 | E11: =C11*D11 -> 215200 | F11: =E11/1000000 -> 0.2152
A12: QA Engineer | B12: Middle | C12: 150000 | D12: 1.076 | E12: =C12*D12 -> 161400 | F12: =E12/1000000 -> 0.1614
A13: DevOps Engineer | B13: Middle+ | C13: 220000 | D13: 1.076 | E13: =C13*D13 -> 236720 | F13: =E13/1000000 -> 0.23672
A15: Страховые взносы 7,6% - льгота для IT-аккредитованных компаний (Avito аккредитована Минцифры России). Состав: ПФР 6% + ОМС 0,1% + ФСС 1,5%. НК РФ ст. 427 п. 1 пп. 3, ФЗ-321 от 14.07.2022. Бессрочная льгота для tech-сектора. Базовая ставка 30,2% применялась бы для не-IT.
A16: Налог на прибыль для IT-аккредитованных: 0% (2025), 5% (2026-2030). Действует до 31.12.2030 (ст. 284 п. 1.15 НК РФ). В модели в PnL уже учтено: 0% в 2026, 5% с 2027.
A17: 2. Roadmap волн инициативы
A18: Wave | B18: Гипотеза (из ДЗ2) | C18: Confidence | D18: Discovery | E18: Development | F18: Launch (полный) | G18: Базовая команда
A19: Wave 1 | B19: Алгоритм персонализир. рекомендаций для селлеров (ARPPU +10%) | C19: 0.75 | D19: мес 1 (Discovery+спека) | E19: мес 1-2 (Dev) | F19: мес 3 (Launch) | G19: PM, ML, BE, FE, Data, QA
A20: Wave 2 | B20: Индикатор соответствия цены рынку (ARPPU +5%) | C20: 0.6 | D20: мес 2 (параллельно с W1 Dev) | E20: мес 3-4 (Dev) | F20: мес 5 (Launch) | G20: PM, BE, FE, ML, QA
A21: Wave 3 | B21: Видео в карточках + лента "Истории" (MAU +3%) | C21: 0.4 | D21: мес 5 (Discovery) | E21: мес 6-7 (Dev, видео-инфра) | F21: мес 8 (Launch) | G21: PM, UX, BE, FE, DevOps, ML, QA
A23: TtM до полного запуска всех 3 волн: | B23: 8 | C23: мес (без буфера)
A24: Буфер на риски задержек: | B24: 0.2
A25: TtM с буфером: | B25: =B23*(1+B24) -> 9.6 | C25: ≈ 10 мес до полного релиза всех 3 волн
A26: TtM первой волны (Wave 1) до релиза: | B26: 3 | C26: мес - алгоритм рекомендаций (на готовой ML-платформе Avito)
A28: 3. Распределение FTE по ролям × месяцам (5 лет, помесячно)
A29: Логика: фичи строятся на готовой инфраструктуре Avito (ML-платформа, CDN, A/B framework). TtM компактный за счёт переиспользования существующих компонентов. После релиза каждой волны команда переходит в Support (минимальный maintenance).
A30: Роль | B30: Salary ref | C30: Unit | D30: 2026 | E30: 2026 | F30: 2026 | G30: 2026 | H30: 2026 | I30: 2026 | J30: 2026 | K30: 2026 | L30: 2026 | M30: 2026 | N30: 2026 | O30: 2026 | P30: 2027 | Q30: 2027 | R30: 2027 | S30: 2027 | T30: 2027 | U30: 2027 | V30: 2027 | W30: 2027 | X30: 2027 | Y30: 2027 | Z30: 2027 | AA30: 2027 | AB30: 2028 | AC30: 2028 | AD30: 2028 | AE30: 2028 | AF30: 2028 | AG30: 2028 | AH30: 2028 | AI30: 2028 | AJ30: 2028 | AK30: 2028 | AL30: 2028 | AM30: 2028 | AN30: 2029 | AO30: 2029 | AP30: 2029 | AQ30: 2029 | AR30: 2029 | AS30: 2029 | AT30: 2029 | AU30: 2029 | AV30: 2029 | AW30: 2029 | AX30: 2029 | AY30: 2029 | AZ30: 2030 | BA30: 2030 | BB30: 2030 | BC30: 2030 | BD30: 2030 | BE30: 2030 | BF30: 2030 | BG30: 2030 | BH30: 2030 | BI30: 2030 | BJ30: 2030 | BK30: 2030 | BL30: 2026 Total | BM30: 2027 Total | BN30: 2028 Total | BO30: 2029 Total | BP30: 2030 Total
D31: Jan | E31: Feb | F31: Mar | G31: Apr | H31: May | I31: Jun | J31: Jul | K31: Aug | L31: Sep | M31: Oct | N31: Nov | O31: Dec | P31: Jan | Q31: Feb | R31: Mar | S31: Apr | T31: May | U31: Jun | V31: Jul | W31: Aug | X31: Sep | Y31: Oct | Z31: Nov | AA31: Dec | AB31: Jan | AC31: Feb | AD31: Mar | AE31: Apr | AF31: May | AG31: Jun | AH31: Jul | AI31: Aug | AJ31: Sep | AK31: Oct | AL31: Nov | AM31: Dec | AN31: Jan | AO31: Feb | AP31: Mar | AQ31: Apr | AR31: May | AS31: Jun | AT31: Jul | AU31: Aug | AV31: Sep | AW31: Oct | AX31: Nov | AY31: Dec | AZ31: Jan | BA31: Feb | BB31: Mar | BC31: Apr | BD31: May | BE31: Jun | BF31: Jul | BG31: Aug | BH31: Sep | BI31: Oct | BJ31: Nov | BK31: Dec
A32: PM | B32: =E6 -> 269000 | C32: FTE | D32: 1 | E32: 1 | F32: 1 | G32: 1 | H32: 1 | I32: 1 | J32: 1 | K32: 0.3 | L32: 0.3 | M32: 0.3 | N32: 0.3 | O32: 0.3 | P32: 0.1 | Q32: 0.1 | R32: 0.1 | S32: 0.1 | T32: 0.1 | U32: 0.1 | V32: 0.1 | W32: 0.1 | X32: 0.1 | Y32: 0.1 | Z32: 0.1 | AA32: 0.1 | AB32: 0.1 | AC32: 0.1 | AD32: 0.1 | AE32: 0.1 | AF32: 0.1 | AG32: 0.1 | AH32: 0.1 | AI32: 0.1 | AJ32: 0.1 | AK32: 0.1 | AL32: 0.1 | AM32: 0.1 | AN32: 0.1 | AO32: 0.1 | AP32: 0.1 | AQ32: 0.1 | AR32: 0.1 | AS32: 0.1 | AT32: 0.1 | AU32: 0.1 | AV32: 0.1 | AW32: 0.1 | AX32: 0.1 | AY32: 0.1 | AZ32: 0.1 | BA32: 0.1 | BB32: 0.1 | BC32: 0.1 | BD32: 0.1 | BE32: 0.1 | BF32: 0.1 | BG32: 0.1 | BH32: 0.1 | BI32: 0.1 | BJ32: 0.1 | BK32: 0.1 | BL32: =AVERAGE(D32:O32) -> 0.70833333 | BM32: =AVERAGE(P32:AA32) -> 0.1 | BN32: =AVERAGE(AB32:AM32) -> 0.1 | BO32: =AVERAGE(AN32:AY32) -> 0.1 | BP32: =AVERAGE(AZ32:BK32) -> 0.1
A33: UX Designer | B33: =E7 -> 193680 | C33: FTE | D33: 0.5 | E33: 0.5 | F33: 0 | G33: 0 | H33: 0.7 | I33: 0.3 | J33: 0.3 | K33: 0.1 | L33: 0.1 | M33: 0.1 | N33: 0.1 | O33: 0.1 | P33: 0 | Q33: 0 | R33: 0 | S33: 0 | T33: 0 | U33: 0 | V33: 0 | W33: 0 | X33: 0 | Y33: 0 | Z33: 0 | AA33: 0 | AB33: 0 | AC33: 0 | AD33: 0 | AE33: 0 | AF33: 0 | AG33: 0 | AH33: 0 | AI33: 0 | AJ33: 0 | AK33: 0 | AL33: 0 | AM33: 0 | AN33: 0 | AO33: 0 | AP33: 0 | AQ33: 0 | AR33: 0 | AS33: 0 | AT33: 0 | AU33: 0 | AV33: 0 | AW33: 0 | AX33: 0 | AY33: 0 | AZ33: 0 | BA33: 0 | BB33: 0 | BC33: 0 | BD33: 0 | BE33: 0 | BF33: 0 | BG33: 0 | BH33: 0 | BI33: 0 | BJ33: 0 | BK33: 0 | BL33: =AVERAGE(D33:O33) -> 0.23333333 | BM33: =AVERAGE(P33:AA33) -> 0 | BN33: =AVERAGE(AB33:AM33) -> 0 | BO33: =AVERAGE(AN33:AY33) -> 0 | BP33: =AVERAGE(AZ33:BK33) -> 0
A34: Data Analyst | B34: =E8 -> 193680 | C34: FTE | D34: 0.5 | E34: 0.5 | F34: 0.5 | G34: 0.5 | H34: 0.5 | I34: 0.5 | J34: 0.5 | K34: 0.3 | L34: 0.3 | M34: 0.3 | N34: 0.3 | O34: 0.3 | P34: 0.2 | Q34: 0.2 | R34: 0.2 | S34: 0.2 | T34: 0.2 | U34: 0.2 | V34: 0.2 | W34: 0.2 | X34: 0.2 | Y34: 0.2 | Z34: 0.2 | AA34: 0.2 | AB34: 0.2 | AC34: 0.2 | AD34: 0.2 | AE34: 0.2 | AF34: 0.2 | AG34: 0.2 | AH34: 0.2 | AI34: 0.2 | AJ34: 0.2 | AK34: 0.2 | AL34: 0.2 | AM34: 0.2 | AN34: 0.2 | AO34: 0.2 | AP34: 0.2 | AQ34: 0.2 | AR34: 0.2 | AS34: 0.2 | AT34: 0.2 | AU34: 0.2 | AV34: 0.2 | AW34: 0.2 | AX34: 0.2 | AY34: 0.2 | AZ34: 0.2 | BA34: 0.2 | BB34: 0.2 | BC34: 0.2 | BD34: 0.2 | BE34: 0.2 | BF34: 0.2 | BG34: 0.2 | BH34: 0.2 | BI34: 0.2 | BJ34: 0.2 | BK34: 0.2 | BL34: =AVERAGE(D34:O34) -> 0.41666667 | BM34: =AVERAGE(P34:AA34) -> 0.2 | BN34: =AVERAGE(AB34:AM34) -> 0.2 | BO34: =AVERAGE(AN34:AY34) -> 0.2 | BP34: =AVERAGE(AZ34:BK34) -> 0.2
A35: ML Engineer | B35: =E9 -> 301280 | C35: FTE | D35: 1 | E35: 1 | F35: 0.5 | G35: 0.5 | H35: 0.5 | I35: 0.5 | J35: 0.5 | K35: 0.3 | L35: 0.3 | M35: 0.3 | N35: 0.3 | O35: 0.3 | P35: 0.2 | Q35: 0.2 | R35: 0.2 | S35: 0.2 | T35: 0.2 | U35: 0.2 | V35: 0.2 | W35: 0.2 | X35: 0.2 | Y35: 0.2 | Z35: 0.2 | AA35: 0.2 | AB35: 0.2 | AC35: 0.2 | AD35: 0.2 | AE35: 0.2 | AF35: 0.2 | AG35: 0.2 | AH35: 0.2 | AI35: 0.2 | AJ35: 0.2 | AK35: 0.2 | AL35: 0.2 | AM35: 0.2 | AN35: 0.2 | AO35: 0.2 | AP35: 0.2 | AQ35: 0.2 | AR35: 0.2 | AS35: 0.2 | AT35: 0.2 | AU35: 0.2 | AV35: 0.2 | AW35: 0.2 | AX35: 0.2 | AY35: 0.2 | AZ35: 0.2 | BA35: 0.2 | BB35: 0.2 | BC35: 0.2 | BD35: 0.2 | BE35: 0.2 | BF35: 0.2 | BG35: 0.2 | BH35: 0.2 | BI35: 0.2 | BJ35: 0.2 | BK35: 0.2 | BL35: =AVERAGE(D35:O35) -> 0.5 | BM35: =AVERAGE(P35:AA35) -> 0.2 | BN35: =AVERAGE(AB35:AM35) -> 0.2 | BO35: =AVERAGE(AN35:AY35) -> 0.2 | BP35: =AVERAGE(AZ35:BK35) -> 0.2
A36: Backend | B36: =E10 -> 269000 | C36: FTE | D36: 1 | E36: 1 | F36: 1.5 | G36: 1.5 | H36: 1.5 | I36: 1.5 | J36: 1.5 | K36: 0.5 | L36: 0.5 | M36: 0.5 | N36: 0.5 | O36: 0.5 | P36: 0.2 | Q36: 0.2 | R36: 0.2 | S36: 0.2 | T36: 0.2 | U36: 0.2 | V36: 0.2 | W36: 0.2 | X36: 0.2 | Y36: 0.2 | Z36: 0.2 | AA36: 0.2 | AB36: 0.2 | AC36: 0.2 | AD36: 0.2 | AE36: 0.2 | AF36: 0.2 | AG36: 0.2 | AH36: 0.2 | AI36: 0.2 | AJ36: 0.2 | AK36: 0.2 | AL36: 0.2 | AM36: 0.2 | AN36: 0.2 | AO36: 0.2 | AP36: 0.2 | AQ36: 0.2 | AR36: 0.2 | AS36: 0.2 | AT36: 0.2 | AU36: 0.2 | AV36: 0.2 | AW36: 0.2 | AX36: 0.2 | AY36: 0.2 | AZ36: 0.2 | BA36: 0.2 | BB36: 0.2 | BC36: 0.2 | BD36: 0.2 | BE36: 0.2 | BF36: 0.2 | BG36: 0.2 | BH36: 0.2 | BI36: 0.2 | BJ36: 0.2 | BK36: 0.2 | BL36: =AVERAGE(D36:O36) -> 1 | BM36: =AVERAGE(P36:AA36) -> 0.2 | BN36: =AVERAGE(AB36:AM36) -> 0.2 | BO36: =AVERAGE(AN36:AY36) -> 0.2 | BP36: =AVERAGE(AZ36:BK36) -> 0.2
A37: Frontend | B37: =E11 -> 215200 | C37: FTE | D37: 0.5 | E37: 0.5 | F37: 1 | G37: 1 | H37: 1.5 | I37: 1.5 | J37: 1.5 | K37: 0.5 | L37: 0.5 | M37: 0.5 | N37: 0.5 | O37: 0.5 | P37: 0.2 | Q37: 0.2 | R37: 0.2 | S37: 0.2 | T37: 0.2 | U37: 0.2 | V37: 0.2 | W37: 0.2 | X37: 0.2 | Y37: 0.2 | Z37: 0.2 | AA37: 0.2 | AB37: 0.2 | AC37: 0.2 | AD37: 0.2 | AE37: 0.2 | AF37: 0.2 | AG37: 0.2 | AH37: 0.2 | AI37: 0.2 | AJ37: 0.2 | AK37: 0.2 | AL37: 0.2 | AM37: 0.2 | AN37: 0.2 | AO37: 0.2 | AP37: 0.2 | AQ37: 0.2 | AR37: 0.2 | AS37: 0.2 | AT37: 0.2 | AU37: 0.2 | AV37: 0.2 | AW37: 0.2 | AX37: 0.2 | AY37: 0.2 | AZ37: 0.2 | BA37: 0.2 | BB37: 0.2 | BC37: 0.2 | BD37: 0.2 | BE37: 0.2 | BF37: 0.2 | BG37: 0.2 | BH37: 0.2 | BI37: 0.2 | BJ37: 0.2 | BK37: 0.2 | BL37: =AVERAGE(D37:O37) -> 0.83333333 | BM37: =AVERAGE(P37:AA37) -> 0.2 | BN37: =AVERAGE(AB37:AM37) -> 0.2 | BO37: =AVERAGE(AN37:AY37) -> 0.2 | BP37: =AVERAGE(AZ37:BK37) -> 0.2
A38: QA | B38: =E12 -> 161400 | C38: FTE | D38: 0.3 | E38: 0.3 | F38: 0.5 | G38: 0.5 | H38: 0.7 | I38: 0.7 | J38: 0.7 | K38: 0.3 | L38: 0.3 | M38: 0.3 | N38: 0.3 | O38: 0.3 | P38: 0.1 | Q38: 0.1 | R38: 0.1 | S38: 0.1 | T38: 0.1 | U38: 0.1 | V38: 0.1 | W38: 0.1 | X38: 0.1 | Y38: 0.1 | Z38: 0.1 | AA38: 0.1 | AB38: 0.1 | AC38: 0.1 | AD38: 0.1 | AE38: 0.1 | AF38: 0.1 | AG38: 0.1 | AH38: 0.1 | AI38: 0.1 | AJ38: 0.1 | AK38: 0.1 | AL38: 0.1 | AM38: 0.1 | AN38: 0.1 | AO38: 0.1 | AP38: 0.1 | AQ38: 0.1 | AR38: 0.1 | AS38: 0.1 | AT38: 0.1 | AU38: 0.1 | AV38: 0.1 | AW38: 0.1 | AX38: 0.1 | AY38: 0.1 | AZ38: 0.1 | BA38: 0.1 | BB38: 0.1 | BC38: 0.1 | BD38: 0.1 | BE38: 0.1 | BF38: 0.1 | BG38: 0.1 | BH38: 0.1 | BI38: 0.1 | BJ38: 0.1 | BK38: 0.1 | BL38: =AVERAGE(D38:O38) -> 0.43333333 | BM38: =AVERAGE(P38:AA38) -> 0.1 | BN38: =AVERAGE(AB38:AM38) -> 0.1 | BO38: =AVERAGE(AN38:AY38) -> 0.1 | BP38: =AVERAGE(AZ38:BK38) -> 0.1
A39: DevOps | B39: =E13 -> 236720 | C39: FTE | D39: 0.1 | E39: 0.1 | F39: 0.1 | G39: 0.1 | H39: 0.5 | I39: 0.5 | J39: 0.5 | K39: 0.2 | L39: 0.2 | M39: 0.2 | N39: 0.2 | O39: 0.2 | P39: 0.1 | Q39: 0.1 | R39: 0.1 | S39: 0.1 | T39: 0.1 | U39: 0.1 | V39: 0.1 | W39: 0.1 | X39: 0.1 | Y39: 0.1 | Z39: 0.1 | AA39: 0.1 | AB39: 0.1 | AC39: 0.1 | AD39: 0.1 | AE39: 0.1 | AF39: 0.1 | AG39: 0.1 | AH39: 0.1 | AI39: 0.1 | AJ39: 0.1 | AK39: 0.1 | AL39: 0.1 | AM39: 0.1 | AN39: 0.1 | AO39: 0.1 | AP39: 0.1 | AQ39: 0.1 | AR39: 0.1 | AS39: 0.1 | AT39: 0.1 | AU39: 0.1 | AV39: 0.1 | AW39: 0.1 | AX39: 0.1 | AY39: 0.1 | AZ39: 0.1 | BA39: 0.1 | BB39: 0.1 | BC39: 0.1 | BD39: 0.1 | BE39: 0.1 | BF39: 0.1 | BG39: 0.1 | BH39: 0.1 | BI39: 0.1 | BJ39: 0.1 | BK39: 0.1 | BL39: =AVERAGE(D39:O39) -> 0.24166667 | BM39: =AVERAGE(P39:AA39) -> 0.1 | BN39: =AVERAGE(AB39:AM39) -> 0.1 | BO39: =AVERAGE(AN39:AY39) -> 0.1 | BP39: =AVERAGE(AZ39:BK39) -> 0.1
A40: Σ FTE команды | D40: =SUM(D32:D39) -> 4.9 | E40: =SUM(E32:E39) -> 4.9 | F40: =SUM(F32:F39) -> 5.1 | G40: =SUM(G32:G39) -> 5.1 | H40: =SUM(H32:H39) -> 6.9 | I40: =SUM(I32:I39) -> 6.5 | J40: =SUM(J32:J39) -> 6.5 | K40: =SUM(K32:K39) -> 2.5 | ... BK40: =SUM(BK32:BK39) -> 1.1 | BL40: =AVERAGE(D40:O40) -> 4.3666667 | BM40: =AVERAGE(P40:AA40) -> 1.1 | BN40: =AVERAGE(AB40:AM40) -> 1.1 | BO40: =AVERAGE(AN40:AY40) -> 1.1 | BP40: =AVERAGE(AZ40:BK40) -> 1.1
A42: 4. Стоимость персонала (₽, с налогами и индексацией ЗП 7% г/г)
A43: Индексация ЗП (×) | B43: 0.07 | C43: г/г | D43: =(1+$B$43)^0 -> 1 | E43: =(1+$B$43)^0 -> 1 | F43: =(1+$B$43)^0 -> 1 | G43: =(1+$B$43)^0 -> 1 | H43: =(1+$B$43)^0 -> 1 | I43: =(1+$B$43)^0 -> 1 | J43: =(1+$B$43)^0 -> 1 | K43: =(1+$B$43)^0 -> 1 | ... O43: =(1+$B$43)^0 -> 1 | P43: =(1+$B$43)^1 -> 1.07 | Q43: =(1+$B$43)^1 -> 1.07 | R43: =(1+$B$43)^1 -> 1.07 | S43: =(1+$B$43)^1 -> 1.07 | T43: =(1+$B$43)^1 -> 1.07 | U43: =(1+$B$43)^1 -> 1.07 | V43: =(1+$B$43)^1 -> 1.07 | W43: =(1+$B$43)^1 -> 1.07 | ... AA43: =(1+$B$43)^1 -> 1.07 | AB43: =(1+$B$43)^2 -> 1.1449 | AC43: =(1+$B$43)^2 -> 1.1449 | AD43: =(1+$B$43)^2 -> 1.1449 | AE43: =(1+$B$43)^2 -> 1.1449 | AF43: =(1+$B$43)^2 -> 1.1449 | AG43: =(1+$B$43)^2 -> 1.1449 | AH43: =(1+$B$43)^2 -> 1.1449 | AI43: =(1+$B$43)^2 -> 1.1449 | ... AM43: =(1+$B$43)^2 -> 1.1449 | AN43: =(1+$B$43)^3 -> 1.225043 | AO43: =(1+$B$43)^3 -> 1.225043 | AP43: =(1+$B$43)^3 -> 1.225043 | AQ43: =(1+$B$43)^3 -> 1.225043 | AR43: =(1+$B$43)^3 -> 1.225043 | AS43: =(1+$B$43)^3 -> 1.225043 | AT43: =(1+$B$43)^3 -> 1.225043 | AU43: =(1+$B$43)^3 -> 1.225043 | ... AY43: =(1+$B$43)^3 -> 1.225043 | AZ43: =(1+$B$43)^4 -> 1.310796 | BA43: =(1+$B$43)^4 -> 1.310796 | BB43: =(1+$B$43)^4 -> 1.310796 | BC43: =(1+$B$43)^4 -> 1.310796 | BD43: =(1+$B$43)^4 -> 1.310796 | BE43: =(1+$B$43)^4 -> 1.310796 | BF43: =(1+$B$43)^4 -> 1.310796 | BG43: =(1+$B$43)^4 -> 1.310796 | ... BK43: =(1+$B$43)^4 -> 1.310796
A44: Cost PM, ₽ | D44: =D32*$E6*D43 -> 269000 | E44: =E32*$E6*E43 -> 269000 | F44: =F32*$E6*F43 -> 269000 | G44: =G32*$E6*G43 -> 269000 | H44: =H32*$E6*H43 -> 269000 | I44: =I32*$E6*I43 -> 269000 | J44: =J32*$E6*J43 -> 269000 | K44: =K32*$E6*K43 -> 80700 | ... BK44: =BK32*$E6*BK43 -> 35260.413 | BL44: =SUM(D44:O44) -> 2286500 | BM44: =SUM(P44:AA44) -> 345396 | BN44: =SUM(AB44:AM44) -> 369573.72 | BO44: =SUM(AN44:AY44) -> 395443.88 | BP44: =SUM(AZ44:BK44) -> 423124.95
A45: Cost UX Designer, ₽ | D45: =D33*$E7*D43 -> 96840 | E45: =E33*$E7*E43 -> 96840 | F45: =F33*$E7*F43 -> 0 | G45: =G33*$E7*G43 -> 0 | H45: =H33*$E7*H43 -> 135576 | I45: =I33*$E7*I43 -> 58104 | J45: =J33*$E7*J43 -> 58104 | K45: =K33*$E7*K43 -> 19368 | ... BK45: =BK33*$E7*BK43 -> 0 | BL45: =SUM(D45:O45) -> 542304 | BM45: =SUM(P45:AA45) -> 0 | BN45: =SUM(AB45:AM45) -> 0 | BO45: =SUM(AN45:AY45) -> 0 | BP45: =SUM(AZ45:BK45) -> 0
A46: Cost Data Analyst, ₽ | D46: =D34*$E8*D43 -> 96840 | E46: =E34*$E8*E43 -> 96840 | F46: =F34*$E8*F43 -> 96840 | G46: =G34*$E8*G43 -> 96840 | H46: =H34*$E8*H43 -> 96840 | I46: =I34*$E8*I43 -> 96840 | J46: =J34*$E8*J43 -> 96840 | K46: =K34*$E8*K43 -> 58104 | ... BK46: =BK34*$E8*BK43 -> 50774.994 | BL46: =SUM(D46:O46) -> 968400 | BM46: =SUM(P46:AA46) -> 497370.24 | BN46: =SUM(AB46:AM46) -> 532186.16 | BO46: =SUM(AN46:AY46) -> 569439.19 | BP46: =SUM(AZ46:BK46) -> 609299.93
A47: Cost ML Engineer, ₽ | D47: =D35*$E9*D43 -> 301280 | E47: =E35*$E9*E43 -> 301280 | F47: =F35*$E9*F43 -> 150640 | G47: =G35*$E9*G43 -> 150640 | H47: =H35*$E9*H43 -> 150640 | I47: =I35*$E9*I43 -> 150640 | J47: =J35*$E9*J43 -> 150640 | K47: =K35*$E9*K43 -> 90384 | ... BK47: =BK35*$E9*BK43 -> 78983.324 | BL47: =SUM(D47:O47) -> 1807680 | BM47: =SUM(P47:AA47) -> 773687.04 | BN47: =SUM(AB47:AM47) -> 827845.13 | BO47: =SUM(AN47:AY47) -> 885794.29 | BP47: =SUM(AZ47:BK47) -> 947799.89
A48: Cost Backend, ₽ | D48: =D36*$E10*D43 -> 269000 | E48: =E36*$E10*E43 -> 269000 | F48: =F36*$E10*F43 -> 403500 | G48: =G36*$E10*G43 -> 403500 | H48: =H36*$E10*H43 -> 403500 | I48: =I36*$E10*I43 -> 403500 | J48: =J36*$E10*J43 -> 403500 | K48: =K36*$E10*K43 -> 134500 | ... BK48: =BK36*$E10*BK43 -> 70520.825 | BL48: =SUM(D48:O48) -> 3228000 | BM48: =SUM(P48:AA48) -> 690792 | BN48: =SUM(AB48:AM48) -> 739147.44 | BO48: =SUM(AN48:AY48) -> 790887.76 | BP48: =SUM(AZ48:BK48) -> 846249.9
A49: Cost Frontend, ₽ | D49: =D37*$E11*D43 -> 107600 | E49: =E37*$E11*E43 -> 107600 | F49: =F37*$E11*F43 -> 215200 | G49: =G37*$E11*G43 -> 215200 | H49: =H37*$E11*H43 -> 322800 | I49: =I37*$E11*I43 -> 322800 | J49: =J37*$E11*J43 -> 322800 | K49: =K37*$E11*K43 -> 107600 | ... BK49: =BK37*$E11*BK43 -> 56416.66 | BL49: =SUM(D49:O49) -> 2152000 | BM49: =SUM(P49:AA49) -> 552633.6 | BN49: =SUM(AB49:AM49) -> 591317.95 | BO49: =SUM(AN49:AY49) -> 632710.21 | BP49: =SUM(AZ49:BK49) -> 676999.92
A50: Cost QA, ₽ | D50: =D38*$E12*D43 -> 48420 | E50: =E38*$E12*E43 -> 48420 | F50: =F38*$E12*F43 -> 80700 | G50: =G38*$E12*G43 -> 80700 | H50: =H38*$E12*H43 -> 112980 | I50: =I38*$E12*I43 -> 112980 | J50: =J38*$E12*J43 -> 112980 | K50: =K38*$E12*K43 -> 48420 | ... BK50: =BK38*$E12*BK43 -> 21156.248 | BL50: =SUM(D50:O50) -> 839280 | BM50: =SUM(P50:AA50) -> 207237.6 | BN50: =SUM(AB50:AM50) -> 221744.23 | BO50: =SUM(AN50:AY50) -> 237266.33 | BP50: =SUM(AZ50:BK50) -> 253874.97
A51: Cost DevOps, ₽ | D51: =D39*$E13*D43 -> 23672 | E51: =E39*$E13*E43 -> 23672 | F51: =F39*$E13*F43 -> 23672 | G51: =G39*$E13*G43 -> 23672 | H51: =H39*$E13*H43 -> 118360 | I51: =I39*$E13*I43 -> 118360 | J51: =J39*$E13*J43 -> 118360 | K51: =K39*$E13*K43 -> 47344 | ... BK51: =BK39*$E13*BK43 -> 31029.163 | BL51: =SUM(D51:O51) -> 686488 | BM51: =SUM(P51:AA51) -> 303948.48 | BN51: =SUM(AB51:AM51) -> 325224.87 | BO51: =SUM(AN51:AY51) -> 347990.61 | BP51: =SUM(AZ51:BK51) -> 372349.96
A52: Σ Staff Cost, ₽/мес | D52: =SUM(D44:D51) -> 1212652 | E52: =SUM(E44:E51) -> 1212652 | F52: =SUM(F44:F51) -> 1239552 | G52: =SUM(G44:G51) -> 1239552 | H52: =SUM(H44:H51) -> 1609696 | I52: =SUM(I44:I51) -> 1532224 | J52: =SUM(J44:J51) -> 1532224 | K52: =SUM(K44:K51) -> 586420 | ... BK52: =SUM(BK44:BK51) -> 344141.63 | BL52: =SUM(D52:O52) -> 12510652 | BM52: =SUM(P52:AA52) -> 3371065 | BN52: =SUM(AB52:AM52) -> 3607039.5 | BO52: =SUM(AN52:AY52) -> 3859532.3 | BP52: =SUM(AZ52:BK52) -> 4129699.5
A53: Σ Staff Cost, млн ₽/мес | D53: =D52/1000000 -> 1.212652 | E53: =E52/1000000 -> 1.212652 | F53: =F52/1000000 -> 1.239552 | G53: =G52/1000000 -> 1.239552 | H53: =H52/1000000 -> 1.609696 | I53: =I52/1000000 -> 1.532224 | J53: =J52/1000000 -> 1.532224 | K53: =K52/1000000 -> 0.58642 | ... BP53: =BP52/1000000 -> 4.1296995

Sheet CashFlow
A1: CashFlow прямым методом - Increment (наша инициатива)
A2: Прямой метод: суммируем фактические денежные потоки (поступления − выплаты) по месяцам. Все суммы в млн ₽. AR=0 дней (платежи приходят сразу), AP=60 дней (платим поставщикам с задержкой).
A4: Параметры
A5: AR delay (мес) | B5: 0
A6: AP delay (мес) | B6: 2
A7: Tax payment delay (мес, после конца квартала) | B7: 1
A8: Reference: PnL!Income Tax row | B8: =12 -> 12
A9: Reference: PnL!НДС row | B9: =13 -> 13
A11: Параметр | B11: Ед. | D11: 2026 | E11: 2026 | F11: 2026 | G11: 2026 | H11: 2026 | I11: 2026 | J11: 2026 | K11: 2026 | L11: 2026 | M11: 2026 | N11: 2026 | O11: 2026 | P11: 2027 | Q11: 2027 | R11: 2027 | S11: 2027 | T11: 2027 | U11: 2027 | V11: 2027 | W11: 2027 | X11: 2027 | Y11: 2027 | Z11: 2027 | AA11: 2027 | AB11: 2028 | AC11: 2028 | AD11: 2028 | AE11: 2028 | AF11: 2028 | AG11: 2028 | AH11: 2028 | AI11: 2028 | AJ11: 2028 | AK11: 2028 | AL11: 2028 | AM11: 2028 | AN11: 2029 | AO11: 2029 | AP11: 2029 | AQ11: 2029 | AR11: 2029 | AS11: 2029 | AT11: 2029 | AU11: 2029 | AV11: 2029 | AW11: 2029 | AX11: 2029 | AY11: 2029 | AZ11: 2030 | BA11: 2030 | BB11: 2030 | BC11: 2030 | BD11: 2030 | BE11: 2030 | BF11: 2030 | BG11: 2030 | BH11: 2030 | BI11: 2030 | BJ11: 2030 | BK11: 2030 | BL11: 2026 Total | BM11: 2027 Total | BN11: 2028 Total | BO11: 2029 Total | BP11: 2030 Total
D12: Jan | E12: Feb | F12: Mar | G12: Apr | H12: May | I12: Jun | J12: Jul | K12: Aug | L12: Sep | M12: Oct | N12: Nov | O12: Dec | P12: Jan | Q12: Feb | R12: Mar | S12: Apr | T12: May | U12: Jun | V12: Jul | W12: Aug | X12: Sep | Y12: Oct | Z12: Nov | AA12: Dec | AB12: Jan | AC12: Feb | AD12: Mar | AE12: Apr | AF12: May | AG12: Jun | AH12: Jul | AI12: Aug | AJ12: Sep | AK12: Oct | AL12: Nov | AM12: Dec | AN12: Jan | AO12: Feb | AP12: Mar | AQ12: Apr | AR12: May | AS12: Jun | AT12: Jul | AU12: Aug | AV12: Sep | AW12: Oct | AX12: Nov | AY12: Dec | AZ12: Jan | BA12: Feb | BB12: Mar | BC12: Apr | BD12: May | BE12: Jun | BF12: Jul | BG12: Aug | BH12: Sep | BI12: Oct | BJ12: Nov | BK12: Dec
A14: ПОСТУПЛЕНИЯ (Increment)
A15: Revenue Increment (без НДС) | B15: млн ₽ | D15: =PnL!D39 -> 0 | E15: =PnL!E39 -> 0 | F15: =PnL!F39 -> 0.15844522 | G15: =PnL!G39 -> 0.27819143 | H15: =PnL!H39 -> 0.49853749 | I15: =PnL!I39 -> 0.74955597 | J15: =PnL!J39 -> 1.0177593 | K15: =PnL!K39 -> 1.3382381 | ... BK15: =PnL!BK39 -> 3.4122621 | BL15: =SUM(D15:O15) -> 12.39892 | BM15: =SUM(P15:AA15) -> 29.299167 | BN15: =SUM(AB15:AM15) -> 30.769894 | BO15: =SUM(AN15:AY15) -> 32.000806 | BP15: =SUM(AZ15:BK15) -> 33.280838
A16: НДС начислен с Revenue (исходящий) | B16: млн ₽ | D16: =D15*PnL!D13 -> 0 | E16: =E15*PnL!E13 -> 0 | F16: =F15*PnL!F13 -> 0.031689044 | G16: =G15*PnL!G13 -> 0.055638286 | H16: =H15*PnL!H13 -> 0.099707497 | I16: =I15*PnL!I13 -> 0.14991119 | J16: =J15*PnL!J13 -> 0.20355185 | K16: =K15*PnL!K13 -> 0.26764763 | ... BK16: =BK15*PnL!BK13 -> 0.75069767 | BL16: =SUM(D16:O16) -> 2.479784 | BM16: =SUM(P16:AA16) -> 6.4458167 | BN16: =SUM(AB16:AM16) -> 6.7693766 | BO16: =SUM(AN16:AY16) -> 7.0401773 | BP16: =SUM(AZ16:BK16) -> 7.3217844
A17: Денежные поступления (Revenue × (1+НДС), AR delay=0) | B17: млн ₽ | D17: =D15+D16 -> 0 | E17: =E15+E16 -> 0 | F17: =F15+F16 -> 0.19013427 | G17: =G15+G16 -> 0.33382972 | H17: =H15+H16 -> 0.59824498 | I17: =I15+I16 -> 0.89946716 | J17: =J15+J16 -> 1.2213111 | K17: =K15+K16 -> 1.6058858 | ... BK17: =BK15+BK16 -> 4.1629598 | BL17: =SUM(D17:O17) -> 14.878704 | BM17: =SUM(P17:AA17) -> 35.744983 | BN17: =SUM(AB17:AM17) -> 37.53927 | BO17: =SUM(AN17:AY17) -> 39.040983 | BP17: =SUM(AZ17:BK17) -> 40.602623
A19: ВЫПЛАТЫ (Increment)
A20: Выплаты по CoS (× (1+НДС), AP delay=2 мес) | B20: млн ₽ | D20: 0 | E20: 0 | F20: =-PnL!D40*(1+PnL!D13) -> 0 | G20: =-PnL!E40*(1+PnL!E13) -> 0 | H20: =-PnL!F40*(1+PnL!F13) -> 0.0076053706 | I20: =-PnL!G40*(1+PnL!G13) -> 0.013353189 | J20: =-PnL!H40*(1+PnL!H13) -> 0.023929799 | K20: =-PnL!I40*(1+PnL!I13) -> 0.035978687 | L20: =-PnL!J40*(1+PnL!J13) -> 0.048852445 | M20: =-PnL!K40*(1+PnL!K13) -> 0.06423543 | ... BK20: =-PnL!BI40*(1+PnL!BI13) -> 0.13786121 | BL20: =SUM(D20:O20) -> 0.35650889 | BM20: =SUM(P20:AA20) -> 1.3728772 | BN20: =SUM(AB20:AM20) -> 1.4897234 | BO20: =SUM(AN20:AY20) -> 1.549343 | BP20: =SUM(AZ20:BK20) -> 1.6113167
A21: Выплаты по Staff (без НДС, без задержки) | B21: млн ₽ | D21: =-PnL!D41 -> 1.212652 | E21: =-PnL!E41 -> 1.212652 | F21: =-PnL!F41 -> 1.239552 | G21: =-PnL!G41 -> 1.239552 | H21: =-PnL!H41 -> 1.609696 | I21: =-PnL!I41 -> 1.532224 | J21: =-PnL!J41 -> 1.532224 | K21: =-PnL!K41 -> 0.58642 | ... BK21: =-PnL!BK41 -> 0.34414163 | BL21: =SUM(D21:O21) -> 12.510652 | BM21: =SUM(P21:AA21) -> 3.371065 | BN21: =SUM(AB21:AM21) -> 3.6070395 | BO21: =SUM(AN21:AY21) -> 3.8595323 | BP21: =SUM(AZ21:BK21) -> 4.1296995
A22: Выплаты по Marketing (× (1+НДС), AP delay=2 мес) | B22: млн ₽ | D22: 0 | E22: 0 | F22: =-PnL!D42*(1+PnL!D13) -> 0 | G22: =-PnL!E42*(1+PnL!E13) -> 0 | H22: =-PnL!F42*(1+PnL!F13) -> 0 | I22: =-PnL!G42*(1+PnL!G13) -> 0 | J22: =-PnL!H42*(1+PnL!H13) -> 0 | K22: =-PnL!I42*(1+PnL!I13) -> 0 | L22: =-PnL!J42*(1+PnL!J13) -> 0 | M22: =-PnL!K42*(1+PnL!K13) -> 0.4 | ... BK22: =-PnL!BI42*(1+PnL!BI13) -> 0.305 | BL22: =SUM(D22:O22) -> 1.2 | BM22: =SUM(P22:AA22) -> 4.5616667 | BN22: =SUM(AB22:AM22) -> 3.66 | BO22: =SUM(AN22:AY22) -> 3.66 | BP22: =SUM(AZ22:BK22) -> 3.66
A23: Выплаты по IT (× (1+НДС), AP delay=2 мес) | B23: млн ₽ | D23: 0 | E23: 0 | F23: =-PnL!D44*(1+PnL!D13) -> 0.15 | G23: =-PnL!E44*(1+PnL!E13) -> 0.15 | H23: =-PnL!F44*(1+PnL!F13) -> 0.99 | I23: =-PnL!G44*(1+PnL!G13) -> 0.15 | J23: =-PnL!H44*(1+PnL!H13) -> 0.15 | K23: =-PnL!I44*(1+PnL!I13) -> 0.15 | L23: =-PnL!J44*(1+PnL!J13) -> 0.15 | M23: =-PnL!K44*(1+PnL!K13) -> 0.51 | ... BK23: =-PnL!BI44*(1+PnL!BI13) -> 0.1525 | BL23: =SUM(D23:O23) -> 2.7 | BM23: =SUM(P23:AA23) -> 2.557 | BN23: =SUM(AB23:AM23) -> 1.83 | BO23: =SUM(AN23:AY23) -> 1.83 | BP23: =SUM(AZ23:BK23) -> 1.83
A24: Выплаты по G&A (× (1+НДС), AP delay=2 мес) | B24: млн ₽ | D24: 0 | E24: 0 | F24: =-PnL!D45*(1+PnL!D13) -> 0.07275912 | G24: =-PnL!E45*(1+PnL!E13) -> 0.07275912 | H24: =-PnL!F45*(1+PnL!F13) -> 0.07437312 | I24: =-PnL!G45*(1+PnL!G13) -> 0.07437312 | J24: =-PnL!H45*(1+PnL!H13) -> 0.09658176 | K24: =-PnL!I45*(1+PnL!I13) -> 0.09193344 | L24: =-PnL!J45*(1+PnL!J13) -> 0.09193344 | M24: =-PnL!K45*(1+PnL!K13) -> 0.0351852 | ... BK24: =-PnL!BI45*(1+PnL!BI13) -> 0.020992639 | BL24: =SUM(D24:O24) -> 0.68026872 | BM24: =SUM(P24:AA24) -> 0.24173287 | BN24: =SUM(AB24:AM24) -> 0.21763034 | BO24: =SUM(AN24:AY24) -> 0.23286446 | BP24: =SUM(AZ24:BK24) -> 0.24916497
A25: Уплата налога на прибыль (квартально, с задержкой 1 мес) | B25: млн ₽ | D25: 0 | E25: 0 | F25: 0 | G25: =-(PnL!D49+PnL!E49+PnL!F49) -> 0 | H25: 0 | I25: 0 | J25: =-(PnL!G49+PnL!H49+PnL!I49) -> 0 | K25: 0 | L25: 0 | M25: =-(PnL!J49+PnL!K49+PnL!L49) -> 0.022371303 | N25: 0 | O25: 0 | P25: =-(PnL!M49+PnL!N49+PnL!O49) -> 0.16400707 | Q25: 0 | R25: 0 | S25: =-(PnL!P49+PnL!Q49+PnL!R49) -> 0.13972656 | T25: 0 | U25: 0 | V25: =-(PnL!S49+PnL!T49+PnL!U49) -> 0.24043916 | W25: 0 | X25: 0 | Y25: =-(PnL!V49+PnL!W49+PnL!X49) -> 0.25430207 | Z25: 0 | AA25: 0 | AB25: =-(PnL!Y49+PnL!Z49+PnL!AA49) -> 0.31074464 | AC25: 0 | AD25: 0 | AE25: =-(PnL!AB49+PnL!AC49+PnL!AD49) -> 0.20194204 | AF25: 0 | AG25: 0 | AH25: =-(PnL!AE49+PnL!AF49+PnL!AG49) -> 0.26642437 | AI25: 0 | AJ25: 0 | AK25: =-(PnL!AH49+PnL!AI49+PnL!AJ49) -> 0.27007103 | AL25: 0 | AM25: 0 | AN25: =-(PnL!AK49+PnL!AL49+PnL!AM49) -> 0.32414788 | AO25: 0 | AP25: 0 | AQ25: =-(PnL!AN49+PnL!AO49+PnL!AP49) -> 0.21085405 | AR25: 0 | AS25: 0 | AT25: =-(PnL!AQ49+PnL!AR49+PnL!AS49) -> 0.27791194 | AU25: 0 | AV25: 0 | AW25: =-(PnL!AT49+PnL!AU49+PnL!AV49) -> 0.28170372 | AX25: 0 | AY25: 0 | AZ25: =-(PnL!AW49+PnL!AX49+PnL!AY49) -> 0.33794354 | BA25: 0 | BB25: 0 | BC25: =-(PnL!AZ49+PnL!BA49+PnL!BB49) -> 0.22001852 | BD25: 0 | BE25: 0 | BF25: =-(PnL!BC49+PnL!BD49+PnL!BE49) -> 0.28975873 | BG25: 0 | BH25: 0 | BI25: =-(PnL!BF49+PnL!BG49+PnL!BH49) -> 0.29370217 | BJ25: 0 | BK25: 0 | BL25: =SUM(D25:O25) -> 0.022371303 | BM25: =SUM(P25:AA25) -> 0.79847486 | BN25: =SUM(AB25:AM25) -> 1.0491821 | BO25: =SUM(AN25:AY25) -> 1.0946176 | BP25: =SUM(AZ25:BK25) -> 1.141423
A26: Уплата НДС (NET) в бюджет (квартально) | B26: млн ₽ | D26: 0 | E26: 0 | F26: 0 | G26: 0 | H26: 0 | I26: 0 | J26: 0 | K26: 0 | L26: 0 | M26: 0 | N26: 0 | O26: 0 | P26: 0 | Q26: 0 | R26: 0 | S26: 0 | T26: 0 | U26: 0 | V26: 0 | W26: 0 | X26: 0 | Y26: 0 | Z26: 0 | AA26: 0 | AB26: 0 | AC26: 0 | AD26: 0 | AE26: 0 | AF26: 0 | AG26: 0 | AH26: 0 | AI26: 0 | AJ26: 0 | AK26: 0 | AL26: 0 | AM26: 0 | AN26: 0 | AO26: 0 | AP26: 0 | AQ26: 0 | AR26: 0 | AS26: 0 | AT26: 0 | AU26: 0 | AV26: 0 | AW26: 0 | AX26: 0 | AY26: 0 | AZ26: 0 | BA26: 0 | BB26: 0 | BC26: 0 | BD26: 0 | BE26: 0 | BF26: 0 | BG26: 0 | BH26: 0 | BI26: 0 | BJ26: 0 | BK26: 0 | BL26: =SUM(D26:O26) -> 0 | BM26: =SUM(P26:AA26) -> 0 | BN26: =SUM(AB26:AM26) -> 0 | BO26: =SUM(AN26:AY26) -> 0 | BP26: =SUM(AZ26:BK26) -> 0
A27: Σ Выплаты | B27: млн ₽ | D27: =SUM(D20:D26) -> 1.212652 | E27: =SUM(E20:E26) -> 1.212652 | F27: =SUM(F20:F26) -> 1.4623111 | G27: =SUM(G20:G26) -> 1.4623111 | H27: =SUM(H20:H26) -> 2.6816745 | I27: =SUM(I20:I26) -> 1.7699503 | J27: =SUM(J20:J26) -> 1.8027356 | K27: =SUM(K20:K26) -> 0.86433213 | ... BK27: =SUM(BK20:BK26) -> 0.96049547 | BL27: =SUM(D27:O27) -> 17.469801 | BM27: =SUM(P27:AA27) -> 12.902817 | BN27: =SUM(AB27:AM27) -> 11.853575 | BO27: =SUM(AN27:AY27) -> 12.226357 | BP27: =SUM(AZ27:BK27) -> 12.621604
A29: Operating CashFlow (поступления − выплаты) | B29: млн ₽ | D29: =D17-D27 -> -1.212652 | E29: =E17-E27 -> -1.212652 | F29: =F17-F27 -> -1.2721769 | G29: =G17-G27 -> -1.1284814 | H29: =H17-H27 -> -2.0834295 | I29: =I17-I27 -> -0.87048314 | J29: =J17-J27 -> -0.58142443 | K29: =K17-K27 -> 0.74155364 | ... BK29: =BK17-BK27 -> 3.2024643 | BL29: =SUM(D29:O29) -> -2.5910968 | BM29: =SUM(P29:AA29) -> 22.842167 | BN29: =SUM(AB29:AM29) -> 25.685695 | BO29: =SUM(AN29:AY29) -> 26.814626 | BP29: =SUM(AZ29:BK29) -> 27.981019
A30: Cumulative CashFlow | B30: млн ₽ | D30: =D29 -> -1.212652 | E30: =D30+E29 -> -2.425304 | F30: =E30+F29 -> -3.6974809 | G30: =F30+G29 -> -4.8259623 | H30: =G30+H29 -> -6.9093918 | I30: =H30+I29 -> -7.7798749 | J30: =I30+J29 -> -8.3612993 | K30: =J30+K29 -> -7.6197457 | L30: =K30+L29 -> -6.5950761 | ... BK30: =BJ30+BK29 -> 100.73241 | BL30: =O30 -> -2.5910968 | BM30: =AA30 -> 20.25107 | BN30: =AM30 -> 45.936765 | BO30: =AY30 -> 72.751391 | BP30: =BK30 -> 100.73241
A32: КЛЮЧЕВЫЕ МЕТРИКИ
A33: Negative CF (min Cumulative CF) — пиковая потребность в финансировании | B33: млн ₽ | C33: =MIN(D30:BK30) -> -8.3612993
A34: Payback период (мес от старта до Cum CF >= 0) | B34: мес | C34: =MATCH(TRUE,INDEX(D30:BK30>=0,0),0) -> 15
A35: Cumulative CF к концу 2030 (NPV — без дисконтирования) | B35: млн ₽ | C35: =BK30 -> 100.73241
A36: NPV (Operating CF, дисконтированный WACC=26.3% годовых) | B36: млн ₽ | C36: =NPV((1+PnL!B10)^(1/12)-1,D29:BK29) -> 47.843436

Sheet Cost assumptions
A1: Cost assumptions - допущения по затратам (₽, помесячно за 5 лет)
A2: Все суммы в рублях. Параметры (жёлтый фон) можно менять, формулы (зелёный) пересчитаются автоматически. CoS - переменные затраты на инкрементальные заказы.
A4: 1. Входные параметры
A5: Параметр | B5: Значение | C5: Ед. | D5: Источник / обоснование
A6: Стоимость обработки доставки на заказ (логистика) | B6: 40 | C6: ₽/заказ | D6: Допущение
A7: Стоимость антифрод-проверки объявления | B7: 8 | C7: ₽/объявление | D7: Экспертно, диапазон 5-15 руб/объявление
A8: Доля incremental заказов в категории Животные | B8: 0.02 | C8: % | D8: Гипотеза: фичи дают +2% к транзакциям. Экспертно - линейный эффект от incremental engagement
A9: Доля incremental объявлений | B9: 0.05 | C9: % | D9: Гипотеза: рекомендации привлекают новых селлеров. Экспертно, +5% к объявлениям
A10: Marketing - % от Revenue (baseline AS IS) | B10: 0.05 | C10: % | D10: Бенчмарк marketing/revenue для classifieds. Avito ~5-7% (отчёт KASE Avito Group 2023)
A11: Marketing incremental - год 1 после запуска | B11: 4000000 | C11: ₽/год | D11: Промокампания + in-app коммуникации новых фич. Для Avito с её аудиторией 50M MAU не нужен большой external marketing - раскатка через персонализацию feed
A12: Marketing incremental - годы 2-5 | B12: 3000000 | C12: ₽/год | D12: Поддержка узнаваемости после ramp-up - минимальный бюджет 3 mR/год
A13: IT licenses - baseline направления | B13: 3000000 | C13: ₽/год | D13: Экспертно - стандартный стек ~3 mR/год для команды 30 чел
A14: IT licenses incremental (ML/CDN/storage) | B14: 1500000 | C14: ₽/год | D14: Экспертно
A15: IT оборудование на нового HC (единоразово) | B15: 100000 | C15: ₽/HC | D15: Ноут MacBook Pro/Workstation + лицензии (IDE, Notion). Экспертно - 100 тыс/чел с учетом того что оборудование уже есть, не всегда закупается новое
A16: G&A - % от Staff costs | B16: 0.05 | C16: % | D16: Юридическая поддержка + бухгалтерия + офис. Стандартное соотношение G&A/Staff в tech-компаниях 5-7%
A17: Baseline staff (направление Avito Animals AS IS) | B17: 25 | C17: FTE | D17: Текущая команда: разработка, аналитика, поддержка. Экспертно - 25 FTE для одного направления (среднего размера в Avito)
... A20: Темп индексации ставок ЗП | B20: 0.07 | C20: % г/г | D20: Экспертно
A25: 2. AS IS затраты (baseline направления Avito Животные)
A26: Статья | B26: Ед. | C26: Параметр | D26: 2026 | E26: 2026 | F26: 2026 | G26: 2026 | H26: 2026 | I26: 2026 | J26: 2026 | K26: 2026 | L26: 2026 | M26: 2026 | N26: 2026 | O26: 2026 | P26: 2027 | Q26: 2027 | R26: 2027 | S26: 2027 | T26: 2027 | U26: 2027 | V26: 2027 | W26: 2027 | X26: 2027 | Y26: 2027 | Z26: 2027 | AA26: 2027 | AB26: 2028 | AC26: 2028 | AD26: 2028 | AE26: 2028 | AF26: 2028 | AG26: 2028 | AH26: 2028 | AI26: 2028 | AJ26: 2028 | AK26: 2028 | AL26: 2028 | AM26: 2028 | AN26: 2029 | AO26: 2029 | AP26: 2029 | AQ26: 2029 | AR26: 2029 | AS26: 2029 | AT26: 2029 | AU26: 2029 | AV26: 2029 | AW26: 2029 | AX26: 2029 | AY26: 2029 | AZ26: 2030 | BA26: 2030 | BB26: 2030 | BC26: 2030 | BD26: 2030 | BE26: 2030 | BF26: 2030 | BG26: 2030 | BH26: 2030 | BI26: 2030 | BJ26: 2030 | BK26: 2030 | BL26: 2026 Total | BM26: 2027 Total | BN26: 2028 Total | BO26: 2029 Total | BP26: 2030 Total
D27: Jan | E27: Feb | F27: Mar | G27: Apr | H27: May | I27: Jun | J27: Jul | K27: Aug | L27: Sep | M27: Oct | N27: Nov | O27: Dec | P27: Jan | Q27: Feb | R27: Mar | S27: Apr | T27: May | U27: Jun | V27: Jul | W27: Aug | X27: Sep | Y27: Oct | Z27: Nov | AA27: Dec | AB27: Jan | AC27: Feb | AD27: Mar | AE27: Apr | AF27: May | AG27: Jun | AH27: Jul | AI27: Aug | AJ27: Sep | AK27: Oct | AL27: Nov | AM27: Dec | AN27: Jan | AO27: Feb | AP27: Mar | AQ27: Apr | AR27: May | AS27: Jun | AT27: Jul | AU27: Aug | AV27: Sep | AW27: Oct | AX27: Nov | AY27: Dec | AZ27: Jan | BA27: Feb | BB27: Mar | BC27: Apr | BD27: May | BE27: Jun | BF27: Jul | BG27: Aug | BH27: Sep | BI27: Oct | BJ27: Nov | BK27: Dec
A28: Revenue (AS IS, ссылка на Baseline TOP-down) - справочно | B28: ₽ | D28: ='Baseline TOP-down'!D24*1000 -> 20454545 | E28: ='Baseline TOP-down'!E24*1000 -> 41043017 | F28: ='Baseline TOP-down'!F24*1000 -> 32941905 | G28: ='Baseline TOP-down'!G24*1000 -> 33049748 | H28: ='Baseline TOP-down'!H24*1000 -> 33157944 | I28: ='Baseline TOP-down'!I24*1000 -> 33266495 | J28: ='Baseline TOP-down'!J24*1000 -> 33375400 | K28: ='Baseline TOP-down'!K24*1000 -> 33484663 | ... BK28: ='Baseline TOP-down'!BK24*1000 -> 47625365 | BL28: =SUM(D28:O28) -> 4.0936014e+08 | BM28: =SUM(P28:AA28) -> 4.1294306e+08 | BN28: =SUM(AB28:AM28) -> 4.2946078e+08 | BO28: =SUM(AN28:AY28) -> 4.4663921e+08 | BP28: =SUM(AZ28:BK28) -> 4.6450478e+08
A29: CoS baseline AS IS (% × Revenue) | B29: ₽ | C29: =B19 -> 0.02 | D29: =D28*$B$19 -> 409090.91 | E29: =E28*$B$19 -> 820860.33 | F29: =F28*$B$19 -> 658838.09 | G29: =G28*$B$19 -> 660994.96 | H29: =H28*$B$19 -> 663158.88 | I29: =I28*$B$19 -> 665329.89 | J29: =J28*$B$19 -> 667508.01 | K29: =K28*$B$19 -> 669693.26 | ... BK29: =BK28*$B$19 -> 952507.29 | BL29: =SUM(D29:O29) -> 8187202.9 | BM29: =SUM(P29:AA29) -> 8258861.1 | BN29: =SUM(AB29:AM29) -> 8589215.6 | BO29: =SUM(AN29:AY29) -> 8932784.2 | BP29: =SUM(AZ29:BK29) -> 9290095.6
A30: Staff baseline AS IS (FTE × Salary × индексация) | B30: ₽ | C30: =B17 -> 25 | D30: =$B$17*$B$18*(1+$B$20)^0 -> 7000000 | E30: =$B$17*$B$18*(1+$B$20)^0 -> 7000000 | F30: =$B$17*$B$18*(1+$B$20)^0 -> 7000000 | G30: =$B$17*$B$18*(1+$B$20)^0 -> 7000000 | H30: =$B$17*$B$18*(1+$B$20)^0 -> 7000000 | I30: =$B$17*$B$18*(1+$B$20)^0 -> 7000000 | J30: =$B$17*$B$18*(1+$B$20)^0 -> 7000000 | K30: =$B$17*$B$18*(1+$B$20)^0 -> 7000000 | ... O30: =$B$17*$B$18*(1+$B$20)^0 -> 7000000 | P30: =$B$17*$B$18*(1+$B$20)^1 -> 7490000 | Q30: =$B$17*$B$18*(1+$B$20)^1 -> 7490000 | R30: =$B$17*$B$18*(1+$B$20)^1 -> 7490000 | S30: =$B$17*$B$18*(1+$B$20)^1 -> 7490000 | T30: =$B$17*$B$18*(1+$B$20)^1 -> 7490000 | U30: =$B$17*$B$18*(1+$B$20)^1 -> 7490000 | V30: =$B$17*$B$18*(1+$B$20)^1 -> 7490000 | W30: =$B$17*$B$18*(1+$B$20)^1 -> 7490000 | ... AA30: =$B$17*$B$18*(1+$B$20)^1 -> 7490000 | AB30: =$B$17*$B$18*(1+$B$20)^2 -> 8014300 | AC30: =$B$17*$B$18*(1+$B$20)^2 -> 8014300 | AD30: =$B$17*$B$18*(1+$B$20)^2 -> 8014300 | AE30: =$B$17*$B$18*(1+$B$20)^2 -> 8014300 | AF30: =$B$17*$B$18*(1+$B$20)^2 -> 8014300 | AG30: =$B$17*$B$18*(1+$B$20)^2 -> 8014300 | AH30: =$B$17*$B$18*(1+$B$20)^2 -> 8014300 | AI30: =$B$17*$B$18*(1+$B$20)^2 -> 8014300 | ... AM30: =$B$17*$B$18*(1+$B$20)^2 -> 8014300 | AN30: =$B$17*$B$18*(1+$B$20)^3 -> 8575301 | AO30: =$B$17*$B$18*(1+$B$20)^3 -> 8575301 | AP30: =$B$17*$B$18*(1+$B$20)^3 -> 8575301 | AQ30: =$B$17*$B$18*(1+$B$20)^3 -> 8575301 | AR30: =$B$17*$B$18*(1+$B$20)^3 -> 8575301 | AS30: =$B$17*$B$18*(1+$B$20)^3 -> 8575301 | AT30: =$B$17*$B$18*(1+$B$20)^3 -> 8575301 | AU30: =$B$17*$B$18*(1+$B$20)^3 -> 8575301 | ... AY30: =$B$17*$B$18*(1+$B$20)^3 -> 8575301 | AZ30: =$B$17*$B$18*(1+$B$20)^4 -> 9175572.1 | BA30: =$B$17*$B$18*(1+$B$20)^4 -> 9175572.1 | BB30: =$B$17*$B$18*(1+$B$20)^4 -> 9175572.1 | BC30: =$B$17*$B$18*(1+$B$20)^4 -> 9175572.1 | BD30: =$B$17*$B$18*(1+$B$20)^4 -> 9175572.1 | BE30: =$B$17*$B$18*(1+$B$20)^4 -> 9175572.1 | BF30: =$B$17*$B$18*(1+$B$20)^4 -> 9175572.1 | BG30: =$B$17*$B$18*(1+$B$20)^4 -> 9175572.1 | ... BK30: =$B$17*$B$18*(1+$B$20)^4 -> 9175572.1 | BL30: =SUM(D30:O30) -> 84000000 | BM30: =SUM(P30:AA30) -> 89880000 | BN30: =SUM(AB30:AM30) -> 96171600 | BO30: =SUM(AN30:AY30) -> 102903612 | BP30: =SUM(AZ30:BK30) -> 1.1010686e+08
A31: Marketing baseline AS IS (% × Revenue) | B31: ₽ | C31: =B10 -> 0.05 | D31: =D28*$B$10 -> 1022727.3 | E31: =E28*$B$10 -> 2052150.8 | F31: =F28*$B$10 -> 1647095.2 | G31: =G28*$B$10 -> 1652487.4 | H31: =H28*$B$10 -> 1657897.2 | I31: =I28*$B$10 -> 1663324.7 | J31: =J28*$B$10 -> 1668770 | K31: =K28*$B$10 -> 1674233.1 | ... BK31: =BK28*$B$10 -> 2381268.2 | BL31: =SUM(D31:O31) -> 20468007 | BM31: =SUM(P31:AA31) -> 20647153 | BN31: =SUM(AB31:AM31) -> 21473039 | BO31: =SUM(AN31:AY31) -> 22331960 | BP31: =SUM(AZ31:BK31) -> 23225239
A32: IT baseline AS IS (равномерно по месяцам) | B32: ₽ | C32: =B13 -> 3000000 | D32: =$B$13/12 -> 250000 | E32: =$B$13/12 -> 250000 | F32: =$B$13/12 -> 250000 | G32: =$B$13/12 -> 250000 | H32: =$B$13/12 -> 250000 | I32: =$B$13/12 -> 250000 | J32: =$B$13/12 -> 250000 | K32: =$B$13/12 -> 250000 | ... BK32: =$B$13/12 -> 250000 | BL32: =SUM(D32:O32) -> 3000000 | BM32: =SUM(P32:AA32) -> 3000000 | BN32: =SUM(AB32:AM32) -> 3000000 | BO32: =SUM(AN32:AY32) -> 3000000 | BP32: =SUM(AZ32:BK32) -> 3000000
A33: G&A baseline AS IS (% × Staff baseline) | B33: ₽ | C33: =B16 -> 0.05 | D33: =D30*$B$16 -> 350000 | E33: =E30*$B$16 -> 350000 | F33: =F30*$B$16 -> 350000 | G33: =G30*$B$16 -> 350000 | H33: =H30*$B$16 -> 350000 | I33: =I30*$B$16 -> 350000 | J33: =J30*$B$16 -> 350000 | K33: =K30*$B$16 -> 350000 | ... BK33: =BK30*$B$16 -> 458778.6 | BL33: =SUM(D33:O33) -> 4200000 | BM33: =SUM(P33:AA33) -> 4494000 | BN33: =SUM(AB33:AM33) -> 4808580 | BO33: =SUM(AN33:AY33) -> 5145180.6 | BP33: =SUM(AZ33:BK33) -> 5505343.2
A34: Σ OPEX AS IS (без CoS, до EBITDA) | D34: =SUM(D29:D33) -> 9031818.2 | E34: =SUM(E29:E33) -> 10473011 | F34: =SUM(F29:F33) -> 9905933.3 | G34: =SUM(G29:G33) -> 9913482.3 | H34: =SUM(H29:H33) -> 9921056.1 | I34: =SUM(I29:I33) -> 9928654.6 | J34: =SUM(J29:J33) -> 9936278 | K34: =SUM(K29:K33) -> 9943926.4 | ... BK34: =SUM(BK29:BK33) -> 13218126 | BL34: =SUM(D34:O34) -> 1.1985521e+08 | BM34: =SUM(P34:AA34) -> 1.2628001e+08 | BN34: =SUM(AB34:AM34) -> 1.3404243e+08 | BO34: =SUM(AN34:AY34) -> 1.4231354e+08 | BP34: =SUM(AZ34:BK34) -> 1.5112754e+08
A36: 3. Increment затраты (от нашей инициативы: 3 волны)
A37: Статья - Revenue INCR = 0 в мес 1-7 (период Discovery+Dev Wave 1, до Launch в мес 8). | B37: Ед. | C37: Параметр | D37: 2026 | E37: 2026 | F37: 2026 | G37: 2026 | H37: 2026 | I37: 2026 | J37: 2026 | K37: 2026 | L37: 2026 | M37: 2026 | N37: 2026 | O37: 2026 | P37: 2027 | Q37: 2027 | R37: 2027 | S37: 2027 | T37: 2027 | U37: 2027 | V37: 2027 | W37: 2027 | X37: 2027 | Y37: 2027 | Z37: 2027 | AA37: 2027 | AB37: 2028 | AC37: 2028 | AD37: 2028 | AE37: 2028 | AF37: 2028 | AG37: 2028 | AH37: 2028 | AI37: 2028 | AJ37: 2028 | AK37: 2028 | AL37: 2028 | AM37: 2028 | AN37: 2029 | AO37: 2029 | AP37: 2029 | AQ37: 2029 | AR37: 2029 | AS37: 2029 | AT37: 2029 | AU37: 2029 | AV37: 2029 | AW37: 2029 | AX37: 2029 | AY37: 2029 | AZ37: 2030 | BA37: 2030 | BB37: 2030 | BC37: 2030 | BD37: 2030 | BE37: 2030 | BF37: 2030 | BG37: 2030 | BH37: 2030 | BI37: 2030 | BJ37: 2030 | BK37: 2030 | BL37: 2026 Total | BM37: 2027 Total | BN37: 2028 Total | BO37: 2029 Total | BP37: 2030 Total
D38: Jan | E38: Feb | F38: Mar | G38: Apr | H38: May | I38: Jun | J38: Jul | K38: Aug | L38: Sep | M38: Oct | N38: Nov | O38: Dec | P38: Jan | Q38: Feb | R38: Mar | S38: Apr | T38: May | U38: Jun | V38: Jul | W38: Aug | X38: Sep | Y38: Oct | Z38: Nov | AA38: Dec | AB38: Jan | AC38: Feb | AD38: Mar | AE38: Apr | AF38: May | AG38: Jun | AH38: Jul | AI38: Aug | AJ38: Sep | AK38: Oct | AL38: Nov | AM38: Dec | AN38: Jan | AO38: Feb | AP38: Mar | AQ38: Apr | AR38: May | AS38: Jun | AT38: Jul | AU38: Aug | AV38: Sep | AW38: Oct | AX38: Nov | AY38: Dec | AZ38: Jan | BA38: Feb | BB38: Mar | BC38: Apr | BD38: May | BE38: Jun | BF38: Jul | BG38: Aug | BH38: Sep | BI38: Oct | BJ38: Nov | BK38: Dec
A39: Revenue incremental (ссылка на Baseline TOP-down R58) - справочно | B39: ₽ | D39: =D28*(MIN((IF(1<'Параметры волн'!$B$12,0,'Параметры волн'!$B$5*'Параметры волн'!$B$11*'Параметры волн'!$B$8/(1+EXP(-(1-'Параметры волн'!$B$12-'Параметры волн'!$B$15)/'Параметры волн'!$B$16))))+(IF(1<'Параметры волн'!$B$13,0,'Параметры волн'!$B$6*'Параметры волн'!$B$11*'Параметры волн'!$B$9/(1+EXP(-(1-'Параметры волн'!$B$13-'Параметры волн'!$B$15)/'Параметры волн'!$B$16))))+(IF(1<'Параметры волн'!$B$14,0,'Параметры волн'!$B$7*'Параметры волн'!$B$10/(1+EXP(-(1-'Параметры волн'!$B$14-'Параметры волн'!$B$15)/'Параметры волн'!$B$16)))),'Параметры волн'!$B$17)) -> 0 | E39: =E28*(MIN((IF(2<'Параметры волн'!$B$12,0,'Параметры волн'!$B$5*'Параметры волн'!$B$11*'Параметры волн'!$B$8/(1+EXP(-(2-'Параметры волн'!$B$12-'Параметры волн'!$B$15)/'Параметры волн'!$B$16))))+(IF(2<'Параметры волн'!$B$13,0,'Параметры волн'!$B$6*'Параметры волн'!$B$11*'Параметры волн'!$B$9/(1+EXP(-(2-'Параметры волн'!$B$13-'Параметры волн'!$B$15)/'Параметры волн'!$B$16))))+(IF(2<'Параметры волн'!$B$14,0,'Параметры волн'!$B$7*'Параметры волн'!$B$10/(1+EXP(-(2-'Параметры волн'!$B$14-'Параметры волн'!$B$15)/'Параметры волн'!$B$16)))),'Параметры волн'!$B$17)) -> 0 | F39: =F28*(MIN((IF(3<'Параметры волн'!$B$12,0,'Параметры волн'!$B$5*'Параметры волн'!$B$11*'Параметры волн'!$B$8/(1+EXP(-(3-'Параметры волн'!$B$12-'Параметры волн'!$B$15)/'Параметры волн'!$B$16))))+(IF(3<'Параметры волн'!$B$13,0,'Параметры волн'!$B$6*'Параметры волн'!$B$11*'Параметры волн'!$B$9/(1+EXP(-(3-'Параметры волн'!$B$13-'Параметры волн'!$B$15)/'Параметры волн'!$B$16))))+(IF(3<'Параметры волн'!$B$14,0,'Параметры волн'!$B$7*'Параметры волн'!$B$10/(1+EXP(-(3-'Параметры волн'!$B$14-'Параметры волн'!$B$15)/'Параметры волн'!$B$16)))),'Параметры волн'!$B$17)) -> 158445.22 | G39: =G28*(MIN((IF(4<'Параметры волн'!$B$12,0,'Параметры волн'!$B$5*'Параметры волн'!$B$11*'Параметры волн'!$B$8/(1+EXP(-(4-'Параметры волн'!$B$12-'Параметры волн'!$B$15)/'Параметры волн'!$B$16))))+(IF(4<'Параметры волн'!$B$13,0,'Параметры волн'!$B$6*'Параметры волн'!$B$11*'Параметры волн'!$B$9/(1+EXP(-(4-'Параметры волн'!$B$13-'Параметры волн'!$B$15)/'Параметры волн'!$B$16))))+(IF(4<'Параметры волн'!$B$14,0,'Параметры волн'!$B$7*'Параметры волн'!$B$10/(1+EXP(-(4-'Параметры волн'!$B$14-'Параметры волн'!$B$15)/'Параметры волн'!$B$16)))),'Параметры волн'!$B$17)) -> 278191.43 | H39: =H28*(MIN((IF(5<'Параметры волн'!$B$12,0,'Параметры волн'!$B$5*'Параметры волн'!$B$11*'Параметры волн'!$B$8/(1+EXP(-(5-'Параметры волн'!$B$12-'Параметры волн'!$B$15)/'Параметры волн'!$B$16))))+(IF(5<'Параметры волн'!$B$13,0,'Параметры волн'!$B$6*'Параметры волн'!$B$11*'Параметры волн'!$B$9/(1+EXP(-(5-'Параметры волн'!$B$13-'Параметры волн'!$B$15)/'Параметры волн'!$B$16))))+(IF(5<'Параметры волн'!$B$14,0,'Параметры волн'!$B$7*'Параметры волн'!$B$10/(1+EXP(-(5-'Параметры волн'!$B$14-'Параметры волн'!$B$15)/'Параметры волн'!$B$16)))),'Параметры волн'!$B$17)) -> 498537.49 | I39: =I28*(MIN((IF(6<'Параметры волн'!$B$12,0,'Параметры волн'!$B$5*'Параметры волн'!$B$11*'Параметры волн'!$B$8/(1+EXP(-(6-'Параметры волн'!$B$12-'Параметры волн'!$B$15)/'Параметры волн'!$B$16))))+(IF(6<'Параметры волн'!$B$13,0,'Параметры волн'!$B$6*'Параметры волн'!$B$11*'Параметры волн'!$B$9/(1+EXP(-(6-'Параметры волн'!$B$13-'Параметры волн'!$B$15)/'Параметры волн'!$B$16))))+(IF(6<'Параметры волн'!$B$14,0,'Параметры волн'!$B$7*'Параметры волн'!$B$10/(1+EXP(-(6-'Параметры волн'!$B$14-'Параметры волн'!$B$15)/'Параметры волн'!$B$16)))),'Параметры волн'!$B$17)) -> 749555.97 | J39: =J28*(MIN((IF(7<'Параметры волн'!$B$12,0,'Параметры волн'!$B$5*'Параметры волн'!$B$11*'Параметры волн'!$B$8/(1+EXP(-(7-'Параметры волн'!$B$12-'Параметры волн'!$B$15)/'Параметры волн'!$B$16))))+(IF(7<'Параметры волн'!$B$13,0,'Параметры волн'!$B$6*'Параметры волн'!$B$11*'Параметры волн'!$B$9/(1+EXP(-(7-'Параметры волн'!$B$13-'Параметры волн'!$B$15)/'Параметры волн'!$B$16))))+(IF(7<'Параметры волн'!$B$14,0,'Параметры волн'!$B$7*'Параметры волн'!$B$10/(1+EXP(-(7-'Параметры волн'!$B$14-'Параметры волн'!$B$15)/'Параметры волн'!$B$16)))),'Параметры волн'!$B$17)) -> 1017759.3 | K39: =K28*(MIN((IF(8<'Параметры волн'!$B$12,0,'Параметры волн'!$B$5*'Параметры волн'!$B$11*'Параметры волн'!$B$8/(1+EXP(-(8-'Параметры волн'!$B$12-'Параметры волн'!$B$15)/'Параметры волн'!$B$16))))+(IF(8<'Параметры волн'!$B$13,0,'Параметры волн'!$B$6*'Параметры волн'!$B$11*'Параметры волн'!$B$9/(1+EXP(-(8-'Параметры волн'!$B$13-'Параметры волн'!$B$15)/'Параметры волн'!$B$16))))+(IF(8<'Параметры волн'!$B$14,0,'Параметры волн'!$B$7*'Параметры волн'!$B$10/(1+EXP(-(8-'Параметры волн'!$B$14-'Параметры волн'!$B$15)/'Параметры волн'!$B$16)))),'Параметры волн'!$B$17)) -> 1338238.1 | L39: =L28*(MIN((IF(9<'Параметры волн'!$B$12,0,'Параметры волн'!$B$5*'Параметры волн'!$B$11*'Параметры волн'!$B$8/(1+EXP(-(9-'Параметры волн'!$B$12-'Параметры волн'!$B$15)/'Параметры волн'!$B$16))))+(IF(9<'Параметры волн'!$B$13,0,'Параметры волн'!$B$6*'Параметры волн'!$B$11*'Параметры волн'!$B$9/(1+EXP(-(9-'Параметры волн'!$B$13-'Параметры волн'!$B$15)/'Параметры волн'!$B$16))))+(IF(9<'Параметры волн'!$B$14,0,'Параметры волн'!$B$7*'Параметры волн'!$B$10/(1+EXP(-(9-'Параметры волн'!$B$14-'Параметры волн'!$B$15)/'Параметры волн'!$B$16)))),'Параметры волн'!$B$17)) -> 1584896.2 | M39: =M28*(MIN((IF(10<'Параметры волн'!$B$12,0,'Параметры волн'!$B$5*'Параметры волн'!$B$11*'Параметры волн'!$B$8/(1+EXP(-(10-'Параметры волн'!$B$12-'Параметры волн'!$B$15)/'Параметры волн'!$B$16))))+(IF(10<'Параметры волн'!$B$13,0,'Параметры волн'!$B$6*'Параметры волн'!$B$11*'Параметры волн'!$B$9/(1+EXP(-(10-'Параметры волн'!$B$13-'Параметры волн'!$B$15)/'Параметры волн'!$B$16))))+(IF(10<'Параметры волн'!$B$14,0,'Параметры волн'!$B$7*'Параметры волн'!$B$10/(1+EXP(-(10-'Параметры волн'!$B$14-'Параметры волн'!$B$15)/'Параметры волн'!$B$16)))),'Параметры волн'!$B$17)) -> 1801644.7 | N39: =N28*(MIN((IF(11<'Параметры волн'!$B$12,0,'Параметры волн'!$B$5*'Параметры волн'!$B$11*'Параметры волн'!$B$8/(1+EXP(-(11-'Параметры волн'!$B$12-'Параметры волн'!$B$15)/'Параметры волн'!$B$16))))+(IF(11<'Параметры волн'!$B$13,0,'Параметры волн'!$B$6*'Параметры волн'!$B$11*'Параметры волн'!$B$9/(1+EXP(-(11-'Параметры волн'!$B$13-'Параметры волн'!$B$15)/'Параметры волн'!$B$16))))+(IF(11<'Параметры волн'!$B$14,0,'Параметры волн'!$B$7*'Параметры волн'!$B$10/(1+EXP(-(11-'Параметры волн'!$B$14-'Параметры волн'!$B$15)/'Параметры волн'!$B$16)))),'Параметры волн'!$B$17)) -> 2390477.8 | O39: =O28*(MIN((IF(12<'Параметры волн'!$B$12,0,'Параметры волн'!$B$5*'Параметры волн'!$B$11*'Параметры волн'!$B$8/(1+EXP(-(12-'Параметры волн'!$B$12-'Параметры волн'!$B$15)/'Параметры волн'!$B$16))))+(IF(12<'Параметры волн'!$B$13,0,'Параметры волн'!$B$6*'Параметры волн'!$B$11*'Параметры волн'!$B$9/(1+EXP(-(12-'Параметры волн'!$B$13-'Параметры волн'!$B$15)/'Параметры волн'!$B$16))))+(IF(12<'Параметры волн'!$B$14,0,'Параметры волн'!$B$7*'Параметры волн'!$B$10/(1+EXP(-(12-'Параметры волн'!$B$14-'Параметры волн'!$B$15)/'Параметры волн'!$B$16)))),'Параметры волн'!$B$17)) -> 2581173.8 | P39: =P28*(MIN((IF(13<'Параметры волн'!$B$12,0,'Параметры волн'!$B$5*'Параметры волн'!$B$11*'Параметры волн'!$B$8/(1+EXP(-(13-'Параметры волн'!$B$12-'Параметры волн'!$B$15)/'Параметры волн'!$B$16))))+(IF(13<'Параметры волн'!$B$13,0,'Параметры волн'!$B$6*'Параметры волн'!$B$11*'Параметры волн'!$B$9/(1+EXP(-(13-'Параметры волн'!$B$13-'Параметры волн'!$B$15)/'Параметры волн'!$B$16))))+(IF(13<'Параметры волн'!$B$14,0,'Параметры волн'!$B$7*'Параметры волн'!$B$10/(1+EXP(-(13-'Параметры волн'!$B$14-'Параметры волн'!$B$15)/'Параметры волн'!$B$16)))),'Параметры волн'!$B$17)) -> 1135296 | Q39: =Q28*(MIN((IF(14<'Параметры волн'!$B$12,0,'Параметры волн'!$B$5*'Параметры волн'!$B$11*'Параметры волн'!$B$8/(1+EXP(-(14-'Параметры волн'!$B$12-'Параметры волн'!$B$15)/'Параметры волн'!$B$16))))+(IF(14<'Параметры волн'!$B$13,0,'Параметры волн'!$B$6*'Параметры волн'!$B$11*'Параметры волн'!$B$9/(1+EXP(-(14-'Параметры волн'!$B$13-'Параметры волн'!$B$15)/'Параметры волн'!$B$16))))+(IF(14<'Параметры волн'!$B$14,0,'Параметры волн'!$B$7*'Параметры волн'!$B$10/(1+EXP(-(14-'Параметры волн'!$B$14-'Параметры волн'!$B$15)/'Параметры волн'!$B$16)))),'Параметры волн'!$B$17)) -> 2351651.1 | R39: =R28*(MIN((IF(15<'Параметры волн'!$B$12,0,'Параметры волн'!$B$5*'Параметры волн'!$B$11*'Параметры волн'!$B$8/(1+EXP(-(15-'Параметры волн'!$B$12-'Параметры волн'!$B$15)/'Параметры волн'!$B$16))))+(IF(15<'Параметры волн'!$B$13,0,'Параметры волн'!$B$6*'Параметры волн'!$B$11*'Параметры волн'!$B$9/(1+EXP(-(15-'Параметры волн'!$B$13-'Параметры волн'!$B$15)/'Параметры волн'!$B$16))))+(IF(15<'Параметры волн'!$B$14,0,'Параметры волн'!$B$7*'Параметры волн'!$B$10/(1+EXP(-(15-'Параметры волн'!$B$14-'Параметры волн'!$B$15)/'Параметры волн'!$B$16)))),'Параметры волн'!$B$17)) -> 2403090.1 | S39: =S28*(MIN((IF(16<'Параметры волн'!$B$12,0,'Параметры волн'!$B$5*'Параметры волн'!$B$11*'Параметры волн'!$B$8/(1+EXP(-(16-'Параметры волн'!$B$12-'Параметры волн'!$B$15)/'Параметры волн'!$B$16))))+(IF(16<'Параметры волн'!$B$13,0,'Параметры волн'!$B$6*'Параметры волн'!$B$11*'Параметры волн'!$B$9/(1+EXP(-(16-'Параметры волн'!$B$13-'Параметры волн'!$B$15)/'Параметры волн'!$B$16))))+(IF(16<'Параметры волн'!$B$14,0,'Параметры волн'!$B$7*'Параметры волн'!$B$10/(1+EXP(-(16-'Параметры волн'!$B$14-'Параметры волн'!$B$15)/'Параметры волн'!$B$16)))),'Параметры волн'!$B$17)) -> 2435358.8 | T39: =T28*(MIN((IF(17<'Параметры волн'!$B$12,0,'Параметры волн'!$B$5*'Параметры волн'!$B$11*'Параметры волн'!$B$8/(1+EXP(-(17-'Параметры волн'!$B$12-'Параметры волн'!$B$15)/'Параметры волн'!$B$16))))+(IF(17<'Параметры волн'!$B$13,0,'Параметры волн'!$B$6*'Параметры волн'!$B$11*'Параметры волн'!$B$9/(1+EXP(-(17-'Параметры волн'!$B$13-'Параметры волн'!$B$15)/'Параметры волн'!$B$16))))+(IF(17<'Параметры волн'!$B$14,0,'Параметры волн'!$B$7*'Параметры волн'!$B$10/(1+EXP(-(17-'Параметры волн'!$B$14-'Параметры волн'!$B$15)/'Параметры волн'!$B$16)))),'Параметры волн'!$B$17)) -> 2456451.7 | U39: =U28*(MIN((IF(18<'Параметры волн'!$B$12,0,'Параметры волн'!$B$5*'Параметры волн'!$B$11*'Параметры волн'!$B$8/(1+EXP(-(18-'Параметры волн'!$B$12-'Параметры волн'!$B$15)/'Параметры волн'!$B$16))))+(IF(18<'Параметры волн'!$B$13,0,'Параметры волн'!$B$6*'Параметры волн'!$B$11*'Параметры волн'!$B$9/(1+EXP(-(18-'Параметры волн'!$B$13-'Параметры волн'!$B$15)/'Параметры волн'!$B$16))))+(IF(18<'Параметры волн'!$B$14,0,'Параметры волн'!$B$7*'Параметры волн'!$B$10/(1+EXP(-(18-'Параметры волн'!$B$14-'Параметры волн'!$B$15)/'Параметры волн'!$B$16)))),'Параметры волн'!$B$17)) -> 2471405.8 | V39: =V28*(MIN((IF(19<'Параметры волн'!$B$12,0,'Параметры волн'!$B$5*'Параметры волн'!$B$11*'Параметры волн'!$B$8/(1+EXP(-(19-'Параметры волн'!$B$12-'Параметры волн'!$B$15)/'Параметры волн'!$B$16))))+(IF(19<'Параметры волн'!$B$13,0,'Параметры волн'!$B$6*'Параметры волн'!$B$11*'Параметры волн'!$B$9/(1+EXP(-(19-'Параметры волн'!$B$13-'Параметры волн'!$B$15)/'Параметры волн'!$B$16))))+(IF(19<'Параметры волн'!$B$14,0,'Параметры волн'!$B$7*'Параметры волн'!$B$10/(1+EXP(-(19-'Параметры волн'!$B$14-'Параметры волн'!$B$15)/'Параметры волн'!$B$16)))),'Параметры волн'!$B$17)) -> 2483099.2 | W39: =W28*(MIN((IF(20<'Параметры волн'!$B$12,0,'Параметры волн'!$B$5*'Параметры волн'!$B$11*'Параметры волн'!$B$8/(1+EXP(-(20-'Параметры волн'!$B$12-'Параметры волн'!$B$15)/'Параметры волн'!$B$16))))+(IF(20<'Параметры волн'!$B$13,0,'Параметры волн'!$B$6*'Параметры волн'!$B$11*'Параметры волн'!$B$9/(1+EXP(-(20-'Параметры волн'!$B$13-'Параметры волн'!$B$15)/'Параметры волн'!$B$16))))+(IF(20<'Параметры волн'!$B$14,0,'Параметры волн'!$B$7*'Параметры волн'!$B$10/(1+EXP(-(20-'Параметры волн'!$B$14-'Параметры волн'!$B$15)/'Параметры волн'!$B$16)))),'Параметры волн'!$B$17)) -> 2493095.2 | X39: =X28*(MIN((IF(21<'Параметры волн'!$B$12,0,'Параметры волн'!$B$5*'Параметры волн'!$B$11*'Параметры волн'!$B$8/(1+EXP(-(21-'Параметры волн'!$B$12-'Параметры волн'!$B$15)/'Параметры волн'!$B$16))))+(IF(21<'Параметры волн'!$B$13,0,'Параметры волн'!$B$6*'Параметры волн'!$B$11*'Параметры волн'!$B$9/(1+EXP(-(21-'Параметры волн'!$B$13-'Параметры волн'!$B$15)/'Параметры волн'!$B$16))))+(IF(21<'Параметры волн'!$B$14,0,'Параметры волн'!$B$7*'Параметры волн'!$B$10/(1+EXP(-(21-'Параметры волн'!$B$14-'Параметры волн'!$B$15)/'Параметры волн'!$B$16)))),'Параметры волн'!$B$17)) -> 2502221.6 | Y39: =Y28*(MIN((IF(22<'Параметры волн'!$B$12,0,'Параметры волн'!$B$5*'Параметры волн'!$B$11*'Параметры волн'!$B$8/(1+EXP(-(22-'Параметры волн'!$B$12-'Параметры волн'!$B$15)/'Параметры волн'!$B$16))))+(IF(22<'Параметры волн'!$B$13,0,'Параметры волн'!$B$6*'Параметры волн'!$B$11*'Параметры волн'!$B$9/(1+EXP(-(22-'Параметры волн'!$B$13-'Параметры волн'!$B$15)/'Параметры волн'!$B$16))))+(IF(22<'Параметры волн'!$B$14,0,'Параметры волн'!$B$7*'Параметры волн'!$B$10/(1+EXP(-(22-'Параметры волн'!$B$14-'Параметры волн'!$B$15)/'Параметры волн'!$B$16)))),'Параметры волн'!$B$17)) -> 2510910.9 | Z39: =Z28*(MIN((IF(23<'Параметры волн'!$B$12,0,'Параметры волн'!$B$5*'Параметры волн'!$B$11*'Параметры волн'!$B$8/(1+EXP(-(23-'Параметры волн'!$B$12-'Параметры волн'!$B$15)/'Параметры волн'!$B$16))))+(IF(23<'Параметры волн'!$B$13,0,'Параметры волн'!$B$6*'Параметры волн'!$B$11*'Параметры волн'!$B$9/(1+EXP(-(23-'Параметры волн'!$B$13-'Параметры волн'!$B$15)/'Параметры волн'!$B$16))))+(IF(23<'Параметры волн'!$B$14,0,'Параметры волн'!$B$7*'Параметры волн'!$B$10/(1+EXP(-(23-'Параметры волн'!$B$14-'Параметры волн'!$B$15)/'Параметры волн'!$B$16)))),'Параметры волн'!$B$17)) -> 3023265.1 | AA39: =AA28*(MIN((IF(24<'Параметры волн'!$B$12,0,'Параметры волн'!$B$5*'Параметры волн'!$B$11*'Параметры волн'!$B$8/(1+EXP(-(24-'Параметры волн'!$B$12-'Параметры волн'!$B$15)/'Параметры волн'!$B$16))))+(IF(24<'Параметры волн'!$B$13,0,'Параметры волн'!$B$6*'Параметры волн'!$B$11*'Параметры волн'!$B$9/(1+EXP(-(24-'Параметры волн'!$B$13-'Параметры волн'!$B$15)/'Параметры волн'!$B$16))))+(IF(24<'Параметры волн'!$B$14,0,'Параметры волн'!$B$7*'Параметры волн'!$B$10/(1+EXP(-(24-'Параметры волн'!$B$14-'Параметры волн'!$B$15)/'Параметры волн'!$B$16)))),'Параметры волн'!$B$17)) -> 3033321.1 | AB39: =AB28*(MIN((IF(25<'Параметры волн'!$B$12,0,'Параметры волн'!$B$5*'Параметры волн'!$B$11*'Параметры волн'!$B$8/(1+EXP(-(25-'Параметры волн'!$B$12-'Параметры волн'!$B$15)/'Параметры волн'!$B$16))))+(IF(25<'Параметры волн'!$B$13,0,'Параметры волн'!$B$6*'Параметры волн'!$B$11*'Параметры волн'!$B$9/(1+EXP(-(25-'Параметры волн'!$B$13-'Параметры волн'!$B$15)/'Параметры волн'!$B$16))))+(IF(25<'Параметры волн'!$B$14,0,'Параметры волн'!$B$7*'Параметры волн'!$B$10/(1+EXP(-(25-'Параметры волн'!$B$14-'Параметры волн'!$B$15)/'Параметры волн'!$B$16)))),'Параметры волн'!$B$17)) -> 1268055.5 | AC39: =AC28*(MIN((IF(26<'Параметры волн'!$B$12,0,'Параметры волн'!$B$5*'Параметры волн'!$B$11*'Параметры волн'!$B$8/(1+EXP(-(26-'Параметры волн'!$B$12-'Параметры волн'!$B$15)/'Параметры волн'!$B$16))))+(IF(26<'Параметры волн'!$B$13,0,'Параметры волн'!$B$6*'Параметры волн'!$B$11*'Параметры волн'!$B$9/(1+EXP(-(26-'Параметры волн'!$B$13-'Параметры волн'!$B$15)/'Параметры волн'!$B$16))))+(IF(26<'Параметры волн'!$B$14,0,'Параметры волн'!$B$7*'Параметры волн'!$B$10/(1+EXP(-(26-'Параметры волн'!$B$14-'Параметры волн'!$B$15)/'Параметры волн'!$B$16)))),'Параметры волн'!$B$17)) -> 2544448.6 | AD39: =AD28*(MIN((IF(27<'Параметры волн'!$B$12,0,'Параметры волн'!$B$5*'Параметры волн'!$B$11*'Параметры волн'!$B$8/(1+EXP(-(27-'Параметры волн'!$B$12-'Параметры волн'!$B$15)/'Параметры волн'!$B$16))))+(IF(27<'Параметры волн'!$B$13,0,'Параметры волн'!$B$6*'Параметры волн'!$B$11*'Параметры волн'!$B$9/(1+EXP(-(27-'Параметры волн'!$B$13-'Параметры волн'!$B$15)/'Параметры волн'!$B$16))))+(IF(27<'Параметры волн'!$B$14,0,'Параметры волн'!$B$7*'Параметры волн'!$B$10/(1+EXP(-(27-'Параметры волн'!$B$14-'Параметры волн'!$B$15)/'Параметры волн'!$B$16)))),'Параметры волн'!$B$17)) -> 2552796.6 | AE39: =AE28*(MIN((IF(28<'Параметры волн'!$B$12,0,'Параметры волн'!$B$5*'Параметры волн'!$B$11*'Параметры волн'!$B$8/(1+EXP(-(28-'Параметры волн'!$B$12-'Параметры волн'!$B$15)/'Параметры волн'!$B$16))))+(IF(28<'Параметры волн'!$B$13,0,'Параметры волн'!$B$6*'Параметры волн'!$B$11*'Параметры волн'!$B$9/(1+EXP(-(28-'Параметры волн'!$B$13-'Параметры волн'!$B$15)/'Параметры волн'!$B$16))))+(IF(28<'Параметры волн'!$B$14,0,'Параметры волн'!$B$7*'Параметры волн'!$B$10/(1+EXP(-(28-'Параметры волн'!$B$14-'Параметры волн'!$B$15)/'Параметры волн'!$B$16)))),'Параметры волн'!$B$17)) -> 2561163.1 | AF39: =AF28*(MIN((IF(29<'Параметры волн'!$B$12,0,'Параметры волн'!$B$5*'Параметры волн'!$B$11*'Параметры волн'!$B$8/(1+EXP(-(29-'Параметры волн'!$B$12-'Параметры волн'!$B$15)/'Параметры волн'!$B$16))))+(IF(29<'Параметры волн'!$B$13,0,'Параметры волн'!$B$6*'Параметры волн'!$B$11*'Параметры волн'!$B$9/(1+EXP(-(29-'Параметры волн'!$B$13-'Параметры волн'!$B$15)/'Параметры волн'!$B$16))))+(IF(29<'Параметры волн'!$B$14,0,'Параметры волн'!$B$7*'Параметры волн'!$B$10/(1+EXP(-(29-'Параметры волн'!$B$14-'Параметры волн'!$B$15)/'Параметры волн'!$B$16)))),'Параметры волн'!$B$17)) -> 2569552.5 | AG39: =AG28*(MIN((IF(30<'Параметры волн'!$B$12,0,'Параметры волн'!$B$5*'Параметры волн'!$B$11*'Параметры волн'!$B$8/(1+EXP(-(30-'Параметры волн'!$B$12-'Параметры волн'!$B$15)/'Параметры волн'!$B$16))))+(IF(30<'Параметры волн'!$B$13,0,'Параметры волн'!$B$6*'Параметры волн'!$B$11*'Параметры волн'!$B$9/(1+EXP(-(30-'Параметры волн'!$B$13-'Параметры волн'!$B$15)/'Параметры волн'!$B$16))))+(IF(30<'Параметры волн'!$B$14,0,'Параметры волн'!$B$7*'Параметры волн'!$B$10/(1+EXP(-(30-'Параметры волн'!$B$14-'Параметры волн'!$B$15)/'Параметры волн'!$B$16)))),'Параметры волн'!$B$17)) -> 2577967 | AH39: =AH28*(MIN((IF(31<'Параметры волн'!$B$12,0,'Параметры волн'!$B$5*'Параметры волн'!$B$11*'Параметры волн'!$B$8/(1+EXP(-(31-'Параметры волн'!$B$12-'Параметры волн'!$B$15)/'Параметры волн'!$B$16))))+(IF(31<'Параметры волн'!$B$13,0,'Параметры волн'!$B$6*'Параметры волн'!$B$11*'Параметры волн'!$B$9/(1+EXP(-(31-'Параметры волн'!$B$13-'Параметры волн'!$B$15)/'Параметры волн'!$B$16))))+(IF(31<'Параметры волн'!$B$14,0,'Параметры волн'!$B$7*'Параметры волн'!$B$10/(1+EXP(-(31-'Параметры волн'!$B$14-'Параметры волн'!$B$15)/'Параметры волн'!$B$16)))),'Параметры волн'!$B$17)) -> 2586407.9 | AI39: =AI28*(MIN((IF(32<'Параметры волн'!$B$12,0,'Параметры волн'!$B$5*'Параметры волн'!$B$11*'Параметры волн'!$B$8/(1+EXP(-(32-'Параметры волн'!$B$12-'Параметры волн'!$B$15)/'Параметры волн'!$B$16))))+(IF(32<'Параметры волн'!$B$13,0,'Параметры волн'!$B$6*'Параметры волн'!$B$11*'Параметры волн'!$B$9/(1+EXP(-(32-'Параметры волн'!$B$13-'Параметры волн'!$B$15)/'Параметры волн'!$B$16))))+(IF(32<'Параметры волн'!$B$14,0,'Параметры волн'!$B$7*'Параметры волн'!$B$10/(1+EXP(-(32-'Параметры волн'!$B$14-'Параметры волн'!$B$15)/'Параметры волн'!$B$16)))),'Параметры волн'!$B$17)) -> 2594875.7 | AJ39: =AJ28*(MIN((IF(33<'Параметры волн'!$B$12,0,'Параметры волн'!$B$5*'Параметры волн'!$B$11*'Параметры волн'!$B$8/(1+EXP(-(33-'Параметры волн'!$B$12-'Параметры волн'!$B$15)/'Параметры волн'!$B$16))))+(IF(33<'Параметры волн'!$B$13,0,'Параметры волн'!$B$6*'Параметры волн'!$B$11*'Параметры волн'!$B$9/(1+EXP(-(33-'Параметры волн'!$B$13-'Параметры волн'!$B$15)/'Параметры волн'!$B$16))))+(IF(33<'Параметры волн'!$B$14,0,'Параметры волн'!$B$7*'Параметры волн'!$B$10/(1+EXP(-(33-'Параметры волн'!$B$14-'Параметры волн'!$B$15)/'Параметры волн'!$B$16)))),'Параметры волн'!$B$17)) -> 2603371 | AK39: =AK28*(MIN((IF(34<'Параметры волн'!$B$12,0,'Параметры волн'!$B$5*'Параметры волн'!$B$11*'Параметры волн'!$B$8/(1+EXP(-(34-'Параметры волн'!$B$12-'Параметры волн'!$B$15)/'Параметры волн'!$B$16))))+(IF(34<'Параметры волн'!$B$13,0,'Параметры волн'!$B$6*'Параметры волн'!$B$11*'Параметры волн'!$B$9/(1+EXP(-(34-'Параметры волн'!$B$13-'Параметры волн'!$B$15)/'Параметры волн'!$B$16))))+(IF(34<'Параметры волн'!$B$14,0,'Параметры волн'!$B$7*'Параметры волн'!$B$10/(1+EXP(-(34-'Параметры волн'!$B$14-'Параметры волн'!$B$15)/'Параметры волн'!$B$16)))),'Параметры волн'!$B$17)) -> 2611894 | AL39: =AL28*(MIN((IF(35<'Параметры волн'!$B$12,0,'Параметры волн'!$B$5*'Параметры волн'!$B$11*'Параметры волн'!$B$8/(1+EXP(-(35-'Параметры волн'!$B$12-'Параметры волн'!$B$15)/'Параметры волн'!$B$16))))+(IF(35<'Параметры волн'!$B$13,0,'Параметры волн'!$B$6*'Параметры волн'!$B$11*'Параметры волн'!$B$9/(1+EXP(-(35-'Параметры волн'!$B$13-'Параметры волн'!$B$15)/'Параметры волн'!$B$16))))+(IF(35<'Параметры волн'!$B$14,0,'Параметры волн'!$B$7*'Параметры волн'!$B$10/(1+EXP(-(35-'Параметры волн'!$B$14-'Параметры волн'!$B$15)/'Параметры волн'!$B$16)))),'Параметры волн'!$B$17)) -> 3144533.6 | AM39: =AM28*(MIN((IF(36<'Параметры волн'!$B$12,0,'Параметры волн'!$B$5*'Параметры волн'!$B$11*'Параметры волн'!$B$8/(1+EXP(-(36-'Параметры волн'!$B$12-'Параметры волн'!$B$15)/'Параметры волн'!$B$16))))+(IF(36<'Параметры волн'!$B$13,0,'Параметры волн'!$B$6*'Параметры волн'!$B$11*'Параметры волн'!$B$9/(1+EXP(-(36-'Параметры волн'!$B$13-'Параметры волн'!$B$15)/'Параметры волн'!$B$16))))+(IF(36<'Параметры волн'!$B$14,0,'Параметры волн'!$B$7*'Параметры волн'!$B$10/(1+EXP(-(36-'Параметры волн'!$B$14-'Параметры волн'!$B$15)/'Параметры волн'!$B$16)))),'Параметры волн'!$B$17)) -> 3154828.1 | AN39: =AN28*(MIN((IF(37<'Параметры волн'!$B$12,0,'Параметры волн'!$B$5*'Параметры волн'!$B$11*'Параметры волн'!$B$8/(1+EXP(-(37-'Параметры волн'!$B$12-'Параметры волн'!$B$15)/'Параметры волн'!$B$16))))+(IF(37<'Параметры волн'!$B$13,0,'Параметры волн'!$B$6*'Параметры волн'!$B$11*'Параметры волн'!$B$9/(1+EXP(-(37-'Параметры волн'!$B$13-'Параметры волн'!$B$15)/'Параметры волн'!$B$16))))+(IF(37<'Параметры волн'!$B$14,0,'Параметры волн'!$B$7*'Параметры волн'!$B$10/(1+EXP(-(37-'Параметры волн'!$B$14-'Параметры волн'!$B$15)/'Параметры волн'!$B$16)))),'Параметры волн'!$B$17)) -> 1318815.1 | AO39: =AO28*(MIN((IF(38<'Параметры волн'!$B$12,0,'Параметры волн'!$B$5*'Параметры волн'!$B$11*'Параметры волн'!$B$8/(1+EXP(-(38-'Параметры волн'!$B$12-'Параметры волн'!$B$15)/'Параметры волн'!$B$16))))+(IF(38<'Параметры волн'!$B$13,0,'Параметры волн'!$B$6*'Параметры волн'!$B$11*'Параметры волн'!$B$9/(1+EXP(-(38-'Параметры волн'!$B$13-'Параметры волн'!$B$15)/'Параметры волн'!$B$16))))+(IF(38<'Параметры волн'!$B$14,0,'Параметры волн'!$B$7*'Параметры волн'!$B$10/(1+EXP(-(38-'Параметры волн'!$B$14-'Параметры волн'!$B$15)/'Параметры волн'!$B$16)))),'Параметры волн'!$B$17)) -> 2646265.1 | AP39: =AP28*(MIN((IF(39<'Параметры волн'!$B$12,0,'Параметры волн'!$B$5*'Параметры волн'!$B$11*'Параметры волн'!$B$8/(1+EXP(-(39-'Параметры волн'!$B$12-'Параметры волн'!$B$15)/'Параметры волн'!$B$16))))+(IF(39<'Параметры волн'!$B$13,0,'Параметры волн'!$B$6*'Параметры волн'!$B$11*'Параметры волн'!$B$9/(1+EXP(-(39-'Параметры волн'!$B$13-'Параметры волн'!$B$15)/'Параметры волн'!$B$16))))+(IF(39<'Параметры волн'!$B$14,0,'Параметры волн'!$B$7*'Параметры волн'!$B$10/(1+EXP(-(39-'Параметры волн'!$B$14-'Параметры волн'!$B$15)/'Параметры волн'!$B$16)))),'Параметры волн'!$B$17)) -> 2654928.3 | AQ39: =AQ28*(MIN((IF(40<'Параметры волн'!$B$12,0,'Параметры волн'!$B$5*'Параметры волн'!$B$11*'Параметры волн'!$B$8/(1+EXP(-(40-'Параметры волн'!$B$12-'Параметры волн'!$B$15)/'Параметры волн'!$B$16))))+(IF(40<'Параметры волн'!$B$13,0,'Параметры волн'!$B$6*'Параметры волн'!$B$11*'Параметры волн'!$B$9/(1+EXP(-(40-'Параметры волн'!$B$13-'Параметры волн'!$B$15)/'Параметры волн'!$B$16))))+(IF(40<'Параметры волн'!$B$14,0,'Параметры волн'!$B$7*'Параметры волн'!$B$10/(1+EXP(-(40-'Параметры волн'!$B$14-'Параметры волн'!$B$15)/'Параметры волн'!$B$16)))),'Параметры волн'!$B$17)) -> 2663619.8 | AR39: =AR28*(MIN((IF(41<'Параметры волн'!$B$12,0,'Параметры волн'!$B$5*'Параметры волн'!$B$11*'Параметры волн'!$B$8/(1+EXP(-(41-'Параметры волн'!$B$12-'Параметры волн'!$B$15)/'Параметры волн'!$B$16))))+(IF(41<'Параметры волн'!$B$13,0,'Параметры волн'!$B$6*'Параметры волн'!$B$11*'Параметры волн'!$B$9/(1+EXP(-(41-'Параметры волн'!$B$13-'Параметры волн'!$B$15)/'Параметры волн'!$B$16))))+(IF(41<'Параметры волн'!$B$14,0,'Параметры волн'!$B$7*'Параметры волн'!$B$10/(1+EXP(-(41-'Параметры волн'!$B$14-'Параметры волн'!$B$15)/'Параметры волн'!$B$16)))),'Параметры волн'!$B$17)) -> 2672339.8 | AS39: =AS28*(MIN((IF(42<'Параметры волн'!$B$12,0,'Параметры волн'!$B$5*'Параметры волн'!$B$11*'Параметры волн'!$B$8/(1+EXP(-(42-'Параметры волн'!$B$12-'Параметры волн'!$B$15)/'Параметры волн'!$B$16))))+(IF(42<'Параметры волн'!$B$13,0,'Параметры волн'!$B$6*'Параметры волн'!$B$11*'Параметры волн'!$B$9/(1+EXP(-(42-'Параметры волн'!$B$13-'Параметры волн'!$B$15)/'Параметры волн'!$B$16))))+(IF(42<'Параметры волн'!$B$14,0,'Параметры волн'!$B$7*'Параметры волн'!$B$10/(1+EXP(-(42-'Параметры волн'!$B$14-'Параметры волн'!$B$15)/'Параметры волн'!$B$16)))),'Параметры волн'!$B$17)) -> 2681088.4 | AT39: =AT28*(MIN((IF(43<'Параметры волн'!$B$12,0,'Параметры волн'!$B$5*'Параметры волн'!$B$11*'Параметры волн'!$B$8/(1+EXP(-(43-'Параметры волн'!$B$12-'Параметры волн'!$B$15)/'Параметры волн'!$B$16))))+(IF(43<'Параметры волн'!$B$13,0,'Параметры волн'!$B$6*'Параметры волн'!$B$11*'Параметры волн'!$B$9/(1+EXP(-(43-'Параметры волн'!$B$13-'Параметры волн'!$B$15)/'Параметры волн'!$B$16))))+(IF(43<'Параметры волн'!$B$14,0,'Параметры волн'!$B$7*'Параметры волн'!$B$10/(1+EXP(-(43-'Параметры волн'!$B$14-'Параметры волн'!$B$15)/'Параметры волн'!$B$16)))),'Параметры волн'!$B$17)) -> 2689865.6 | AU39: =AU28*(MIN((IF(44<'Параметры волн'!$B$12,0,'Параметры волн'!$B$5*'Параметры волн'!$B$11*'Параметры волн'!$B$8/(1+EXP(-(44-'Параметры волн'!$B$12-'Параметры волн'!$B$15)/'Параметры волн'!$B$16))))+(IF(44<'Параметры волн'!$B$13,0,'Параметры волн'!$B$6*'Параметры волн'!$B$11*'Параметры волн'!$B$9/(1+EXP(-(44-'Параметры волн'!$B$13-'Параметры волн'!$B$15)/'Параметры волн'!$B$16))))+(IF(44<'Параметры волн'!$B$14,0,'Параметры волн'!$B$7*'Параметры волн'!$B$10/(1+EXP(-(44-'Параметры волн'!$B$14-'Параметры волн'!$B$15)/'Параметры волн'!$B$16)))),'Параметры волн'!$B$17)) -> 2698671.5 | AV39: =AV28*(MIN((IF(45<'Параметры волн'!$B$12,0,'Параметры волн'!$B$5*'Параметры волн'!$B$11*'Параметры волн'!$B$8/(1+EXP(-(45-'Параметры волн'!$B$12-'Параметры волн'!$B$15)/'Параметры волн'!$B$16))))+(IF(45<'Параметры волн'!$B$13,0,'Параметры волн'!$B$6*'Параметры волн'!$B$11*'Параметры волн'!$B$9/(1+EXP(-(45-'Параметры волн'!$B$13-'Параметры волн'!$B$15)/'Параметры волн'!$B$16))))+(IF(45<'Параметры волн'!$B$14,0,'Параметры волн'!$B$7*'Параметры волн'!$B$10/(1+EXP(-(45-'Параметры волн'!$B$14-'Параметры волн'!$B$15)/'Параметры волн'!$B$16)))),'Параметры волн'!$B$17)) -> 2707506.2 | AW39: =AW28*(MIN((IF(46<'Параметры волн'!$B$12,0,'Параметры волн'!$B$5*'Параметры волн'!$B$11*'Параметры волн'!$B$8/(1+EXP(-(46-'Параметры волн'!$B$12-'Параметры волн'!$B$15)/'Параметры волн'!$B$16))))+(IF(46<'Параметры волн'!$B$13,0,'Параметры волн'!$B$6*'Параметры волн'!$B$11*'Параметры волн'!$B$9/(1+EXP(-(46-'Параметры волн'!$B$13-'Параметры волн'!$B$15)/'Параметры волн'!$B$16))))+(IF(46<'Параметры волн'!$B$14,0,'Параметры волн'!$B$7*'Параметры волн'!$B$10/(1+EXP(-(46-'Параметры волн'!$B$14-'Параметры волн'!$B$15)/'Параметры волн'!$B$16)))),'Параметры волн'!$B$17)) -> 2716369.9 | AX39: =AX28*(MIN((IF(47<'Параметры волн'!$B$12,0,'Параметры волн'!$B$5*'Параметры волн'!$B$11*'Параметры волн'!$B$8/(1+EXP(-(47-'Параметры волн'!$B$12-'Параметры волн'!$B$15)/'Параметры волн'!$B$16))))+(IF(47<'Параметры волн'!$B$13,0,'Параметры волн'!$B$6*'Параметры волн'!$B$11*'Параметры волн'!$B$9/(1+EXP(-(47-'Параметры волн'!$B$13-'Параметры волн'!$B$15)/'Параметры волн'!$B$16))))+(IF(47<'Параметры волн'!$B$14,0,'Параметры волн'!$B$7*'Параметры волн'!$B$10/(1+EXP(-(47-'Параметры волн'!$B$14-'Параметры волн'!$B$15)/'Параметры волн'!$B$16)))),'Параметры волн'!$B$17)) -> 3270315.1 | AY39: =AY28*(MIN((IF(48<'Параметры волн'!$B$12,0,'Параметры волн'!$B$5*'Параметры волн'!$B$11*'Параметры волн'!$B$8/(1+EXP(-(48-'Параметры волн'!$B$12-'Параметры волн'!$B$15)/'Параметры волн'!$B$16))))+(IF(48<'Параметры волн'!$B$13,0,'Параметры волн'!$B$6*'Параметры волн'!$B$11*'Параметры волн'!$B$9/(1+EXP(-(48-'Параметры волн'!$B$13-'Параметры волн'!$B$15)/'Параметры волн'!$B$16))))+(IF(48<'Параметры волн'!$B$14,0,'Параметры волн'!$B$7*'Параметры волн'!$B$10/(1+EXP(-(48-'Параметры волн'!$B$14-'Параметры волн'!$B$15)/'Параметры волн'!$B$16)))),'Параметры волн'!$B$17)) -> 3281021.3 | AZ39: =AZ28*(MIN((IF(49<'Параметры волн'!$B$12,0,'Параметры волн'!$B$5*'Параметры волн'!$B$11*'Параметры волн'!$B$8/(1+EXP(-(49-'Параметры волн'!$B$12-'Параметры волн'!$B$15)/'Параметры волн'!$B$16))))+(IF(49<'Параметры волн'!$B$13,0,'Параметры волн'!$B$6*'Параметры волн'!$B$11*'Параметры волн'!$B$9/(1+EXP(-(49-'Параметры волн'!$B$13-'Параметры волн'!$B$15)/'Параметры волн'!$B$16))))+(IF(49<'Параметры волн'!$B$14,0,'Параметры волн'!$B$7*'Параметры волн'!$B$10/(1+EXP(-(49-'Параметры волн'!$B$14-'Параметры волн'!$B$15)/'Параметры волн'!$B$16)))),'Параметры волн'!$B$17)) -> 1371567.7 | BA39: =BA28*(MIN((IF(50<'Параметры волн'!$B$12,0,'Параметры волн'!$B$5*'Параметры волн'!$B$11*'Параметры волн'!$B$8/(1+EXP(-(50-'Параметры волн'!$B$12-'Параметры волн'!$B$15)/'Параметры волн'!$B$16))))+(IF(50<'Параметры волн'!$B$13,0,'Параметры волн'!$B$6*'Параметры волн'!$B$11*'Параметры волн'!$B$9/(1+EXP(-(50-'Параметры волн'!$B$13-'Параметры волн'!$B$15)/'Параметры волн'!$B$16))))+(IF(50<'Параметры волн'!$B$14,0,'Параметры волн'!$B$7*'Параметры волн'!$B$10/(1+EXP(-(50-'Параметры волн'!$B$14-'Параметры волн'!$B$15)/'Параметры волн'!$B$16)))),'Параметры волн'!$B$17)) -> 2752115.7 | BB39: =BB28*(MIN((IF(51<'Параметры волн'!$B$12,0,'Параметры волн'!$B$5*'Параметры волн'!$B$11*'Параметры волн'!$B$8/(1+EXP(-(51-'Параметры волн'!$B$12-'Параметры волн'!$B$15)/'Параметры волн'!$B$16))))+(IF(51<'Параметры волн'!$B$13,0,'Параметры волн'!$B$6*'Параметры волн'!$B$11*'Параметры волн'!$B$9/(1+EXP(-(51-'Параметры волн'!$B$13-'Параметры волн'!$B$15)/'Параметры волн'!$B$16))))+(IF(51<'Параметры волн'!$B$14,0,'Параметры волн'!$B$7*'Параметры волн'!$B$10/(1+EXP(-(51-'Параметры волн'!$B$14-'Параметры волн'!$B$15)/'Параметры волн'!$B$16)))),'Параметры волн'!$B$17)) -> 2761125.4 | BC39: =BC28*(MIN((IF(52<'Параметры волн'!$B$12,0,'Параметры волн'!$B$5*'Параметры волн'!$B$11*'Параметры волн'!$B$8/(1+EXP(-(52-'Параметры волн'!$B$12-'Параметры волн'!$B$15)/'Параметры волн'!$B$16))))+(IF(52<'Параметры волн'!$B$13,0,'Параметры волн'!$B$6*'Параметры волн'!$B$11*'Параметры волн'!$B$9/(1+EXP(-(52-'Параметры волн'!$B$13-'Параметры волн'!$B$15)/'Параметры волн'!$B$16))))+(IF(52<'Параметры волн'!$B$14,0,'Параметры волн'!$B$7*'Параметры волн'!$B$10/(1+EXP(-(52-'Параметры волн'!$B$14-'Параметры волн'!$B$15)/'Параметры волн'!$B$16)))),'Параметры волн'!$B$17)) -> 2770164.6 | BD39: =BD28*(MIN((IF(53<'Параметры волн'!$B$12,0,'Параметры волн'!$B$5*'Параметры волн'!$B$11*'Параметры волн'!$B$8/(1+EXP(-(53-'Параметры волн'!$B$12-'Параметры волн'!$B$15)/'Параметры волн'!$B$16))))+(IF(53<'Параметры волн'!$B$13,0,'Параметры волн'!$B$6*'Параметры волн'!$B$11*'Параметры волн'!$B$9/(1+EXP(-(53-'Параметры волн'!$B$13-'Параметры волн'!$B$15)/'Параметры волн'!$B$16))))+(IF(53<'Параметры волн'!$B$14,0,'Параметры волн'!$B$7*'Параметры волн'!$B$10/(1+EXP(-(53-'Параметры волн'!$B$14-'Параметры волн'!$B$15)/'Параметры волн'!$B$16)))),'Параметры волн'!$B$17)) -> 2779233.4 | BE39: =BE28*(MIN((IF(54<'Параметры волн'!$B$12,0,'Параметры волн'!$B$5*'Параметры волн'!$B$11*'Параметры волн'!$B$8/(1+EXP(-(54-'Параметры волн'!$B$12-'Параметры волн'!$B$15)/'Параметры волн'!$B$16))))+(IF(54<'Параметры волн'!$B$13,0,'Параметры волн'!$B$6*'Параметры волн'!$B$11*'Параметры волн'!$B$9/(1+EXP(-(54-'Параметры волн'!$B$13-'Параметры волн'!$B$15)/'Параметры волн'!$B$16))))+(IF(54<'Параметры волн'!$B$14,0,'Параметры волн'!$B$7*'Параметры волн'!$B$10/(1+EXP(-(54-'Параметры волн'!$B$14-'Параметры волн'!$B$15)/'Параметры волн'!$B$16)))),'Параметры волн'!$B$17)) -> 2788331.9 | BF39: =BF28*(MIN((IF(55<'Параметры волн'!$B$12,0,'Параметры волн'!$B$5*'Параметры волн'!$B$11*'Параметры волн'!$B$8/(1+EXP(-(55-'Параметры волн'!$B$12-'Параметры волн'!$B$15)/'Параметры волн'!$B$16))))+(IF(55<'Параметры волн'!$B$13,0,'Параметры волн'!$B$6*'Параметры волн'!$B$11*'Параметры волн'!$B$9/(1+EXP(-(55-'Параметры волн'!$B$13-'Параметры волн'!$B$15)/'Параметры волн'!$B$16))))+(IF(55<'Параметры волн'!$B$14,0,'Параметры волн'!$B$7*'Параметры волн'!$B$10/(1+EXP(-(55-'Параметры волн'!$B$14-'Параметры волн'!$B$15)/'Параметры волн'!$B$16)))),'Параметры волн'!$B$17)) -> 2797460.2 | BG39: =BG28*(MIN((IF(56<'Параметры волн'!$B$12,0,'Параметры волн'!$B$5*'Параметры волн'!$B$11*'Параметры волн'!$B$8/(1+EXP(-(56-'Параметры волн'!$B$12-'Параметры волн'!$B$15)/'Параметры волн'!$B$16))))+(IF(56<'Параметры волн'!$B$13,0,'Параметры волн'!$B$6*'Параметры волн'!$B$11*'Параметры волн'!$B$9/(1+EXP(-(56-'Параметры волн'!$B$13-'Параметры волн'!$B$15)/'Параметры волн'!$B$16))))+(IF(56<'Параметры волн'!$B$14,0,'Параметры волн'!$B$7*'Параметры волн'!$B$10/(1+EXP(-(56-'Параметры волн'!$B$14-'Параметры волн'!$B$15)/'Параметры волн'!$B$16)))),'Параметры волн'!$B$17)) -> 2806618.3 | BH39: =BH28*(MIN((IF(57<'Параметры волн'!$B$12,0,'Параметры волн'!$B$5*'Параметры волн'!$B$11*'Параметры волн'!$B$8/(1+EXP(-(57-'Параметры волн'!$B$12-'Параметры волн'!$B$15)/'Параметры волн'!$B$16))))+(IF(57<'Параметры волн'!$B$13,0,'Параметры волн'!$B$6*'Параметры волн'!$B$11*'Параметры волн'!$B$9/(1+EXP(-(57-'Параметры волн'!$B$13-'Параметры волн'!$B$15)/'Параметры волн'!$B$16))))+(IF(57<'Параметры волн'!$B$14,0,'Параметры волн'!$B$7*'Параметры волн'!$B$10/(1+EXP(-(57-'Параметры волн'!$B$14-'Параметры волн'!$B$15)/'Параметры волн'!$B$16)))),'Параметры волн'!$B$17)) -> 2815806.5 | BI39: =BI28*(MIN((IF(58<'Параметры волн'!$B$12,0,'Параметры волн'!$B$5*'Параметры волн'!$B$11*'Параметры волн'!$B$8/(1+EXP(-(58-'Параметры волн'!$B$12-'Параметры волн'!$B$15)/'Параметры волн'!$B$16))))+(IF(58<'Параметры волн'!$B$13,0,'Параметры волн'!$B$6*'Параметры волн'!$B$11*'Параметры волн'!$B$9/(1+EXP(-(58-'Параметры волн'!$B$13-'Параметры волн'!$B$15)/'Параметры волн'!$B$16))))+(IF(58<'Параметры волн'!$B$14,0,'Параметры волн'!$B$7*'Параметры волн'!$B$10/(1+EXP(-(58-'Параметры волн'!$B$14-'Параметры волн'!$B$15)/'Параметры волн'!$B$16)))),'Параметры волн'!$B$17)) -> 2825024.7 | BJ39: =BJ28*(MIN((IF(59<'Параметры волн'!$B$12,0,'Параметры волн'!$B$5*'Параметры волн'!$B$11*'Параметры волн'!$B$8/(1+EXP(-(59-'Параметры волн'!$B$12-'Параметры волн'!$B$15)/'Параметры волн'!$B$16))))+(IF(59<'Параметры волн'!$B$13,0,'Параметры волн'!$B$6*'Параметры волн'!$B$11*'Параметры волн'!$B$9/(1+EXP(-(59-'Параметры волн'!$B$13-'Параметры волн'!$B$15)/'Параметры волн'!$B$16))))+(IF(59<'Параметры волн'!$B$14,0,'Параметры волн'!$B$7*'Параметры волн'!$B$10/(1+EXP(-(59-'Параметры волн'!$B$14-'Параметры волн'!$B$15)/'Параметры волн'!$B$16)))),'Параметры волн'!$B$17)) -> 3401127.7 | BK39: =BK28*(MIN((IF(60<'Параметры волн'!$B$12,0,'Параметры волн'!$B$5*'Параметры волн'!$B$11*'Параметры волн'!$B$8/(1+EXP(-(60-'Параметры волн'!$B$12-'Параметры волн'!$B$15)/'Параметры волн'!$B$16))))+(IF(60<'Параметры волн'!$B$13,0,'Параметры волн'!$B$6*'Параметры волн'!$B$11*'Параметры волн'!$B$9/(1+EXP(-(60-'Параметры волн'!$B$13-'Параметры волн'!$B$15)/'Параметры волн'!$B$16))))+(IF(60<'Параметры волн'!$B$14,0,'Параметры волн'!$B$7*'Параметры волн'!$B$10/(1+EXP(-(60-'Параметры волн'!$B$14-'Параметры волн'!$B$15)/'Параметры волн'!$B$16)))),'Параметры волн'!$B$17)) -> 3412262.1 | BL39: =SUM(D39:O39) -> 12398920 | BM39: =SUM(P39:AA39) -> 29299167 | BN39: =SUM(AB39:AM39) -> 30769894 | BO39: =SUM(AN39:AY39) -> 32000806 | BP39: =SUM(AZ39:BK39) -> 33280838
A40: CoS incremental (логистика + антифрод на incremental заказы) | B40: ₽ | C40: 0.04 | D40: =D39*$C$40 -> 0 | E40: =E39*$C$40 -> 0 | F40: =F39*$C$40 -> 6337.8089 | G40: =G39*$C$40 -> 11127.657 | H40: =H39*$C$40 -> 19941.499 | I40: =I39*$C$40 -> 29982.239 | J40: =J39*$C$40 -> 40710.371 | K40: =K39*$C$40 -> 53529.525 | ... BK40: =BK39*$C$40 -> 136490.48 | BL40: =SUM(D40:O40) -> 495956.8 | BM40: =SUM(P40:AA40) -> 1171966.7 | BN40: =SUM(AB40:AM40) -> 1230795.7 | BO40: =SUM(AN40:AY40) -> 1280032.2 | BP40: =SUM(AZ40:BK40) -> 1331233.5
A41: Staff incremental (наша команда инициативы) | B41: ₽ | D41: ='Команда и TtM'!D52 -> 1212652 | E41: ='Команда и TtM'!E52 -> 1212652 | F41: ='Команда и TtM'!F52 -> 1239552 | G41: ='Команда и TtM'!G52 -> 1239552 | H41: ='Команда и TtM'!H52 -> 1609696 | I41: ='Команда и TtM'!I52 -> 1532224 | J41: ='Команда и TtM'!J52 -> 1532224 | K41: ='Команда и TtM'!K52 -> 586420 | ... BK41: ='Команда и TtM'!BK52 -> 344141.63 | BL41: =SUM(D41:O41) -> 12510652 | BM41: =SUM(P41:AA41) -> 3371065 | BN41: =SUM(AB41:AM41) -> 3607039.5 | BO41: =SUM(AN41:AY41) -> 3859532.3 | BP41: =SUM(AZ41:BK41) -> 4129699.5
A42: Marketing incremental (промо новых фич) | B42: ₽ | D42: 0 | E42: 0 | F42: 0 | G42: 0 | H42: 0 | I42: 0 | J42: 0 | K42: =$B$11/12 -> 333333.33 | L42: =$B$11/12 -> 333333.33 | M42: =$B$11/12 -> 333333.33 | N42: =$B$11/12 -> 333333.33 | O42: =$B$11/12 -> 333333.33 | P42: =$B$11/12 -> 333333.33 | Q42: =$B$11/12 -> 333333.33 | R42: =$B$11/12 -> 333333.33 | ... V42: =$B$11/12 -> 333333.33 | W42: =$B$12/12 -> 250000 | X42: =$B$12/12 -> 250000 | Y42: =$B$12/12 -> 250000 | Z42: =$B$12/12 -> 250000 | AA42: =$B$12/12 -> 250000 | AB42: =$B$12/12 -> 250000 | AC42: =$B$12/12 -> 250000 | AD42: =$B$12/12 -> 250000 | ... BK42: =$B$12/12 -> 250000 | BL42: =SUM(D42:O42) -> 1666666.7 | BM42: =SUM(P42:AA42) -> 3583333.3 | BN42: =SUM(AB42:AM42) -> 3000000 | BO42: =SUM(AN42:AY42) -> 3000000 | BP42: =SUM(AZ42:BK42) -> 3000000
A43: IT incremental (лицензии + оборудование на новых HC) | B43: ₽ | D43: =$B$14/12 -> 125000 | E43: =$B$14/12 -> 125000 | F43: =$B$14/12+7*$B$15 -> 825000 | G43: =$B$14/12 -> 125000 | H43: =$B$14/12 -> 125000 | I43: =$B$14/12 -> 125000 | J43: =$B$14/12 -> 125000 | K43: =$B$14/12+3*$B$15 -> 425000 | L43: =$B$14/12 -> 125000 | M43: =$B$14/12 -> 125000 | N43: =$B$14/12 -> 125000 | O43: =$B$14/12 -> 125000 | P43: =$B$14/12 -> 125000 | Q43: =$B$14/12+6*$B$15 -> 725000 | R43: =$B$14/12 -> 125000 | S43: =$B$14/12 -> 125000 | T43: =$B$14/12 -> 125000 | U43: =$B$14/12 -> 125000 | V43: =$B$14/12 -> 125000 | W43: =$B$14/12 -> 125000 | X43: =$B$14/12 -> 125000 | Y43: =$B$14/12 -> 125000 | ... BK43: =$B$14/12 -> 125000 | BL43: =SUM(D43:O43) -> 2500000 | BM43: =SUM(P43:AA43) -> 2100000 | BN43: =SUM(AB43:AM43) -> 1500000 | BO43: =SUM(AN43:AY43) -> 1500000 | BP43: =SUM(AZ43:BK43) -> 1500000
A44: G&A incremental (% × Staff incr) | B44: ₽ | D44: =D41*$B$16 -> 60632.6 | E44: =E41*$B$16 -> 60632.6 | F44: =F41*$B$16 -> 61977.6 | G44: =G41*$B$16 -> 61977.6 | H44: =H41*$B$16 -> 80484.8 | I44: =I41*$B$16 -> 76611.2 | J44: =J41*$B$16 -> 76611.2 | K44: =K41*$B$16 -> 29321 | ... BK44: =BK41*$B$16 -> 17207.081 | BL44: =SUM(D44:O44) -> 625532.6 | BM44: =SUM(P44:AA44) -> 168553.25 | BN44: =SUM(AB44:AM44) -> 180351.98 | BO44: =SUM(AN44:AY44) -> 192976.61 | BP44: =SUM(AZ44:BK44) -> 206484.98
A45: Σ OPEX Increment (без CoS, до EBITDA) | D45: =SUM(D40:D44) -> 1398284.6 | E45: =SUM(E40:E44) -> 1398284.6 | F45: =SUM(F40:F44) -> 2132867.4 | G45: =SUM(G40:G44) -> 1437657.3 | H45: =SUM(H40:H44) -> 1835122.3 | I45: =SUM(I40:I44) -> 1763817.4 | J45: =SUM(J40:J44) -> 1774545.6 | K45: =SUM(K40:K44) -> 1427603.9 | ... BK45: =SUM(BK40:BK44) -> 872839.19 | BL45: =SUM(D45:O45) -> 17798808 | BM45: =SUM(P45:AA45) -> 10394918 | BN45: =SUM(AB45:AM45) -> 9518187.2 | BO45: =SUM(AN45:AY45) -> 9832541.1 | BP45: =SUM(AZ45:BK45) -> 10167418

Sheet Sensitivity
A1: Sensitivity-анализ: чувствительность EBITDA Increment 2030 к ключевым параметрам
A2: Подход: показываем линейный эффект ±изменения каждого параметра на EBITDA INCR 2030 (млн ₽). Расчёт через прокси-формулы (Δparam × соответствующая база × margin). Применимо для приоритизации проверок гипотез.
A4: Базовые значения 2030 (из модели)
A5: Revenue INCR 2030, млн ₽ | B5: =PnL!BP39 -> 33.280838
A6: EBITDA INCR 2030, млн ₽ | B6: =PnL!BP47 -> 23.11342
A7: Staff INCR 2030, млн ₽ | B7: =-PnL!BP41 -> 4.1296995
A8: Marketing INCR 2030, млн ₽ | B8: =-PnL!BP42 -> 3
A9: CoS INCR 2030, млн ₽ | B9: =-PnL!BP40 -> 1.3312335
A10: Контрибуционная маржа INCR 2030 (Rev−CoS)/Rev | B10: =(B5-B9)/B5 -> 0.96
A12: Tornado-анализ: ΔEBITDA INCR 2030 (млн ₽) при ±отклонении параметра
A13: Параметр | B13: База | C13: Сценарий «−» | D13: Δ EBITDA «−», млн ₽ | E13: Сценарий «+» | F13: Δ EBITDA «+», млн ₽ | G13: Размах |Δ|, млн ₽ | H13: Источник прокси-формулы
A14: Индексация ЗП (год/год) | B14: ='Cost assumptions'!B20 -> 0.07 | C14: −2pp (5%) | D14: =-B7*((1+0.05)^4-(1+'Cost assumptions'!B20)^4)/((1+'Cost assumptions'!B20)^4) -> 0.30021306 | E14: +3pp (10%) | F14: =-B7*((1+0.1)^4-(1+'Cost assumptions'!B20)^4)/((1+'Cost assumptions'!B20)^4) -> -0.48298851 | G14: =ABS(D14)+ABS(F14) -> 0.78320157 | H14: ΔStaff2030 = Staff × ((1+i_new)^4−(1+i_base)^4)/(1+i_base)^4
A15: CoS Increment, % от Rev INCR | B15: ='Cost assumptions'!C40 -> 0.04 | C15: −2pp (2%) | D15: =B5*('Cost assumptions'!C40-0.02) -> 0.66561677 | E15: +2pp (6%) | F15: =B5*('Cost assumptions'!C40-0.06) -> -0.66561677 | G15: =ABS(D15)+ABS(F15) -> 1.3312335 | H15: ΔEBITDA = Revenue INCR × Δrate (знак противоположный CoS)
A16: Marketing год 1 после запуска, млн ₽ | B16: ='Cost assumptions'!B11/1000000 -> 4 | C16: −5 млн (10 млн) | D16: 0 | E16: +5 млн (20 млн) | F16: 0 | G16: 0 | H16: Marketing год 1 → влияет на 2026-2027, на 2030 EBITDA не меняется. Влияние на cumulative CF.
A17: Marketing годы 2-5, млн ₽/год | B17: ='Cost assumptions'!B12/1000000 -> 3 | C17: −2 млн (3 млн) | D17: =2 -> 2 | E17: +5 млн (10 млн) | F17: =-5 -> -5 | G17: =ABS(D17)+ABS(F17) -> 7 | H17: ΔEBITDA = -Δ marketing (прямой эффект годового бюджета)
A18: Take rate (доставка, %) | B18: ='Монетизация и юнит'!F23/100 -> 0.03 | C18: −1pp (2%) | D18: =B5*(-1/3)*0.7*B10 -> -7.4549078 | E18: +2pp (5%) | F18: =B5*(2/3)*0.7*B10 -> 14.909816 | G18: =ABS(D18)+ABS(F18) -> 22.364723 | H18: Δ% Rev = Δtake/take × 70% (доля транзакц.выручки); × контриб.маржу
A19: AOV зоотоваров, ₽ | B19: ='Монетизация и юнит'!F19 -> 1700 | C19: −200 (1500) | D19: =B5*(-200/'Монетизация и юнит'!F19)*0.7*B10 -> -2.6311439 | E19: +300 (2000) | F19: =B5*(300/'Монетизация и юнит'!F19)*0.7*B10 -> 3.9467159 | G19: =ABS(D19)+ABS(F19) -> 6.5778598 | H19: Аналогично Take rate (через транзакционный слой Revenue × контрибуционная маржа)
A20: Средняя confidence rate гипотез | B20: =0.5833 -> 0.5833 | C20: −0.2 (~0.38) | D20: =B5*(-0.2/0.5833)*B10 -> -10.954776 | E20: +0.15 (~0.73) | F20: =B5*(0.15/0.5833)*B10 -> 8.2160822 | G20: =ABS(D20)+ABS(F20) -> 19.170858 | H20: Confidence пропорционально влияет на uplift → на Revenue INCR
A21: Размер команды (FTE) | B21: ='Команда и TtM'!BP40 -> 1.1 | C21: −20% FTE | D21: =B7*0.2 -> 0.82593991 | E21: +20% FTE | F21: =-B7*0.2 -> -0.82593991 | G21: =ABS(D21)+ABS(F21) -> 1.6518798 | H21: ΔEBITDA = -Δstaff_count × Staff INCR (линейно)
A22: Churn покупателя зоотоваров (мес) | B22: 0.15 | C22: −5pp (10%) | D22: =B5*0.05*0.7*B10 -> 1.1182362 | E22: +5pp (20%) | F22: =-B5*0.05*0.7*B10 -> -1.1182362 | G22: =ABS(D22)+ABS(F22) -> 2.2364723 | H22: Δchurn влияет на LT → ARPU транзакций; оценка по эластичности ~1:1
A23: WACC (риск премии) | B23: =PnL!B10 -> 0.263 | C23: −5pp (21%) | D23: Влияет на NPV, не на EBITDA | E23: +5pp (31%) | F23: См. NPV в листе CashFlow | G23: — | H23: WACC влияет только на NPV. См. CashFlow!C36
A25: ВЫВОДЫ
A26: • Самые чувствительные параметры — те, которые имеют наибольший |Δ|. Их следует валидировать в первую очередь через A/B тесты.
A27: • Take rate и AOV — лоу-хэнгинг: можно тестировать ценовые эксперименты (хантовая категория, готовые наборы).
A28: • Confidence гипотез — главный риск раскатки. Каждая гипотеза должна пройти A/B перед полным rollout.
A29: • Зарплатная индексация — внешний фактор, риск перетекания талантов в банки. План: keep-программа, бонусы за владение функционалом.
A30: • Размер команды (+20%): риск перерасхода, contingency через FTE freeze после релиза Wave 1.

Sheet Чекеры
A1: Чекеры - валидация модели по 3 осям
A2: Каждый чекер проверяет конкретное допущение/инвариант. OK = условие выполнено, FAIL = требует ревизии модели.
A4: Чекер | B4: Метрика | C4: Порог | D4: Текущее значение | E4: Результат
A5: 1. ТЕХНИЧЕСКИЕ
A6: Σ помесячных Revenue 2026 AS IS = годовой итог | B6: Σ Jan-Dec = Year total | C6: |Δ| < 0.1 | D6: =ABS(SUM(PnL!D20:O20)-PnL!BL20)<0.1 -> TRUE | E6: =IF(D6,"OK","FAIL") -> OK
A7: AS IS + Increment = TO BE (Revenue 2026) | B7: TO BE = AS IS + INCREMENT | C7: |Δ| < 0.1 | D7: =ABS((PnL!BL20+PnL!BL39)-PnL!BL58)<0.1 -> TRUE | E7: =IF(D7,"OK","FAIL") -> OK
A8: Нет ошибок #REF! на ключевых листах | B8: COUNTIF(ISERROR) | C8: =0 -> 0 | D8: =ISNUMBER(PnL!BP74) -> TRUE | E8: =IF(D8,"OK","FAIL") -> OK
A9: Σ помесячных EBITDA Increment 2026 = годовой итог | B9: Σ месяцев = Год | C9: |Δ| < 0.1 | D9: =ABS(SUM(PnL!D47:O47)-PnL!BL47)<0.1 -> TRUE | E9: =IF(D9,"OK","FAIL") -> OK
A10: CashFlow: cumulative = sum operating CF | B10: Cum CF Dec 2030 = Σ CF (60 мес) | C10: |Δ| < 0.1 | D10: =ABS(CashFlow!BK30-SUM(CashFlow!D29:BK29))<0.1 -> TRUE | E10: =IF(D10,"OK","FAIL") -> OK
A12: 2. ЛОГИЧЕСКИЕ
A13: Revenue TO BE 2026 < SOM 2026 (рынок не превышен) | B13: Revenue / (SOM Dec × 12) | C13: Revenue < SOM | D13: =PnL!BL58<'Baseline TOP-down'!O10*12/1000 -> TRUE | E13: =IF(D13,"OK","FAIL") -> OK
A14: Revenue TO BE 2030 < SOM 2030 | B14: Revenue 2030 < SOM 2030 (annualized) | C14: Revenue < SOM | D14: =PnL!BP58<'Baseline TOP-down'!BK10*12/1000 -> TRUE | E14: =IF(D14,"OK","FAIL") -> OK
A15: EBITDA margin TO BE > AS IS (инициатива улучшает экономику) 2030 | B15: TO BE EBITDA% > AS IS EBITDA% к 2030 | C15: TO BE > AS IS | D15: =(PnL!BP66/PnL!BP58)>(PnL!BP28/PnL!BP20) -> TRUE | E15: =IF(D15,"OK","FAIL") -> OK
A16: EBITDA Increment > 0 в году после полного запуска (2028) | B16: EBITDA INCR 2028 > 0 | C16: > 0 | D16: =PnL!BN47>0 -> TRUE | E16: =IF(D16,"OK","FAIL") -> OK
A17: Cumulative CF становится положительным до конца 2030 | B17: min Cum CF >= 0 на горизонте | C17: CumCF(60)>0 | D17: =CashFlow!BK30>0 -> TRUE | E17: =IF(D17,"OK","FAIL") -> OK
A18: Staff Increment / Revenue Increment < 50% (2030) | B18: Staff INCR / Revenue INCR | C18: < 50% | D18: =IFERROR(-PnL!BP41/PnL!BP39,1)<0.5 -> TRUE | E18: =IF(D18,"OK","FAIL") -> OK
A20: 3. РЕАЛИСТИЧНОСТЬ (vs бенчмарки)
A21: Зарплата ML eng в коридоре рынка (250-350k gross) | B21: ML salary gross | C21: 250к ≤ x ≤ 350к | D21: =AND('Команда и TtM'!C9>=250000,'Команда и TtM'!C9<=350000) -> TRUE | E21: =IF(D21,"OK","FAIL") -> OK
A22: Зарплата Backend eng в коридоре (200-320k gross) | B22: BE salary gross | C22: 200к ≤ x ≤ 320к | D22: =AND('Команда и TtM'!C10>=200000,'Команда и TtM'!C10<=320000) -> TRUE | E22: =IF(D22,"OK","FAIL") -> OK
A23: EBITDA margin AS IS 2026 в коридоре 40-60% (для Avito-like) | B23: EBITDA% AS IS 2026 | C23: 40-60% | D23: =AND((PnL!BL28/PnL!BL20)>=0.4,(PnL!BL28/PnL!BL20)<=0.7) -> FALSE | E23: =IF(D23,"OK","FAIL") -> FAIL
A24: Доля Staff INCR в Revenue INCR < 100% к 2030 (есть operating leverage) | B24: Staff INCR / Revenue INCR 2030 | C24: < 100% | D24: =IFERROR(-PnL!BP41/PnL!BP39,2)<1 -> TRUE | E24: =IF(D24,"OK","FAIL") -> OK
A25: Marketing INCR / Revenue INCR < 20% к 2030 | B25: Mkt INCR / Revenue INCR 2030 | C25: < 20% | D25: =IFERROR(-PnL!BP42/PnL!BP39,2)<0.2 -> TRUE | E25: =IF(D25,"OK","FAIL") -> OK
A26: TtM с буфером в коридоре 18-24 мес | B26: TtM мес | C26: 18 ≤ TtM ≤ 24 | D26: =AND('Команда и TtM'!B25>=18,'Команда и TtM'!B25<=24) -> FALSE | E26: =IF(D26,"OK","FAIL") -> FAIL
A28: 4. UNIT ECONOMICS
A29: LTV покупателя зоотоваров (сегмент.) > 3 × CAC | B29: LTV pet supplies > 3×CAC | C29: > 3 | D29: ='Монетизация и юнит'!F103/'Монетизация и юнит'!G103>3 -> FALSE | E29: =IF(D29,"OK","FAIL") -> FAIL
A30: LTV (общий) > CAC | B30: LTV > CAC | C30: > 1 | D30: ='Монетизация и юнит'!E32>'Монетизация и юнит'!F10 -> TRUE | E30: =IF(D30,"OK","FAIL") -> OK
A31: Payback period < 12 мес (быстрая окупаемость инициативы) | B31: CF cum > 0 в первые 24 мес | C31: < 24 мес | D31: {=IFERROR(MATCH(TRUE,INDEX(CashFlow!D30:BK30>=0,0),0),100)<24} -> TRUE | E31: =IF(D31,"OK","FAIL") -> OK
A33: ИТОГО
A34: Σ OK | E34: =COUNTIF(E5:E39,"OK")
A35: Σ FAIL | E35: =COUNTIF(E5:E39,"FAIL")
A37: 5. ДОПОЛНИТЕЛЬНЫЕ Unit economics (сегментированные)
A38: LTV продавца-классифайда > 3 × CAC (профи держат retention) | B38: LTV seller > 3×CAC | C38: > 3 | D38: ='Монетизация и юнит'!F104/'Монетизация и юнит'!G104>3 -> FALSE | E38: =IF(D38,"OK","FAIL") -> FAIL
A39: Взвешенный LTV (3 сегмента) > Взвешенный CAC | B39: Wgt LTV / Wgt CAC | C39: > 1 | D39: ='Монетизация и юнит'!F105>'Монетизация и юнит'!G105 -> TRUE | E39: =IF(D39,"OK","FAIL") -> OK

Sheet Графики
A1: Графики (визуализация PnL и CashFlow)
A3: Сводка по годам (PnL и CashFlow)
A4: Год | B4: Revenue AS IS | C4: Revenue INCR | D4: Revenue TO BE | E4: EBITDA AS IS | F4: EBITDA INCR | G4: EBITDA TO BE | H4: FCF INCR
A5: 2026 | B5: =PnL!BL20 -> 409.36014 | C5: =PnL!BL39 -> 12.39892 | D5: =PnL!BL58 -> 421.75906 | E5: =PnL!BL28 -> 289.50493 | F5: =PnL!BL47 -> -5.399888 | G5: =PnL!BL66 -> 284.10505 | H5: =PnL!BL55 -> -9.5668114
A6: 2027 | B6: =PnL!BM20 -> 412.94306 | C6: =PnL!BM39 -> 29.299167 | D6: =PnL!BM58 -> 442.24222 | E6: =PnL!BM28 -> 286.66304 | F6: =PnL!BM47 -> 18.904248 | G6: =PnL!BM66 -> 305.56729 | H6: =PnL!BM55 -> 16.893697
A7: 2028 | B7: =PnL!BN20 -> 429.46078 | C7: =PnL!BN39 -> 30.769894 | D7: =PnL!BN58 -> 460.23067 | E7: =PnL!BN28 -> 295.41834 | F7: =PnL!BN47 -> 21.251706 | G7: =PnL!BN66 -> 316.67005 | H7: =PnL!BN55 -> 19.957794
A8: 2029 | B8: =PnL!BO20 -> 446.63921 | C8: =PnL!BO39 -> 32.000806 | D8: =PnL!BO58 -> 478.64002 | E8: =PnL!BO28 -> 304.32567 | F8: =PnL!BO47 -> 22.168265 | G8: =PnL!BO66 -> 326.49394 | H8: =PnL!BO55 -> 20.819665
A9: 2030 | B9: =PnL!BP20 -> 464.50478 | C9: =PnL!BP39 -> 33.280838 | D9: =PnL!BP58 -> 497.78562 | E9: =PnL!BP28 -> 313.37724 | F9: =PnL!BP47 -> 23.11342 | G9: =PnL!BP66 -> 336.49066 | H9: =PnL!BP55 -> 21.708018
A11: Cumulative CashFlow (Increment) — помесячно 2026-2030
A12: Месяц # | B12: 2026-01 | C12: 2026-02 | D12: 2026-03 | E12: 2026-04 | F12: 2026-05 | G12: 2026-06 | H12: 2026-07 | I12: 2026-08 | J12: 2026-09 | K12: 2026-10 | L12: 2026-11 | M12: 2026-12 | N12: 2027-01 | O12: 2027-02 | P12: 2027-03 | Q12: 2027-04 | R12: 2027-05 | S12: 2027-06 | T12: 2027-07 | U12: 2027-08 | V12: 2027-09 | W12: 2027-10 | X12: 2027-11 | Y12: 2027-12 | Z12: 2028-01 | AA12: 2028-02 | AB12: 2028-03 | AC12: 2028-04 | AD12: 2028-05 | AE12: 2028-06 | AF12: 2028-07 | AG12: 2028-08 | AH12: 2028-09 | AI12: 2028-10 | AJ12: 2028-11 | AK12: 2028-12 | AL12: 2029-01 | AM12: 2029-02 | AN12: 2029-03 | AO12: 2029-04 | AP12: 2029-05 | AQ12: 2029-06 | AR12: 2029-07 | AS12: 2029-08 | AT12: 2029-09 | AU12: 2029-10 | AV12: 2029-11 | AW12: 2029-12 | AX12: 2030-01 | AY12: 2030-02 | AZ12: 2030-03 | BA12: 2030-04 | BB12: 2030-05 | BC12: 2030-06 | BD12: 2030-07 | BE12: 2030-08 | BF12: 2030-09 | BG12: 2030-10 | BH12: 2030-11 | BI12: 2030-12
A13: Cum CF, млн ₽ | B13: =CashFlow!D30 -> -1.212652 | C13: =CashFlow!E30 -> -2.425304 | D13: =CashFlow!F30 -> -3.6974809 | E13: =CashFlow!G30 -> -4.8259623 | F13: =CashFlow!H30 -> -6.9093918 | G13: =CashFlow!I30 -> -7.7798749 | H13: =CashFlow!J30 -> -8.3612993 | I13: =CashFlow!K30 -> -7.6197457 | ... BI13: =CashFlow!BK30 -> 100.73241
A15: Структура OPEX 2030 TO BE
A16: Статья | B16: 2030, млн ₽
A17: CoS | B17: =-PnL!BP59 -> 10.621329
A18: Staff costs | B18: =-PnL!BP60 -> 114.23656
A19: Marketing | B19: =-PnL!BP61 -> 26.225239
A20: IT | B20: =-PnL!BP63 -> 4.5
A21: G&A | B21: =-PnL!BP64 -> 5.7118282
A23: Точка безубыточности | B23: =CashFlow!C34 -> 15 | C23: мес от старта

Sheet Монетизация и юнит
A1: Обновлен сегментированным LTV
A2: LTV = ARPU × Lifetime × GM%
A3: ARPU = ARPPU × Conversion_to_paid
A4: ARPU_transaction = AOV × F × Take rate
A6: Классифайдный слой
B7: ARPPU | C7: х | D7: Conversion_to_paid | J7: LTV | M7: CAC
A8: ARPU | B8: =Assumptions!C11 -> 0.75 | C8: х | D8: =Assumptions!C23 -> 0.05 | E8: = | F8: =B8*D8*1000 -> 37.5 | G8: руб.
A10: САС | B10: Допущение | C10: в месяц | E10: = | F10: 300 | G10: руб.
A12: churn | B12: 0.2 | C12: Уходят после покупки животного, часть может вернуться за сопутствующими товарами
A13: LT | B13: 1 | C13: / | D13: 0.2 | E13: = | F13: =B13/D13 -> 5 | G13: мес
A15: GM% | B15: Допущение. Низкие переменные издержки у цифровой платформы, но расходы на поддержку, антифрод и инфраструктуру | F15: 0.6
A18: Транзакционный слой
A19: AOV | B19: Допущение | C19: Корм+наполнитель | E19: = | F19: 1700 | G19: руб.
A21: Частота покупок (F) | B21: Допущение | C21: Расход корма и прочих товаров | E21: = | F21: 2 | G21: раз/мес.
A23: Take rate | B23: Допущение | C23: На доставку всего 1%, низкая маржа с продажи корма | E23: = | F23: 3 | G23: %
A25: Совокупный расчет
A27: ARPU (классифайд) | C27: =F8 -> 37.5 | D27: руб. | J27: Retention | K27: Churn | L27: Lifetime | M27: LTV | N27: САС
A28: ARPU (транзакции) | C28: =F19*F23/100*F21 -> 102 | D28: руб. | I28: 1 | J28: 0.95 | K28: =1-J28 -> 0.05 | L28: =1/K28 -> 20 | M28: =$C$30*L28*$F$15 -> 1674 | N28: 300
I29: 2 | J29: 0.9 | K29: =1-J29 -> 0.1 | L29: =1/K29 -> 10 | M29: =$C$30*L29*$F$15 -> 837 | N29: 300
A30: ARPU | C30: =C27+C28 -> 139.5 | D30: руб. | I30: 3 | J30: 0.85 | K30: =1-J30 -> 0.15 | L30: =1/K30 -> 6.6666667 | M30: =$C$30*L30*$F$15 -> 558 | N30: 300
B31: ARPU | C31: LT | D31: GM% | E31: GM% | I31: 4 | J31: 0.8 | K31: =1-J31 -> 0.2 | L31: =1/K31 -> 5 | M31: =$C$30*L31*$F$15 -> 418.5 | N31: 300
A32: LTV | B32: =C30 -> 139.5 | C32: =F13 -> 5 | D32: =F15 -> 0.6 | E32: =B32*C32*D32 -> 418.5 | F32: руб. | I32: 5 | J32: 0.75 | K32: =1-J32 -> 0.25 | L32: =1/K32 -> 4 | M32: =$C$30*L32*$F$15 -> 334.8 | N32: 300
I33: 6 | J33: 0.7 | K33: =1-J33 -> 0.3 | L33: =1/K33 -> 3.3333333 | M33: =$C$30*L33*$F$15 -> 279 | N33: 300
B34: LTV | C34: - | D34: CAC | I34: 7 | J34: 0.65 | K34: =1-J34 -> 0.35 | L34: =1/K34 -> 2.8571429 | M34: =$C$30*L34*$F$15 -> 239.14286 | N34: 300
A35: UE | B35: =E32 -> 418.5 | C35: - | D35: =F10 -> 300 | E35: =B35-D35 -> 118.5 | F35: руб. | G35: Положительная | I35: 8 | J35: 0.6 | K35: =1-J35 -> 0.4 | L35: =1/K35 -> 2.5 | M35: =$C$30*L35*$F$15 -> 209.25 | N35: 300
I36: 9 | J36: 0.55 | K36: =1-J36 -> 0.45 | L36: =1/K36 -> 2.2222222 | M36: =$C$30*L36*$F$15 -> 186 | N36: 300
A37: LTV > CAC → модель устойчива | I37: 10 | J37: 0.5 | K37: =1-J37 -> 0.5 | L37: =1/K37 -> 2 | M37: =$C$30*L37*$F$15 -> 167.4 | N37: 300
A38: запас небольшой → чувствительна к: | I38: 11 | J38: 0.45 | K38: =1-J38 -> 0.55 | L38: =1/K38 -> 1.8181818 | M38: =$C$30*L38*$F$15 -> 152.18182 | N38: 300
A39: росту CAC | I39: 12 | J39: 0.4 | K39: =1-J39 -> 0.6 | L39: =1/K39 -> 1.6666667 | M39: =$C$30*L39*$F$15 -> 139.5 | N39: 300
A40: падению retention | I40: 13 | J40: 0.35 | K40: =1-J40 -> 0.65 | L40: =1/K40 -> 1.5384615 | M40: =$C$30*L40*$F$15 -> 128.76923 | N40: 300
I41: 14 | J41: 0.3 | K41: =1-J41 -> 0.7 | L41: =1/K41 -> 1.4285714 | M41: =$C$30*L41*$F$15 -> 119.57143 | N41: 300
A42: Самые рискованые допущения | I42: 15 | J42: 0.25 | K42: =1-J42 -> 0.75 | L42: =1/K42 -> 1.3333333 | M42: =$C$30*L42*$F$15 -> 111.6 | N42: 300
A43: Conversion to paid = 5% | I43: 16 | J43: 0.2 | K43: =1-J43 -> 0.8 | L43: =1/K43 -> 1.25 | M43: =$C$30*L43*$F$15 -> 104.625 | N43: 300
A44: Частота покупок = 2 | I44: 17 | J44: 0.15 | K44: =1-J44 -> 0.85 | L44: =1/K44 -> 1.1764706 | M44: =$C$30*L44*$F$15 -> 98.470588 | N44: 300
A45: Take rate = 5% (может ограничиваться конкуренцией с другими площадками) | I45: 18 | J45: 0.1 | K45: =1-J45 -> 0.9 | L45: =1/K45 -> 1.1111111 | M45: =$C$30*L45*$F$15 -> 93 | N45: 300
I46: 19 | J46: 0.05 | K46: =1-J46 -> 0.95 | L46: =1/K46 -> 1.0526316 | M46: =$C$30*L46*$F$15 -> 88.105263 | N46: 300
A47: фишечки: Дополнительно в рамках развития монетизационной модели целесообразен бандлинг в момент совершения целевого действия. Например, при покупке животного пользователю могут предлагаться готовые наборы (корм, переноска, аксессуары) по сниженной цене. Данная механика позволяет увеличить средний чек (AOV) и частоту покупок (frequency), что напрямую влияет на рост ARPU и LTV. Бандлинг снизит когнитивную нагрузку на пользователя и повышает конверсию в покупку, так как закрывает комплексную потребность в одном сценарии. Внедрение бандлинга является одним из ключевых драйверов роста транзакционной выручки без существенного увеличения CAC. Каннибализация: Введение транзакционной модели может частично каннибализировать доходы от классифайдной модели (например, снижение спроса на платное продвижение объявлений). Ожидается, что рост общего числа сделок и вовлечённости пользователей компенсирует данный эффект за счёт увеличения совокупного ARPU. Масштабирование: Модель является масштабируемой, так как при росте MAU выручка растёт пропорционально, а предельные издержки остаются низкими. Основным ограничением масштабирования может выступать рост CAC при насыщении рынка и усилении конкуренции за трафик.
A72: Альтернативы
A73: Подписочная модель не является оптимальной, так как поведение пользователей в категории носит нерегулярный характер: пользователи приходят под конкретную задачуи не готовы платить фиксированную плату на постоянной основе. Это снижило бы конверсию в подписку и ограничило выручку. Рекламная модель также не является основной, поскольку ценность продукта для пользователя заключается в совершении целевого действия (покупки или продажи), а не в потреблении контента. Использование рекламы может ухудшить пользовательский опыт и снизить конверсию в ключевые действия. В связи с этим гибридная модель (классифайд + транзакции) лучше соответствует пользовательской ценности: пользователь платит только в момент получения ценности (продвижение объявления или совершение сделки), что повышает конверсию и общую эффективность монетизации.
A98: СЕГМЕНТИРОВАННЫЙ LTV (обновление по фидбеку ДЗ_3)
A99: Замечание из рецензии: общий LTV без сегментации скрывает разную экономику пользователей. Разделяем на 3 сегмента: покупатель питомца (одноразовый), покупатель зоотоваров (повторный), продавец-классифайд (профи). Считаем LTV для каждого.
A101: Сегмент | B101: ARPU/ARPPU, ₽/мес | C101: Conversion to paid | D101: Lifetime (мес) | E101: GM% | F101: LTV, ₽ | G101: CAC, ₽ | H101: LTV/CAC | I101: Статус | J101: Комментарий
A102: 1. Покупатель питомца | B102: 0 | C102: 0 | D102: 0.5 | E102: 0 | F102: =B102*D102*E102 -> 0 | G102: 0 | H102: =IFERROR(F102/G102,"n/a") -> n/a | I102: монетизация через селлера | J102: Покупатель питомца — разовая сделка C2C. Avito зарабатывает не с него, а с продавца (комиссия за продвижение). LTV покупателя = 0 в нашей модели; CAC относится к воронке продавца.
A103: 2. Покупатель зоотоваров | B103: =F19*F23/100*F21 -> 102 | C103: 1 | D103: 8 | E103: 0.4 | F103: =B103*D103*E103 -> 326.4 | G103: 200 | H103: =F103/G103 -> 1.632 | I103: слабое превышение | J103: Повторяемая покупка корма/наполнителя. Lifetime 8 мес исходя из churn ~12,5%/мес. GM% 40% — учитывает логистику и низкую маржу с продажи корма. CAC 200₽ — конвертируется из существующих пользователей платформы.
A104: 3. Продавец-классифайд (профи) | B104: =Assumptions!C11*1000 -> 750 | C104: =Assumptions!C23 -> 0.05 | D104: 20 | E104: 0.85 | F104: =B104*C104*D104*E104 -> 637.5 | G104: 400 | H104: =F104/G104 -> 1.59375 | I104: слабое превышение | J104: Профессиональный селлер (питомники, частные заводчики). Lifetime 20 мес (churn ~5%/мес). GM% 85% — почти чистая прибыль с продажи продвижения. CAC 400₽ — выше за счёт B2B-воронки.
A105: Σ Взвешенный LTV (по MAU) | B105: — | D105: — | E105: — | F105: =0.3*F102+0.5*F103+0.2*F104 -> 290.7 | G105: =0.3*G102+0.5*G103+0.2*G104 -> 180 | H105: =F105/G105 -> 1.615 | I105: слабое превышение | J105: Веса MAU: покупатель питомца 30%, покупатель зоотоваров 50%, продавец 20%.
A107: Старый LTV (ДЗ3, без сегментации) | F107: =E32 -> 418.5 | G107: =F10 -> 300 | H107: =F107/G107 -> 1.395
A109: Выводы по сегментированному LTV:
A112: • Покупатель питомца — не монетизирован напрямую (LTV = 0). Окупаемость воронки через продавца.
A113: • Все 3 гипотезы из ДЗ2 поддерживают LTV селлера (рекомендации, индикатор цены) и покупателя (видео).
A114: • Главные риски: рост CAC (особенно для профи) и падение retention зоотоваров (конкуренция WB/Ozon).

Sheet Гипотезы
A1: Гипотеза | B1: Метрика | C1: Confidence | D1: Confidence Rate | E1: uplift | J1: % раскатки | O1: Источник / обоснование | P1: Метод проверки | Q1: Риск каннибализации | R1: Комментарий:
E2: 2026 | F2: 2027 | G2: 2028 | H2: 2029 | I2: 2030 | J2: 2026 | K2: 2027 | L2: 2028 | M2: 2029 | N2: 2030
A3: Если внедрим алгоритм, который анализирует каждое объявление профессионального продавца в категории «Животные» и даёт персонализированные рекомендации по улучшению объявления через платные услуги, то увеличим ARPPU на 10% за счет релевантных советов, основанных на данных и трендах рынка | B3: ARPPU | C3: medium | D3: 0.75 | E3: 0.1 | J3: 0.3 | K3: 0.7 | L3: 1 | M3: 1 | N3: 1 | O3: ML рекомендации для исполнителей повысили количество целевых действий более чем на 10%: https://avito.tech/content/kkyjs1y6n1-kak-s-pomoschyu-ml-modeli-mi-pomogli-isp | P3: A/B-тест на 20% трафика, длительность - месяц (4 недели). Тестовой группе предлагается алгоритм рекомендаций, замеряется прирост ARPU. При наличии спроса на функцию и повышении ARPU происходит дальнейшая раскатка | Q3: Риск 1: рекомендации алгоритма для самых активных пользователей продвижения могут дать более низкий чек. Митигация: порог среднего чека, при котором алгоритм не рекомендует более дешевое продвижение, чем было ранее. Риск 2: перегрузка активных пользователей с несколькими объявлениями (много пушей и рекомендаций). Митигация: ручная настройка частоты рекомендаций и сигналов алгоритма | R3: Алгоритм учитывает: -породу и возраст животного -качество фотографий -наличие документов (родословная, прививки) -цену относительно рыночной -географию Взят дисконт от значения из кейса на 3 пп
A4: Если добавим в карточку объявления о животном индикатор соответствия цены рыночному уровню за отдельную плату, то увеличим число сделок на платформе, так как снизим неопределенность пользователя при просмотре карточки. Это приведет к увеличению ARPU, так как при уверенности в цене пользователь будет чаще совершать целевое действие (за которое платит продавец), не тратя время на скролл выдачи и сравнение цен | B4: ARPPU | C4: medium | D4: 0.6 | E4: 0.05 | J4: 0.1 | K4: 0.5 | L4: 1 | M4: 1 | N4: 1 | O4: В Авито внедрен схожий функционал, но для Авто. Животных так же можно категоризировать по породам / возрасту / родословной, чтобы причины разницы цен была прозрачна | P4: A/B-тест на 10% трафика, длительность - 3 недели | Q4: Если индикатор будет слишком сильно сокращать сессию и пользователь будет мгновенно находить "идеальное по цене" животное и сразу совершать целевое действие, это может привести к снижению количества просмотренных объявлений за сессию. Авито потерять средства на "вовлеченности" (показах рекламы в ленте). Рост ARPU от сделок должен компенсировать потенциальное падение ARPU от рекламы в ленте из-за сокращения пути пользователя. | R4: Подразумевается, что пользователь сможет за разовую оплату добавить индикатор, кратно повышающий доверие через доказательство рыночной цены. (есл цена выше рынка - указывается причина в виде родословной / наличия всех документов и пр.)
A5: Если мы добавим возможность загружать короткие видео (до 30–60 секунд) в карточку объявления о животном, а также создадим отдельную ленту «Истории», где будут показываться видео с питомцами, то MAU увеличится на 3%, увелиивая вероятность импульсивной покупки внутри категории | B5: MAU | C5: low | D5: 0.4 | E5: 0.03 | J5: 0.3 | K5: 1 | L5: 1 | M5: 1 | N5: 1 | O5: Рост конверсий за счет UGC и вовлеченности (пользователи охотно взаимодействуют с контентом о питомцах): https://www.sostav.ru/publication/kejs-food-ru-78331.html Прямое влияние видео на конверсии (Кейс Krasnodog): использование коротких эмоциональных видео о животных для приюта "Краснодог" привело к бизнес-результатам: за две недели количество донатов выросло на 60%, а регулярные подписки - на 25% https://taf25.marketing.uz//case/120.htm | P5: MVP -> АБ на сегмент с высокой вероятностью импульсных покупок (котята, щенки и пр.). Контрольная группа: пользователи видят стандартные карточки с фото. В выдаче нет блока «Истории». Тестовая группа: пользователи видят карточки, где у части объявлений есть видео (до 60 сек). Если метрики вовлеченности (time in app, dau, mau) растут, то идет доработка с точками совершения целевого действия (В выдаче появляется отдельный блок или вкладка «Истории с питомцами») | Q5: Риск. Пользователи могут начать проводить все время в ленте «Истории», просматривая развлекательный контент с питомцами, но при этом реже переходить в основной каталог для поиска и покупки. Метрика MAU вырастет за счет потребления контента, но транзакционная активность (количество сделок) может остаться на прежнем уровне или даже упасть. Митигация: монетизация ленты историй через рекламные вставки для компенсации сниженя просмотров карточек и рекламы в прежних местах

Sheet Параметры волн
A1: Параметры волн инициативы (входы для расчёта Revenue Increment)
A2: Эти параметры используются для реалистичного расчёта Revenue INCR в Cost assumptions row 39. Формула: Revenue INCR = Revenue AS IS × MIN(Σ(uplift_W × доля × confidence × S-curve), CAP).
A4: Параметр | B4: Значение | C4: Ед.
A5: W1: ARPPU uplift (Алгоритм рекомендаций) | B5: 0.2 | C5: %
A6: W2: ARPPU uplift (Индикатор цены) | B6: 0.07 | C6: %
A7: W3: MAU uplift (Видео + Истории) | B7: 0.05 | C7: %
A8: W1: Confidence rate | B8: 0.75 | C8: %
A9: W2: Confidence rate | B9: 0.6 | C9: %
A10: W3: Confidence rate | B10: 0.4 | C10: %
A11: Доля классифайдного слоя в ARPU | B11: 0.269 | C11: %
A12: W1: Launch month | B12: 3 | C12: мес
A13: W2: Launch month | B13: 5 | C13: мес
A14: W3: Launch month | B14: 8 | C14: мес
A15: S-curve: T_half (мес до 50% раскатки) | B15: 3 | C15: мес
A16: S-curve: k (крутизна) | B16: 1.5 | C16: мес
A17: Cap uplift: max общий incremental к Revenue | B17: 0.08 | C17: %

Sheet Baseline TOP-down
U1: fact | V1: plan
D2: 2026 | E2: =D2 -> 2026 | F2: =E2 -> 2026 | G2: =F2 -> 2026 | H2: =G2 -> 2026 | I2: =H2 -> 2026 | J2: =I2 -> 2026 | K2: =J2 -> 2026 | L2: =K2 -> 2026 | ... O2: =N2 -> 2026 | P2: =D2+1 -> 2027 | Q2: =P2 -> 2027 | R2: =Q2 -> 2027 | S2: =R2 -> 2027 | T2: =S2 -> 2027 | U2: =T2 -> 2027 | V2: =U2 -> 2027 | W2: =V2 -> 2027 | X2: =W2 -> 2027 | ... AA2: =Z2 -> 2027 | AB2: =P2+1 -> 2028 | AC2: =AB2 -> 2028 | AD2: =AC2 -> 2028 | AE2: =AD2 -> 2028 | AF2: =AE2 -> 2028 | AG2: =AF2 -> 2028 | AH2: =AG2 -> 2028 | AI2: =AH2 -> 2028 | AJ2: =AI2 -> 2028 | ... AM2: =AL2 -> 2028 | AN2: =AB2+1 -> 2029 | AO2: =AN2 -> 2029 | AP2: =AO2 -> 2029 | AQ2: =AP2 -> 2029 | AR2: =AQ2 -> 2029 | AS2: =AR2 -> 2029 | AT2: =AS2 -> 2029 | AU2: =AT2 -> 2029 | AV2: =AU2 -> 2029 | ... AY2: =AX2 -> 2029 | AZ2: =AN2+1 -> 2030 | BA2: =AZ2 -> 2030 | BB2: =BA2 -> 2030 | BC2: =BB2 -> 2030 | BD2: =BC2 -> 2030 | BE2: =BD2 -> 2030 | BF2: =BE2 -> 2030 | BG2: =BF2 -> 2030 | BH2: =BG2 -> 2030 | ... BK2: =BJ2 -> 2030 | BM2: 2026 | BO2: 2027 | BQ2: 2028 | BS2: 2029 | BU2: 2030 | BW2: 5Y
B3: Parameter | C3: Unit | D3: 31 | E3: 28 | F3: 31 | G3: 30 | H3: 31 | I3: 30 | J3: 31 | K3: 31 | L3: 30 | M3: 31 | N3: 30 | O3: 31 | P3: 31 | Q3: 28 | R3: 31 | S3: 30 | T3: 31 | U3: 30 | V3: 31 | W3: 31 | X3: 30 | Y3: 31 | Z3: 30 | AA3: 31 | AB3: 31 | AC3: 28 | AD3: 31 | AE3: 30 | AF3: 31 | AG3: 30 | AH3: 31 | AI3: 31 | AJ3: 30 | AK3: 31 | AL3: 30 | AM3: 31 | AN3: 31 | AO3: 28 | AP3: 31 | AQ3: 30 | AR3: 31 | AS3: 30 | AT3: 31 | AU3: 31 | AV3: 30 | AW3: 31 | AX3: 30 | AY3: 31 | AZ3: 31 | BA3: 29 | BB3: 31 | BC3: 30 | BD3: 31 | BE3: 30 | BF3: 31 | BG3: 31 | BH3: 30 | BI3: 31 | BJ3: 30 | BK3: 31
D4: Jan | E4: Feb | F4: Mar | G4: Apr | H4: May | I4: Jun | J4: Jul | K4: Aug | L4: Sep | M4: Oct | N4: Nov | O4: Dec | P4: Jan | Q4: Feb | R4: Mar | S4: Apr | T4: May | U4: Jun | V4: Jul | W4: Aug | X4: Sep | Y4: Oct | Z4: Nov | AA4: Dec | AB4: Jan | AC4: Feb | AD4: Mar | AE4: Apr | AF4: May | AG4: Jun | AH4: Jul | AI4: Aug | AJ4: Sep | AK4: Oct | AL4: Nov | AM4: Dec | AN4: Jan | AO4: Feb | AP4: Mar | AQ4: Apr | AR4: May | AS4: Jun | AT4: Jul | AU4: Aug | AV4: Sep | AW4: Oct | AX4: Nov | AY4: Dec | AZ4: Jan | BA4: Feb | BB4: Mar | BC4: Apr | BD4: May | BE4: Jun | BF4: Jul | BG4: Aug | BH4: Sep | BI4: Oct | BJ4: Nov | BK4: Dec
B6: MARKET ASSUMPTIONS
A8: Тут могут быть другие гипотезы о метриках рынка, применимые к вашему продукту. Этот блок — "ограничение сверху" для вашей модели | B8: Total market size (SAM) | C8: ths rub | D8: =Assumptions!C7*Assumptions!C8/12 -> 1875000 | E8: =D8*D9 -> 1895489.3 | F8: =E8*E9 -> 1916202.4 | G8: =F8*F9 -> 1937141.9 | H8: =G8*G9 -> 1958310.2 | I8: =H8*H9 -> 1979709.9 | J8: =I8*I9 -> 2001343.3 | K8: =J8*J9 -> 2023213.2 | L8: =K8*K9 -> 2045322.1 | ... BK8: =BJ8*BJ9 -> 3560282.8 | BM8: =SUMIF($D$2:$BK$2,BM$2,$D8:$BK8) -> 23902781 | BO8: =SUMIF($D$2:$BK$2,BO2,$D8:$BK8) -> 27232599 | BQ8: =SUMIF($D$2:$BK$2,BQ2,$D8:$BK8) -> 31026283 | BS8: =SUMIF($D$2:$BK$2,BS2,$D8:$BK8) -> 35348452 | BU8: =SUMIF($D$2:$BK$2,BU2,$D8:$BK8) -> 40272729 | BW8: =BM8+BO8+BQ8+BS8+BU8 -> 1.5778284e+08
B9: % change MoM | C9: % | D9: =Assumptions!$C$22 -> 1.0109276 | E9: =Assumptions!$C$22 -> 1.0109276 | F9: =Assumptions!$C$22 -> 1.0109276 | G9: =Assumptions!$C$22 -> 1.0109276 | H9: =Assumptions!$C$22 -> 1.0109276 | I9: =Assumptions!$C$22 -> 1.0109276 | J9: =Assumptions!$C$22 -> 1.0109276 | K9: =Assumptions!$C$22 -> 1.0109276 | ... BK9: =Assumptions!$C$22 -> 1.0109276
B10: SOM (year) | C10: ths rub | D10: =D8*Assumptions!$C$9 -> 937500 | E10: =E8*Assumptions!$C$9 -> 947744.63 | F10: =F8*Assumptions!$C$9 -> 958101.2 | G10: =G8*Assumptions!$C$9 -> 968570.95 | H10: =H8*Assumptions!$C$9 -> 979155.11 | I10: =I8*Assumptions!$C$9 -> 989854.93 | J10: =J8*Assumptions!$C$9 -> 1000671.7 | K10: =K8*Assumptions!$C$9 -> 1011606.6 | ... BK10: =BK8*Assumptions!$C$9 -> 1780141.4
B11: SOM (month) | C11: ths rub | D11: =D10/12 -> 78125 | E11: =E10/12 -> 78978.719 | F11: =F10/12 -> 79841.767 | G11: =G10/12 -> 80714.246 | H11: =H10/12 -> 81596.259 | I11: =I10/12 -> 82487.911 | J11: =J10/12 -> 83389.306 | K11: =K10/12 -> 84300.551 | ... BK11: =BK10/12 -> 148345.12
B12: ARPU | C12: ths rub | D12: =Assumptions!$C$11 -> 0.75 | E12: =D12*D13 -> 0.7524553 | F12: =E12*E13 -> 0.75491865 | G12: =F12*F13 -> 0.75739005 | H12: =G12*G13 -> 0.75986955 | I12: =H12*H13 -> 0.76235717 | J12: =I12*I13 -> 0.76485293 | K12: =J12*J13 -> 0.76735686 | L12: =K12*K13 -> 0.76986898 | ... BK12: =BJ12*BJ13 -> 0.90951217 | BM12: =AVERAGEIFS($D12:$BK12,$D$2:$BK$2,BM$2) -> 0.76365263 | BO12: =AVERAGEIFS($D12:$BK12,$D2:$BK2,BO2) -> 0.79419874 | BQ12: =AVERAGEIFS($D12:$BK12,$D2:$BK2,BQ2) -> 0.82596669 | BS12: =AVERAGEIFS($D12:$BK12,$D2:$BK2,BS2) -> 0.85900535 | BU12: =AVERAGEIFS($D12:$BK12,$D2:$BK2,BU2) -> 0.89336557 | BW12: =AVERAGE(BM12:BU12) -> 0.8272378
B13: % change MoM | C13: % | D13: =Assumptions!$C$14 -> 1.0032737 | E13: =Assumptions!$C$14 -> 1.0032737 | F13: =Assumptions!$C$14 -> 1.0032737 | G13: =Assumptions!$C$14 -> 1.0032737 | H13: =Assumptions!$C$14 -> 1.0032737 | I13: =Assumptions!$C$14 -> 1.0032737 | J13: =Assumptions!$C$14 -> 1.0032737 | K13: =Assumptions!$C$14 -> 1.0032737 | ... BK13: =Assumptions!$C$14 -> 1.0032737
A15: Сезонный коэффициент | B15: Seasonal coefficient | C15: % | D15: 0.5 | E15: 1 | F15: 1 | G15: 1 | H15: 1 | I15: 1 | J15: 1 | K15: 1 | L15: 1 | M15: 1 | N15: 1.2 | O15: 1.2 | P15: 0.5 | Q15: 1 | R15: 1 | S15: 1 | T15: 1 | U15: 1 | V15: 1 | W15: 1 | X15: 1 | Y15: 1 | Z15: 1.2 | AA15: 1.2 | AB15: 0.5 | AC15: 1 | AD15: 1 | AE15: 1 | AF15: 1 | AG15: 1 | AH15: 1 | AI15: 1 | AJ15: 1 | AK15: 1 | AL15: 1.2 | AM15: 1.2 | AN15: 0.5 | AO15: 1 | AP15: 1 | AQ15: 1 | AR15: 1 | AS15: 1 | AT15: 1 | AU15: 1 | AV15: 1 | AW15: 1 | AX15: 1.2 | AY15: 1.2 | AZ15: 0.5 | BA15: 1 | BB15: 1 | BC15: 1 | BD15: 1 | BE15: 1 | BF15: 1 | BG15: 1 | BH15: 1 | BI15: 1 | BJ15: 1.2 | BK15: 1.2
B17: BASELINE
B19: MAU | C19: ths users | D19: =Assumptions!$C$2*D15 -> 3000 | E19: =Assumptions!$C$2*E15 -> 6000 | F19: =Assumptions!$C$2*F15 -> 6000 | G19: =Assumptions!$C$2*G15 -> 6000 | H19: =Assumptions!$C$2*H15 -> 6000 | I19: =Assumptions!$C$2*I15 -> 6000 | J19: =Assumptions!$C$2*J15 -> 6000 | K19: =Assumptions!$C$2*K15 -> 6000 | ... BK19: =Assumptions!$C$2*BK15 -> 7200 | BM19: =AVERAGEIFS($D19:$BK19,$D$2:$BK$2,BM$2) -> 5950 | BO19: =AVERAGEIFS($D19:$BK19,$D$2:$BK$2,BO$2) -> 5950 | BQ19: =AVERAGEIFS($D19:$BK19,$D$2:$BK$2,BQ$2) -> 5950 | BS19: =AVERAGEIFS($D19:$BK19,$D$2:$BK$2,BS$2) -> 5950 | BU19: =AVERAGEIFS($D19:$BK19,$D$2:$BK$2,BU$2) -> 5950 | BW19: =AVERAGE(BM19:BU19) -> 5950
B20: DAU | C20: ths users | D20: =D19/D3 -> 96.774194 | E20: =E19/E3 -> 214.28571 | F20: =F19/F3 -> 193.54839 | G20: =G19/G3 -> 200 | H20: =H19/H3 -> 193.54839 | I20: =I19/I3 -> 200 | J20: =J19/J3 -> 193.54839 | K20: =K19/K3 -> 193.54839 | ... BK20: =BK19/BK3 -> 232.25806 | BM20: =AVERAGEIFS($D20:$BK20,$D$2:$BK$2,BM$2) -> 195.92166 | BO20: =AVERAGEIFS($D20:$BK20,$D$2:$BK$2,BO$2) -> 195.92166 | BQ20: =AVERAGEIFS($D20:$BK20,$D$2:$BK$2,BQ$2) -> 195.92166 | BS20: =AVERAGEIFS($D20:$BK20,$D$2:$BK$2,BS$2) -> 195.92166 | BU20: =AVERAGEIFS($D20:$BK20,$D$2:$BK$2,BU$2) -> 195.3059 | BW20: =AVERAGE(BM20:BU20) -> 195.79851
B21: Доля продавцов | C21: % | D21: =Assumptions!C24 -> 0.18181818 | E21: =D21 -> 0.18181818 | F21: =E21 -> 0.18181818 | G21: =F21 -> 0.18181818 | H21: =G21 -> 0.18181818 | I21: =H21 -> 0.18181818 | J21: =I21 -> 0.18181818 | K21: =J21 -> 0.18181818 | L21: =K21 -> 0.18181818 | ... BK21: =BJ21 -> 0.18181818
B22: ARPPU (month) | C22: ths rub | D22: =D12 -> 0.75 | E22: =E12 -> 0.7524553 | F22: =F12 -> 0.75491865 | G22: =G12 -> 0.75739005 | H22: =H12 -> 0.75986955 | I22: =I12 -> 0.76235717 | J22: =J12 -> 0.76485293 | K22: =K12 -> 0.76735686 | ... BK22: =BK12 -> 0.90951217 | BM22: =AVERAGEIFS($D22:$BK22,$D$2:$BK$2,BM$2) -> 0.76365263 | BO22: 0.295 | BQ22: 0.299 | BS22: 0.299 | BU22: 0.299 | BW22: =AVERAGE(BM22:BU22) -> 0.39113053
B23: Конверсия в платящих пользователей | C23: % | D23: =Assumptions!C23 -> 0.05 | E23: =D23 -> 0.05 | F23: 0.04 | G23: 0.04 | H23: 0.04 | I23: 0.04 | J23: 0.04 | K23: 0.04 | L23: 0.04 | M23: 0.04 | N23: 0.04 | O23: 0.04 | P23: 0.04 | Q23: 0.04 | R23: 0.04 | S23: 0.04 | T23: 0.04 | U23: 0.04 | V23: 0.04 | W23: 0.04 | X23: 0.04 | Y23: 0.04 | Z23: 0.04 | AA23: 0.04 | AB23: 0.04 | AC23: 0.04 | AD23: 0.04 | AE23: 0.04 | AF23: 0.04 | AG23: 0.04 | AH23: 0.04 | AI23: 0.04 | AJ23: 0.04 | AK23: 0.04 | AL23: 0.04 | AM23: 0.04 | AN23: 0.04 | AO23: 0.04 | AP23: 0.04 | AQ23: 0.04 | AR23: 0.04 | AS23: 0.04 | AT23: 0.04 | AU23: 0.04 | AV23: 0.04 | AW23: 0.04 | AX23: 0.04 | AY23: 0.04 | AZ23: 0.04 | BA23: 0.04 | BB23: 0.04 | BC23: 0.04 | BD23: 0.04 | BE23: 0.04 | BF23: 0.04 | BG23: 0.04 | BH23: 0.04 | BI23: 0.04 | BJ23: 0.04 | BK23: 0.04
B24: Total Revenue (month) | C24: ths rub | D24: =D19*D21*D23*D22*1000 -> 20454.545 | E24: =E19*E21*E23*E22*1000 -> 41043.017 | F24: =F19*F21*F23*F22*1000 -> 32941.905 | G24: =G19*G21*G23*G22*1000 -> 33049.748 | H24: =H19*H21*H23*H22*1000 -> 33157.944 | I24: =I19*I21*I23*I22*1000 -> 33266.495 | J24: =J19*J21*J23*J22*1000 -> 33375.4 | K24: =K19*K21*K23*K22*1000 -> 33484.663 | ... BK24: =BK19*BK21*BK23*BK22*1000 -> 47625.365 | BM24: =SUMIF($D$2:$BK$2,BM$2,$D24:$BK24) -> 409360.14 | BO24: =SUMIF($D$2:$BK$2,BO$2,$D24:$BK24) -> 412943.06 | BQ24: =SUMIF($D$2:$BK$2,BQ$2,$D24:$BK24) -> 429460.78 | BS24: =SUMIF($D$2:$BK$2,BS$2,$D24:$BK24) -> 446639.21 | BU24: =SUMIF($D$2:$BK$2,BU$2,$D24:$BK24) -> 464504.78 | BW24: =BM24+BO24+BQ24+BS24+BU24 -> 2162908
B26: Число объявлений всего | C26: ths units | D26: 1200 | E26: 1200 | F26: 1200 | G26: 1200 | H26: 1200 | I26: 1200 | J26: 1200 | K26: 1200 | L26: 1200 | M26: 1200 | N26: 1200 | O26: 1200 | P26: 1200 | Q26: 1200 | R26: 1200 | S26: 1200 | T26: 1200 | U26: 1200 | V26: 1200 | W26: 1200 | X26: 1200 | Y26: 1200 | Z26: 1200 | AA26: 1200 | AB26: 1200 | AC26: 1200 | AD26: 1200 | AE26: 1200 | AF26: 1200 | AG26: 1200 | AH26: 1200 | AI26: 1200 | AJ26: 1200 | AK26: 1200 | AL26: 1200 | AM26: 1200 | AN26: 1200 | AO26: 1200 | AP26: 1200 | AQ26: 1200 | AR26: 1200 | AS26: 1200 | AT26: 1200 | AU26: 1200 | AV26: 1200 | AW26: 1200 | AX26: 1200 | AY26: 1200 | AZ26: 1200 | BA26: 1200 | BB26: 1200 | BC26: 1200 | BD26: 1200 | BE26: 1200 | BF26: 1200 | BG26: 1200 | BH26: 1200 | BI26: 1200 | BJ26: 1200 | BK26: 1200 | BM26: =SUMIF($D$2:$BK$2,BM$2,$D26:$BK26) -> 14400 | BO26: =SUMIF($D$2:$BK$2,BO$2,$D26:$BK26) -> 14400 | BQ26: =SUMIF($D$2:$BK$2,BQ$2,$D26:$BK26) -> 14400 | BS26: =SUMIF($D$2:$BK$2,BS$2,$D26:$BK26) -> 14400 | BU26: =SUMIF($D$2:$BK$2,BU$2,$D26:$BK26) -> 14400 | BW26: =BM26+BO26+BQ26+BS26+BU26 -> 72000
B27: Средний чек на объявление | C27: ths rub | D27: =D24/D26/1000 -> 0.017045455 | E27: =E24/E26/1000 -> 0.034202514 | F27: =F24/F26/1000 -> 0.027451587 | G27: =G24/G26/1000 -> 0.027541457 | H27: =H24/H26/1000 -> 0.02763162 | I27: =I24/I26/1000 -> 0.027722079 | J27: =J24/J26/1000 -> 0.027812834 | K27: =K24/K26/1000 -> 0.027903886 | ... BK27: =BK24/BK26/1000 -> 0.039687804
B30: HYPOTHESYS
B33: Алгоритм рекомендаций для селлеров | C33: uplift | D33: =Гипотезы!$E$3 -> 0.1 | E33: =Гипотезы!$E$3 -> 0.1 | F33: =Гипотезы!$E$3 -> 0.1 | G33: =Гипотезы!$E$3 -> 0.1 | H33: =Гипотезы!$E$3 -> 0.1 | I33: =Гипотезы!$E$3 -> 0.1 | J33: =Гипотезы!$E$3 -> 0.1 | K33: =Гипотезы!$E$3 -> 0.1 | ... BK33: =Гипотезы!$E$3 -> 0.1
B34: Индикатор рыночной цены | C34: uplift | D34: =Гипотезы!$E$4 -> 0.05 | E34: =Гипотезы!$E$4 -> 0.05 | F34: =Гипотезы!$E$4 -> 0.05 | G34: =Гипотезы!$E$4 -> 0.05 | H34: =Гипотезы!$E$4 -> 0.05 | I34: =Гипотезы!$E$4 -> 0.05 | J34: =Гипотезы!$E$4 -> 0.05 | K34: =Гипотезы!$E$4 -> 0.05 | ... BK34: =Гипотезы!$E$4 -> 0.05
B35: Видео в карточках | C35: uplift | D35: =Гипотезы!$E$5 -> 0.03 | E35: =Гипотезы!$E$5 -> 0.03 | F35: =Гипотезы!$E$5 -> 0.03 | G35: =Гипотезы!$E$5 -> 0.03 | H35: =Гипотезы!$E$5 -> 0.03 | I35: =Гипотезы!$E$5 -> 0.03 | J35: =Гипотезы!$E$5 -> 0.03 | K35: =Гипотезы!$E$5 -> 0.03 | ... BK35: =Гипотезы!$E$5 -> 0.03
B38: Confidence rate
B41: Алгоритм рекомендаций для селлеров | C41: discount | D41: =1-Гипотезы!$D$3 -> 0.25 | E41: =1-Гипотезы!$D$3 -> 0.25 | F41: =1-Гипотезы!$D$3 -> 0.25 | G41: =1-Гипотезы!$D$3 -> 0.25 | H41: =1-Гипотезы!$D$3 -> 0.25 | I41: =1-Гипотезы!$D$3 -> 0.25 | J41: =1-Гипотезы!$D$3 -> 0.25 | K41: =1-Гипотезы!$D$3 -> 0.25 | ... BK41: =1-Гипотезы!$D$3 -> 0.25
B42: Индикатор рыночной цены | C42: discount | D42: =1-Гипотезы!$D$4 -> 0.4 | E42: =1-Гипотезы!$D$4 -> 0.4 | F42: =1-Гипотезы!$D$4 -> 0.4 | G42: =1-Гипотезы!$D$4 -> 0.4 | H42: =1-Гипотезы!$D$4 -> 0.4 | I42: =1-Гипотезы!$D$4 -> 0.4 | J42: =1-Гипотезы!$D$4 -> 0.4 | K42: =1-Гипотезы!$D$4 -> 0.4 | ... BK42: =1-Гипотезы!$D$4 -> 0.4
B43: Видео в карточках | C43: discount | D43: =1-Гипотезы!$D$5 -> 0.6 | E43: =1-Гипотезы!$D$5 -> 0.6 | F43: =1-Гипотезы!$D$5 -> 0.6 | G43: =1-Гипотезы!$D$5 -> 0.6 | H43: =1-Гипотезы!$D$5 -> 0.6 | I43: =1-Гипотезы!$D$5 -> 0.6 | J43: =1-Гипотезы!$D$5 -> 0.6 | K43: =1-Гипотезы!$D$5 -> 0.6 | ... BK43: =1-Гипотезы!$D$5 -> 0.6
B46: CASE TOTAL
B47: учтена раскатка
B48: MAU | C48: ths users | D48: =D19+D19*(1+D35)*(1-D43)*Гипотезы!$J$5 -> 3370.8 | E48: =E19+E19*(1+E35)*(1-E43)*Гипотезы!$J$5 -> 6741.6 | F48: =F19+F19*(1+F35)*(1-F43)*Гипотезы!$J$5 -> 6741.6 | G48: =G19+G19*(1+G35)*(1-G43)*Гипотезы!$J$5 -> 6741.6 | H48: =H19+H19*(1+H35)*(1-H43)*Гипотезы!$J$5 -> 6741.6 | I48: =I19+I19*(1+I35)*(1-I43)*Гипотезы!$J$5 -> 6741.6 | J48: =J19+J19*(1+J35)*(1-J43)*Гипотезы!$J$5 -> 6741.6 | K48: =K19+K19*(1+K35)*(1-K43)*Гипотезы!$J$5 -> 6741.6 | ... O48: =O19+O19*(1+O35)*(1-O43)*Гипотезы!$J$5 -> 8089.92 | P48: =P19+P19*(1+P35)*(1-P43)*Гипотезы!$K$5 -> 4236 | Q48: =Q19+Q19*(1+Q35)*(1-Q43)*Гипотезы!$K$5 -> 8472 | R48: =R19+R19*(1+R35)*(1-R43)*Гипотезы!$K$5 -> 8472 | S48: =S19+S19*(1+S35)*(1-S43)*Гипотезы!$K$5 -> 8472 | T48: =T19+T19*(1+T35)*(1-T43)*Гипотезы!$K$5 -> 8472 | U48: =U19+U19*(1+U35)*(1-U43)*Гипотезы!$K$5 -> 8472 | V48: =V19+V19*(1+V35)*(1-V43)*Гипотезы!$K$5 -> 8472 | W48: =W19+W19*(1+W35)*(1-W43)*Гипотезы!$K$5 -> 8472 | ... AA48: =AA19+AA19*(1+AA35)*(1-AA43)*Гипотезы!$K$5 -> 10166.4 | AB48: =AB19+AB19*(1+AB35)*(1-AB43)*Гипотезы!$L$5 -> 4236 | AC48: =AC19+AC19*(1+AC35)*(1-AC43)*Гипотезы!$L$5 -> 8472 | AD48: =AD19+AD19*(1+AD35)*(1-AD43)*Гипотезы!$L$5 -> 8472 | AE48: =AE19+AE19*(1+AE35)*(1-AE43)*Гипотезы!$L$5 -> 8472 | AF48: =AF19+AF19*(1+AF35)*(1-AF43)*Гипотезы!$L$5 -> 8472 | AG48: =AG19+AG19*(1+AG35)*(1-AG43)*Гипотезы!$L$5 -> 8472 | AH48: =AH19+AH19*(1+AH35)*(1-AH43)*Гипотезы!$L$5 -> 8472 | AI48: =AI19+AI19*(1+AI35)*(1-AI43)*Гипотезы!$L$5 -> 8472 | ... AM48: =AM19+AM19*(1+AM35)*(1-AM43)*Гипотезы!$L$5 -> 10166.4 | AN48: =AN19+AN19*(1+AN35)*(1-AN43)*Гипотезы!$M$5 -> 4236 | AO48: =AO19+AO19*(1+AO35)*(1-AO43)*Гипотезы!$M$5 -> 8472 | AP48: =AP19+AP19*(1+AP35)*(1-AP43)*Гипотезы!$M$5 -> 8472 | AQ48: =AQ19+AQ19*(1+AQ35)*(1-AQ43)*Гипотезы!$M$5 -> 8472 | AR48: =AR19+AR19*(1+AR35)*(1-AR43)*Гипотезы!$M$5 -> 8472 | AS48: =AS19+AS19*(1+AS35)*(1-AS43)*Гипотезы!$M$5 -> 8472 | AT48: =AT19+AT19*(1+AT35)*(1-AT43)*Гипотезы!$M$5 -> 8472 | AU48: =AU19+AU19*(1+AU35)*(1-AU43)*Гипотезы!$M$5 -> 8472 | ... AY48: =AY19+AY19*(1+AY35)*(1-AY43)*Гипотезы!$M$5 -> 10166.4 | AZ48: =AZ19+AZ19*(1+AZ35)*(1-AZ43)*Гипотезы!$N$5 -> 4236 | BA48: =BA19+BA19*(1+BA35)*(1-BA43)*Гипотезы!$N$5 -> 8472 | BB48: =BB19+BB19*(1+BB35)*(1-BB43)*Гипотезы!$N$5 -> 8472 | BC48: =BC19+BC19*(1+BC35)*(1-BC43)*Гипотезы!$N$5 -> 8472 | BD48: =BD19+BD19*(1+BD35)*(1-BD43)*Гипотезы!$N$5 -> 8472 | BE48: =BE19+BE19*(1+BE35)*(1-BE43)*Гипотезы!$N$5 -> 8472 | BF48: =BF19+BF19*(1+BF35)*(1-BF43)*Гипотезы!$N$5 -> 8472 | BG48: =BG19+BG19*(1+BG35)*(1-BG43)*Гипотезы!$N$5 -> 8472 | ... BK48: =BK19+BK19*(1+BK35)*(1-BK43)*Гипотезы!$N$5 -> 10166.4 | BM48: =SUMIF($D$2:$BK$2,BM$2,$D48:$BK48) -> 80225.04 | BO48: =SUMIF($D$2:$BK$2,BO$2,$D48:$BK48) -> 100816.8 | BQ48: =SUMIF($D$2:$BK$2,BQ$2,$D48:$BK48) -> 100816.8 | BS48: =SUMIF($D$2:$BK$2,BS$2,$D48:$BK48) -> 100816.8 | BU48: =SUMIF($D$2:$BK$2,BU$2,$D48:$BK48) -> 100816.8 | BW48: =BM48+BO48+BQ48+BS48+BU48 -> 483492.24
B49: ARPPU (month) | C49: ths rub | D49: =D22+D22*D33*(1-D41)*Гипотезы!$J$3+D22*D34*(1-D42)*Гипотезы!$J$4 -> 0.769125 | E49: =E22+E22*E33*(1-E41)*Гипотезы!$J$3+E22*E34*(1-E42)*Гипотезы!$J$4 -> 0.77164292 | F49: =F22+F22*F33*(1-F41)*Гипотезы!$J$3+F22*F34*(1-F42)*Гипотезы!$J$4 -> 0.77416907 | G49: =G22+G22*G33*(1-G41)*Гипотезы!$J$3+G22*G34*(1-G42)*Гипотезы!$J$4 -> 0.7767035 | H49: =H22+H22*H33*(1-H41)*Гипотезы!$J$3+H22*H34*(1-H42)*Гипотезы!$J$4 -> 0.77924623 | I49: =I22+I22*I33*(1-I41)*Гипотезы!$J$3+I22*I34*(1-I42)*Гипотезы!$J$4 -> 0.78179728 | J49: =J22+J22*J33*(1-J41)*Гипотезы!$J$3+J22*J34*(1-J42)*Гипотезы!$J$4 -> 0.78435668 | K49: =K22+K22*K33*(1-K41)*Гипотезы!$J$3+K22*K34*(1-K42)*Гипотезы!$J$4 -> 0.78692446 | ... O49: =O22+O22*O33*(1-O41)*Гипотезы!$J$3+O22*O34*(1-O42)*Гипотезы!$J$4 -> 0.79727991 | P49: =P22+P22*P33*(1-P41)*Гипотезы!$K$3+P22*P34*(1-P42)*Гипотезы!$K$4 -> 0.83265 | Q49: =Q22+Q22*Q33*(1-Q41)*Гипотезы!$K$3+Q22*Q34*(1-Q42)*Гипотезы!$K$4 -> 0.83537588 | R49: =R22+R22*R33*(1-R41)*Гипотезы!$K$3+R22*R34*(1-R42)*Гипотезы!$K$4 -> 0.83811068 | S49: =S22+S22*S33*(1-S41)*Гипотезы!$K$3+S22*S34*(1-S42)*Гипотезы!$K$4 -> 0.84085444 | T49: =T22+T22*T33*(1-T41)*Гипотезы!$K$3+T22*T34*(1-T42)*Гипотезы!$K$4 -> 0.84360718 | U49: =U22+U22*U33*(1-U41)*Гипотезы!$K$3+U22*U34*(1-U42)*Гипотезы!$K$4 -> 0.84636893 | V49: =V22+V22*V33*(1-V41)*Гипотезы!$K$3+V22*V34*(1-V42)*Гипотезы!$K$4 -> 0.84913972 | W49: =W22+W22*W33*(1-W41)*Гипотезы!$K$3+W22*W34*(1-W42)*Гипотезы!$K$4 -> 0.85191958 | ... AA49: =AA22+AA22*AA33*(1-AA41)*Гипотезы!$K$3+AA22*AA34*(1-AA42)*Гипотезы!$K$4 -> 0.86313034 | AB49: =AB22+AB22*AB33*(1-AB41)*Гипотезы!$L$3+AB22*AB34*(1-AB42)*Гипотезы!$L$4 -> 0.896376 | AC49: =AC22+AC22*AC33*(1-AC41)*Гипотезы!$L$3+AC22*AC34*(1-AC42)*Гипотезы!$L$4 -> 0.8993105 | AD49: =AD22+AD22*AD33*(1-AD41)*Гипотезы!$L$3+AD22*AD34*(1-AD42)*Гипотезы!$L$4 -> 0.90225461 | AE49: =AE22+AE22*AE33*(1-AE41)*Гипотезы!$L$3+AE22*AE34*(1-AE42)*Гипотезы!$L$4 -> 0.90520836 | AF49: =AF22+AF22*AF33*(1-AF41)*Гипотезы!$L$3+AF22*AF34*(1-AF42)*Гипотезы!$L$4 -> 0.90817177 | AG49: =AG22+AG22*AG33*(1-AG41)*Гипотезы!$L$3+AG22*AG34*(1-AG42)*Гипотезы!$L$4 -> 0.91114489 | AH49: =AH22+AH22*AH33*(1-AH41)*Гипотезы!$L$3+AH22*AH34*(1-AH42)*Гипотезы!$L$4 -> 0.91412774 | AI49: =AI22+AI22*AI33*(1-AI41)*Гипотезы!$L$3+AI22*AI34*(1-AI42)*Гипотезы!$L$4 -> 0.91712036 | ... AM49: =AM22+AM22*AM33*(1-AM41)*Гипотезы!$L$3+AM22*AM34*(1-AM42)*Гипотезы!$L$4 -> 0.92918912 | AN49: =AN22+AN22*AN33*(1-AN41)*Гипотезы!$M$3+AN22*AN34*(1-AN42)*Гипотезы!$M$4 -> 0.93223104 | AO49: =AO22+AO22*AO33*(1-AO41)*Гипотезы!$M$3+AO22*AO34*(1-AO42)*Гипотезы!$M$4 -> 0.93528292 | AP49: =AP22+AP22*AP33*(1-AP41)*Гипотезы!$M$3+AP22*AP34*(1-AP42)*Гипотезы!$M$4 -> 0.93834479 | AQ49: =AQ22+AQ22*AQ33*(1-AQ41)*Гипотезы!$M$3+AQ22*AQ34*(1-AQ42)*Гипотезы!$M$4 -> 0.94141669 | AR49: =AR22+AR22*AR33*(1-AR41)*Гипотезы!$M$3+AR22*AR34*(1-AR42)*Гипотезы!$M$4 -> 0.94449864 | AS49: =AS22+AS22*AS33*(1-AS41)*Гипотезы!$M$3+AS22*AS34*(1-AS42)*Гипотезы!$M$4 -> 0.94759069 | AT49: =AT22+AT22*AT33*(1-AT41)*Гипотезы!$M$3+AT22*AT34*(1-AT42)*Гипотезы!$M$4 -> 0.95069285 | AU49: =AU22+AU22*AU33*(1-AU41)*Гипотезы!$M$3+AU22*AU34*(1-AU42)*Гипотезы!$M$4 -> 0.95380517 | ... AY49: =AY22+AY22*AY33*(1-AY41)*Гипотезы!$M$3+AY22*AY34*(1-AY42)*Гипотезы!$M$4 -> 0.96635668 | AZ49: =AZ22+AZ22*AZ33*(1-AZ41)*Гипотезы!$N$3+AZ22*AZ34*(1-AZ42)*Гипотезы!$N$4 -> 0.96952028 | BA49: =BA22+BA22*BA33*(1-BA41)*Гипотезы!$N$3+BA22*BA34*(1-BA42)*Гипотезы!$N$4 -> 0.97269424 | BB49: =BB22+BB22*BB33*(1-BB41)*Гипотезы!$N$3+BB22*BB34*(1-BB42)*Гипотезы!$N$4 -> 0.97587859 | BC49: =BC22+BC22*BC33*(1-BC41)*Гипотезы!$N$3+BC22*BC34*(1-BC42)*Гипотезы!$N$4 -> 0.97907336 | BD49: =BD22+BD22*BD33*(1-BD41)*Гипотезы!$N$3+BD22*BD34*(1-BD42)*Гипотезы!$N$4 -> 0.98227859 | BE49: =BE22+BE22*BE33*(1-BE41)*Гипотезы!$N$3+BE22*BE34*(1-BE42)*Гипотезы!$N$4 -> 0.98549431 | BF49: =BF22+BF22*BF33*(1-BF41)*Гипотезы!$N$3+BF22*BF34*(1-BF42)*Гипотезы!$N$4 -> 0.98872057 | BG49: =BG22+BG22*BG33*(1-BG41)*Гипотезы!$N$3+BG22*BG34*(1-BG42)*Гипотезы!$N$4 -> 0.99195738 | ... BK49: =BK22+BK22*BK33*(1-BK41)*Гипотезы!$N$3+BK22*BK34*(1-BK42)*Гипотезы!$N$4 -> 1.0050109
B50: Доля продавцов | C50: % | D50: 0.2 | E50: 0.2 | F50: 0.2 | G50: 0.2 | H50: 0.2 | I50: 0.2 | J50: 0.2 | K50: 0.2 | L50: 0.2 | M50: 0.2 | N50: 0.2 | O50: 0.2 | P50: 0.2 | Q50: 0.2 | R50: 0.2 | S50: 0.2 | T50: 0.2 | U50: 0.2 | V50: 0.2 | W50: 0.2 | X50: 0.2 | Y50: 0.2 | Z50: 0.2 | AA50: 0.2 | AB50: 0.2 | AC50: 0.2 | AD50: 0.2 | AE50: 0.2 | AF50: 0.2 | AG50: 0.2 | AH50: 0.2 | AI50: 0.2 | AJ50: 0.2 | AK50: 0.2 | AL50: 0.2 | AM50: 0.2 | AN50: 0.2 | AO50: 0.2 | AP50: 0.2 | AQ50: 0.2 | AR50: 0.2 | AS50: 0.2 | AT50: 0.2 | AU50: 0.2 | AV50: 0.2 | AW50: 0.2 | AX50: 0.2 | AY50: 0.2 | AZ50: 0.2 | BA50: 0.2 | BB50: 0.2 | BC50: 0.2 | BD50: 0.2 | BE50: 0.2 | BF50: 0.2 | BG50: 0.2 | BH50: 0.2 | BI50: 0.2 | BJ50: 0.2 | BK50: 0.2
B51: Конверсия в платящих пользователей | C51: % | D51: 0.04 | E51: 0.04 | F51: 0.04 | G51: 0.04 | H51: 0.04 | I51: 0.04 | J51: 0.04 | K51: 0.04 | L51: 0.04 | M51: 0.04 | N51: 0.04 | O51: 0.04 | P51: 0.04 | Q51: 0.04 | R51: 0.04 | S51: 0.04 | T51: 0.04 | U51: 0.04 | V51: 0.04 | W51: 0.04 | X51: 0.04 | Y51: 0.04 | Z51: 0.04 | AA51: 0.04 | AB51: 0.04 | AC51: 0.04 | AD51: 0.04 | AE51: 0.04 | AF51: 0.04 | AG51: 0.04 | AH51: 0.04 | AI51: 0.04 | AJ51: 0.04 | AK51: 0.04 | AL51: 0.04 | AM51: 0.04 | AN51: 0.04 | AO51: 0.04 | AP51: 0.04 | AQ51: 0.04 | AR51: 0.04 | AS51: 0.04 | AT51: 0.04 | AU51: 0.04 | AV51: 0.04 | AW51: 0.04 | AX51: 0.04 | AY51: 0.04 | AZ51: 0.04 | BA51: 0.04 | BB51: 0.04 | BC51: 0.04 | BD51: 0.04 | BE51: 0.04 | BF51: 0.04 | BG51: 0.04 | BH51: 0.04 | BI51: 0.04 | BJ51: 0.04 | BK51: 0.04
B52: Total Revenue | C52: ths rub | D52: =D48*D49*D50*D51*1000 -> 20740.532 | E52: =E48*E49*E50*E51*1000 -> 41616.863 | F52: =F48*F49*F50*F51*1000 -> 41753.106 | G52: =G48*G49*G50*G51*1000 -> 41889.795 | H52: =H48*H49*H50*H51*1000 -> 42026.931 | I52: =I48*I49*I50*I51*1000 -> 42164.516 | J52: =J48*J49*J50*J51*1000 -> 42302.552 | K52: =K48*K49*K50*K51*1000 -> 42441.039 | ... BK52: =BK48*BK49*BK50*BK51*1000 -> 81738.746 | BM52: =SUMIF($D$2:$BK$2,BM$2,$D52:$BK52) -> 503265.21 | BO52: =SUMIF($D$2:$BK$2,BO$2,$D52:$BK52) -> 684676.52 | BQ52: =SUMIF($D$2:$BK$2,BQ$2,$D52:$BK52) -> 737077.52 | BS52: =SUMIF($D$2:$BK$2,BS$2,$D52:$BK52) -> 766560.62 | BU52: =SUMIF($D$2:$BK$2,BU$2,$D52:$BK52) -> 797223.05 | BW52: =BM52+BO52+BQ52+BS52+BU52 -> 3488802.9
B55: Incremental values
B58: Total Revenue incremental | C58: mln Rub | D58: =D52-D24 -> 285.98695 | E58: =E52-E24 -> 573.84638 | F58: =F52-F24 -> 8811.2012 | G58: =G52-G24 -> 8840.0467 | H58: =H52-H24 -> 8868.9868 | I58: =I52-I24 -> 8898.0215 | J58: =J52-J24 -> 8927.1513 | K58: =K52-K24 -> 8956.3765 | ... BK58: =BK52-BK24 -> 34113.382 | BM58: =SUMIF($D$2:$BK$2,BM$2,$D58:$BK58) -> 93905.066 | BO58: =SUMIF($D$2:$BK$2,BO$2,$D58:$BK58) -> 271733.46 | BQ58: =SUMIF($D$2:$BK$2,BQ$2,$D58:$BK58) -> 307616.74 | BS58: =SUMIF($D$2:$BK$2,BS$2,$D58:$BK58) -> 319921.41 | BU58: =SUMIF($D$2:$BK$2,BU$2,$D58:$BK58) -> 332718.27 | BW58: =BM58+BO58+BQ58+BS58+BU58 -> 1325895
B62: CANNIBALIZATION
B63: Каннибализация не учтена, так как все фичи подразумевают либо отсеивание убыточной инициативы на этапе теста, либо монетизацию, компенсирующую каннибализацию
B65: Изменения выручки
L467: Rev New 26, ths rub
L468: Rev Baseline 26, ths rub

Sheet Assumptions
A1: Показатель | B1: Ед. изм. | C1: Значение | D1: Источник | E1: Примечание
A2: MAU | B2: тыс. чел. | C2: 6000 | D2: Лист Данные для ДЗ №1
A3: Число объявлений | B3: тыс. ед. | C3: 1200 | D3: Лист Данные для ДЗ №1
A4: Объявлений на пользователя | B4: ед. | C4: =C3/C2 -> 0.2 | D4: Лист Данные для ДЗ №1 | E4: Разделением на байеров и селлеров пренебрегаем, так как пользователь может попасть в обе группы, что в текущей модели нецелесообразно
A5: Конверсия DAU -> Order placed | B5: % | C5: 0.17 | D5: Лист Данные для ДЗ №1 | E5: Конверсия из DAU в публикацию объявления. Посчитал, что за 1 день публикуется более 650 объявлений о продаже собак в Москве, собаки - около 1/3 от общего числа объявлений. Если экстраполировать на другие категрии и регионы, обращая внимание на общее кол-во объявлений категории, получим примерное значение (возможно завышено)
A6: Конверсия DAU -> Order placed > Order paid | B6: % | C6: 0.15 | D6: Гипотеза | E6: Оценил по количеству объявлений с продвижением в серпе. Неуверен в репрезентативности выборки, так как может варьироваться от региона к региону
A7: ТАМ | B7: тыс. руб./год | C7: 90000000 | D7: Лист Данные для ДЗ №1 | E7: Все стоимостные значения в тыс., чтобы было удобнее считать
A8: Доля онлайн-сегмента | B8: % | C8: 0.25 | D8: Лист Данные для ДЗ №1 | E8: Для оценки SAM
A9: Потенциальная доля Авито на рынке | B9: % | C9: 0.5 | D9: Лист Данные для ДЗ №1 | E9: Для оценки SOM
A10: Годовой ARPU | B10: тыс. руб. | C10: 2 | D10: Лист Данные для ДЗ №1 | E10: Взято значение ближе к середине диапозона, так как товары в категории животные, как правило, имеют невысокую стоимость (за исключением породистых животных)
A11: Месячный ARPPU | B11: тыс. руб. | C11: 0.75 | D11: Фактические данные | E11: Гипотетически средняя цена будет ближе к минимальной на платформе (600 руб), так как основаня часть, публикующая животных, делает это разово и не является профпродавцом с высоким средним чеком
A12: Месячный ARPU | B12: тыс. руб. | C12: =C10/12 -> 0.16666667
A13: Годовая инфляция (индекс) | B13: % г/г | C13: 1.04 | D13: Прогноз социально-экономического развития Российской Федерации на 2026 год и на плановый период 2027 и 2028 годов https://www.economy.gov.ru/material/directions/makroec/prognozy_socialno_ekonomicheskogo_razvitiya/prognoz_socialno_ekonomicheskogo_razvitiya_rf_na_2026_god_i_na_planovyy_period_2027_i_2028_godov.html | E13: Рост цен частично заложен в рост рынка. Был взят официальный таргет инфляции. Его возможная заниженность компенсируется тем, что ценовая политика не дублирует уровень инфляции. Поэтому инфляция в модели используется в качестве консервативного сценария индексации ARPU
A14: Инфляция в месяц (индекс) | B14: % м/м | C14: =C13^(1/12) -> 1.0032737
A15: Темп роста рынка животных и зоотоваров 2025 | B15: % | C15: 1.158 | D15: https://companies.rbc.ru/news/sC0u2z43j7/ryinok-zootovarov-v-rossii-vyiros-do-590-mlrd-rublej/
A16: Темп роста рынка животных и зоотоваров 2024 | B16: % | C16: 1.177 | D16: https://companies.rbc.ru/news/sC0u2z43j7/ryinok-zootovarov-v-rossii-vyiros-do-590-mlrd-rublej/
A17: Темп роста рынка животных и зоотоваров 2023 | B17: % | C17: 1.312 | D17: https://companies.rbc.ru/news/sC0u2z43j7/ryinok-zootovarov-v-rossii-vyiros-do-590-mlrd-rublej/
A18: Темп роста рынка животных и зоотоваров 2022 | B18: % | C18: 1.245 | D18: https://companies.rbc.ru/news/sC0u2z43j7/ryinok-zootovarov-v-rossii-vyiros-do-590-mlrd-rublej/
A19: Средний темп роста рынка за 4 года | B19: % | C19: =GEOMEAN(C15:C18) -> 1.2215101 | E19: Изначальный ускоренный рост был обеспечен не столько увеличением потребления, сколько ценовым фактором. Поэтому в расчет будет закладываться замедление роста рынка ввиду замедления инфляции.
A20: Замедление темпа роста рынка | B20: % | C20: =C15/C16-1 -> -0.016142736
A21: Темп роста рынка в модель | B21: % | C21: =C15+C20*C15 -> 1.1393067 | E21: С учетом динамики замедления роста. В среднесрочной перспективе оставлено текущее значение, закладывается улучшение экономической конъюнктуры. Но эффект высокой базы не даст прежних темпов прироста более 15%
A22: Темп роста рынка в месяц | B22: % | C22: =C21^(1/12) -> 1.0109276 | E22: Для расчета в ежемесячном разрезе
A23: Конверсия в платящего пользователя | B23: % | C23: 0.05 | D23: Лист Данные для ДЗ №1 | E23: Bottom-up: конверсия ~3–5%
A24: Доля продавцов | B24: % | C24: =E24 -> 0.18181818 | D24: Значительная часть заходит на платформу чтобы посмотреть на животынх. Очень низкая конверсия в покупку (по исходным данным). Селлером может выступать каждый кто заходит, так как платформа С2С. Если около половины (до 50%) заходит просто так, то оставшиеся пользоватли - потенциальные продавцы или покупатели. С учетом, что объявлений 1,2 млн, а продавцы выкладывают минимум 1 объявление (пусть среднее 1,1 объявлений на продавца), то доля продавцов 1,2 млн объявлений / 1,3 / MAU = | E24: =C3/1.1/C2 -> 0.18181818

Sheet Текстовое пояснение
A1: Бизнес-контекст
A2: Выбрано направление «Животные» внутри Авито — категория объявлений о продаже питомцев и сопутствующих товаров. Продукт находится в фазе роста с переходом к масштабированию: базовый спрос сформирован (product–market fit достигнут), фокус смещается на повышение доверия, увеличение доли транзакций внутри платформы и рост повторных покупок.
A5: Целевая аудитория
A6: 1 Частные продавцы (заводчики, владельцы животных). 2 Профессиональные участники (питомники, магазины, приюты). 3 Покупатели питомцев — семьи, одинокие пользователи, люди с выраженной эмоциональной мотивацией. 4 Повторные покупатели сопутствующих товаров (корм, аксессуары, услуги). 5 Аудитория чувствительна к доверию и безопасности сделки.
A9: Ключевые проблемы, которые решает продукт
A10: Снижение риска мошенничества и недобросовестных продавцов; прозрачность информации о животном; удобный поиск по параметрам; коммуникация через встроенный чат; возможность дальнейших покупок товаров для ухода. Продукт закрывает как рациональные (поиск, сравнение), так и эмоциональные потребности (забота, ответственность)
A12: Ключевые метрики успеха
A13: MAU/DAU категории; количество размещённых объявлений; конверсия DAU → Order placed; конверсия Order placed → Paid; доля платных размещений; ARPU; Total Revenue; доля повторных покупок в сегменте товаров; рост SOM относительно SAM.
A15: Выбор метода расчёта baseline
A16: Top-down — для ограничения сверху через SAM и темпы роста рынка. Такой подход отражает специфику категории: с одной стороны, рынок уже сформирован и имеет макроограничения; с другой — монетизация напрямую зависит от конверсий внутри продукта.
A18: Преимущества и ограничения метода
A19: Top-down позволяет проверить модель на превышение ёмкости рынка, но менее точен без детальных данных.
... A28: Факторы и риски, влияющие на точность прогноза

Sheet Данные для ДЗ №1
A1: 1. Общие рыночные данные
A3: Продукт | B3: TAM (объём рынка, млрд ₽/год) | C3: SAM (доля онлайн-сегмента, %) | D3: SOM (доля Avito на рынке, оценка) | E3: Источник / примечание
A4: 1.1 Лента объявлений (Search / логика ранжирования) | B4: Не применимо как самостоятельный рынок | C4: — | D4: — | E4: Это инфраструктурная функция, влияющая на весь трафик Avito. Её "рынок" — совокупность всех категорий. Однако можно оценить экономический эффект: улучшение релевантности на 10% → +5–8% к конверсии в контакт. База: 50 млн MAU, 4% CTR → ~2 млн контактов/день. Увеличение эффективности ленты = рост GMV платформы.
A5: 1.2 Рекомендации пользователю | B5: Не применимо как самостоятельный рынок | C5: — | D5: — | E5: Также инфраструктурная фича. Влияет на вовлечённость. Доступна в отдельных сценариях (например - в карточке товара) Можно оценить через время в приложении и частоту визитов. Эффект: персонализированные рекомендации увеличивают return rate на 15–20%. Аналог: Amazon (35% продаж через рекомендации). На Avito доля рекомендаций в общем трафике — до 15%.
A6: 2.1 Продвижение объявлений | B6: Не применимо как самостоятельный рынок | C6: — | D6: — | E6: Инфраструктурная фича, работает на уровне объявлений. Доступно всем при размещении объявлений (100% контента покрыта услугой).
A7: 3.1 Воронка для электроники (смартфоны) | B7: 250 | C7: 0.6 | D7: 35–40% | E7: Отчёт ФИТР 2024
A8: 3.2 Мода и одежда | B8: 180 | C8: 0.45 | D8: 0.3 | E8: Data Insight
A9: 3.4 Хобби | B9: 40 | C9: 0.3 | D9: 0.45 | E9: Аналоги Etsy, OLX
A10: 3.5 Спортинвентарь | B10: 110 | C10: 0.4 | D10: 0.45 | E10: Включает велосипеды, лыжи, тренажёры, снаряжение. Онлайн-сегмент растёт (спорт как lifestyle). Avito — лидер среди C2C-платформ. Конкуренты: Decathlon, Wildberries, Озон, Sportmaster. Источник: Data Insight, Romir.
A11: 3.7 Мебель и мебель на заказ (подраздел "Новая мебель") | B11: 380 | C11: 0.3 | D11: 0.35 | E11: Рынок новой мебели (не б/у). Включает магазины и мастеров. Онлайн-продажи растут медленнее из-за специфики (замеры, доставка). Avito — ключевая площадка для небольших производителей и студий. Конкуренты: IKEA, Мебель-онлайн, Joom.
A12: 3.9 Животные и товары для животных | B12: 90 | C12: 0.25 | D12: 0.5 | E12: Ветеринарные ассоциации
A13: 4.1 Крупногабаритная доставка (КГТ) | B13: 80(рынок доставки габаритов) | C13: 15% (онлайн-платформы) | D13: 0.2 | E13: McKinsey Logistics
A14: 4.5 Примерки | B14: 25–30 млрд ₽ (потенциал выручки от комиссий и логистики) | C14: 100% (только онлайн) | D14: 100% (единственный игрок в C2C) | E14: Это сервис внутри платформы, нет отдельного рынка. TAM = потенциальный доход: 400 тыс. заказов/мес × 750 ₽ (средняя комиссия + логистика) = ~360 млн ₽/год. Рынок ограничен логистикой и географией. Avito — первый и пока единственный массовый игрок в C2C-примерках.
A15: 4.7 Корзина | B15: — | C15: — | D15: — | E15: Рассчитывается через GMV
A16: 5.1 Тревел / аренда жилья | B16: 3 млн сделок в год | C16: 0.65 | D16: 0.4 | E16: ЦИАН, Avito Realty Report
A17: 6.1 Каталог автомобилей | B17: 6 млн авто в год (шт.) | C17: 0.7 | D17: 0.5 | E17: ГИБДД + Автостат, новые авто и авто с пробегом
A18: 8.1 Стройка (запрос предложений или транзакция) 8.2 Ремонт (запрос предложений или транзакция) | B18: 1.2 трлн ₽ | C18: 20% (онлайн-запросы) | D18: 0.25 | E18: NPS строительных компаний
A20: 2. Ключевые продуктовые метрики Avito (оценочные, усреднённые)
A22: Метрика | B22: Значение | C22: Комментарий
A23: MAU (все направления) | B23: 50 млн | C23: Общая аудитория Avito (источник: публичные отчёты)
A24: Конверсия просмотра объявления → контакт | B24: 0,03–0,05% | C24: Зависит от категории (выше в дорогих, ниже в массовых)
A25: Среднее количество объявлений на пользователя (продавец) в месяц | B25: 1.2–1.8 | C25: C2C vs B2B
A26: Доля профессиональных продавцов в контенте | B26: 20-50% | C26: в зависимости от категории
A27: Частота публикаций объявлений(активность) | B27: 1.5 раза в месяц | C27: Усреднено для всех сегментов и категорий
A28: ARPU (с продавца, годовой) | B28: 1 200 – 3 500 ₽ | C28: Зависит от категории (выше в авто, недвижимости)
A29: GMV (на одно объявление) | B29: 50 000 ₽ (электроника), 120 000 ₽ (авто), 300 000 ₽ (недвижимость) | C29: Можно давать по категориям
A30: Take Rate, % | B30: 0,5-10% | C30: Зависит от категории (референс аналогов по рынку конкретной категории)
A31: Доля транзакций внутри платформы | B31: 10–15% (растёт) | C31: Для корзины, примерки, КГТ — выше, усредненно для всей площадки, по категориям может значимо отличаться
A33: 3. Разбивка по категориям
A35: Продукт | B35: Основная метрика (MAU, кол-во объявлений, число заказов) | D35: Драйверы роста | E35: Особенности baseline
A36: 1.1 Лента объявлений (Search / логика ранжирования) | B36: 50 млн MAU, 200 млн просмотров/день | D36: Релевантность, персонализация, скорость загрузки | E36: Baseline строится через улучшение CTR и удержание: +1% к CTR = +X млн контактов/мес. Используется bottom-up: от поведения пользователя → к общему трафику, важен сплит категорий в выдаче
A37: 1.2 Рекомендации пользователю | B37: 30 млн MAU, 15 млн рекомендаций/день | D37: Качество алгоритма, частота показов, кликабельность | E37: Bottom-up: от доли кликов на рекомендации → к росту времени в приложении и конверсии. Эффект измеряется через uplift в смежных категориях, важен сплит категорий в выдаче
A38: 2.1 Продвижение объявлений | B38: 12–15 млн активных продавцов, 5 млн платных действий/мес | D38: Видимость, ROI для продавца, момент предложения | E38: Bottom-up: ARPU с продавца × число активных продавцов. Учитывается доля тех, кто использует платные опции (~15–20%), влияние срока размещения
A39: 3.1 Воронка для электроники (смартфоны) | B39: 12 млн MAU, 8 млн объявлений | D39: Релевантность поиска, доверие | E39: Bottom-up: конверсия → сделка
A40: 3.2 Мода и одежда | B40: 9 млн MAU, 6 млн объявлений | D40: Рекомендации, размеры | E40: Bottom-up: частота покупок, сезонность, конверсия → сделка
A41: 3.4 Хобби | B41: 3 млн MAU, 500 тыс. объявлений | D41: Сообщества, уникальность | E41: Bottom-up: редкие запросы, долгий цикл
A42: 3.5 Спортинвентарь | B42: 4 млн MAU, 800 тыс. объявлений | D42: Доверие к состоянию, фильтры по характеристикам, интеграция с проверкой | E42: Bottom-up: конверсия просмотра → контакт (4–6%), средний чек ~30 000 ₽. GMV = число сделок × AOV. Сезонность, конверсия → сделка
A43: 3.7 Мебель и мебель на заказ (подраздел "Новая мебель") | B43: 5 млн MAU, 600 тыс. объявлений | D43: Качество фото, портфолио, конфигуратор, доверие | E43: Bottom-up: число запросов КП × конверсия в сделку (~5–8%). Для новой мебели — выше ARPU, но ниже частота.
A44: 3.9 Животные и товары для животных | B44: 6 млн MAU, 1.2 млн объявлений | D44: Доверие к продавцу, верификация, породы, гео | E44: Bottom-up: конверсия ~3–5%. Высокая эмоциональная вовлечённость, но низкая частота покупок. Для товаров — аналог маркетплейса.
A45: 4.1 Крупногабаритная доставка (КГТ) | B45: 1.2 млн заказов/мес | D45: Покрытие городов, сроки | E45: Bottom-up: заказы × средний чек доставки
A46: 4.5 Примерки | B46: 400 тыс. заказов/мес | D46: Удержание, отказы после примерки | E46: Uplift от базовой конверсии, связь с фешн через долю примерок
... A51: 8.2 Ремонт (запрос предложений или транзакция) | B51: 3.5 млн запросов/мес, 500 тыс. сделок | D51: Простота подачи заявки, скорость ответа, страхование | E51: Bottom-up: конверсия ~15%. Фокус на массовых услугах (сантехник, электрик). Возможен top-down по объёму рынка бытовых услуг.
